Workbook

Sheet Detalles movimientos
C2: VENTAS GRANEL ECOGAS SPA
C4: Fecha | D4: Nombre Cliente | E4: Camión | F4: Vende | G4: Dirección | H4: Precio | I4: Litros Vendidos | J4: Total Recaudado | K4: Medio de pago | L4: Comisiones | M4: Observación | N4: COMPRA ENAP | O4: Litros Comprados | Q4: _Idx_CJ | R4: _Idx_Ignacio | S4: _Idx_Tripulacion | T4: _Idx_ENAP carga
C5: 46226 | D5: ENAP carga | E5: VJYL61 | F5: ENAP carga | I5: 11481 | K5: ENAP carga | L5: =IF(F5="CJ", I5*200, "") | M5: Guía N° xxxxx | N5: 3836889 | O5: 11481 | Q5: =IF(F5="CJ", COUNTIF(F$5:F5, "CJ"), "") | R5: =IF(F5="Ignacio", COUNTIF(F$5:F5, "Ignacio"), "") | S5: =IF(F5="Tripulacion", COUNTIF(F$5:F5, "Tripulacion"), "") | T5: =IF(F5="ENAP carga", COUNTIF(F$5:F5, "ENAP carga"), "") -> 1
C6: 46230 | D6: Ignacio Guerrero | E6: VJYL61 | F6: Ignacio | I6: 1403 | K6: Extraccion | L6: =IF(F6="CJ", I6*200, "") | M6: Extraccion | Q6: =IF(F6="CJ", COUNTIF(F$5:F6, "CJ"), "") | R6: =IF(F6="Ignacio", COUNTIF(F$5:F6, "Ignacio"), "") -> 1 | S6: =IF(F6="Tripulacion", COUNTIF(F$5:F6, "Tripulacion"), "") | T6: =IF(F6="ENAP carga", COUNTIF(F$5:F6, "ENAP carga"), "")
C7: 46230 | D7: Ricardo Brisas del Raco | E7: VJYL61 | F7: CJ | G7: Brisas del Raco | H7: 1000 | I7: 179.2 | J7: =H7*I7 -> 179200 | K7: Tarjeta | L7: =I7*200 -> 35840 | M7: Comision Pagada | Q7: =IF(F7="CJ", COUNTIF(F$5:F7, "CJ"), "") -> 1 | R7: =IF(F7="Ignacio", COUNTIF(F$5:F7, "Ignacio"), "") | S7: =IF(F7="Tripulacion", COUNTIF(F$5:F7, "Tripulacion"), "") | T7: =IF(F7="ENAP carga", COUNTIF(F$5:F7, "ENAP carga"), "")
C8: 46230 | D8: Ale Turko | E8: VJYL61 | F8: CJ | H8: 1000 | I8: 518.1 | J8: =H8*I8 -> 518100 | K8: Pendiente de pago | L8: =I8*200 -> 103620 | M8: Comision Pagada | Q8: =IF(F8="CJ", COUNTIF(F$5:F8, "CJ"), "") -> 2 | R8: =IF(F8="Ignacio", COUNTIF(F$5:F8, "Ignacio"), "") | S8: =IF(F8="Tripulacion", COUNTIF(F$5:F8, "Tripulacion"), "") | T8: =IF(F8="ENAP carga", COUNTIF(F$5:F8, "ENAP carga"), "")
C9: 46230 | D9: Tirua | E9: VJYL61 | F9: CJ | H9: 1000 | I9: 488.2 | J9: =H9*I9 -> 488200 | K9: Pendiente de pago | L9: =I9*200 -> 97640 | M9: Comision Pagada | Q9: =IF(F9="CJ", COUNTIF(F$5:F9, "CJ"), "") -> 3 | R9: =IF(F9="Ignacio", COUNTIF(F$5:F9, "Ignacio"), "") | S9: =IF(F9="Tripulacion", COUNTIF(F$5:F9, "Tripulacion"), "") | T9: =IF(F9="ENAP carga", COUNTIF(F$5:F9, "ENAP carga"), "")
C10: 46230 | D10: Ciao Italia | E10: VJYL61 | F10: CJ | H10: 1000 | I10: 500.3 | J10: =H10*I10 -> 500300 | K10: Pendiente de pago | L10: =I10*200 -> 100060 | M10: Comision Pagada | Q10: =IF(F10="CJ", COUNTIF(F$5:F10, "CJ"), "") -> 4 | R10: =IF(F10="Ignacio", COUNTIF(F$5:F10, "Ignacio"), "") | S10: =IF(F10="Tripulacion", COUNTIF(F$5:F10, "Tripulacion"), "") | T10: =IF(F10="ENAP carga", COUNTIF(F$5:F10, "ENAP carga"), "")
C11: 46230 | D11: Claudio Ulloa | E11: VJYL61 | F11: CJ | H11: 1000 | I11: 237.9 | J11: =H11*I11 -> 237900 | K11: Pendiente de pago | L11: =I11*200 -> 47580 | M11: Comision Pagada | Q11: =IF(F11="CJ", COUNTIF(F$5:F11, "CJ"), "") -> 5 | R11: =IF(F11="Ignacio", COUNTIF(F$5:F11, "Ignacio"), "") | S11: =IF(F11="Tripulacion", COUNTIF(F$5:F11, "Tripulacion"), "") | T11: =IF(F11="ENAP carga", COUNTIF(F$5:F11, "ENAP carga"), "")
C12: 46230 | D12: Francisco Ulloa | E12: VJYL61 | F12: CJ | H12: 1000 | I12: 205.1 | J12: =H12*I12 -> 205100 | K12: Pendiente de pago | L12: =I12*200 -> 41020 | M12: Comision Pagada | Q12: =IF(F12="CJ", COUNTIF(F$5:F12, "CJ"), "") -> 6 | R12: =IF(F12="Ignacio", COUNTIF(F$5:F12, "Ignacio"), "") | S12: =IF(F12="Tripulacion", COUNTIF(F$5:F12, "Tripulacion"), "") | T12: =IF(F12="ENAP carga", COUNTIF(F$5:F12, "ENAP carga"), "")
C13: 46230 | D13: Alicia Pavez | E13: VJYL61 | F13: CJ | H13: 1000 | I13: 300 | J13: =H13*I13 -> 300000 | K13: Transferencia | L13: =I13*200 -> 60000 | M13: Comision Pagada | P13: =SUM(I7:I13) -> 2428.8 | Q13: =IF(F13="CJ", COUNTIF(F$5:F13, "CJ"), "") -> 7 | R13: =IF(F13="Ignacio", COUNTIF(F$5:F13, "Ignacio"), "") | S13: =IF(F13="Tripulacion", COUNTIF(F$5:F13, "Tripulacion"), "") | T13: =IF(F13="ENAP carga", COUNTIF(F$5:F13, "ENAP carga"), "")
C14: 46231 | D14: Vanessa | E14: VJYL61 | F14: CJ | H14: 1000 | I14: 200 | J14: =H14*I14 -> 200000 | K14: Transferencia | L14: =IF(F14="CJ", I14*200, "") -> 40000 | Q14: =IF(F14="CJ", COUNTIF(F$5:F14, "CJ"), "") -> 8 | R14: =IF(F14="Ignacio", COUNTIF(F$5:F14, "Ignacio"), "") | S14: =IF(F14="Tripulacion", COUNTIF(F$5:F14, "Tripulacion"), "") | T14: =IF(F14="ENAP carga", COUNTIF(F$5:F14, "ENAP carga"), "")
C15: 46231 | D15: Franco Garcia | E15: VJYL61 | F15: Tripulacion | G15: Santa Rita 1177 parcela 14 Pirque | I15: 912 | J15: =H15*I15 -> 0 | L15: =IF(F15="CJ", I15*200, "") | Q15: =IF(F15="CJ", COUNTIF(F$5:F15, "CJ"), "") | R15: =IF(F15="Ignacio", COUNTIF(F$5:F15, "Ignacio"), "") | S15: =IF(F15="Tripulacion", COUNTIF(F$5:F15, "Tripulacion"), "") -> 1 | T15: =IF(F15="ENAP carga", COUNTIF(F$5:F15, "ENAP carga"), "")
C16: 46233 | D16: Simon | E16: VJYL61 | F16: CJ | G16: Camino el Chalaco 66B | H16: 1000 | I16: 747 | J16: =H16*I16 -> 747000 | K16: Transferencia | L16: =IF(F16="CJ", I16*200, "") -> 149400 | M16: Factura | P16: Ebal spa - RUT: 77.625.623-4 - Av Gabriela 3264 La Pintana - Giro Construccion | Q16: =IF(F16="CJ", COUNTIF(F$5:F16, "CJ"), "") -> 9 | R16: =IF(F16="Ignacio", COUNTIF(F$5:F16, "Ignacio"), "") | S16: =IF(F16="Tripulacion", COUNTIF(F$5:F16, "Tripulacion"), "") | T16: =IF(F16="ENAP carga", COUNTIF(F$5:F16, "ENAP carga"), "")
C17: 46237 | D17: Manuel Vergara Ricci | E17: VJYL61 | F17: CJ | G17: Avenida Virginia subercaseaux 4175 (parcela 15) | H17: 1100 | I17: 200 | J17: =H17*I17 -> 220000 | K17: Transferencia | L17: =IF(F17="CJ", I17*200, "") -> 40000 | Q17: =IF(F17="CJ", COUNTIF(F$5:F17, "CJ"), "") -> 10 | R17: =IF(F17="Ignacio", COUNTIF(F$5:F17, "Ignacio"), "") | S17: =IF(F17="Tripulacion", COUNTIF(F$5:F17, "Tripulacion"), "") | T17: =IF(F17="ENAP carga", COUNTIF(F$5:F17, "ENAP carga"), "")
C18: 46237 | D18: Gabriela Rojas | E18: VJYL61 | F18: CJ | G18: Camino de las flores 1262 Pirque | H18: 1100 | I18: 350 | J18: =H18*I18 -> 385000 | K18: Transferencia en dos | L18: =IF(F18="CJ", I18*200, "") -> 70000 | M18: Quedó saldo de $35 mil para mañana | Q18: =IF(F18="CJ", COUNTIF(F$5:F18, "CJ"), "") -> 11 | R18: =IF(F18="Ignacio", COUNTIF(F$5:F18, "Ignacio"), "") | S18: =IF(F18="Tripulacion", COUNTIF(F$5:F18, "Tripulacion"), "") | T18: =IF(F18="ENAP carga", COUNTIF(F$5:F18, "ENAP carga"), "")
C19: 46238 | D19: Ignacio Guerrero | E19: VJYL61 | F19: Ignacio | I19: 1403 | K19: Extraccion | L19: =IF(F19="CJ", I19*200, "") | M19: Extraccion | Q19: =IF(F19="CJ", COUNTIF(F$5:F19, "CJ"), "") | R19: =IF(F19="Ignacio", COUNTIF(F$5:F19, "Ignacio"), "") -> 2 | S19: =IF(F19="Tripulacion", COUNTIF(F$5:F19, "Tripulacion"), "") | T19: =IF(F19="ENAP carga", COUNTIF(F$5:F19, "ENAP carga"), "")
C20: 46239 | D20: Casa de Reposo Brisas | E20: VJYL61 | F20: CJ | G20: Brisas del raco parcela 36 Pirque | H20: 1100 | I20: 270 | J20: =H20*I20 -> 297000 | K20: Transferencia | L20: =IF(F20="CJ", I20*200, "") -> 54000 | M20: Factura | P20: Residencia Adulto Mayor Amor Eterno SpA - Rut 76.699.397-4 - Los Almendros Parcela2B Pirque | Q20: =IF(F20="CJ", COUNTIF(F$5:F20, "CJ"), "") -> 12 | R20: =IF(F20="Ignacio", COUNTIF(F$5:F20, "Ignacio"), "") | S20: =IF(F20="Tripulacion", COUNTIF(F$5:F20, "Tripulacion"), "") | T20: =IF(F20="ENAP carga", COUNTIF(F$5:F20, "ENAP carga"), "")
C21: 46241 | D21: Gastronomca Exquisite | E21: VJYL61 | F21: Tripulacion | G21: JP Alesaandri 114 Nuñoa | H21: 1000 | I21: 350 | J21: =H21*I21 -> 350000 | K21: Transferencia | L21: =IF(F21="CJ", I21*200, "") | M21: Factura | P21: Gastronomica Exquisite SpA - Rut: 77.714.318-2 - JP alessandri 114 Nuñoa | Q21: =IF(F21="CJ", COUNTIF(F$5:F21, "CJ"), "") | R21: =IF(F21="Ignacio", COUNTIF(F$5:F21, "Ignacio"), "") | S21: =IF(F21="Tripulacion", COUNTIF(F$5:F21, "Tripulacion"), "") -> 2 | T21: =IF(F21="ENAP carga", COUNTIF(F$5:F21, "ENAP carga"), "")
C22: 46241 | D22: Panaderia Maipu | E22: VJYL61 | F22: Tripulacion | G22: Av los carreras 706B, plaza de los porotos | H22: 1000 | I22: 109 | J22: =H22*I22 -> 109000 | K22: Transferencia | L22: =IF(F22="CJ", I22*200, "") | Q22: =IF(F22="CJ", COUNTIF(F$5:F22, "CJ"), "") | R22: =IF(F22="Ignacio", COUNTIF(F$5:F22, "Ignacio"), "") | S22: =IF(F22="Tripulacion", COUNTIF(F$5:F22, "Tripulacion"), "") -> 3 | T22: =IF(F22="ENAP carga", COUNTIF(F$5:F22, "ENAP carga"), "")
C23: 46242 | D23: Ignacio Guerrero | E23: VJYL61 | F23: Ignacio | I23: 2219 | K23: Extraccion | L23: =IF(F23="CJ", I23*200, "") | M23: Extraccion | Q23: =IF(F23="CJ", COUNTIF(F$5:F23, "CJ"), "") | R23: =IF(F23="Ignacio", COUNTIF(F$5:F23, "Ignacio"), "") -> 3 | S23: =IF(F23="Tripulacion", COUNTIF(F$5:F23, "Tripulacion"), "") | T23: =IF(F23="ENAP carga", COUNTIF(F$5:F23, "ENAP carga"), "")
C24: 46245 | D24: Eli Ciao Italia | E24: VJYL61 | F24: CJ | G24: Camino rinconada san Vicente parcela 38 | H24: 1100 | I24: 404 | J24: =H24*I24 -> 444400 | K24: Transferencia | L24: =IF(F24="CJ", I24*200, "") -> 80800 | Q24: =IF(F24="CJ", COUNTIF(F$5:F24, "CJ"), "") -> 13 | R24: =IF(F24="Ignacio", COUNTIF(F$5:F24, "Ignacio"), "") | S24: =IF(F24="Tripulacion", COUNTIF(F$5:F24, "Tripulacion"), "") | T24: =IF(F24="ENAP carga", COUNTIF(F$5:F24, "ENAP carga"), "")
C25: 46245 | D25: Javier Quiroz | E25: VJYL61 | F25: CJ | G25: Condominio majadas C parcela 5 | H25: 1100 | I25: 509 | J25: =H25*I25 -> 559900 | K25: Transferencia | L25: =IF(F25="CJ", I25*200, "") -> 101800 | Q25: =IF(F25="CJ", COUNTIF(F$5:F25, "CJ"), "") -> 14 | R25: =IF(F25="Ignacio", COUNTIF(F$5:F25, "Ignacio"), "") | S25: =IF(F25="Tripulacion", COUNTIF(F$5:F25, "Tripulacion"), "") | T25: =IF(F25="ENAP carga", COUNTIF(F$5:F25, "ENAP carga"), "")
C26: 46246 | D26: ENAP carga | E26: VJYL42 | F26: ENAP carga | I26: 11617 | K26: ENAP carga | L26: =IF(F26="CJ", I26*200, "") | M26: Guía N° 2356186 | N26: 3882182 | O26: 11617 | Q26: =IF(F26="CJ", COUNTIF(F$5:F26, "CJ"), "") | R26: =IF(F26="Ignacio", COUNTIF(F$5:F26, "Ignacio"), "") | S26: =IF(F26="Tripulacion", COUNTIF(F$5:F26, "Tripulacion"), "") | T26: =IF(F26="ENAP carga", COUNTIF(F$5:F26, "ENAP carga"), "") -> 2
C27: 46247 | D27: Ignacio Guerrero | E27: VJYL42 | F27: Ignacio | I27: 11539 | K27: Extraccion | L27: =IF(F27="CJ", I27*200, "") | M27: Extraccion | Q27: =IF(F27="CJ", COUNTIF(F$5:F27, "CJ"), "") | R27: =IF(F27="Ignacio", COUNTIF(F$5:F27, "Ignacio"), "") -> 4 | S27: =IF(F27="Tripulacion", COUNTIF(F$5:F27, "Tripulacion"), "") | T27: =IF(F27="ENAP carga", COUNTIF(F$5:F27, "ENAP carga"), "")
C28: 46247 | D28: ENAP carga | E28: VJYL61 | F28: ENAP carga | I28: 11481 | K28: ENAP carga | L28: =IF(F28="CJ", I28*200, "") | M28: Guía N° 2356453 | N28: 3836889 | O28: 11481 | Q28: =IF(F28="CJ", COUNTIF(F$5:F28, "CJ"), "") | R28: =IF(F28="Ignacio", COUNTIF(F$5:F28, "Ignacio"), "") | S28: =IF(F28="Tripulacion", COUNTIF(F$5:F28, "Tripulacion"), "") | T28: =IF(F28="ENAP carga", COUNTIF(F$5:F28, "ENAP carga"), "") -> 3
L29: =IF(F29="CJ", I29*200, "") | Q29: =IF(F29="CJ", COUNTIF(F$5:F29, "CJ"), "") | R29: =IF(F29="Ignacio", COUNTIF(F$5:F29, "Ignacio"), "") | S29: =IF(F29="Tripulacion", COUNTIF(F$5:F29, "Tripulacion"), "") | T29: =IF(F29="ENAP carga", COUNTIF(F$5:F29, "ENAP carga"), "")
L30: =IF(F30="CJ", I30*200, "") | Q30: =IF(F30="CJ", COUNTIF(F$5:F30, "CJ"), "") | R30: =IF(F30="Ignacio", COUNTIF(F$5:F30, "Ignacio"), "") | S30: =IF(F30="Tripulacion", COUNTIF(F$5:F30, "Tripulacion"), "") | T30: =IF(F30="ENAP carga", COUNTIF(F$5:F30, "ENAP carga"), "")
L31: =IF(F31="CJ", I31*200, "") | Q31: =IF(F31="CJ", COUNTIF(F$5:F31, "CJ"), "") | R31: =IF(F31="Ignacio", COUNTIF(F$5:F31, "Ignacio"), "") | S31: =IF(F31="Tripulacion", COUNTIF(F$5:F31, "Tripulacion"), "") | T31: =IF(F31="ENAP carga", COUNTIF(F$5:F31, "ENAP carga"), "")
L32: =IF(F32="CJ", I32*200, "") | Q32: =IF(F32="CJ", COUNTIF(F$5:F32, "CJ"), "") | R32: =IF(F32="Ignacio", COUNTIF(F$5:F32, "Ignacio"), "") | S32: =IF(F32="Tripulacion", COUNTIF(F$5:F32, "Tripulacion"), "") | T32: =IF(F32="ENAP carga", COUNTIF(F$5:F32, "ENAP carga"), "")
L33: =IF(F33="CJ", I33*200, "") | Q33: =IF(F33="CJ", COUNTIF(F$5:F33, "CJ"), "") | R33: =IF(F33="Ignacio", COUNTIF(F$5:F33, "Ignacio"), "") | S33: =IF(F33="Tripulacion", COUNTIF(F$5:F33, "Tripulacion"), "") | T33: =IF(F33="ENAP carga", COUNTIF(F$5:F33, "ENAP carga"), "")
L34: =IF(F34="CJ", I34*200, "") | Q34: =IF(F34="CJ", COUNTIF(F$5:F34, "CJ"), "") | R34: =IF(F34="Ignacio", COUNTIF(F$5:F34, "Ignacio"), "") | S34: =IF(F34="Tripulacion", COUNTIF(F$5:F34, "Tripulacion"), "") | T34: =IF(F34="ENAP carga", COUNTIF(F$5:F34, "ENAP carga"), "")
L35: =IF(F35="CJ", I35*200, "") | Q35: =IF(F35="CJ", COUNTIF(F$5:F35, "CJ"), "") | R35: =IF(F35="Ignacio", COUNTIF(F$5:F35, "Ignacio"), "") | S35: =IF(F35="Tripulacion", COUNTIF(F$5:F35, "Tripulacion"), "") | T35: =IF(F35="ENAP carga", COUNTIF(F$5:F35, "ENAP carga"), "")
L36: =IF(F36="CJ", I36*200, "") | Q36: =IF(F36="CJ", COUNTIF(F$5:F36, "CJ"), "") | R36: =IF(F36="Ignacio", COUNTIF(F$5:F36, "Ignacio"), "") | S36: =IF(F36="Tripulacion", COUNTIF(F$5:F36, "Tripulacion"), "") | T36: =IF(F36="ENAP carga", COUNTIF(F$5:F36, "ENAP carga"), "")
L37: =IF(F37="CJ", I37*200, "") | Q37: =IF(F37="CJ", COUNTIF(F$5:F37, "CJ"), "") | R37: =IF(F37="Ignacio", COUNTIF(F$5:F37, "Ignacio"), "") | S37: =IF(F37="Tripulacion", COUNTIF(F$5:F37, "Tripulacion"), "") | T37: =IF(F37="ENAP carga", COUNTIF(F$5:F37, "ENAP carga"), "")
L38: =IF(F38="CJ", I38*200, "") | Q38: =IF(F38="CJ", COUNTIF(F$5:F38, "CJ"), "") | R38: =IF(F38="Ignacio", COUNTIF(F$5:F38, "Ignacio"), "") | S38: =IF(F38="Tripulacion", COUNTIF(F$5:F38, "Tripulacion"), "") | T38: =IF(F38="ENAP carga", COUNTIF(F$5:F38, "ENAP carga"), "")
L39: =IF(F39="CJ", I39*200, "") | Q39: =IF(F39="CJ", COUNTIF(F$5:F39, "CJ"), "") | R39: =IF(F39="Ignacio", COUNTIF(F$5:F39, "Ignacio"), "") | S39: =IF(F39="Tripulacion", COUNTIF(F$5:F39, "Tripulacion"), "") | T39: =IF(F39="ENAP carga", COUNTIF(F$5:F39, "ENAP carga"), "")
L40: =IF(F40="CJ", I40*200, "") | Q40: =IF(F40="CJ", COUNTIF(F$5:F40, "CJ"), "") | R40: =IF(F40="Ignacio", COUNTIF(F$5:F40, "Ignacio"), "") | S40: =IF(F40="Tripulacion", COUNTIF(F$5:F40, "Tripulacion"), "") | T40: =IF(F40="ENAP carga", COUNTIF(F$5:F40, "ENAP carga"), "")
... L1000: =IF(F1000="CJ", I1000*200, "") | Q1000: =IF(F1000="CJ", COUNTIF(F$5:F1000, "CJ"), "") | R1000: =IF(F1000="Ignacio", COUNTIF(F$5:F1000, "Ignacio"), "") | S1000: =IF(F1000="Tripulacion", COUNTIF(F$5:F1000, "Tripulacion"), "") | T1000: =IF(F1000="ENAP carga", COUNTIF(F$5:F1000, "ENAP carga"), "")

Sheet CJ
B2: RESUMEN Y MOVIMIENTOS INDIVIDUALES: CJ (COMISIONISTA JC)
B3: Sincronización en tiempo real - Control de Comisiones y Ventas
B5: TOTAL LITROS | E5: TOTAL VENTAS ($) | H5: COMISIONES PAGADAS ($) | K5: COMISIONES PENDIENTES ($)
B6: =SUMIFS('Detalles movimientos'!I$5:I$1000, 'Detalles movimientos'!F$5:F$1000, "CJ") -> 5108.8 | E6: =SUMIFS('Detalles movimientos'!J$5:J$1000, 'Detalles movimientos'!F$5:F$1000, "CJ") -> 5282100 | H6: =SUMIFS('Detalles movimientos'!L$5:L$1000, 'Detalles movimientos'!F$5:F$1000, "CJ", 'Detalles movimientos'!M$5:M$1000, "*Comision Pagada*") -> 485760 | K6: =SUMIFS('Detalles movimientos'!L$5:L$1000, 'Detalles movimientos'!F$5:F$1000, "CJ", 'Detalles movimientos'!M$5:M$1000, "<>*Comision Pagada*") -> 536000
B9: PERÍODO COMISIONES PAGADAS: | D9: ="Del " & TEXT(_xlfn.MINIFS('Detalles movimientos'!C$5:C$1000, 'Detalles movimientos'!F$5:F$1000, "CJ", 'Detalles movimientos'!M$5:M$1000, "*Comision Pagada*"), "dd/mm/yyyy") & " al " & TEXT(_xlfn.MAXIFS('Detalles movimientos'!C$5:C$1000, 'Detalles movimientos'!F$5:F$1000, "CJ", 'Detalles movimientos'!M$5:M$1000, "*Comision Pagada*"), "dd/mm/yyyy") -> Del 27/07/2026 al 27/07/2026 | H9: PERÍODO COMISIONES PENDIENTES: | J9: ="Del " & TEXT(_xlfn.MINIFS('Detalles movimientos'!C$5:C$1000, 'Detalles movimientos'!F$5:F$1000, "CJ", 'Detalles movimientos'!M$5:M$1000, "<>*Comision Pagada*", 'Detalles movimientos'!C$5:C$1000, ">0"), "dd/mm/yyyy") & " al " & TEXT(_xlfn.MAXIFS('Detalles movimientos'!C$5:C$1000, 'Detalles movimientos'!F$5:F$1000, "CJ", 'Detalles movimientos'!M$5:M$1000, "<>*Comision Pagada*"), "dd/mm/yyyy") -> Del 28/07/2026 al 11/08/2026
B12: Fecha | C12: Nombre Cliente | D12: Camión | E12: Vende | F12: Dirección | G12: Precio | H12: Litros | I12: Total | J12: Medio de pago | K12: Comisiones | L12: Observación | M12: Facturación / Detalles
B13: =IFERROR(INDEX('Detalles movimientos'!C$5:C$1000, MATCH(1, 'Detalles movimientos'!$Q$5:$Q$1000, 0)), "") -> 46230 | C13: =IFERROR(INDEX('Detalles movimientos'!D$5:D$1000, MATCH(1, 'Detalles movimientos'!$Q$5:$Q$1000, 0)), "") -> Ricardo Brisas del Raco | D13: =IFERROR(INDEX('Detalles movimientos'!E$5:E$1000, MATCH(1, 'Detalles movimientos'!$Q$5:$Q$1000, 0)), "") -> VJYL61 | E13: =IFERROR(INDEX('Detalles movimientos'!F$5:F$1000, MATCH(1, 'Detalles movimientos'!$Q$5:$Q$1000, 0)), "") -> CJ | F13: =IFERROR(INDEX('Detalles movimientos'!G$5:G$1000, MATCH(1, 'Detalles movimientos'!$Q$5:$Q$1000, 0)), "") -> Brisas del Raco | G13: =IFERROR(INDEX('Detalles movimientos'!H$5:H$1000, MATCH(1, 'Detalles movimientos'!$Q$5:$Q$1000, 0)), "") -> 1000 | H13: =IFERROR(INDEX('Detalles movimientos'!I$5:I$1000, MATCH(1, 'Detalles movimientos'!$Q$5:$Q$1000, 0)), "") -> 179.2 | I13: =IFERROR(INDEX('Detalles movimientos'!J$5:J$1000, MATCH(1, 'Detalles movimientos'!$Q$5:$Q$1000, 0)), "") -> 179200 | ... L13: =IFERROR(INDEX('Detalles movimientos'!M$5:M$1000, MATCH(1, 'Detalles movimientos'!$Q$5:$Q$1000, 0)), "") -> Comision Pagada | M13: =IFERROR(INDEX('Detalles movimientos'!P$5:P$1000, MATCH(1, 'Detalles movimientos'!$Q$5:$Q$1000, 0)), "") -> 0
B14: =IFERROR(INDEX('Detalles movimientos'!C$5:C$1000, MATCH(2, 'Detalles movimientos'!$Q$5:$Q$1000, 0)), "") -> 46230 | C14: =IFERROR(INDEX('Detalles movimientos'!D$5:D$1000, MATCH(2, 'Detalles movimientos'!$Q$5:$Q$1000, 0)), "") -> Ale Turko | D14: =IFERROR(INDEX('Detalles movimientos'!E$5:E$1000, MATCH(2, 'Detalles movimientos'!$Q$5:$Q$1000, 0)), "") -> VJYL61 | E14: =IFERROR(INDEX('Detalles movimientos'!F$5:F$1000, MATCH(2, 'Detalles movimientos'!$Q$5:$Q$1000, 0)), "") -> CJ | F14: =IFERROR(INDEX('Detalles movimientos'!G$5:G$1000, MATCH(2, 'Detalles movimientos'!$Q$5:$Q$1000, 0)), "") -> 0 | G14: =IFERROR(INDEX('Detalles movimientos'!H$5:H$1000, MATCH(2, 'Detalles movimientos'!$Q$5:$Q$1000, 0)), "") -> 1000 | H14: =IFERROR(INDEX('Detalles movimientos'!I$5:I$1000, MATCH(2, 'Detalles movimientos'!$Q$5:$Q$1000, 0)), "") -> 518.1 | I14: =IFERROR(INDEX('Detalles movimientos'!J$5:J$1000, MATCH(2, 'Detalles movimientos'!$Q$5:$Q$1000, 0)), "") -> 518100 | ... L14: =IFERROR(INDEX('Detalles movimientos'!M$5:M$1000, MATCH(2, 'Detalles movimientos'!$Q$5:$Q$1000, 0)), "") -> Comision Pagada | M14: =IFERROR(INDEX('Detalles movimientos'!P$5:P$1000, MATCH(2, 'Detalles movimientos'!$Q$5:$Q$1000, 0)), "") -> 0
B15: =IFERROR(INDEX('Detalles movimientos'!C$5:C$1000, MATCH(3, 'Detalles movimientos'!$Q$5:$Q$1000, 0)), "") -> 46230 | C15: =IFERROR(INDEX('Detalles movimientos'!D$5:D$1000, MATCH(3, 'Detalles movimientos'!$Q$5:$Q$1000, 0)), "") -> Tirua | D15: =IFERROR(INDEX('Detalles movimientos'!E$5:E$1000, MATCH(3, 'Detalles movimientos'!$Q$5:$Q$1000, 0)), "") -> VJYL61 | E15: =IFERROR(INDEX('Detalles movimientos'!F$5:F$1000, MATCH(3, 'Detalles movimientos'!$Q$5:$Q$1000, 0)), "") -> CJ | F15: =IFERROR(INDEX('Detalles movimientos'!G$5:G$1000, MATCH(3, 'Detalles movimientos'!$Q$5:$Q$1000, 0)), "") -> 0 | G15: =IFERROR(INDEX('Detalles movimientos'!H$5:H$1000, MATCH(3, 'Detalles movimientos'!$Q$5:$Q$1000, 0)), "") -> 1000 | H15: =IFERROR(INDEX('Detalles movimientos'!I$5:I$1000, MATCH(3, 'Detalles movimientos'!$Q$5:$Q$1000, 0)), "") -> 488.2 | I15: =IFERROR(INDEX('Detalles movimientos'!J$5:J$1000, MATCH(3, 'Detalles movimientos'!$Q$5:$Q$1000, 0)), "") -> 488200 | ... L15: =IFERROR(INDEX('Detalles movimientos'!M$5:M$1000, MATCH(3, 'Detalles movimientos'!$Q$5:$Q$1000, 0)), "") -> Comision Pagada | M15: =IFERROR(INDEX('Detalles movimientos'!P$5:P$1000, MATCH(3, 'Detalles movimientos'!$Q$5:$Q$1000, 0)), "") -> 0
B16: =IFERROR(INDEX('Detalles movimientos'!C$5:C$1000, MATCH(4, 'Detalles movimientos'!$Q$5:$Q$1000, 0)), "") -> 46230 | C16: =IFERROR(INDEX('Detalles movimientos'!D$5:D$1000, MATCH(4, 'Detalles movimientos'!$Q$5:$Q$1000, 0)), "") -> Ciao Italia | D16: =IFERROR(INDEX('Detalles movimientos'!E$5:E$1000, MATCH(4, 'Detalles movimientos'!$Q$5:$Q$1000, 0)), "") -> VJYL61 | E16: =IFERROR(INDEX('Detalles movimientos'!F$5:F$1000, MATCH(4, 'Detalles movimientos'!$Q$5:$Q$1000, 0)), "") -> CJ | F16: =IFERROR(INDEX('Detalles movimientos'!G$5:G$1000, MATCH(4, 'Detalles movimientos'!$Q$5:$Q$1000, 0)), "") -> 0 | G16: =IFERROR(INDEX('Detalles movimientos'!H$5:H$1000, MATCH(4, 'Detalles movimientos'!$Q$5:$Q$1000, 0)), "") -> 1000 | H16: =IFERROR(INDEX('Detalles movimientos'!I$5:I$1000, MATCH(4, 'Detalles movimientos'!$Q$5:$Q$1000, 0)), "") -> 500.3 | I16: =IFERROR(INDEX('Detalles movimientos'!J$5:J$1000, MATCH(4, 'Detalles movimientos'!$Q$5:$Q$1000, 0)), "") -> 500300 | ... L16: =IFERROR(INDEX('Detalles movimientos'!M$5:M$1000, MATCH(4, 'Detalles movimientos'!$Q$5:$Q$1000, 0)), "") -> Comision Pagada | M16: =IFERROR(INDEX('Detalles movimientos'!P$5:P$1000, MATCH(4, 'Detalles movimientos'!$Q$5:$Q$1000, 0)), "") -> 0
B17: =IFERROR(INDEX('Detalles movimientos'!C$5:C$1000, MATCH(5, 'Detalles movimientos'!$Q$5:$Q$1000, 0)), "") -> 46230 | C17: =IFERROR(INDEX('Detalles movimientos'!D$5:D$1000, MATCH(5, 'Detalles movimientos'!$Q$5:$Q$1000, 0)), "") -> Claudio Ulloa | D17: =IFERROR(INDEX('Detalles movimientos'!E$5:E$1000, MATCH(5, 'Detalles movimientos'!$Q$5:$Q$1000, 0)), "") -> VJYL61 | E17: =IFERROR(INDEX('Detalles movimientos'!F$5:F$1000, MATCH(5, 'Detalles movimientos'!$Q$5:$Q$1000, 0)), "") -> CJ | F17: =IFERROR(INDEX('Detalles movimientos'!G$5:G$1000, MATCH(5, 'Detalles movimientos'!$Q$5:$Q$1000, 0)), "") -> 0 | G17: =IFERROR(INDEX('Detalles movimientos'!H$5:H$1000, MATCH(5, 'Detalles movimientos'!$Q$5:$Q$1000, 0)), "") -> 1000 | H17: =IFERROR(INDEX('Detalles movimientos'!I$5:I$1000, MATCH(5, 'Detalles movimientos'!$Q$5:$Q$1000, 0)), "") -> 237.9 | I17: =IFERROR(INDEX('Detalles movimientos'!J$5:J$1000, MATCH(5, 'Detalles movimientos'!$Q$5:$Q$1000, 0)), "") -> 237900 | ... L17: =IFERROR(INDEX('Detalles movimientos'!M$5:M$1000, MATCH(5, 'Detalles movimientos'!$Q$5:$Q$1000, 0)), "") -> Comision Pagada | M17: =IFERROR(INDEX('Detalles movimientos'!P$5:P$1000, MATCH(5, 'Detalles movimientos'!$Q$5:$Q$1000, 0)), "") -> 0
B18: =IFERROR(INDEX('Detalles movimientos'!C$5:C$1000, MATCH(6, 'Detalles movimientos'!$Q$5:$Q$1000, 0)), "") -> 46230 | C18: =IFERROR(INDEX('Detalles movimientos'!D$5:D$1000, MATCH(6, 'Detalles movimientos'!$Q$5:$Q$1000, 0)), "") -> Francisco Ulloa | D18: =IFERROR(INDEX('Detalles movimientos'!E$5:E$1000, MATCH(6, 'Detalles movimientos'!$Q$5:$Q$1000, 0)), "") -> VJYL61 | E18: =IFERROR(INDEX('Detalles movimientos'!F$5:F$1000, MATCH(6, 'Detalles movimientos'!$Q$5:$Q$1000, 0)), "") -> CJ | F18: =IFERROR(INDEX('Detalles movimientos'!G$5:G$1000, MATCH(6, 'Detalles movimientos'!$Q$5:$Q$1000, 0)), "") -> 0 | G18: =IFERROR(INDEX('Detalles movimientos'!H$5:H$1000, MATCH(6, 'Detalles movimientos'!$Q$5:$Q$1000, 0)), "") -> 1000 | H18: =IFERROR(INDEX('Detalles movimientos'!I$5:I$1000, MATCH(6, 'Detalles movimientos'!$Q$5:$Q$1000, 0)), "") -> 205.1 | I18: =IFERROR(INDEX('Detalles movimientos'!J$5:J$1000, MATCH(6, 'Detalles movimientos'!$Q$5:$Q$1000, 0)), "") -> 205100 | ... L18: =IFERROR(INDEX('Detalles movimientos'!M$5:M$1000, MATCH(6, 'Detalles movimientos'!$Q$5:$Q$1000, 0)), "") -> Comision Pagada | M18: =IFERROR(INDEX('Detalles movimientos'!P$5:P$1000, MATCH(6, 'Detalles movimientos'!$Q$5:$Q$1000, 0)), "") -> 0
B19: =IFERROR(INDEX('Detalles movimientos'!C$5:C$1000, MATCH(7, 'Detalles movimientos'!$Q$5:$Q$1000, 0)), "") -> 46230 | C19: =IFERROR(INDEX('Detalles movimientos'!D$5:D$1000, MATCH(7, 'Detalles movimientos'!$Q$5:$Q$1000, 0)), "") -> Alicia Pavez | D19: =IFERROR(INDEX('Detalles movimientos'!E$5:E$1000, MATCH(7, 'Detalles movimientos'!$Q$5:$Q$1000, 0)), "") -> VJYL61 | E19: =IFERROR(INDEX('Detalles movimientos'!F$5:F$1000, MATCH(7, 'Detalles movimientos'!$Q$5:$Q$1000, 0)), "") -> CJ | F19: =IFERROR(INDEX('Detalles movimientos'!G$5:G$1000, MATCH(7, 'Detalles movimientos'!$Q$5:$Q$1000, 0)), "") -> 0 | G19: =IFERROR(INDEX('Detalles movimientos'!H$5:H$1000, MATCH(7, 'Detalles movimientos'!$Q$5:$Q$1000, 0)), "") -> 1000 | H19: =IFERROR(INDEX('Detalles movimientos'!I$5:I$1000, MATCH(7, 'Detalles movimientos'!$Q$5:$Q$1000, 0)), "") -> 300 | I19: =IFERROR(INDEX('Detalles movimientos'!J$5:J$1000, MATCH(7, 'Detalles movimientos'!$Q$5:$Q$1000, 0)), "") -> 300000 | ... L19: =IFERROR(INDEX('Detalles movimientos'!M$5:M$1000, MATCH(7, 'Detalles movimientos'!$Q$5:$Q$1000, 0)), "") -> Comision Pagada | M19: =IFERROR(INDEX('Detalles movimientos'!P$5:P$1000, MATCH(7, 'Detalles movimientos'!$Q$5:$Q$1000, 0)), "") -> 2428.8
B20: =IFERROR(INDEX('Detalles movimientos'!C$5:C$1000, MATCH(8, 'Detalles movimientos'!$Q$5:$Q$1000, 0)), "") -> 46231 | C20: =IFERROR(INDEX('Detalles movimientos'!D$5:D$1000, MATCH(8, 'Detalles movimientos'!$Q$5:$Q$1000, 0)), "") -> Vanessa | D20: =IFERROR(INDEX('Detalles movimientos'!E$5:E$1000, MATCH(8, 'Detalles movimientos'!$Q$5:$Q$1000, 0)), "") -> VJYL61 | E20: =IFERROR(INDEX('Detalles movimientos'!F$5:F$1000, MATCH(8, 'Detalles movimientos'!$Q$5:$Q$1000, 0)), "") -> CJ | F20: =IFERROR(INDEX('Detalles movimientos'!G$5:G$1000, MATCH(8, 'Detalles movimientos'!$Q$5:$Q$1000, 0)), "") -> 0 | G20: =IFERROR(INDEX('Detalles movimientos'!H$5:H$1000, MATCH(8, 'Detalles movimientos'!$Q$5:$Q$1000, 0)), "") -> 1000 | H20: =IFERROR(INDEX('Detalles movimientos'!I$5:I$1000, MATCH(8, 'Detalles movimientos'!$Q$5:$Q$1000, 0)), "") -> 200 | I20: =IFERROR(INDEX('Detalles movimientos'!J$5:J$1000, MATCH(8, 'Detalles movimientos'!$Q$5:$Q$1000, 0)), "") -> 200000 | ... L20: =IFERROR(INDEX('Detalles movimientos'!M$5:M$1000, MATCH(8, 'Detalles movimientos'!$Q$5:$Q$1000, 0)), "") -> 0 | M20: =IFERROR(INDEX('Detalles movimientos'!P$5:P$1000, MATCH(8, 'Detalles movimientos'!$Q$5:$Q$1000, 0)), "") -> 0
B21: =IFERROR(INDEX('Detalles movimientos'!C$5:C$1000, MATCH(9, 'Detalles movimientos'!$Q$5:$Q$1000, 0)), "") -> 46233 | C21: =IFERROR(INDEX('Detalles movimientos'!D$5:D$1000, MATCH(9, 'Detalles movimientos'!$Q$5:$Q$1000, 0)), "") -> Simon | D21: =IFERROR(INDEX('Detalles movimientos'!E$5:E$1000, MATCH(9, 'Detalles movimientos'!$Q$5:$Q$1000, 0)), "") -> VJYL61 | E21: =IFERROR(INDEX('Detalles movimientos'!F$5:F$1000, MATCH(9, 'Detalles movimientos'!$Q$5:$Q$1000, 0)), "") -> CJ | F21: =IFERROR(INDEX('Detalles movimientos'!G$5:G$1000, MATCH(9, 'Detalles movimientos'!$Q$5:$Q$1000, 0)), "") -> Camino el Chalaco 66B | G21: =IFERROR(INDEX('Detalles movimientos'!H$5:H$1000, MATCH(9, 'Detalles movimientos'!$Q$5:$Q$1000, 0)), "") -> 1000 | H21: =IFERROR(INDEX('Detalles movimientos'!I$5:I$1000, MATCH(9, 'Detalles movimientos'!$Q$5:$Q$1000, 0)), "") -> 747 | I21: =IFERROR(INDEX('Detalles movimientos'!J$5:J$1000, MATCH(9, 'Detalles movimientos'!$Q$5:$Q$1000, 0)), "") -> 747000 | ... L21: =IFERROR(INDEX('Detalles movimientos'!M$5:M$1000, MATCH(9, 'Detalles movimientos'!$Q$5:$Q$1000, 0)), "") -> Factura | M21: =IFERROR(INDEX('Detalles movimientos'!P$5:P$1000, MATCH(9, 'Detalles movimientos'!$Q$5:$Q$1000, 0)), "") -> Ebal spa - RUT: 77.625.623-4 - Av Gabriela 3264 La Pintana - Giro Construccion
B22: =IFERROR(INDEX('Detalles movimientos'!C$5:C$1000, MATCH(10, 'Detalles movimientos'!$Q$5:$Q$1000, 0)), "") -> 46237 | C22: =IFERROR(INDEX('Detalles movimientos'!D$5:D$1000, MATCH(10, 'Detalles movimientos'!$Q$5:$Q$1000, 0)), "") -> Manuel Vergara Ricci | D22: =IFERROR(INDEX('Detalles movimientos'!E$5:E$1000, MATCH(10, 'Detalles movimientos'!$Q$5:$Q$1000, 0)), "") -> VJYL61 | E22: =IFERROR(INDEX('Detalles movimientos'!F$5:F$1000, MATCH(10, 'Detalles movimientos'!$Q$5:$Q$1000, 0)), "") -> CJ | F22: =IFERROR(INDEX('Detalles movimientos'!G$5:G$1000, MATCH(10, 'Detalles movimientos'!$Q$5:$Q$1000, 0)), "") -> Avenida Virginia subercaseaux 4175 (parcela 15) | G22: =IFERROR(INDEX('Detalles movimientos'!H$5:H$1000, MATCH(10, 'Detalles movimientos'!$Q$5:$Q$1000, 0)), "") -> 1100 | H22: =IFERROR(INDEX('Detalles movimientos'!I$5:I$1000, MATCH(10, 'Detalles movimientos'!$Q$5:$Q$1000, 0)), "") -> 200 | I22: =IFERROR(INDEX('Detalles movimientos'!J$5:J$1000, MATCH(10, 'Detalles movimientos'!$Q$5:$Q$1000, 0)), "") -> 220000 | ... L22: =IFERROR(INDEX('Detalles movimientos'!M$5:M$1000, MATCH(10, 'Detalles movimientos'!$Q$5:$Q$1000, 0)), "") -> 0 | M22: =IFERROR(INDEX('Detalles movimientos'!P$5:P$1000, MATCH(10, 'Detalles movimientos'!$Q$5:$Q$1000, 0)), "") -> 0
B23: =IFERROR(INDEX('Detalles movimientos'!C$5:C$1000, MATCH(11, 'Detalles movimientos'!$Q$5:$Q$1000, 0)), "") -> 46237 | C23: =IFERROR(INDEX('Detalles movimientos'!D$5:D$1000, MATCH(11, 'Detalles movimientos'!$Q$5:$Q$1000, 0)), "") -> Gabriela Rojas | D23: =IFERROR(INDEX('Detalles movimientos'!E$5:E$1000, MATCH(11, 'Detalles movimientos'!$Q$5:$Q$1000, 0)), "") -> VJYL61 | E23: =IFERROR(INDEX('Detalles movimientos'!F$5:F$1000, MATCH(11, 'Detalles movimientos'!$Q$5:$Q$1000, 0)), "") -> CJ | F23: =IFERROR(INDEX('Detalles movimientos'!G$5:G$1000, MATCH(11, 'Detalles movimientos'!$Q$5:$Q$1000, 0)), "") -> Camino de las flores 1262 Pirque | G23: =IFERROR(INDEX('Detalles movimientos'!H$5:H$1000, MATCH(11, 'Detalles movimientos'!$Q$5:$Q$1000, 0)), "") -> 1100 | H23: =IFERROR(INDEX('Detalles movimientos'!I$5:I$1000, MATCH(11, 'Detalles movimientos'!$Q$5:$Q$1000, 0)), "") -> 350 | I23: =IFERROR(INDEX('Detalles movimientos'!J$5:J$1000, MATCH(11, 'Detalles movimientos'!$Q$5:$Q$1000, 0)), "") -> 385000 | ... L23: =IFERROR(INDEX('Detalles movimientos'!M$5:M$1000, MATCH(11, 'Detalles movimientos'!$Q$5:$Q$1000, 0)), "") -> Quedó saldo de $35 mil para mañana | M23: =IFERROR(INDEX('Detalles movimientos'!P$5:P$1000, MATCH(11, 'Detalles movimientos'!$Q$5:$Q$1000, 0)), "") -> 0
B24: =IFERROR(INDEX('Detalles movimientos'!C$5:C$1000, MATCH(12, 'Detalles movimientos'!$Q$5:$Q$1000, 0)), "") -> 46239 | C24: =IFERROR(INDEX('Detalles movimientos'!D$5:D$1000, MATCH(12, 'Detalles movimientos'!$Q$5:$Q$1000, 0)), "") -> Casa de Reposo Brisas | D24: =IFERROR(INDEX('Detalles movimientos'!E$5:E$1000, MATCH(12, 'Detalles movimientos'!$Q$5:$Q$1000, 0)), "") -> VJYL61 | E24: =IFERROR(INDEX('Detalles movimientos'!F$5:F$1000, MATCH(12, 'Detalles movimientos'!$Q$5:$Q$1000, 0)), "") -> CJ | F24: =IFERROR(INDEX('Detalles movimientos'!G$5:G$1000, MATCH(12, 'Detalles movimientos'!$Q$5:$Q$1000, 0)), "") -> Brisas del raco parcela 36 Pirque | G24: =IFERROR(INDEX('Detalles movimientos'!H$5:H$1000, MATCH(12, 'Detalles movimientos'!$Q$5:$Q$1000, 0)), "") -> 1100 | H24: =IFERROR(INDEX('Detalles movimientos'!I$5:I$1000, MATCH(12, 'Detalles movimientos'!$Q$5:$Q$1000, 0)), "") -> 270 | I24: =IFERROR(INDEX('Detalles movimientos'!J$5:J$1000, MATCH(12, 'Detalles movimientos'!$Q$5:$Q$1000, 0)), "") -> 297000 | ... L24: =IFERROR(INDEX('Detalles movimientos'!M$5:M$1000, MATCH(12, 'Detalles movimientos'!$Q$5:$Q$1000, 0)), "") -> Factura | M24: =IFERROR(INDEX('Detalles movimientos'!P$5:P$1000, MATCH(12, 'Detalles movimientos'!$Q$5:$Q$1000, 0)), "") -> Residencia Adulto Mayor Amor Eterno SpA - Rut 76.699.397-4 - Los Almendros Parcela2B Pirque
B25: =IFERROR(INDEX('Detalles movimientos'!C$5:C$1000, MATCH(13, 'Detalles movimientos'!$Q$5:$Q$1000, 0)), "") -> 46245 | C25: =IFERROR(INDEX('Detalles movimientos'!D$5:D$1000, MATCH(13, 'Detalles movimientos'!$Q$5:$Q$1000, 0)), "") -> Eli Ciao Italia | D25: =IFERROR(INDEX('Detalles movimientos'!E$5:E$1000, MATCH(13, 'Detalles movimientos'!$Q$5:$Q$1000, 0)), "") -> VJYL61 | E25: =IFERROR(INDEX('Detalles movimientos'!F$5:F$1000, MATCH(13, 'Detalles movimientos'!$Q$5:$Q$1000, 0)), "") -> CJ | F25: =IFERROR(INDEX('Detalles movimientos'!G$5:G$1000, MATCH(13, 'Detalles movimientos'!$Q$5:$Q$1000, 0)), "") -> Camino rinconada san Vicente parcela 38 | G25: =IFERROR(INDEX('Detalles movimientos'!H$5:H$1000, MATCH(13, 'Detalles movimientos'!$Q$5:$Q$1000, 0)), "") -> 1100 | H25: =IFERROR(INDEX('Detalles movimientos'!I$5:I$1000, MATCH(13, 'Detalles movimientos'!$Q$5:$Q$1000, 0)), "") -> 404 | I25: =IFERROR(INDEX('Detalles movimientos'!J$5:J$1000, MATCH(13, 'Detalles movimientos'!$Q$5:$Q$1000, 0)), "") -> 444400 | ... L25: =IFERROR(INDEX('Detalles movimientos'!M$5:M$1000, MATCH(13, 'Detalles movimientos'!$Q$5:$Q$1000, 0)), "") -> 0 | M25: =IFERROR(INDEX('Detalles movimientos'!P$5:P$1000, MATCH(13, 'Detalles movimientos'!$Q$5:$Q$1000, 0)), "") -> 0
B26: =IFERROR(INDEX('Detalles movimientos'!C$5:C$1000, MATCH(14, 'Detalles movimientos'!$Q$5:$Q$1000, 0)), "") -> 46245 | C26: =IFERROR(INDEX('Detalles movimientos'!D$5:D$1000, MATCH(14, 'Detalles movimientos'!$Q$5:$Q$1000, 0)), "") -> Javier Quiroz | D26: =IFERROR(INDEX('Detalles movimientos'!E$5:E$1000, MATCH(14, 'Detalles movimientos'!$Q$5:$Q$1000, 0)), "") -> VJYL61 | E26: =IFERROR(INDEX('Detalles movimientos'!F$5:F$1000, MATCH(14, 'Detalles movimientos'!$Q$5:$Q$1000, 0)), "") -> CJ | F26: =IFERROR(INDEX('Detalles movimientos'!G$5:G$1000, MATCH(14, 'Detalles movimientos'!$Q$5:$Q$1000, 0)), "") -> Condominio majadas C parcela 5 | G26: =IFERROR(INDEX('Detalles movimientos'!H$5:H$1000, MATCH(14, 'Detalles movimientos'!$Q$5:$Q$1000, 0)), "") -> 1100 | H26: =IFERROR(INDEX('Detalles movimientos'!I$5:I$1000, MATCH(14, 'Detalles movimientos'!$Q$5:$Q$1000, 0)), "") -> 509 | I26: =IFERROR(INDEX('Detalles movimientos'!J$5:J$1000, MATCH(14, 'Detalles movimientos'!$Q$5:$Q$1000, 0)), "") -> 559900 | ... L26: =IFERROR(INDEX('Detalles movimientos'!M$5:M$1000, MATCH(14, 'Detalles movimientos'!$Q$5:$Q$1000, 0)), "") -> 0 | M26: =IFERROR(INDEX('Detalles movimientos'!P$5:P$1000, MATCH(14, 'Detalles movimientos'!$Q$5:$Q$1000, 0)), "") -> 0
B27: =IFERROR(INDEX('Detalles movimientos'!C$5:C$1000, MATCH(15, 'Detalles movimientos'!$Q$5:$Q$1000, 0)), "") | C27: =IFERROR(INDEX('Detalles movimientos'!D$5:D$1000, MATCH(15, 'Detalles movimientos'!$Q$5:$Q$1000, 0)), "") | D27: =IFERROR(INDEX('Detalles movimientos'!E$5:E$1000, MATCH(15, 'Detalles movimientos'!$Q$5:$Q$1000, 0)), "") | E27: =IFERROR(INDEX('Detalles movimientos'!F$5:F$1000, MATCH(15, 'Detalles movimientos'!$Q$5:$Q$1000, 0)), "") | F27: =IFERROR(INDEX('Detalles movimientos'!G$5:G$1000, MATCH(15, 'Detalles movimientos'!$Q$5:$Q$1000, 0)), "") | G27: =IFERROR(INDEX('Detalles movimientos'!H$5:H$1000, MATCH(15, 'Detalles movimientos'!$Q$5:$Q$1000, 0)), "") | H27: =IFERROR(INDEX('Detalles movimientos'!I$5:I$1000, MATCH(15, 'Detalles movimientos'!$Q$5:$Q$1000, 0)), "") | I27: =IFERROR(INDEX('Detalles movimientos'!J$5:J$1000, MATCH(15, 'Detalles movimientos'!$Q$5:$Q$1000, 0)), "") | ... L27: =IFERROR(INDEX('Detalles movimientos'!M$5:M$1000, MATCH(15, 'Detalles movimientos'!$Q$5:$Q$1000, 0)), "") | M27: =IFERROR(INDEX('Detalles movimientos'!P$5:P$1000, MATCH(15, 'Detalles movimientos'!$Q$5:$Q$1000, 0)), "")
B28: =IFERROR(INDEX('Detalles movimientos'!C$5:C$1000, MATCH(16, 'Detalles movimientos'!$Q$5:$Q$1000, 0)), "") | C28: =IFERROR(INDEX('Detalles movimientos'!D$5:D$1000, MATCH(16, 'Detalles movimientos'!$Q$5:$Q$1000, 0)), "") | D28: =IFERROR(INDEX('Detalles movimientos'!E$5:E$1000, MATCH(16, 'Detalles movimientos'!$Q$5:$Q$1000, 0)), "") | E28: =IFERROR(INDEX('Detalles movimientos'!F$5:F$1000, MATCH(16, 'Detalles movimientos'!$Q$5:$Q$1000, 0)), "") | F28: =IFERROR(INDEX('Detalles movimientos'!G$5:G$1000, MATCH(16, 'Detalles movimientos'!$Q$5:$Q$1000, 0)), "") | G28: =IFERROR(INDEX('Detalles movimientos'!H$5:H$1000, MATCH(16, 'Detalles movimientos'!$Q$5:$Q$1000, 0)), "") | H28: =IFERROR(INDEX('Detalles movimientos'!I$5:I$1000, MATCH(16, 'Detalles movimientos'!$Q$5:$Q$1000, 0)), "") | I28: =IFERROR(INDEX('Detalles movimientos'!J$5:J$1000, MATCH(16, 'Detalles movimientos'!$Q$5:$Q$1000, 0)), "") | ... L28: =IFERROR(INDEX('Detalles movimientos'!M$5:M$1000, MATCH(16, 'Detalles movimientos'!$Q$5:$Q$1000, 0)), "") | M28: =IFERROR(INDEX('Detalles movimientos'!P$5:P$1000, MATCH(16, 'Detalles movimientos'!$Q$5:$Q$1000, 0)), "")
B29: =IFERROR(INDEX('Detalles movimientos'!C$5:C$1000, MATCH(17, 'Detalles movimientos'!$Q$5:$Q$1000, 0)), "") | C29: =IFERROR(INDEX('Detalles movimientos'!D$5:D$1000, MATCH(17, 'Detalles movimientos'!$Q$5:$Q$1000, 0)), "") | D29: =IFERROR(INDEX('Detalles movimientos'!E$5:E$1000, MATCH(17, 'Detalles movimientos'!$Q$5:$Q$1000, 0)), "") | E29: =IFERROR(INDEX('Detalles movimientos'!F$5:F$1000, MATCH(17, 'Detalles movimientos'!$Q$5:$Q$1000, 0)), "") | F29: =IFERROR(INDEX('Detalles movimientos'!G$5:G$1000, MATCH(17, 'Detalles movimientos'!$Q$5:$Q$1000, 0)), "") | G29: =IFERROR(INDEX('Detalles movimientos'!H$5:H$1000, MATCH(17, 'Detalles movimientos'!$Q$5:$Q$1000, 0)), "") | H29: =IFERROR(INDEX('Detalles movimientos'!I$5:I$1000, MATCH(17, 'Detalles movimientos'!$Q$5:$Q$1000, 0)), "") | I29: =IFERROR(INDEX('Detalles movimientos'!J$5:J$1000, MATCH(17, 'Detalles movimientos'!$Q$5:$Q$1000, 0)), "") | ... L29: =IFERROR(INDEX('Detalles movimientos'!M$5:M$1000, MATCH(17, 'Detalles movimientos'!$Q$5:$Q$1000, 0)), "") | M29: =IFERROR(INDEX('Detalles movimientos'!P$5:P$1000, MATCH(17, 'Detalles movimientos'!$Q$5:$Q$1000, 0)), "")
B30: =IFERROR(INDEX('Detalles movimientos'!C$5:C$1000, MATCH(18, 'Detalles movimientos'!$Q$5:$Q$1000, 0)), "") | C30: =IFERROR(INDEX('Detalles movimientos'!D$5:D$1000, MATCH(18, 'Detalles movimientos'!$Q$5:$Q$1000, 0)), "") | D30: =IFERROR(INDEX('Detalles movimientos'!E$5:E$1000, MATCH(18, 'Detalles movimientos'!$Q$5:$Q$1000, 0)), "") | E30: =IFERROR(INDEX('Detalles movimientos'!F$5:F$1000, MATCH(18, 'Detalles movimientos'!$Q$5:$Q$1000, 0)), "") | F30: =IFERROR(INDEX('Detalles movimientos'!G$5:G$1000, MATCH(18, 'Detalles movimientos'!$Q$5:$Q$1000, 0)), "") | G30: =IFERROR(INDEX('Detalles movimientos'!H$5:H$1000, MATCH(18, 'Detalles movimientos'!$Q$5:$Q$1000, 0)), "") | H30: =IFERROR(INDEX('Detalles movimientos'!I$5:I$1000, MATCH(18, 'Detalles movimientos'!$Q$5:$Q$1000, 0)), "") | I30: =IFERROR(INDEX('Detalles movimientos'!J$5:J$1000, MATCH(18, 'Detalles movimientos'!$Q$5:$Q$1000, 0)), "") | ... L30: =IFERROR(INDEX('Detalles movimientos'!M$5:M$1000, MATCH(18, 'Detalles movimientos'!$Q$5:$Q$1000, 0)), "") | M30: =IFERROR(INDEX('Detalles movimientos'!P$5:P$1000, MATCH(18, 'Detalles movimientos'!$Q$5:$Q$1000, 0)), "")
B31: =IFERROR(INDEX('Detalles movimientos'!C$5:C$1000, MATCH(19, 'Detalles movimientos'!$Q$5:$Q$1000, 0)), "") | C31: =IFERROR(INDEX('Detalles movimientos'!D$5:D$1000, MATCH(19, 'Detalles movimientos'!$Q$5:$Q$1000, 0)), "") | D31: =IFERROR(INDEX('Detalles movimientos'!E$5:E$1000, MATCH(19, 'Detalles movimientos'!$Q$5:$Q$1000, 0)), "") | E31: =IFERROR(INDEX('Detalles movimientos'!F$5:F$1000, MATCH(19, 'Detalles movimientos'!$Q$5:$Q$1000, 0)), "") | F31: =IFERROR(INDEX('Detalles movimientos'!G$5:G$1000, MATCH(19, 'Detalles movimientos'!$Q$5:$Q$1000, 0)), "") | G31: =IFERROR(INDEX('Detalles movimientos'!H$5:H$1000, MATCH(19, 'Detalles movimientos'!$Q$5:$Q$1000, 0)), "") | H31: =IFERROR(INDEX('Detalles movimientos'!I$5:I$1000, MATCH(19, 'Detalles movimientos'!$Q$5:$Q$1000, 0)), "") | I31: =IFERROR(INDEX('Detalles movimientos'!J$5:J$1000, MATCH(19, 'Detalles movimientos'!$Q$5:$Q$1000, 0)), "") | ... L31: =IFERROR(INDEX('Detalles movimientos'!M$5:M$1000, MATCH(19, 'Detalles movimientos'!$Q$5:$Q$1000, 0)), "") | M31: =IFERROR(INDEX('Detalles movimientos'!P$5:P$1000, MATCH(19, 'Detalles movimientos'!$Q$5:$Q$1000, 0)), "")
B32: =IFERROR(INDEX('Detalles movimientos'!C$5:C$1000, MATCH(20, 'Detalles movimientos'!$Q$5:$Q$1000, 0)), "") | C32: =IFERROR(INDEX('Detalles movimientos'!D$5:D$1000, MATCH(20, 'Detalles movimientos'!$Q$5:$Q$1000, 0)), "") | D32: =IFERROR(INDEX('Detalles movimientos'!E$5:E$1000, MATCH(20, 'Detalles movimientos'!$Q$5:$Q$1000, 0)), "") | E32: =IFERROR(INDEX('Detalles movimientos'!F$5:F$1000, MATCH(20, 'Detalles movimientos'!$Q$5:$Q$1000, 0)), "") | F32: =IFERROR(INDEX('Detalles movimientos'!G$5:G$1000, MATCH(20, 'Detalles movimientos'!$Q$5:$Q$1000, 0)), "") | G32: =IFERROR(INDEX('Detalles movimientos'!H$5:H$1000, MATCH(20, 'Detalles movimientos'!$Q$5:$Q$1000, 0)), "") | H32: =IFERROR(INDEX('Detalles movimientos'!I$5:I$1000, MATCH(20, 'Detalles movimientos'!$Q$5:$Q$1000, 0)), "") | I32: =IFERROR(INDEX('Detalles movimientos'!J$5:J$1000, MATCH(20, 'Detalles movimientos'!$Q$5:$Q$1000, 0)), "") | ... L32: =IFERROR(INDEX('Detalles movimientos'!M$5:M$1000, MATCH(20, 'Detalles movimientos'!$Q$5:$Q$1000, 0)), "") | M32: =IFERROR(INDEX('Detalles movimientos'!P$5:P$1000, MATCH(20, 'Detalles movimientos'!$Q$5:$Q$1000, 0)), "")
B33: =IFERROR(INDEX('Detalles movimientos'!C$5:C$1000, MATCH(21, 'Detalles movimientos'!$Q$5:$Q$1000, 0)), "") | C33: =IFERROR(INDEX('Detalles movimientos'!D$5:D$1000, MATCH(21, 'Detalles movimientos'!$Q$5:$Q$1000, 0)), "") | D33: =IFERROR(INDEX('Detalles movimientos'!E$5:E$1000, MATCH(21, 'Detalles movimientos'!$Q$5:$Q$1000, 0)), "") | E33: =IFERROR(INDEX('Detalles movimientos'!F$5:F$1000, MATCH(21, 'Detalles movimientos'!$Q$5:$Q$1000, 0)), "") | F33: =IFERROR(INDEX('Detalles movimientos'!G$5:G$1000, MATCH(21, 'Detalles movimientos'!$Q$5:$Q$1000, 0)), "") | G33: =IFERROR(INDEX('Detalles movimientos'!H$5:H$1000, MATCH(21, 'Detalles movimientos'!$Q$5:$Q$1000, 0)), "") | H33: =IFERROR(INDEX('Detalles movimientos'!I$5:I$1000, MATCH(21, 'Detalles movimientos'!$Q$5:$Q$1000, 0)), "") | I33: =IFERROR(INDEX('Detalles movimientos'!J$5:J$1000, MATCH(21, 'Detalles movimientos'!$Q$5:$Q$1000, 0)), "") | ... L33: =IFERROR(INDEX('Detalles movimientos'!M$5:M$1000, MATCH(21, 'Detalles movimientos'!$Q$5:$Q$1000, 0)), "") | M33: =IFERROR(INDEX('Detalles movimientos'!P$5:P$1000, MATCH(21, 'Detalles movimientos'!$Q$5:$Q$1000, 0)), "")
B34: =IFERROR(INDEX('Detalles movimientos'!C$5:C$1000, MATCH(22, 'Detalles movimientos'!$Q$5:$Q$1000, 0)), "") | C34: =IFERROR(INDEX('Detalles movimientos'!D$5:D$1000, MATCH(22, 'Detalles movimientos'!$Q$5:$Q$1000, 0)), "") | D34: =IFERROR(INDEX('Detalles movimientos'!E$5:E$1000, MATCH(22, 'Detalles movimientos'!$Q$5:$Q$1000, 0)), "") | E34: =IFERROR(INDEX('Detalles movimientos'!F$5:F$1000, MATCH(22, 'Detalles movimientos'!$Q$5:$Q$1000, 0)), "") | F34: =IFERROR(INDEX('Detalles movimientos'!G$5:G$1000, MATCH(22, 'Detalles movimientos'!$Q$5:$Q$1000, 0)), "") | G34: =IFERROR(INDEX('Detalles movimientos'!H$5:H$1000, MATCH(22, 'Detalles movimientos'!$Q$5:$Q$1000, 0)), "") | H34: =IFERROR(INDEX('Detalles movimientos'!I$5:I$1000, MATCH(22, 'Detalles movimientos'!$Q$5:$Q$1000, 0)), "") | I34: =IFERROR(INDEX('Detalles movimientos'!J$5:J$1000, MATCH(22, 'Detalles movimientos'!$Q$5:$Q$1000, 0)), "") | ... L34: =IFERROR(INDEX('Detalles movimientos'!M$5:M$1000, MATCH(22, 'Detalles movimientos'!$Q$5:$Q$1000, 0)), "") | M34: =IFERROR(INDEX('Detalles movimientos'!P$5:P$1000, MATCH(22, 'Detalles movimientos'!$Q$5:$Q$1000, 0)), "")
B35: =IFERROR(INDEX('Detalles movimientos'!C$5:C$1000, MATCH(23, 'Detalles movimientos'!$Q$5:$Q$1000, 0)), "") | C35: =IFERROR(INDEX('Detalles movimientos'!D$5:D$1000, MATCH(23, 'Detalles movimientos'!$Q$5:$Q$1000, 0)), "") | D35: =IFERROR(INDEX('Detalles movimientos'!E$5:E$1000, MATCH(23, 'Detalles movimientos'!$Q$5:$Q$1000, 0)), "") | E35: =IFERROR(INDEX('Detalles movimientos'!F$5:F$1000, MATCH(23, 'Detalles movimientos'!$Q$5:$Q$1000, 0)), "") | F35: =IFERROR(INDEX('Detalles movimientos'!G$5:G$1000, MATCH(23, 'Detalles movimientos'!$Q$5:$Q$1000, 0)), "") | G35: =IFERROR(INDEX('Detalles movimientos'!H$5:H$1000, MATCH(23, 'Detalles movimientos'!$Q$5:$Q$1000, 0)), "") | H35: =IFERROR(INDEX('Detalles movimientos'!I$5:I$1000, MATCH(23, 'Detalles movimientos'!$Q$5:$Q$1000, 0)), "") | I35: =IFERROR(INDEX('Detalles movimientos'!J$5:J$1000, MATCH(23, 'Detalles movimientos'!$Q$5:$Q$1000, 0)), "") | ... L35: =IFERROR(INDEX('Detalles movimientos'!M$5:M$1000, MATCH(23, 'Detalles movimientos'!$Q$5:$Q$1000, 0)), "") | M35: =IFERROR(INDEX('Detalles movimientos'!P$5:P$1000, MATCH(23, 'Detalles movimientos'!$Q$5:$Q$1000, 0)), "")
B36: =IFERROR(INDEX('Detalles movimientos'!C$5:C$1000, MATCH(24, 'Detalles movimientos'!$Q$5:$Q$1000, 0)), "") | C36: =IFERROR(INDEX('Detalles movimientos'!D$5:D$1000, MATCH(24, 'Detalles movimientos'!$Q$5:$Q$1000, 0)), "") | D36: =IFERROR(INDEX('Detalles movimientos'!E$5:E$1000, MATCH(24, 'Detalles movimientos'!$Q$5:$Q$1000, 0)), "") | E36: =IFERROR(INDEX('Detalles movimientos'!F$5:F$1000, MATCH(24, 'Detalles movimientos'!$Q$5:$Q$1000, 0)), "") | F36: =IFERROR(INDEX('Detalles movimientos'!G$5:G$1000, MATCH(24, 'Detalles movimientos'!$Q$5:$Q$1000, 0)), "") | G36: =IFERROR(INDEX('Detalles movimientos'!H$5:H$1000, MATCH(24, 'Detalles movimientos'!$Q$5:$Q$1000, 0)), "") | H36: =IFERROR(INDEX('Detalles movimientos'!I$5:I$1000, MATCH(24, 'Detalles movimientos'!$Q$5:$Q$1000, 0)), "") | I36: =IFERROR(INDEX('Detalles movimientos'!J$5:J$1000, MATCH(24, 'Detalles movimientos'!$Q$5:$Q$1000, 0)), "") | ... L36: =IFERROR(INDEX('Detalles movimientos'!M$5:M$1000, MATCH(24, 'Detalles movimientos'!$Q$5:$Q$1000, 0)), "") | M36: =IFERROR(INDEX('Detalles movimientos'!P$5:P$1000, MATCH(24, 'Detalles movimientos'!$Q$5:$Q$1000, 0)), "")
B37: =IFERROR(INDEX('Detalles movimientos'!C$5:C$1000, MATCH(25, 'Detalles movimientos'!$Q$5:$Q$1000, 0)), "") | C37: =IFERROR(INDEX('Detalles movimientos'!D$5:D$1000, MATCH(25, 'Detalles movimientos'!$Q$5:$Q$1000, 0)), "") | D37: =IFERROR(INDEX('Detalles movimientos'!E$5:E$1000, MATCH(25, 'Detalles movimientos'!$Q$5:$Q$1000, 0)), "") | E37: =IFERROR(INDEX('Detalles movimientos'!F$5:F$1000, MATCH(25, 'Detalles movimientos'!$Q$5:$Q$1000, 0)), "") | F37: =IFERROR(INDEX('Detalles movimientos'!G$5:G$1000, MATCH(25, 'Detalles movimientos'!$Q$5:$Q$1000, 0)), "") | G37: =IFERROR(INDEX('Detalles movimientos'!H$5:H$1000, MATCH(25, 'Detalles movimientos'!$Q$5:$Q$1000, 0)), "") | H37: =IFERROR(INDEX('Detalles movimientos'!I$5:I$1000, MATCH(25, 'Detalles movimientos'!$Q$5:$Q$1000, 0)), "") | I37: =IFERROR(INDEX('Detalles movimientos'!J$5:J$1000, MATCH(25, 'Detalles movimientos'!$Q$5:$Q$1000, 0)), "") | ... L37: =IFERROR(INDEX('Detalles movimientos'!M$5:M$1000, MATCH(25, 'Detalles movimientos'!$Q$5:$Q$1000, 0)), "") | M37: =IFERROR(INDEX('Detalles movimientos'!P$5:P$1000, MATCH(25, 'Detalles movimientos'!$Q$5:$Q$1000, 0)), "")
B38: =IFERROR(INDEX('Detalles movimientos'!C$5:C$1000, MATCH(26, 'Detalles movimientos'!$Q$5:$Q$1000, 0)), "") | C38: =IFERROR(INDEX('Detalles movimientos'!D$5:D$1000, MATCH(26, 'Detalles movimientos'!$Q$5:$Q$1000, 0)), "") | D38: =IFERROR(INDEX('Detalles movimientos'!E$5:E$1000, MATCH(26, 'Detalles movimientos'!$Q$5:$Q$1000, 0)), "") | E38: =IFERROR(INDEX('Detalles movimientos'!F$5:F$1000, MATCH(26, 'Detalles movimientos'!$Q$5:$Q$1000, 0)), "") | F38: =IFERROR(INDEX('Detalles movimientos'!G$5:G$1000, MATCH(26, 'Detalles movimientos'!$Q$5:$Q$1000, 0)), "") | G38: =IFERROR(INDEX('Detalles movimientos'!H$5:H$1000, MATCH(26, 'Detalles movimientos'!$Q$5:$Q$1000, 0)), "") | H38: =IFERROR(INDEX('Detalles movimientos'!I$5:I$1000, MATCH(26, 'Detalles movimientos'!$Q$5:$Q$1000, 0)), "") | I38: =IFERROR(INDEX('Detalles movimientos'!J$5:J$1000, MATCH(26, 'Detalles movimientos'!$Q$5:$Q$1000, 0)), "") | ... L38: =IFERROR(INDEX('Detalles movimientos'!M$5:M$1000, MATCH(26, 'Detalles movimientos'!$Q$5:$Q$1000, 0)), "") | M38: =IFERROR(INDEX('Detalles movimientos'!P$5:P$1000, MATCH(26, 'Detalles movimientos'!$Q$5:$Q$1000, 0)), "")
B39: =IFERROR(INDEX('Detalles movimientos'!C$5:C$1000, MATCH(27, 'Detalles movimientos'!$Q$5:$Q$1000, 0)), "") | C39: =IFERROR(INDEX('Detalles movimientos'!D$5:D$1000, MATCH(27, 'Detalles movimientos'!$Q$5:$Q$1000, 0)), "") | D39: =IFERROR(INDEX('Detalles movimientos'!E$5:E$1000, MATCH(27, 'Detalles movimientos'!$Q$5:$Q$1000, 0)), "") | E39: =IFERROR(INDEX('Detalles movimientos'!F$5:F$1000, MATCH(27, 'Detalles movimientos'!$Q$5:$Q$1000, 0)), "") | F39: =IFERROR(INDEX('Detalles movimientos'!G$5:G$1000, MATCH(27, 'Detalles movimientos'!$Q$5:$Q$1000, 0)), "") | G39: =IFERROR(INDEX('Detalles movimientos'!H$5:H$1000, MATCH(27, 'Detalles movimientos'!$Q$5:$Q$1000, 0)), "") | H39: =IFERROR(INDEX('Detalles movimientos'!I$5:I$1000, MATCH(27, 'Detalles movimientos'!$Q$5:$Q$1000, 0)), "") | I39: =IFERROR(INDEX('Detalles movimientos'!J$5:J$1000, MATCH(27, 'Detalles movimientos'!$Q$5:$Q$1000, 0)), "") | ... L39: =IFERROR(INDEX('Detalles movimientos'!M$5:M$1000, MATCH(27, 'Detalles movimientos'!$Q$5:$Q$1000, 0)), "") | M39: =IFERROR(INDEX('Detalles movimientos'!P$5:P$1000, MATCH(27, 'Detalles movimientos'!$Q$5:$Q$1000, 0)), "")
B40: =IFERROR(INDEX('Detalles movimientos'!C$5:C$1000, MATCH(28, 'Detalles movimientos'!$Q$5:$Q$1000, 0)), "") | C40: =IFERROR(INDEX('Detalles movimientos'!D$5:D$1000, MATCH(28, 'Detalles movimientos'!$Q$5:$Q$1000, 0)), "") | D40: =IFERROR(INDEX('Detalles movimientos'!E$5:E$1000, MATCH(28, 'Detalles movimientos'!$Q$5:$Q$1000, 0)), "") | E40: =IFERROR(INDEX('Detalles movimientos'!F$5:F$1000, MATCH(28, 'Detalles movimientos'!$Q$5:$Q$1000, 0)), "") | F40: =IFERROR(INDEX('Detalles movimientos'!G$5:G$1000, MATCH(28, 'Detalles movimientos'!$Q$5:$Q$1000, 0)), "") | G40: =IFERROR(INDEX('Detalles movimientos'!H$5:H$1000, MATCH(28, 'Detalles movimientos'!$Q$5:$Q$1000, 0)), "") | H40: =IFERROR(INDEX('Detalles movimientos'!I$5:I$1000, MATCH(28, 'Detalles movimientos'!$Q$5:$Q$1000, 0)), "") | I40: =IFERROR(INDEX('Detalles movimientos'!J$5:J$1000, MATCH(28, 'Detalles movimientos'!$Q$5:$Q$1000, 0)), "") | ... L40: =IFERROR(INDEX('Detalles movimientos'!M$5:M$1000, MATCH(28, 'Detalles movimientos'!$Q$5:$Q$1000, 0)), "") | M40: =IFERROR(INDEX('Detalles movimientos'!P$5:P$1000, MATCH(28, 'Detalles movimientos'!$Q$5:$Q$1000, 0)), "")
B41: =IFERROR(INDEX('Detalles movimientos'!C$5:C$1000, MATCH(29, 'Detalles movimientos'!$Q$5:$Q$1000, 0)), "") | C41: =IFERROR(INDEX('Detalles movimientos'!D$5:D$1000, MATCH(29, 'Detalles movimientos'!$Q$5:$Q$1000, 0)), "") | D41: =IFERROR(INDEX('Detalles movimientos'!E$5:E$1000, MATCH(29, 'Detalles movimientos'!$Q$5:$Q$1000, 0)), "") | E41: =IFERROR(INDEX('Detalles movimientos'!F$5:F$1000, MATCH(29, 'Detalles movimientos'!$Q$5:$Q$1000, 0)), "") | F41: =IFERROR(INDEX('Detalles movimientos'!G$5:G$1000, MATCH(29, 'Detalles movimientos'!$Q$5:$Q$1000, 0)), "") | G41: =IFERROR(INDEX('Detalles movimientos'!H$5:H$1000, MATCH(29, 'Detalles movimientos'!$Q$5:$Q$1000, 0)), "") | H41: =IFERROR(INDEX('Detalles movimientos'!I$5:I$1000, MATCH(29, 'Detalles movimientos'!$Q$5:$Q$1000, 0)), "") | I41: =IFERROR(INDEX('Detalles movimientos'!J$5:J$1000, MATCH(29, 'Detalles movimientos'!$Q$5:$Q$1000, 0)), "") | ... L41: =IFERROR(INDEX('Detalles movimientos'!M$5:M$1000, MATCH(29, 'Detalles movimientos'!$Q$5:$Q$1000, 0)), "") | M41: =IFERROR(INDEX('Detalles movimientos'!P$5:P$1000, MATCH(29, 'Detalles movimientos'!$Q$5:$Q$1000, 0)), "")
B42: =IFERROR(INDEX('Detalles movimientos'!C$5:C$1000, MATCH(30, 'Detalles movimientos'!$Q$5:$Q$1000, 0)), "") | C42: =IFERROR(INDEX('Detalles movimientos'!D$5:D$1000, MATCH(30, 'Detalles movimientos'!$Q$5:$Q$1000, 0)), "") | D42: =IFERROR(INDEX('Detalles movimientos'!E$5:E$1000, MATCH(30, 'Detalles movimientos'!$Q$5:$Q$1000, 0)), "") | E42: =IFERROR(INDEX('Detalles movimientos'!F$5:F$1000, MATCH(30, 'Detalles movimientos'!$Q$5:$Q$1000, 0)), "") | F42: =IFERROR(INDEX('Detalles movimientos'!G$5:G$1000, MATCH(30, 'Detalles movimientos'!$Q$5:$Q$1000, 0)), "") | G42: =IFERROR(INDEX('Detalles movimientos'!H$5:H$1000, MATCH(30, 'Detalles movimientos'!$Q$5:$Q$1000, 0)), "") | H42: =IFERROR(INDEX('Detalles movimientos'!I$5:I$1000, MATCH(30, 'Detalles movimientos'!$Q$5:$Q$1000, 0)), "") | I42: =IFERROR(INDEX('Detalles movimientos'!J$5:J$1000, MATCH(30, 'Detalles movimientos'!$Q$5:$Q$1000, 0)), "") | ... L42: =IFERROR(INDEX('Detalles movimientos'!M$5:M$1000, MATCH(30, 'Detalles movimientos'!$Q$5:$Q$1000, 0)), "") | M42: =IFERROR(INDEX('Detalles movimientos'!P$5:P$1000, MATCH(30, 'Detalles movimientos'!$Q$5:$Q$1000, 0)), "")
B43: =IFERROR(INDEX('Detalles movimientos'!C$5:C$1000, MATCH(31, 'Detalles movimientos'!$Q$5:$Q$1000, 0)), "") | C43: =IFERROR(INDEX('Detalles movimientos'!D$5:D$1000, MATCH(31, 'Detalles movimientos'!$Q$5:$Q$1000, 0)), "") | D43: =IFERROR(INDEX('Detalles movimientos'!E$5:E$1000, MATCH(31, 'Detalles movimientos'!$Q$5:$Q$1000, 0)), "") | E43: =IFERROR(INDEX('Detalles movimientos'!F$5:F$1000, MATCH(31, 'Detalles movimientos'!$Q$5:$Q$1000, 0)), "") | F43: =IFERROR(INDEX('Detalles movimientos'!G$5:G$1000, MATCH(31, 'Detalles movimientos'!$Q$5:$Q$1000, 0)), "") | G43: =IFERROR(INDEX('Detalles movimientos'!H$5:H$1000, MATCH(31, 'Detalles movimientos'!$Q$5:$Q$1000, 0)), "") | H43: =IFERROR(INDEX('Detalles movimientos'!I$5:I$1000, MATCH(31, 'Detalles movimientos'!$Q$5:$Q$1000, 0)), "") | I43: =IFERROR(INDEX('Detalles movimientos'!J$5:J$1000, MATCH(31, 'Detalles movimientos'!$Q$5:$Q$1000, 0)), "") | ... L43: =IFERROR(INDEX('Detalles movimientos'!M$5:M$1000, MATCH(31, 'Detalles movimientos'!$Q$5:$Q$1000, 0)), "") | M43: =IFERROR(INDEX('Detalles movimientos'!P$5:P$1000, MATCH(31, 'Detalles movimientos'!$Q$5:$Q$1000, 0)), "")
B44: =IFERROR(INDEX('Detalles movimientos'!C$5:C$1000, MATCH(32, 'Detalles movimientos'!$Q$5:$Q$1000, 0)), "") | C44: =IFERROR(INDEX('Detalles movimientos'!D$5:D$1000, MATCH(32, 'Detalles movimientos'!$Q$5:$Q$1000, 0)), "") | D44: =IFERROR(INDEX('Detalles movimientos'!E$5:E$1000, MATCH(32, 'Detalles movimientos'!$Q$5:$Q$1000, 0)), "") | E44: =IFERROR(INDEX('Detalles movimientos'!F$5:F$1000, MATCH(32, 'Detalles movimientos'!$Q$5:$Q$1000, 0)), "") | F44: =IFERROR(INDEX('Detalles movimientos'!G$5:G$1000, MATCH(32, 'Detalles movimientos'!$Q$5:$Q$1000, 0)), "") | G44: =IFERROR(INDEX('Detalles movimientos'!H$5:H$1000, MATCH(32, 'Detalles movimientos'!$Q$5:$Q$1000, 0)), "") | H44: =IFERROR(INDEX('Detalles movimientos'!I$5:I$1000, MATCH(32, 'Detalles movimientos'!$Q$5:$Q$1000, 0)), "") | I44: =IFERROR(INDEX('Detalles movimientos'!J$5:J$1000, MATCH(32, 'Detalles movimientos'!$Q$5:$Q$1000, 0)), "") | ... L44: =IFERROR(INDEX('Detalles movimientos'!M$5:M$1000, MATCH(32, 'Detalles movimientos'!$Q$5:$Q$1000, 0)), "") | M44: =IFERROR(INDEX('Detalles movimientos'!P$5:P$1000, MATCH(32, 'Detalles movimientos'!$Q$5:$Q$1000, 0)), "")
B45: =IFERROR(INDEX('Detalles movimientos'!C$5:C$1000, MATCH(33, 'Detalles movimientos'!$Q$5:$Q$1000, 0)), "") | C45: =IFERROR(INDEX('Detalles movimientos'!D$5:D$1000, MATCH(33, 'Detalles movimientos'!$Q$5:$Q$1000, 0)), "") | D45: =IFERROR(INDEX('Detalles movimientos'!E$5:E$1000, MATCH(33, 'Detalles movimientos'!$Q$5:$Q$1000, 0)), "") | E45: =IFERROR(INDEX('Detalles movimientos'!F$5:F$1000, MATCH(33, 'Detalles movimientos'!$Q$5:$Q$1000, 0)), "") | F45: =IFERROR(INDEX('Detalles movimientos'!G$5:G$1000, MATCH(33, 'Detalles movimientos'!$Q$5:$Q$1000, 0)), "") | G45: =IFERROR(INDEX('Detalles movimientos'!H$5:H$1000, MATCH(33, 'Detalles movimientos'!$Q$5:$Q$1000, 0)), "") | H45: =IFERROR(INDEX('Detalles movimientos'!I$5:I$1000, MATCH(33, 'Detalles movimientos'!$Q$5:$Q$1000, 0)), "") | I45: =IFERROR(INDEX('Detalles movimientos'!J$5:J$1000, MATCH(33, 'Detalles movimientos'!$Q$5:$Q$1000, 0)), "") | ... L45: =IFERROR(INDEX('Detalles movimientos'!M$5:M$1000, MATCH(33, 'Detalles movimientos'!$Q$5:$Q$1000, 0)), "") | M45: =IFERROR(INDEX('Detalles movimientos'!P$5:P$1000, MATCH(33, 'Detalles movimientos'!$Q$5:$Q$1000, 0)), "")
B46: =IFERROR(INDEX('Detalles movimientos'!C$5:C$1000, MATCH(34, 'Detalles movimientos'!$Q$5:$Q$1000, 0)), "") | C46: =IFERROR(INDEX('Detalles movimientos'!D$5:D$1000, MATCH(34, 'Detalles movimientos'!$Q$5:$Q$1000, 0)), "") | D46: =IFERROR(INDEX('Detalles movimientos'!E$5:E$1000, MATCH(34, 'Detalles movimientos'!$Q$5:$Q$1000, 0)), "") | E46: =IFERROR(INDEX('Detalles movimientos'!F$5:F$1000, MATCH(34, 'Detalles movimientos'!$Q$5:$Q$1000, 0)), "") | F46: =IFERROR(INDEX('Detalles movimientos'!G$5:G$1000, MATCH(34, 'Detalles movimientos'!$Q$5:$Q$1000, 0)), "") | G46: =IFERROR(INDEX('Detalles movimientos'!H$5:H$1000, MATCH(34, 'Detalles movimientos'!$Q$5:$Q$1000, 0)), "") | H46: =IFERROR(INDEX('Detalles movimientos'!I$5:I$1000, MATCH(34, 'Detalles movimientos'!$Q$5:$Q$1000, 0)), "") | I46: =IFERROR(INDEX('Detalles movimientos'!J$5:J$1000, MATCH(34, 'Detalles movimientos'!$Q$5:$Q$1000, 0)), "") | ... L46: =IFERROR(INDEX('Detalles movimientos'!M$5:M$1000, MATCH(34, 'Detalles movimientos'!$Q$5:$Q$1000, 0)), "") | M46: =IFERROR(INDEX('Detalles movimientos'!P$5:P$1000, MATCH(34, 'Detalles movimientos'!$Q$5:$Q$1000, 0)), "")
B47: =IFERROR(INDEX('Detalles movimientos'!C$5:C$1000, MATCH(35, 'Detalles movimientos'!$Q$5:$Q$1000, 0)), "") | C47: =IFERROR(INDEX('Detalles movimientos'!D$5:D$1000, MATCH(35, 'Detalles movimientos'!$Q$5:$Q$1000, 0)), "") | D47: =IFERROR(INDEX('Detalles movimientos'!E$5:E$1000, MATCH(35, 'Detalles movimientos'!$Q$5:$Q$1000, 0)), "") | E47: =IFERROR(INDEX('Detalles movimientos'!F$5:F$1000, MATCH(35, 'Detalles movimientos'!$Q$5:$Q$1000, 0)), "") | F47: =IFERROR(INDEX('Detalles movimientos'!G$5:G$1000, MATCH(35, 'Detalles movimientos'!$Q$5:$Q$1000, 0)), "") | G47: =IFERROR(INDEX('Detalles movimientos'!H$5:H$1000, MATCH(35, 'Detalles movimientos'!$Q$5:$Q$1000, 0)), "") | H47: =IFERROR(INDEX('Detalles movimientos'!I$5:I$1000, MATCH(35, 'Detalles movimientos'!$Q$5:$Q$1000, 0)), "") | I47: =IFERROR(INDEX('Detalles movimientos'!J$5:J$1000, MATCH(35, 'Detalles movimientos'!$Q$5:$Q$1000, 0)), "") | ... L47: =IFERROR(INDEX('Detalles movimientos'!M$5:M$1000, MATCH(35, 'Detalles movimientos'!$Q$5:$Q$1000, 0)), "") | M47: =IFERROR(INDEX('Detalles movimientos'!P$5:P$1000, MATCH(35, 'Detalles movimientos'!$Q$5:$Q$1000, 0)), "")
B48: =IFERROR(INDEX('Detalles movimientos'!C$5:C$1000, MATCH(36, 'Detalles movimientos'!$Q$5:$Q$1000, 0)), "") | C48: =IFERROR(INDEX('Detalles movimientos'!D$5:D$1000, MATCH(36, 'Detalles movimientos'!$Q$5:$Q$1000, 0)), "") | D48: =IFERROR(INDEX('Detalles movimientos'!E$5:E$1000, MATCH(36, 'Detalles movimientos'!$Q$5:$Q$1000, 0)), "") | E48: =IFERROR(INDEX('Detalles movimientos'!F$5:F$1000, MATCH(36, 'Detalles movimientos'!$Q$5:$Q$1000, 0)), "") | F48: =IFERROR(INDEX('Detalles movimientos'!G$5:G$1000, MATCH(36, 'Detalles movimientos'!$Q$5:$Q$1000, 0)), "") | G48: =IFERROR(INDEX('Detalles movimientos'!H$5:H$1000, MATCH(36, 'Detalles movimientos'!$Q$5:$Q$1000, 0)), "") | H48: =IFERROR(INDEX('Detalles movimientos'!I$5:I$1000, MATCH(36, 'Detalles movimientos'!$Q$5:$Q$1000, 0)), "") | I48: =IFERROR(INDEX('Detalles movimientos'!J$5:J$1000, MATCH(36, 'Detalles movimientos'!$Q$5:$Q$1000, 0)), "") | ... L48: =IFERROR(INDEX('Detalles movimientos'!M$5:M$1000, MATCH(36, 'Detalles movimientos'!$Q$5:$Q$1000, 0)), "") | M48: =IFERROR(INDEX('Detalles movimientos'!P$5:P$1000, MATCH(36, 'Detalles movimientos'!$Q$5:$Q$1000, 0)), "")
B49: =IFERROR(INDEX('Detalles movimientos'!C$5:C$1000, MATCH(37, 'Detalles movimientos'!$Q$5:$Q$1000, 0)), "") | C49: =IFERROR(INDEX('Detalles movimientos'!D$5:D$1000, MATCH(37, 'Detalles movimientos'!$Q$5:$Q$1000, 0)), "") | D49: =IFERROR(INDEX('Detalles movimientos'!E$5:E$1000, MATCH(37, 'Detalles movimientos'!$Q$5:$Q$1000, 0)), "") | E49: =IFERROR(INDEX('Detalles movimientos'!F$5:F$1000, MATCH(37, 'Detalles movimientos'!$Q$5:$Q$1000, 0)), "") | F49: =IFERROR(INDEX('Detalles movimientos'!G$5:G$1000, MATCH(37, 'Detalles movimientos'!$Q$5:$Q$1000, 0)), "") | G49: =IFERROR(INDEX('Detalles movimientos'!H$5:H$1000, MATCH(37, 'Detalles movimientos'!$Q$5:$Q$1000, 0)), "") | H49: =IFERROR(INDEX('Detalles movimientos'!I$5:I$1000, MATCH(37, 'Detalles movimientos'!$Q$5:$Q$1000, 0)), "") | I49: =IFERROR(INDEX('Detalles movimientos'!J$5:J$1000, MATCH(37, 'Detalles movimientos'!$Q$5:$Q$1000, 0)), "") | ... L49: =IFERROR(INDEX('Detalles movimientos'!M$5:M$1000, MATCH(37, 'Detalles movimientos'!$Q$5:$Q$1000, 0)), "") | M49: =IFERROR(INDEX('Detalles movimientos'!P$5:P$1000, MATCH(37, 'Detalles movimientos'!$Q$5:$Q$1000, 0)), "")
B50: =IFERROR(INDEX('Detalles movimientos'!C$5:C$1000, MATCH(38, 'Detalles movimientos'!$Q$5:$Q$1000, 0)), "") | C50: =IFERROR(INDEX('Detalles movimientos'!D$5:D$1000, MATCH(38, 'Detalles movimientos'!$Q$5:$Q$1000, 0)), "") | D50: =IFERROR(INDEX('Detalles movimientos'!E$5:E$1000, MATCH(38, 'Detalles movimientos'!$Q$5:$Q$1000, 0)), "") | E50: =IFERROR(INDEX('Detalles movimientos'!F$5:F$1000, MATCH(38, 'Detalles movimientos'!$Q$5:$Q$1000, 0)), "") | F50: =IFERROR(INDEX('Detalles movimientos'!G$5:G$1000, MATCH(38, 'Detalles movimientos'!$Q$5:$Q$1000, 0)), "") | G50: =IFERROR(INDEX('Detalles movimientos'!H$5:H$1000, MATCH(38, 'Detalles movimientos'!$Q$5:$Q$1000, 0)), "") | H50: =IFERROR(INDEX('Detalles movimientos'!I$5:I$1000, MATCH(38, 'Detalles movimientos'!$Q$5:$Q$1000, 0)), "") | I50: =IFERROR(INDEX('Detalles movimientos'!J$5:J$1000, MATCH(38, 'Detalles movimientos'!$Q$5:$Q$1000, 0)), "") | ... L50: =IFERROR(INDEX('Detalles movimientos'!M$5:M$1000, MATCH(38, 'Detalles movimientos'!$Q$5:$Q$1000, 0)), "") | M50: =IFERROR(INDEX('Detalles movimientos'!P$5:P$1000, MATCH(38, 'Detalles movimientos'!$Q$5:$Q$1000, 0)), "")
B51: =IFERROR(INDEX('Detalles movimientos'!C$5:C$1000, MATCH(39, 'Detalles movimientos'!$Q$5:$Q$1000, 0)), "") | C51: =IFERROR(INDEX('Detalles movimientos'!D$5:D$1000, MATCH(39, 'Detalles movimientos'!$Q$5:$Q$1000, 0)), "") | D51: =IFERROR(INDEX('Detalles movimientos'!E$5:E$1000, MATCH(39, 'Detalles movimientos'!$Q$5:$Q$1000, 0)), "") | E51: =IFERROR(INDEX('Detalles movimientos'!F$5:F$1000, MATCH(39, 'Detalles movimientos'!$Q$5:$Q$1000, 0)), "") | F51: =IFERROR(INDEX('Detalles movimientos'!G$5:G$1000, MATCH(39, 'Detalles movimientos'!$Q$5:$Q$1000, 0)), "") | G51: =IFERROR(INDEX('Detalles movimientos'!H$5:H$1000, MATCH(39, 'Detalles movimientos'!$Q$5:$Q$1000, 0)), "") | H51: =IFERROR(INDEX('Detalles movimientos'!I$5:I$1000, MATCH(39, 'Detalles movimientos'!$Q$5:$Q$1000, 0)), "") | I51: =IFERROR(INDEX('Detalles movimientos'!J$5:J$1000, MATCH(39, 'Detalles movimientos'!$Q$5:$Q$1000, 0)), "") | ... L51: =IFERROR(INDEX('Detalles movimientos'!M$5:M$1000, MATCH(39, 'Detalles movimientos'!$Q$5:$Q$1000, 0)), "") | M51: =IFERROR(INDEX('Detalles movimientos'!P$5:P$1000, MATCH(39, 'Detalles movimientos'!$Q$5:$Q$1000, 0)), "")
B52: =IFERROR(INDEX('Detalles movimientos'!C$5:C$1000, MATCH(40, 'Detalles movimientos'!$Q$5:$Q$1000, 0)), "") | C52: =IFERROR(INDEX('Detalles movimientos'!D$5:D$1000, MATCH(40, 'Detalles movimientos'!$Q$5:$Q$1000, 0)), "") | D52: =IFERROR(INDEX('Detalles movimientos'!E$5:E$1000, MATCH(40, 'Detalles movimientos'!$Q$5:$Q$1000, 0)), "") | E52: =IFERROR(INDEX('Detalles movimientos'!F$5:F$1000, MATCH(40, 'Detalles movimientos'!$Q$5:$Q$1000, 0)), "") | F52: =IFERROR(INDEX('Detalles movimientos'!G$5:G$1000, MATCH(40, 'Detalles movimientos'!$Q$5:$Q$1000, 0)), "") | G52: =IFERROR(INDEX('Detalles movimientos'!H$5:H$1000, MATCH(40, 'Detalles movimientos'!$Q$5:$Q$1000, 0)), "") | H52: =IFERROR(INDEX('Detalles movimientos'!I$5:I$1000, MATCH(40, 'Detalles movimientos'!$Q$5:$Q$1000, 0)), "") | I52: =IFERROR(INDEX('Detalles movimientos'!J$5:J$1000, MATCH(40, 'Detalles movimientos'!$Q$5:$Q$1000, 0)), "") | ... L52: =IFERROR(INDEX('Detalles movimientos'!M$5:M$1000, MATCH(40, 'Detalles movimientos'!$Q$5:$Q$1000, 0)), "") | M52: =IFERROR(INDEX('Detalles movimientos'!P$5:P$1000, MATCH(40, 'Detalles movimientos'!$Q$5:$Q$1000, 0)), "")
B53: =IFERROR(INDEX('Detalles movimientos'!C$5:C$1000, MATCH(41, 'Detalles movimientos'!$Q$5:$Q$1000, 0)), "") | C53: =IFERROR(INDEX('Detalles movimientos'!D$5:D$1000, MATCH(41, 'Detalles movimientos'!$Q$5:$Q$1000, 0)), "") | D53: =IFERROR(INDEX('Detalles movimientos'!E$5:E$1000, MATCH(41, 'Detalles movimientos'!$Q$5:$Q$1000, 0)), "") | E53: =IFERROR(INDEX('Detalles movimientos'!F$5:F$1000, MATCH(41, 'Detalles movimientos'!$Q$5:$Q$1000, 0)), "") | F53: =IFERROR(INDEX('Detalles movimientos'!G$5:G$1000, MATCH(41, 'Detalles movimientos'!$Q$5:$Q$1000, 0)), "") | G53: =IFERROR(INDEX('Detalles movimientos'!H$5:H$1000, MATCH(41, 'Detalles movimientos'!$Q$5:$Q$1000, 0)), "") | H53: =IFERROR(INDEX('Detalles movimientos'!I$5:I$1000, MATCH(41, 'Detalles movimientos'!$Q$5:$Q$1000, 0)), "") | I53: =IFERROR(INDEX('Detalles movimientos'!J$5:J$1000, MATCH(41, 'Detalles movimientos'!$Q$5:$Q$1000, 0)), "") | ... L53: =IFERROR(INDEX('Detalles movimientos'!M$5:M$1000, MATCH(41, 'Detalles movimientos'!$Q$5:$Q$1000, 0)), "") | M53: =IFERROR(INDEX('Detalles movimientos'!P$5:P$1000, MATCH(41, 'Detalles movimientos'!$Q$5:$Q$1000, 0)), "")
B54: =IFERROR(INDEX('Detalles movimientos'!C$5:C$1000, MATCH(42, 'Detalles movimientos'!$Q$5:$Q$1000, 0)), "") | C54: =IFERROR(INDEX('Detalles movimientos'!D$5:D$1000, MATCH(42, 'Detalles movimientos'!$Q$5:$Q$1000, 0)), "") | D54: =IFERROR(INDEX('Detalles movimientos'!E$5:E$1000, MATCH(42, 'Detalles movimientos'!$Q$5:$Q$1000, 0)), "") | E54: =IFERROR(INDEX('Detalles movimientos'!F$5:F$1000, MATCH(42, 'Detalles movimientos'!$Q$5:$Q$1000, 0)), "") | F54: =IFERROR(INDEX('Detalles movimientos'!G$5:G$1000, MATCH(42, 'Detalles movimientos'!$Q$5:$Q$1000, 0)), "") | G54: =IFERROR(INDEX('Detalles movimientos'!H$5:H$1000, MATCH(42, 'Detalles movimientos'!$Q$5:$Q$1000, 0)), "") | H54: =IFERROR(INDEX('Detalles movimientos'!I$5:I$1000, MATCH(42, 'Detalles movimientos'!$Q$5:$Q$1000, 0)), "") | I54: =IFERROR(INDEX('Detalles movimientos'!J$5:J$1000, MATCH(42, 'Detalles movimientos'!$Q$5:$Q$1000, 0)), "") | ... L54: =IFERROR(INDEX('Detalles movimientos'!M$5:M$1000, MATCH(42, 'Detalles movimientos'!$Q$5:$Q$1000, 0)), "") | M54: =IFERROR(INDEX('Detalles movimientos'!P$5:P$1000, MATCH(42, 'Detalles movimientos'!$Q$5:$Q$1000, 0)), "")
B55: =IFERROR(INDEX('Detalles movimientos'!C$5:C$1000, MATCH(43, 'Detalles movimientos'!$Q$5:$Q$1000, 0)), "") | C55: =IFERROR(INDEX('Detalles movimientos'!D$5:D$1000, MATCH(43, 'Detalles movimientos'!$Q$5:$Q$1000, 0)), "") | D55: =IFERROR(INDEX('Detalles movimientos'!E$5:E$1000, MATCH(43, 'Detalles movimientos'!$Q$5:$Q$1000, 0)), "") | E55: =IFERROR(INDEX('Detalles movimientos'!F$5:F$1000, MATCH(43, 'Detalles movimientos'!$Q$5:$Q$1000, 0)), "") | F55: =IFERROR(INDEX('Detalles movimientos'!G$5:G$1000, MATCH(43, 'Detalles movimientos'!$Q$5:$Q$1000, 0)), "") | G55: =IFERROR(INDEX('Detalles movimientos'!H$5:H$1000, MATCH(43, 'Detalles movimientos'!$Q$5:$Q$1000, 0)), "") | H55: =IFERROR(INDEX('Detalles movimientos'!I$5:I$1000, MATCH(43, 'Detalles movimientos'!$Q$5:$Q$1000, 0)), "") | I55: =IFERROR(INDEX('Detalles movimientos'!J$5:J$1000, MATCH(43, 'Detalles movimientos'!$Q$5:$Q$1000, 0)), "") | ... L55: =IFERROR(INDEX('Detalles movimientos'!M$5:M$1000, MATCH(43, 'Detalles movimientos'!$Q$5:$Q$1000, 0)), "") | M55: =IFERROR(INDEX('Detalles movimientos'!P$5:P$1000, MATCH(43, 'Detalles movimientos'!$Q$5:$Q$1000, 0)), "")
B56: =IFERROR(INDEX('Detalles movimientos'!C$5:C$1000, MATCH(44, 'Detalles movimientos'!$Q$5:$Q$1000, 0)), "") | C56: =IFERROR(INDEX('Detalles movimientos'!D$5:D$1000, MATCH(44, 'Detalles movimientos'!$Q$5:$Q$1000, 0)), "") | D56: =IFERROR(INDEX('Detalles movimientos'!E$5:E$1000, MATCH(44, 'Detalles movimientos'!$Q$5:$Q$1000, 0)), "") | E56: =IFERROR(INDEX('Detalles movimientos'!F$5:F$1000, MATCH(44, 'Detalles movimientos'!$Q$5:$Q$1000, 0)), "") | F56: =IFERROR(INDEX('Detalles movimientos'!G$5:G$1000, MATCH(44, 'Detalles movimientos'!$Q$5:$Q$1000, 0)), "") | G56: =IFERROR(INDEX('Detalles movimientos'!H$5:H$1000, MATCH(44, 'Detalles movimientos'!$Q$5:$Q$1000, 0)), "") | H56: =IFERROR(INDEX('Detalles movimientos'!I$5:I$1000, MATCH(44, 'Detalles movimientos'!$Q$5:$Q$1000, 0)), "") | I56: =IFERROR(INDEX('Detalles movimientos'!J$5:J$1000, MATCH(44, 'Detalles movimientos'!$Q$5:$Q$1000, 0)), "") | ... L56: =IFERROR(INDEX('Detalles movimientos'!M$5:M$1000, MATCH(44, 'Detalles movimientos'!$Q$5:$Q$1000, 0)), "") | M56: =IFERROR(INDEX('Detalles movimientos'!P$5:P$1000, MATCH(44, 'Detalles movimientos'!$Q$5:$Q$1000, 0)), "")
B57: =IFERROR(INDEX('Detalles movimientos'!C$5:C$1000, MATCH(45, 'Detalles movimientos'!$Q$5:$Q$1000, 0)), "") | C57: =IFERROR(INDEX('Detalles movimientos'!D$5:D$1000, MATCH(45, 'Detalles movimientos'!$Q$5:$Q$1000, 0)), "") | D57: =IFERROR(INDEX('Detalles movimientos'!E$5:E$1000, MATCH(45, 'Detalles movimientos'!$Q$5:$Q$1000, 0)), "") | E57: =IFERROR(INDEX('Detalles movimientos'!F$5:F$1000, MATCH(45, 'Detalles movimientos'!$Q$5:$Q$1000, 0)), "") | F57: =IFERROR(INDEX('Detalles movimientos'!G$5:G$1000, MATCH(45, 'Detalles movimientos'!$Q$5:$Q$1000, 0)), "") | G57: =IFERROR(INDEX('Detalles movimientos'!H$5:H$1000, MATCH(45, 'Detalles movimientos'!$Q$5:$Q$1000, 0)), "") | H57: =IFERROR(INDEX('Detalles movimientos'!I$5:I$1000, MATCH(45, 'Detalles movimientos'!$Q$5:$Q$1000, 0)), "") | I57: =IFERROR(INDEX('Detalles movimientos'!J$5:J$1000, MATCH(45, 'Detalles movimientos'!$Q$5:$Q$1000, 0)), "") | ... L57: =IFERROR(INDEX('Detalles movimientos'!M$5:M$1000, MATCH(45, 'Detalles movimientos'!$Q$5:$Q$1000, 0)), "") | M57: =IFERROR(INDEX('Detalles movimientos'!P$5:P$1000, MATCH(45, 'Detalles movimientos'!$Q$5:$Q$1000, 0)), "")
B58: =IFERROR(INDEX('Detalles movimientos'!C$5:C$1000, MATCH(46, 'Detalles movimientos'!$Q$5:$Q$1000, 0)), "") | C58: =IFERROR(INDEX('Detalles movimientos'!D$5:D$1000, MATCH(46, 'Detalles movimientos'!$Q$5:$Q$1000, 0)), "") | D58: =IFERROR(INDEX('Detalles movimientos'!E$5:E$1000, MATCH(46, 'Detalles movimientos'!$Q$5:$Q$1000, 0)), "") | E58: =IFERROR(INDEX('Detalles movimientos'!F$5:F$1000, MATCH(46, 'Detalles movimientos'!$Q$5:$Q$1000, 0)), "") | F58: =IFERROR(INDEX('Detalles movimientos'!G$5:G$1000, MATCH(46, 'Detalles movimientos'!$Q$5:$Q$1000, 0)), "") | G58: =IFERROR(INDEX('Detalles movimientos'!H$5:H$1000, MATCH(46, 'Detalles movimientos'!$Q$5:$Q$1000, 0)), "") | H58: =IFERROR(INDEX('Detalles movimientos'!I$5:I$1000, MATCH(46, 'Detalles movimientos'!$Q$5:$Q$1000, 0)), "") | I58: =IFERROR(INDEX('Detalles movimientos'!J$5:J$1000, MATCH(46, 'Detalles movimientos'!$Q$5:$Q$1000, 0)), "") | ... L58: =IFERROR(INDEX('Detalles movimientos'!M$5:M$1000, MATCH(46, 'Detalles movimientos'!$Q$5:$Q$1000, 0)), "") | M58: =IFERROR(INDEX('Detalles movimientos'!P$5:P$1000, MATCH(46, 'Detalles movimientos'!$Q$5:$Q$1000, 0)), "")
B59: =IFERROR(INDEX('Detalles movimientos'!C$5:C$1000, MATCH(47, 'Detalles movimientos'!$Q$5:$Q$1000, 0)), "") | C59: =IFERROR(INDEX('Detalles movimientos'!D$5:D$1000, MATCH(47, 'Detalles movimientos'!$Q$5:$Q$1000, 0)), "") | D59: =IFERROR(INDEX('Detalles movimientos'!E$5:E$1000, MATCH(47, 'Detalles movimientos'!$Q$5:$Q$1000, 0)), "") | E59: =IFERROR(INDEX('Detalles movimientos'!F$5:F$1000, MATCH(47, 'Detalles movimientos'!$Q$5:$Q$1000, 0)), "") | F59: =IFERROR(INDEX('Detalles movimientos'!G$5:G$1000, MATCH(47, 'Detalles movimientos'!$Q$5:$Q$1000, 0)), "") | G59: =IFERROR(INDEX('Detalles movimientos'!H$5:H$1000, MATCH(47, 'Detalles movimientos'!$Q$5:$Q$1000, 0)), "") | H59: =IFERROR(INDEX('Detalles movimientos'!I$5:I$1000, MATCH(47, 'Detalles movimientos'!$Q$5:$Q$1000, 0)), "") | I59: =IFERROR(INDEX('Detalles movimientos'!J$5:J$1000, MATCH(47, 'Detalles movimientos'!$Q$5:$Q$1000, 0)), "") | ... L59: =IFERROR(INDEX('Detalles movimientos'!M$5:M$1000, MATCH(47, 'Detalles movimientos'!$Q$5:$Q$1000, 0)), "") | M59: =IFERROR(INDEX('Detalles movimientos'!P$5:P$1000, MATCH(47, 'Detalles movimientos'!$Q$5:$Q$1000, 0)), "")
B60: =IFERROR(INDEX('Detalles movimientos'!C$5:C$1000, MATCH(48, 'Detalles movimientos'!$Q$5:$Q$1000, 0)), "") | C60: =IFERROR(INDEX('Detalles movimientos'!D$5:D$1000, MATCH(48, 'Detalles movimientos'!$Q$5:$Q$1000, 0)), "") | D60: =IFERROR(INDEX('Detalles movimientos'!E$5:E$1000, MATCH(48, 'Detalles movimientos'!$Q$5:$Q$1000, 0)), "") | E60: =IFERROR(INDEX('Detalles movimientos'!F$5:F$1000, MATCH(48, 'Detalles movimientos'!$Q$5:$Q$1000, 0)), "") | F60: =IFERROR(INDEX('Detalles movimientos'!G$5:G$1000, MATCH(48, 'Detalles movimientos'!$Q$5:$Q$1000, 0)), "") | G60: =IFERROR(INDEX('Detalles movimientos'!H$5:H$1000, MATCH(48, 'Detalles movimientos'!$Q$5:$Q$1000, 0)), "") | H60: =IFERROR(INDEX('Detalles movimientos'!I$5:I$1000, MATCH(48, 'Detalles movimientos'!$Q$5:$Q$1000, 0)), "") | I60: =IFERROR(INDEX('Detalles movimientos'!J$5:J$1000, MATCH(48, 'Detalles movimientos'!$Q$5:$Q$1000, 0)), "") | ... L60: =IFERROR(INDEX('Detalles movimientos'!M$5:M$1000, MATCH(48, 'Detalles movimientos'!$Q$5:$Q$1000, 0)), "") | M60: =IFERROR(INDEX('Detalles movimientos'!P$5:P$1000, MATCH(48, 'Detalles movimientos'!$Q$5:$Q$1000, 0)), "")
B61: =IFERROR(INDEX('Detalles movimientos'!C$5:C$1000, MATCH(49, 'Detalles movimientos'!$Q$5:$Q$1000, 0)), "") | C61: =IFERROR(INDEX('Detalles movimientos'!D$5:D$1000, MATCH(49, 'Detalles movimientos'!$Q$5:$Q$1000, 0)), "") | D61: =IFERROR(INDEX('Detalles movimientos'!E$5:E$1000, MATCH(49, 'Detalles movimientos'!$Q$5:$Q$1000, 0)), "") | E61: =IFERROR(INDEX('Detalles movimientos'!F$5:F$1000, MATCH(49, 'Detalles movimientos'!$Q$5:$Q$1000, 0)), "") | F61: =IFERROR(INDEX('Detalles movimientos'!G$5:G$1000, MATCH(49, 'Detalles movimientos'!$Q$5:$Q$1000, 0)), "") | G61: =IFERROR(INDEX('Detalles movimientos'!H$5:H$1000, MATCH(49, 'Detalles movimientos'!$Q$5:$Q$1000, 0)), "") | H61: =IFERROR(INDEX('Detalles movimientos'!I$5:I$1000, MATCH(49, 'Detalles movimientos'!$Q$5:$Q$1000, 0)), "") | I61: =IFERROR(INDEX('Detalles movimientos'!J$5:J$1000, MATCH(49, 'Detalles movimientos'!$Q$5:$Q$1000, 0)), "") | ... L61: =IFERROR(INDEX('Detalles movimientos'!M$5:M$1000, MATCH(49, 'Detalles movimientos'!$Q$5:$Q$1000, 0)), "") | M61: =IFERROR(INDEX('Detalles movimientos'!P$5:P$1000, MATCH(49, 'Detalles movimientos'!$Q$5:$Q$1000, 0)), "")
B62: =IFERROR(INDEX('Detalles movimientos'!C$5:C$1000, MATCH(50, 'Detalles movimientos'!$Q$5:$Q$1000, 0)), "") | C62: =IFERROR(INDEX('Detalles movimientos'!D$5:D$1000, MATCH(50, 'Detalles movimientos'!$Q$5:$Q$1000, 0)), "") | D62: =IFERROR(INDEX('Detalles movimientos'!E$5:E$1000, MATCH(50, 'Detalles movimientos'!$Q$5:$Q$1000, 0)), "") | E62: =IFERROR(INDEX('Detalles movimientos'!F$5:F$1000, MATCH(50, 'Detalles movimientos'!$Q$5:$Q$1000, 0)), "") | F62: =IFERROR(INDEX('Detalles movimientos'!G$5:G$1000, MATCH(50, 'Detalles movimientos'!$Q$5:$Q$1000, 0)), "") | G62: =IFERROR(INDEX('Detalles movimientos'!H$5:H$1000, MATCH(50, 'Detalles movimientos'!$Q$5:$Q$1000, 0)), "") | H62: =IFERROR(INDEX('Detalles movimientos'!I$5:I$1000, MATCH(50, 'Detalles movimientos'!$Q$5:$Q$1000, 0)), "") | I62: =IFERROR(INDEX('Detalles movimientos'!J$5:J$1000, MATCH(50, 'Detalles movimientos'!$Q$5:$Q$1000, 0)), "") | ... L62: =IFERROR(INDEX('Detalles movimientos'!M$5:M$1000, MATCH(50, 'Detalles movimientos'!$Q$5:$Q$1000, 0)), "") | M62: =IFERROR(INDEX('Detalles movimientos'!P$5:P$1000, MATCH(50, 'Detalles movimientos'!$Q$5:$Q$1000, 0)), "")
B63: =IFERROR(INDEX('Detalles movimientos'!C$5:C$1000, MATCH(51, 'Detalles movimientos'!$Q$5:$Q$1000, 0)), "") | C63: =IFERROR(INDEX('Detalles movimientos'!D$5:D$1000, MATCH(51, 'Detalles movimientos'!$Q$5:$Q$1000, 0)), "") | D63: =IFERROR(INDEX('Detalles movimientos'!E$5:E$1000, MATCH(51, 'Detalles movimientos'!$Q$5:$Q$1000, 0)), "") | E63: =IFERROR(INDEX('Detalles movimientos'!F$5:F$1000, MATCH(51, 'Detalles movimientos'!$Q$5:$Q$1000, 0)), "") | F63: =IFERROR(INDEX('Detalles movimientos'!G$5:G$1000, MATCH(51, 'Detalles movimientos'!$Q$5:$Q$1000, 0)), "") | G63: =IFERROR(INDEX('Detalles movimientos'!H$5:H$1000, MATCH(51, 'Detalles movimientos'!$Q$5:$Q$1000, 0)), "") | H63: =IFERROR(INDEX('Detalles movimientos'!I$5:I$1000, MATCH(51, 'Detalles movimientos'!$Q$5:$Q$1000, 0)), "") | I63: =IFERROR(INDEX('Detalles movimientos'!J$5:J$1000, MATCH(51, 'Detalles movimientos'!$Q$5:$Q$1000, 0)), "") | ... L63: =IFERROR(INDEX('Detalles movimientos'!M$5:M$1000, MATCH(51, 'Detalles movimientos'!$Q$5:$Q$1000, 0)), "") | M63: =IFERROR(INDEX('Detalles movimientos'!P$5:P$1000, MATCH(51, 'Detalles movimientos'!$Q$5:$Q$1000, 0)), "")
B64: =IFERROR(INDEX('Detalles movimientos'!C$5:C$1000, MATCH(52, 'Detalles movimientos'!$Q$5:$Q$1000, 0)), "") | C64: =IFERROR(INDEX('Detalles movimientos'!D$5:D$1000, MATCH(52, 'Detalles movimientos'!$Q$5:$Q$1000, 0)), "") | D64: =IFERROR(INDEX('Detalles movimientos'!E$5:E$1000, MATCH(52, 'Detalles movimientos'!$Q$5:$Q$1000, 0)), "") | E64: =IFERROR(INDEX('Detalles movimientos'!F$5:F$1000, MATCH(52, 'Detalles movimientos'!$Q$5:$Q$1000, 0)), "") | F64: =IFERROR(INDEX('Detalles movimientos'!G$5:G$1000, MATCH(52, 'Detalles movimientos'!$Q$5:$Q$1000, 0)), "") | G64: =IFERROR(INDEX('Detalles movimientos'!H$5:H$1000, MATCH(52, 'Detalles movimientos'!$Q$5:$Q$1000, 0)), "") | H64: =IFERROR(INDEX('Detalles movimientos'!I$5:I$1000, MATCH(52, 'Detalles movimientos'!$Q$5:$Q$1000, 0)), "") | I64: =IFERROR(INDEX('Detalles movimientos'!J$5:J$1000, MATCH(52, 'Detalles movimientos'!$Q$5:$Q$1000, 0)), "") | ... L64: =IFERROR(INDEX('Detalles movimientos'!M$5:M$1000, MATCH(52, 'Detalles movimientos'!$Q$5:$Q$1000, 0)), "") | M64: =IFERROR(INDEX('Detalles movimientos'!P$5:P$1000, MATCH(52, 'Detalles movimientos'!$Q$5:$Q$1000, 0)), "")
B65: =IFERROR(INDEX('Detalles movimientos'!C$5:C$1000, MATCH(53, 'Detalles movimientos'!$Q$5:$Q$1000, 0)), "") | C65: =IFERROR(INDEX('Detalles movimientos'!D$5:D$1000, MATCH(53, 'Detalles movimientos'!$Q$5:$Q$1000, 0)), "") | D65: =IFERROR(INDEX('Detalles movimientos'!E$5:E$1000, MATCH(53, 'Detalles movimientos'!$Q$5:$Q$1000, 0)), "") | E65: =IFERROR(INDEX('Detalles movimientos'!F$5:F$1000, MATCH(53, 'Detalles movimientos'!$Q$5:$Q$1000, 0)), "") | F65: =IFERROR(INDEX('Detalles movimientos'!G$5:G$1000, MATCH(53, 'Detalles movimientos'!$Q$5:$Q$1000, 0)), "") | G65: =IFERROR(INDEX('Detalles movimientos'!H$5:H$1000, MATCH(53, 'Detalles movimientos'!$Q$5:$Q$1000, 0)), "") | H65: =IFERROR(INDEX('Detalles movimientos'!I$5:I$1000, MATCH(53, 'Detalles movimientos'!$Q$5:$Q$1000, 0)), "") | I65: =IFERROR(INDEX('Detalles movimientos'!J$5:J$1000, MATCH(53, 'Detalles movimientos'!$Q$5:$Q$1000, 0)), "") | ... L65: =IFERROR(INDEX('Detalles movimientos'!M$5:M$1000, MATCH(53, 'Detalles movimientos'!$Q$5:$Q$1000, 0)), "") | M65: =IFERROR(INDEX('Detalles movimientos'!P$5:P$1000, MATCH(53, 'Detalles movimientos'!$Q$5:$Q$1000, 0)), "")
B66: =IFERROR(INDEX('Detalles movimientos'!C$5:C$1000, MATCH(54, 'Detalles movimientos'!$Q$5:$Q$1000, 0)), "") | C66: =IFERROR(INDEX('Detalles movimientos'!D$5:D$1000, MATCH(54, 'Detalles movimientos'!$Q$5:$Q$1000, 0)), "") | D66: =IFERROR(INDEX('Detalles movimientos'!E$5:E$1000, MATCH(54, 'Detalles movimientos'!$Q$5:$Q$1000, 0)), "") | E66: =IFERROR(INDEX('Detalles movimientos'!F$5:F$1000, MATCH(54, 'Detalles movimientos'!$Q$5:$Q$1000, 0)), "") | F66: =IFERROR(INDEX('Detalles movimientos'!G$5:G$1000, MATCH(54, 'Detalles movimientos'!$Q$5:$Q$1000, 0)), "") | G66: =IFERROR(INDEX('Detalles movimientos'!H$5:H$1000, MATCH(54, 'Detalles movimientos'!$Q$5:$Q$1000, 0)), "") | H66: =IFERROR(INDEX('Detalles movimientos'!I$5:I$1000, MATCH(54, 'Detalles movimientos'!$Q$5:$Q$1000, 0)), "") | I66: =IFERROR(INDEX('Detalles movimientos'!J$5:J$1000, MATCH(54, 'Detalles movimientos'!$Q$5:$Q$1000, 0)), "") | ... L66: =IFERROR(INDEX('Detalles movimientos'!M$5:M$1000, MATCH(54, 'Detalles movimientos'!$Q$5:$Q$1000, 0)), "") | M66: =IFERROR(INDEX('Detalles movimientos'!P$5:P$1000, MATCH(54, 'Detalles movimientos'!$Q$5:$Q$1000, 0)), "")
B67: =IFERROR(INDEX('Detalles movimientos'!C$5:C$1000, MATCH(55, 'Detalles movimientos'!$Q$5:$Q$1000, 0)), "") | C67: =IFERROR(INDEX('Detalles movimientos'!D$5:D$1000, MATCH(55, 'Detalles movimientos'!$Q$5:$Q$1000, 0)), "") | D67: =IFERROR(INDEX('Detalles movimientos'!E$5:E$1000, MATCH(55, 'Detalles movimientos'!$Q$5:$Q$1000, 0)), "") | E67: =IFERROR(INDEX('Detalles movimientos'!F$5:F$1000, MATCH(55, 'Detalles movimientos'!$Q$5:$Q$1000, 0)), "") | F67: =IFERROR(INDEX('Detalles movimientos'!G$5:G$1000, MATCH(55, 'Detalles movimientos'!$Q$5:$Q$1000, 0)), "") | G67: =IFERROR(INDEX('Detalles movimientos'!H$5:H$1000, MATCH(55, 'Detalles movimientos'!$Q$5:$Q$1000, 0)), "") | H67: =IFERROR(INDEX('Detalles movimientos'!I$5:I$1000, MATCH(55, 'Detalles movimientos'!$Q$5:$Q$1000, 0)), "") | I67: =IFERROR(INDEX('Detalles movimientos'!J$5:J$1000, MATCH(55, 'Detalles movimientos'!$Q$5:$Q$1000, 0)), "") | ... L67: =IFERROR(INDEX('Detalles movimientos'!M$5:M$1000, MATCH(55, 'Detalles movimientos'!$Q$5:$Q$1000, 0)), "") | M67: =IFERROR(INDEX('Detalles movimientos'!P$5:P$1000, MATCH(55, 'Detalles movimientos'!$Q$5:$Q$1000, 0)), "")
B68: =IFERROR(INDEX('Detalles movimientos'!C$5:C$1000, MATCH(56, 'Detalles movimientos'!$Q$5:$Q$1000, 0)), "") | C68: =IFERROR(INDEX('Detalles movimientos'!D$5:D$1000, MATCH(56, 'Detalles movimientos'!$Q$5:$Q$1000, 0)), "") | D68: =IFERROR(INDEX('Detalles movimientos'!E$5:E$1000, MATCH(56, 'Detalles movimientos'!$Q$5:$Q$1000, 0)), "") | E68: =IFERROR(INDEX('Detalles movimientos'!F$5:F$1000, MATCH(56, 'Detalles movimientos'!$Q$5:$Q$1000, 0)), "") | F68: =IFERROR(INDEX('Detalles movimientos'!G$5:G$1000, MATCH(56, 'Detalles movimientos'!$Q$5:$Q$1000, 0)), "") | G68: =IFERROR(INDEX('Detalles movimientos'!H$5:H$1000, MATCH(56, 'Detalles movimientos'!$Q$5:$Q$1000, 0)), "") | H68: =IFERROR(INDEX('Detalles movimientos'!I$5:I$1000, MATCH(56, 'Detalles movimientos'!$Q$5:$Q$1000, 0)), "") | I68: =IFERROR(INDEX('Detalles movimientos'!J$5:J$1000, MATCH(56, 'Detalles movimientos'!$Q$5:$Q$1000, 0)), "") | ... L68: =IFERROR(INDEX('Detalles movimientos'!M$5:M$1000, MATCH(56, 'Detalles movimientos'!$Q$5:$Q$1000, 0)), "") | M68: =IFERROR(INDEX('Detalles movimientos'!P$5:P$1000, MATCH(56, 'Detalles movimientos'!$Q$5:$Q$1000, 0)), "")
B69: =IFERROR(INDEX('Detalles movimientos'!C$5:C$1000, MATCH(57, 'Detalles movimientos'!$Q$5:$Q$1000, 0)), "") | C69: =IFERROR(INDEX('Detalles movimientos'!D$5:D$1000, MATCH(57, 'Detalles movimientos'!$Q$5:$Q$1000, 0)), "") | D69: =IFERROR(INDEX('Detalles movimientos'!E$5:E$1000, MATCH(57, 'Detalles movimientos'!$Q$5:$Q$1000, 0)), "") | E69: =IFERROR(INDEX('Detalles movimientos'!F$5:F$1000, MATCH(57, 'Detalles movimientos'!$Q$5:$Q$1000, 0)), "") | F69: =IFERROR(INDEX('Detalles movimientos'!G$5:G$1000, MATCH(57, 'Detalles movimientos'!$Q$5:$Q$1000, 0)), "") | G69: =IFERROR(INDEX('Detalles movimientos'!H$5:H$1000, MATCH(57, 'Detalles movimientos'!$Q$5:$Q$1000, 0)), "") | H69: =IFERROR(INDEX('Detalles movimientos'!I$5:I$1000, MATCH(57, 'Detalles movimientos'!$Q$5:$Q$1000, 0)), "") | I69: =IFERROR(INDEX('Detalles movimientos'!J$5:J$1000, MATCH(57, 'Detalles movimientos'!$Q$5:$Q$1000, 0)), "") | ... L69: =IFERROR(INDEX('Detalles movimientos'!M$5:M$1000, MATCH(57, 'Detalles movimientos'!$Q$5:$Q$1000, 0)), "") | M69: =IFERROR(INDEX('Detalles movimientos'!P$5:P$1000, MATCH(57, 'Detalles movimientos'!$Q$5:$Q$1000, 0)), "")
B70: =IFERROR(INDEX('Detalles movimientos'!C$5:C$1000, MATCH(58, 'Detalles movimientos'!$Q$5:$Q$1000, 0)), "") | C70: =IFERROR(INDEX('Detalles movimientos'!D$5:D$1000, MATCH(58, 'Detalles movimientos'!$Q$5:$Q$1000, 0)), "") | D70: =IFERROR(INDEX('Detalles movimientos'!E$5:E$1000, MATCH(58, 'Detalles movimientos'!$Q$5:$Q$1000, 0)), "") | E70: =IFERROR(INDEX('Detalles movimientos'!F$5:F$1000, MATCH(58, 'Detalles movimientos'!$Q$5:$Q$1000, 0)), "") | F70: =IFERROR(INDEX('Detalles movimientos'!G$5:G$1000, MATCH(58, 'Detalles movimientos'!$Q$5:$Q$1000, 0)), "") | G70: =IFERROR(INDEX('Detalles movimientos'!H$5:H$1000, MATCH(58, 'Detalles movimientos'!$Q$5:$Q$1000, 0)), "") | H70: =IFERROR(INDEX('Detalles movimientos'!I$5:I$1000, MATCH(58, 'Detalles movimientos'!$Q$5:$Q$1000, 0)), "") | I70: =IFERROR(INDEX('Detalles movimientos'!J$5:J$1000, MATCH(58, 'Detalles movimientos'!$Q$5:$Q$1000, 0)), "") | ... L70: =IFERROR(INDEX('Detalles movimientos'!M$5:M$1000, MATCH(58, 'Detalles movimientos'!$Q$5:$Q$1000, 0)), "") | M70: =IFERROR(INDEX('Detalles movimientos'!P$5:P$1000, MATCH(58, 'Detalles movimientos'!$Q$5:$Q$1000, 0)), "")
B71: =IFERROR(INDEX('Detalles movimientos'!C$5:C$1000, MATCH(59, 'Detalles movimientos'!$Q$5:$Q$1000, 0)), "") | C71: =IFERROR(INDEX('Detalles movimientos'!D$5:D$1000, MATCH(59, 'Detalles movimientos'!$Q$5:$Q$1000, 0)), "") | D71: =IFERROR(INDEX('Detalles movimientos'!E$5:E$1000, MATCH(59, 'Detalles movimientos'!$Q$5:$Q$1000, 0)), "") | E71: =IFERROR(INDEX('Detalles movimientos'!F$5:F$1000, MATCH(59, 'Detalles movimientos'!$Q$5:$Q$1000, 0)), "") | F71: =IFERROR(INDEX('Detalles movimientos'!G$5:G$1000, MATCH(59, 'Detalles movimientos'!$Q$5:$Q$1000, 0)), "") | G71: =IFERROR(INDEX('Detalles movimientos'!H$5:H$1000, MATCH(59, 'Detalles movimientos'!$Q$5:$Q$1000, 0)), "") | H71: =IFERROR(INDEX('Detalles movimientos'!I$5:I$1000, MATCH(59, 'Detalles movimientos'!$Q$5:$Q$1000, 0)), "") | I71: =IFERROR(INDEX('Detalles movimientos'!J$5:J$1000, MATCH(59, 'Detalles movimientos'!$Q$5:$Q$1000, 0)), "") | ... L71: =IFERROR(INDEX('Detalles movimientos'!M$5:M$1000, MATCH(59, 'Detalles movimientos'!$Q$5:$Q$1000, 0)), "") | M71: =IFERROR(INDEX('Detalles movimientos'!P$5:P$1000, MATCH(59, 'Detalles movimientos'!$Q$5:$Q$1000, 0)), "")
B72: =IFERROR(INDEX('Detalles movimientos'!C$5:C$1000, MATCH(60, 'Detalles movimientos'!$Q$5:$Q$1000, 0)), "") | C72: =IFERROR(INDEX('Detalles movimientos'!D$5:D$1000, MATCH(60, 'Detalles movimientos'!$Q$5:$Q$1000, 0)), "") | D72: =IFERROR(INDEX('Detalles movimientos'!E$5:E$1000, MATCH(60, 'Detalles movimientos'!$Q$5:$Q$1000, 0)), "") | E72: =IFERROR(INDEX('Detalles movimientos'!F$5:F$1000, MATCH(60, 'Detalles movimientos'!$Q$5:$Q$1000, 0)), "") | F72: =IFERROR(INDEX('Detalles movimientos'!G$5:G$1000, MATCH(60, 'Detalles movimientos'!$Q$5:$Q$1000, 0)), "") | G72: =IFERROR(INDEX('Detalles movimientos'!H$5:H$1000, MATCH(60, 'Detalles movimientos'!$Q$5:$Q$1000, 0)), "") | H72: =IFERROR(INDEX('Detalles movimientos'!I$5:I$1000, MATCH(60, 'Detalles movimientos'!$Q$5:$Q$1000, 0)), "") | I72: =IFERROR(INDEX('Detalles movimientos'!J$5:J$1000, MATCH(60, 'Detalles movimientos'!$Q$5:$Q$1000, 0)), "") | ... L72: =IFERROR(INDEX('Detalles movimientos'!M$5:M$1000, MATCH(60, 'Detalles movimientos'!$Q$5:$Q$1000, 0)), "") | M72: =IFERROR(INDEX('Detalles movimientos'!P$5:P$1000, MATCH(60, 'Detalles movimientos'!$Q$5:$Q$1000, 0)), "")
B73: =IFERROR(INDEX('Detalles movimientos'!C$5:C$1000, MATCH(61, 'Detalles movimientos'!$Q$5:$Q$1000, 0)), "") | C73: =IFERROR(INDEX('Detalles movimientos'!D$5:D$1000, MATCH(61, 'Detalles movimientos'!$Q$5:$Q$1000, 0)), "") | D73: =IFERROR(INDEX('Detalles movimientos'!E$5:E$1000, MATCH(61, 'Detalles movimientos'!$Q$5:$Q$1000, 0)), "") | E73: =IFERROR(INDEX('Detalles movimientos'!F$5:F$1000, MATCH(61, 'Detalles movimientos'!$Q$5:$Q$1000, 0)), "") | F73: =IFERROR(INDEX('Detalles movimientos'!G$5:G$1000, MATCH(61, 'Detalles movimientos'!$Q$5:$Q$1000, 0)), "") | G73: =IFERROR(INDEX('Detalles movimientos'!H$5:H$1000, MATCH(61, 'Detalles movimientos'!$Q$5:$Q$1000, 0)), "") | H73: =IFERROR(INDEX('Detalles movimientos'!I$5:I$1000, MATCH(61, 'Detalles movimientos'!$Q$5:$Q$1000, 0)), "") | I73: =IFERROR(INDEX('Detalles movimientos'!J$5:J$1000, MATCH(61, 'Detalles movimientos'!$Q$5:$Q$1000, 0)), "") | ... L73: =IFERROR(INDEX('Detalles movimientos'!M$5:M$1000, MATCH(61, 'Detalles movimientos'!$Q$5:$Q$1000, 0)), "") | M73: =IFERROR(INDEX('Detalles movimientos'!P$5:P$1000, MATCH(61, 'Detalles movimientos'!$Q$5:$Q$1000, 0)), "")
B74: =IFERROR(INDEX('Detalles movimientos'!C$5:C$1000, MATCH(62, 'Detalles movimientos'!$Q$5:$Q$1000, 0)), "") | C74: =IFERROR(INDEX('Detalles movimientos'!D$5:D$1000, MATCH(62, 'Detalles movimientos'!$Q$5:$Q$1000, 0)), "") | D74: =IFERROR(INDEX('Detalles movimientos'!E$5:E$1000, MATCH(62, 'Detalles movimientos'!$Q$5:$Q$1000, 0)), "") | E74: =IFERROR(INDEX('Detalles movimientos'!F$5:F$1000, MATCH(62, 'Detalles movimientos'!$Q$5:$Q$1000, 0)), "") | F74: =IFERROR(INDEX('Detalles movimientos'!G$5:G$1000, MATCH(62, 'Detalles movimientos'!$Q$5:$Q$1000, 0)), "") | G74: =IFERROR(INDEX('Detalles movimientos'!H$5:H$1000, MATCH(62, 'Detalles movimientos'!$Q$5:$Q$1000, 0)), "") | H74: =IFERROR(INDEX('Detalles movimientos'!I$5:I$1000, MATCH(62, 'Detalles movimientos'!$Q$5:$Q$1000, 0)), "") | I74: =IFERROR(INDEX('Detalles movimientos'!J$5:J$1000, MATCH(62, 'Detalles movimientos'!$Q$5:$Q$1000, 0)), "") | ... L74: =IFERROR(INDEX('Detalles movimientos'!M$5:M$1000, MATCH(62, 'Detalles movimientos'!$Q$5:$Q$1000, 0)), "") | M74: =IFERROR(INDEX('Detalles movimientos'!P$5:P$1000, MATCH(62, 'Detalles movimientos'!$Q$5:$Q$1000, 0)), "")
B75: =IFERROR(INDEX('Detalles movimientos'!C$5:C$1000, MATCH(63, 'Detalles movimientos'!$Q$5:$Q$1000, 0)), "") | C75: =IFERROR(INDEX('Detalles movimientos'!D$5:D$1000, MATCH(63, 'Detalles movimientos'!$Q$5:$Q$1000, 0)), "") | D75: =IFERROR(INDEX('Detalles movimientos'!E$5:E$1000, MATCH(63, 'Detalles movimientos'!$Q$5:$Q$1000, 0)), "") | E75: =IFERROR(INDEX('Detalles movimientos'!F$5:F$1000, MATCH(63, 'Detalles movimientos'!$Q$5:$Q$1000, 0)), "") | F75: =IFERROR(INDEX('Detalles movimientos'!G$5:G$1000, MATCH(63, 'Detalles movimientos'!$Q$5:$Q$1000, 0)), "") | G75: =IFERROR(INDEX('Detalles movimientos'!H$5:H$1000, MATCH(63, 'Detalles movimientos'!$Q$5:$Q$1000, 0)), "") | H75: =IFERROR(INDEX('Detalles movimientos'!I$5:I$1000, MATCH(63, 'Detalles movimientos'!$Q$5:$Q$1000, 0)), "") | I75: =IFERROR(INDEX('Detalles movimientos'!J$5:J$1000, MATCH(63, 'Detalles movimientos'!$Q$5:$Q$1000, 0)), "") | ... L75: =IFERROR(INDEX('Detalles movimientos'!M$5:M$1000, MATCH(63, 'Detalles movimientos'!$Q$5:$Q$1000, 0)), "") | M75: =IFERROR(INDEX('Detalles movimientos'!P$5:P$1000, MATCH(63, 'Detalles movimientos'!$Q$5:$Q$1000, 0)), "")
B76: =IFERROR(INDEX('Detalles movimientos'!C$5:C$1000, MATCH(64, 'Detalles movimientos'!$Q$5:$Q$1000, 0)), "") | C76: =IFERROR(INDEX('Detalles movimientos'!D$5:D$1000, MATCH(64, 'Detalles movimientos'!$Q$5:$Q$1000, 0)), "") | D76: =IFERROR(INDEX('Detalles movimientos'!E$5:E$1000, MATCH(64, 'Detalles movimientos'!$Q$5:$Q$1000, 0)), "") | E76: =IFERROR(INDEX('Detalles movimientos'!F$5:F$1000, MATCH(64, 'Detalles movimientos'!$Q$5:$Q$1000, 0)), "") | F76: =IFERROR(INDEX('Detalles movimientos'!G$5:G$1000, MATCH(64, 'Detalles movimientos'!$Q$5:$Q$1000, 0)), "") | G76: =IFERROR(INDEX('Detalles movimientos'!H$5:H$1000, MATCH(64, 'Detalles movimientos'!$Q$5:$Q$1000, 0)), "") | H76: =IFERROR(INDEX('Detalles movimientos'!I$5:I$1000, MATCH(64, 'Detalles movimientos'!$Q$5:$Q$1000, 0)), "") | I76: =IFERROR(INDEX('Detalles movimientos'!J$5:J$1000, MATCH(64, 'Detalles movimientos'!$Q$5:$Q$1000, 0)), "") | ... L76: =IFERROR(INDEX('Detalles movimientos'!M$5:M$1000, MATCH(64, 'Detalles movimientos'!$Q$5:$Q$1000, 0)), "") | M76: =IFERROR(INDEX('Detalles movimientos'!P$5:P$1000, MATCH(64, 'Detalles movimientos'!$Q$5:$Q$1000, 0)), "")
B77: =IFERROR(INDEX('Detalles movimientos'!C$5:C$1000, MATCH(65, 'Detalles movimientos'!$Q$5:$Q$1000, 0)), "") | C77: =IFERROR(INDEX('Detalles movimientos'!D$5:D$1000, MATCH(65, 'Detalles movimientos'!$Q$5:$Q$1000, 0)), "") | D77: =IFERROR(INDEX('Detalles movimientos'!E$5:E$1000, MATCH(65, 'Detalles movimientos'!$Q$5:$Q$1000, 0)), "") | E77: =IFERROR(INDEX('Detalles movimientos'!F$5:F$1000, MATCH(65, 'Detalles movimientos'!$Q$5:$Q$1000, 0)), "") | F77: =IFERROR(INDEX('Detalles movimientos'!G$5:G$1000, MATCH(65, 'Detalles movimientos'!$Q$5:$Q$1000, 0)), "") | G77: =IFERROR(INDEX('Detalles movimientos'!H$5:H$1000, MATCH(65, 'Detalles movimientos'!$Q$5:$Q$1000, 0)), "") | H77: =IFERROR(INDEX('Detalles movimientos'!I$5:I$1000, MATCH(65, 'Detalles movimientos'!$Q$5:$Q$1000, 0)), "") | I77: =IFERROR(INDEX('Detalles movimientos'!J$5:J$1000, MATCH(65, 'Detalles movimientos'!$Q$5:$Q$1000, 0)), "") | ... L77: =IFERROR(INDEX('Detalles movimientos'!M$5:M$1000, MATCH(65, 'Detalles movimientos'!$Q$5:$Q$1000, 0)), "") | M77: =IFERROR(INDEX('Detalles movimientos'!P$5:P$1000, MATCH(65, 'Detalles movimientos'!$Q$5:$Q$1000, 0)), "")
B78: =IFERROR(INDEX('Detalles movimientos'!C$5:C$1000, MATCH(66, 'Detalles movimientos'!$Q$5:$Q$1000, 0)), "") | C78: =IFERROR(INDEX('Detalles movimientos'!D$5:D$1000, MATCH(66, 'Detalles movimientos'!$Q$5:$Q$1000, 0)), "") | D78: =IFERROR(INDEX('Detalles movimientos'!E$5:E$1000, MATCH(66, 'Detalles movimientos'!$Q$5:$Q$1000, 0)), "") | E78: =IFERROR(INDEX('Detalles movimientos'!F$5:F$1000, MATCH(66, 'Detalles movimientos'!$Q$5:$Q$1000, 0)), "") | F78: =IFERROR(INDEX('Detalles movimientos'!G$5:G$1000, MATCH(66, 'Detalles movimientos'!$Q$5:$Q$1000, 0)), "") | G78: =IFERROR(INDEX('Detalles movimientos'!H$5:H$1000, MATCH(66, 'Detalles movimientos'!$Q$5:$Q$1000, 0)), "") | H78: =IFERROR(INDEX('Detalles movimientos'!I$5:I$1000, MATCH(66, 'Detalles movimientos'!$Q$5:$Q$1000, 0)), "") | I78: =IFERROR(INDEX('Detalles movimientos'!J$5:J$1000, MATCH(66, 'Detalles movimientos'!$Q$5:$Q$1000, 0)), "") | ... L78: =IFERROR(INDEX('Detalles movimientos'!M$5:M$1000, MATCH(66, 'Detalles movimientos'!$Q$5:$Q$1000, 0)), "") | M78: =IFERROR(INDEX('Detalles movimientos'!P$5:P$1000, MATCH(66, 'Detalles movimientos'!$Q$5:$Q$1000, 0)), "")
B79: =IFERROR(INDEX('Detalles movimientos'!C$5:C$1000, MATCH(67, 'Detalles movimientos'!$Q$5:$Q$1000, 0)), "") | C79: =IFERROR(INDEX('Detalles movimientos'!D$5:D$1000, MATCH(67, 'Detalles movimientos'!$Q$5:$Q$1000, 0)), "") | D79: =IFERROR(INDEX('Detalles movimientos'!E$5:E$1000, MATCH(67, 'Detalles movimientos'!$Q$5:$Q$1000, 0)), "") | E79: =IFERROR(INDEX('Detalles movimientos'!F$5:F$1000, MATCH(67, 'Detalles movimientos'!$Q$5:$Q$1000, 0)), "") | F79: =IFERROR(INDEX('Detalles movimientos'!G$5:G$1000, MATCH(67, 'Detalles movimientos'!$Q$5:$Q$1000, 0)), "") | G79: =IFERROR(INDEX('Detalles movimientos'!H$5:H$1000, MATCH(67, 'Detalles movimientos'!$Q$5:$Q$1000, 0)), "") | H79: =IFERROR(INDEX('Detalles movimientos'!I$5:I$1000, MATCH(67, 'Detalles movimientos'!$Q$5:$Q$1000, 0)), "") | I79: =IFERROR(INDEX('Detalles movimientos'!J$5:J$1000, MATCH(67, 'Detalles movimientos'!$Q$5:$Q$1000, 0)), "") | ... L79: =IFERROR(INDEX('Detalles movimientos'!M$5:M$1000, MATCH(67, 'Detalles movimientos'!$Q$5:$Q$1000, 0)), "") | M79: =IFERROR(INDEX('Detalles movimientos'!P$5:P$1000, MATCH(67, 'Detalles movimientos'!$Q$5:$Q$1000, 0)), "")
B80: =IFERROR(INDEX('Detalles movimientos'!C$5:C$1000, MATCH(68, 'Detalles movimientos'!$Q$5:$Q$1000, 0)), "") | C80: =IFERROR(INDEX('Detalles movimientos'!D$5:D$1000, MATCH(68, 'Detalles movimientos'!$Q$5:$Q$1000, 0)), "") | D80: =IFERROR(INDEX('Detalles movimientos'!E$5:E$1000, MATCH(68, 'Detalles movimientos'!$Q$5:$Q$1000, 0)), "") | E80: =IFERROR(INDEX('Detalles movimientos'!F$5:F$1000, MATCH(68, 'Detalles movimientos'!$Q$5:$Q$1000, 0)), "") | F80: =IFERROR(INDEX('Detalles movimientos'!G$5:G$1000, MATCH(68, 'Detalles movimientos'!$Q$5:$Q$1000, 0)), "") | G80: =IFERROR(INDEX('Detalles movimientos'!H$5:H$1000, MATCH(68, 'Detalles movimientos'!$Q$5:$Q$1000, 0)), "") | H80: =IFERROR(INDEX('Detalles movimientos'!I$5:I$1000, MATCH(68, 'Detalles movimientos'!$Q$5:$Q$1000, 0)), "") | I80: =IFERROR(INDEX('Detalles movimientos'!J$5:J$1000, MATCH(68, 'Detalles movimientos'!$Q$5:$Q$1000, 0)), "") | ... L80: =IFERROR(INDEX('Detalles movimientos'!M$5:M$1000, MATCH(68, 'Detalles movimientos'!$Q$5:$Q$1000, 0)), "") | M80: =IFERROR(INDEX('Detalles movimientos'!P$5:P$1000, MATCH(68, 'Detalles movimientos'!$Q$5:$Q$1000, 0)), "")
B81: =IFERROR(INDEX('Detalles movimientos'!C$5:C$1000, MATCH(69, 'Detalles movimientos'!$Q$5:$Q$1000, 0)), "") | C81: =IFERROR(INDEX('Detalles movimientos'!D$5:D$1000, MATCH(69, 'Detalles movimientos'!$Q$5:$Q$1000, 0)), "") | D81: =IFERROR(INDEX('Detalles movimientos'!E$5:E$1000, MATCH(69, 'Detalles movimientos'!$Q$5:$Q$1000, 0)), "") | E81: =IFERROR(INDEX('Detalles movimientos'!F$5:F$1000, MATCH(69, 'Detalles movimientos'!$Q$5:$Q$1000, 0)), "") | F81: =IFERROR(INDEX('Detalles movimientos'!G$5:G$1000, MATCH(69, 'Detalles movimientos'!$Q$5:$Q$1000, 0)), "") | G81: =IFERROR(INDEX('Detalles movimientos'!H$5:H$1000, MATCH(69, 'Detalles movimientos'!$Q$5:$Q$1000, 0)), "") | H81: =IFERROR(INDEX('Detalles movimientos'!I$5:I$1000, MATCH(69, 'Detalles movimientos'!$Q$5:$Q$1000, 0)), "") | I81: =IFERROR(INDEX('Detalles movimientos'!J$5:J$1000, MATCH(69, 'Detalles movimientos'!$Q$5:$Q$1000, 0)), "") | ... L81: =IFERROR(INDEX('Detalles movimientos'!M$5:M$1000, MATCH(69, 'Detalles movimientos'!$Q$5:$Q$1000, 0)), "") | M81: =IFERROR(INDEX('Detalles movimientos'!P$5:P$1000, MATCH(69, 'Detalles movimientos'!$Q$5:$Q$1000, 0)), "")
B82: =IFERROR(INDEX('Detalles movimientos'!C$5:C$1000, MATCH(70, 'Detalles movimientos'!$Q$5:$Q$1000, 0)), "") | C82: =IFERROR(INDEX('Detalles movimientos'!D$5:D$1000, MATCH(70, 'Detalles movimientos'!$Q$5:$Q$1000, 0)), "") | D82: =IFERROR(INDEX('Detalles movimientos'!E$5:E$1000, MATCH(70, 'Detalles movimientos'!$Q$5:$Q$1000, 0)), "") | E82: =IFERROR(INDEX('Detalles movimientos'!F$5:F$1000, MATCH(70, 'Detalles movimientos'!$Q$5:$Q$1000, 0)), "") | F82: =IFERROR(INDEX('Detalles movimientos'!G$5:G$1000, MATCH(70, 'Detalles movimientos'!$Q$5:$Q$1000, 0)), "") | G82: =IFERROR(INDEX('Detalles movimientos'!H$5:H$1000, MATCH(70, 'Detalles movimientos'!$Q$5:$Q$1000, 0)), "") | H82: =IFERROR(INDEX('Detalles movimientos'!I$5:I$1000, MATCH(70, 'Detalles movimientos'!$Q$5:$Q$1000, 0)), "") | I82: =IFERROR(INDEX('Detalles movimientos'!J$5:J$1000, MATCH(70, 'Detalles movimientos'!$Q$5:$Q$1000, 0)), "") | ... L82: =IFERROR(INDEX('Detalles movimientos'!M$5:M$1000, MATCH(70, 'Detalles movimientos'!$Q$5:$Q$1000, 0)), "") | M82: =IFERROR(INDEX('Detalles movimientos'!P$5:P$1000, MATCH(70, 'Detalles movimientos'!$Q$5:$Q$1000, 0)), "")
B83: =IFERROR(INDEX('Detalles movimientos'!C$5:C$1000, MATCH(71, 'Detalles movimientos'!$Q$5:$Q$1000, 0)), "") | C83: =IFERROR(INDEX('Detalles movimientos'!D$5:D$1000, MATCH(71, 'Detalles movimientos'!$Q$5:$Q$1000, 0)), "") | D83: =IFERROR(INDEX('Detalles movimientos'!E$5:E$1000, MATCH(71, 'Detalles movimientos'!$Q$5:$Q$1000, 0)), "") | E83: =IFERROR(INDEX('Detalles movimientos'!F$5:F$1000, MATCH(71, 'Detalles movimientos'!$Q$5:$Q$1000, 0)), "") | F83: =IFERROR(INDEX('Detalles movimientos'!G$5:G$1000, MATCH(71, 'Detalles movimientos'!$Q$5:$Q$1000, 0)), "") | G83: =IFERROR(INDEX('Detalles movimientos'!H$5:H$1000, MATCH(71, 'Detalles movimientos'!$Q$5:$Q$1000, 0)), "") | H83: =IFERROR(INDEX('Detalles movimientos'!I$5:I$1000, MATCH(71, 'Detalles movimientos'!$Q$5:$Q$1000, 0)), "") | I83: =IFERROR(INDEX('Detalles movimientos'!J$5:J$1000, MATCH(71, 'Detalles movimientos'!$Q$5:$Q$1000, 0)), "") | ... L83: =IFERROR(INDEX('Detalles movimientos'!M$5:M$1000, MATCH(71, 'Detalles movimientos'!$Q$5:$Q$1000, 0)), "") | M83: =IFERROR(INDEX('Detalles movimientos'!P$5:P$1000, MATCH(71, 'Detalles movimientos'!$Q$5:$Q$1000, 0)), "")
B84: =IFERROR(INDEX('Detalles movimientos'!C$5:C$1000, MATCH(72, 'Detalles movimientos'!$Q$5:$Q$1000, 0)), "") | C84: =IFERROR(INDEX('Detalles movimientos'!D$5:D$1000, MATCH(72, 'Detalles movimientos'!$Q$5:$Q$1000, 0)), "") | D84: =IFERROR(INDEX('Detalles movimientos'!E$5:E$1000, MATCH(72, 'Detalles movimientos'!$Q$5:$Q$1000, 0)), "") | E84: =IFERROR(INDEX('Detalles movimientos'!F$5:F$1000, MATCH(72, 'Detalles movimientos'!$Q$5:$Q$1000, 0)), "") | F84: =IFERROR(INDEX('Detalles movimientos'!G$5:G$1000, MATCH(72, 'Detalles movimientos'!$Q$5:$Q$1000, 0)), "") | G84: =IFERROR(INDEX('Detalles movimientos'!H$5:H$1000, MATCH(72, 'Detalles movimientos'!$Q$5:$Q$1000, 0)), "") | H84: =IFERROR(INDEX('Detalles movimientos'!I$5:I$1000, MATCH(72, 'Detalles movimientos'!$Q$5:$Q$1000, 0)), "") | I84: =IFERROR(INDEX('Detalles movimientos'!J$5:J$1000, MATCH(72, 'Detalles movimientos'!$Q$5:$Q$1000, 0)), "") | ... L84: =IFERROR(INDEX('Detalles movimientos'!M$5:M$1000, MATCH(72, 'Detalles movimientos'!$Q$5:$Q$1000, 0)), "") | M84: =IFERROR(INDEX('Detalles movimientos'!P$5:P$1000, MATCH(72, 'Detalles movimientos'!$Q$5:$Q$1000, 0)), "")
B85: =IFERROR(INDEX('Detalles movimientos'!C$5:C$1000, MATCH(73, 'Detalles movimientos'!$Q$5:$Q$1000, 0)), "") | C85: =IFERROR(INDEX('Detalles movimientos'!D$5:D$1000, MATCH(73, 'Detalles movimientos'!$Q$5:$Q$1000, 0)), "") | D85: =IFERROR(INDEX('Detalles movimientos'!E$5:E$1000, MATCH(73, 'Detalles movimientos'!$Q$5:$Q$1000, 0)), "") | E85: =IFERROR(INDEX('Detalles movimientos'!F$5:F$1000, MATCH(73, 'Detalles movimientos'!$Q$5:$Q$1000, 0)), "") | F85: =IFERROR(INDEX('Detalles movimientos'!G$5:G$1000, MATCH(73, 'Detalles movimientos'!$Q$5:$Q$1000, 0)), "") | G85: =IFERROR(INDEX('Detalles movimientos'!H$5:H$1000, MATCH(73, 'Detalles movimientos'!$Q$5:$Q$1000, 0)), "") | H85: =IFERROR(INDEX('Detalles movimientos'!I$5:I$1000, MATCH(73, 'Detalles movimientos'!$Q$5:$Q$1000, 0)), "") | I85: =IFERROR(INDEX('Detalles movimientos'!J$5:J$1000, MATCH(73, 'Detalles movimientos'!$Q$5:$Q$1000, 0)), "") | ... L85: =IFERROR(INDEX('Detalles movimientos'!M$5:M$1000, MATCH(73, 'Detalles movimientos'!$Q$5:$Q$1000, 0)), "") | M85: =IFERROR(INDEX('Detalles movimientos'!P$5:P$1000, MATCH(73, 'Detalles movimientos'!$Q$5:$Q$1000, 0)), "")
B86: =IFERROR(INDEX('Detalles movimientos'!C$5:C$1000, MATCH(74, 'Detalles movimientos'!$Q$5:$Q$1000, 0)), "") | C86: =IFERROR(INDEX('Detalles movimientos'!D$5:D$1000, MATCH(74, 'Detalles movimientos'!$Q$5:$Q$1000, 0)), "") | D86: =IFERROR(INDEX('Detalles movimientos'!E$5:E$1000, MATCH(74, 'Detalles movimientos'!$Q$5:$Q$1000, 0)), "") | E86: =IFERROR(INDEX('Detalles movimientos'!F$5:F$1000, MATCH(74, 'Detalles movimientos'!$Q$5:$Q$1000, 0)), "") | F86: =IFERROR(INDEX('Detalles movimientos'!G$5:G$1000, MATCH(74, 'Detalles movimientos'!$Q$5:$Q$1000, 0)), "") | G86: =IFERROR(INDEX('Detalles movimientos'!H$5:H$1000, MATCH(74, 'Detalles movimientos'!$Q$5:$Q$1000, 0)), "") | H86: =IFERROR(INDEX('Detalles movimientos'!I$5:I$1000, MATCH(74, 'Detalles movimientos'!$Q$5:$Q$1000, 0)), "") | I86: =IFERROR(INDEX('Detalles movimientos'!J$5:J$1000, MATCH(74, 'Detalles movimientos'!$Q$5:$Q$1000, 0)), "") | ... L86: =IFERROR(INDEX('Detalles movimientos'!M$5:M$1000, MATCH(74, 'Detalles movimientos'!$Q$5:$Q$1000, 0)), "") | M86: =IFERROR(INDEX('Detalles movimientos'!P$5:P$1000, MATCH(74, 'Detalles movimientos'!$Q$5:$Q$1000, 0)), "")
B87: =IFERROR(INDEX('Detalles movimientos'!C$5:C$1000, MATCH(75, 'Detalles movimientos'!$Q$5:$Q$1000, 0)), "") | C87: =IFERROR(INDEX('Detalles movimientos'!D$5:D$1000, MATCH(75, 'Detalles movimientos'!$Q$5:$Q$1000, 0)), "") | D87: =IFERROR(INDEX('Detalles movimientos'!E$5:E$1000, MATCH(75, 'Detalles movimientos'!$Q$5:$Q$1000, 0)), "") | E87: =IFERROR(INDEX('Detalles movimientos'!F$5:F$1000, MATCH(75, 'Detalles movimientos'!$Q$5:$Q$1000, 0)), "") | F87: =IFERROR(INDEX('Detalles movimientos'!G$5:G$1000, MATCH(75, 'Detalles movimientos'!$Q$5:$Q$1000, 0)), "") | G87: =IFERROR(INDEX('Detalles movimientos'!H$5:H$1000, MATCH(75, 'Detalles movimientos'!$Q$5:$Q$1000, 0)), "") | H87: =IFERROR(INDEX('Detalles movimientos'!I$5:I$1000, MATCH(75, 'Detalles movimientos'!$Q$5:$Q$1000, 0)), "") | I87: =IFERROR(INDEX('Detalles movimientos'!J$5:J$1000, MATCH(75, 'Detalles movimientos'!$Q$5:$Q$1000, 0)), "") | ... L87: =IFERROR(INDEX('Detalles movimientos'!M$5:M$1000, MATCH(75, 'Detalles movimientos'!$Q$5:$Q$1000, 0)), "") | M87: =IFERROR(INDEX('Detalles movimientos'!P$5:P$1000, MATCH(75, 'Detalles movimientos'!$Q$5:$Q$1000, 0)), "")
B88: =IFERROR(INDEX('Detalles movimientos'!C$5:C$1000, MATCH(76, 'Detalles movimientos'!$Q$5:$Q$1000, 0)), "") | C88: =IFERROR(INDEX('Detalles movimientos'!D$5:D$1000, MATCH(76, 'Detalles movimientos'!$Q$5:$Q$1000, 0)), "") | D88: =IFERROR(INDEX('Detalles movimientos'!E$5:E$1000, MATCH(76, 'Detalles movimientos'!$Q$5:$Q$1000, 0)), "") | E88: =IFERROR(INDEX('Detalles movimientos'!F$5:F$1000, MATCH(76, 'Detalles movimientos'!$Q$5:$Q$1000, 0)), "") | F88: =IFERROR(INDEX('Detalles movimientos'!G$5:G$1000, MATCH(76, 'Detalles movimientos'!$Q$5:$Q$1000, 0)), "") | G88: =IFERROR(INDEX('Detalles movimientos'!H$5:H$1000, MATCH(76, 'Detalles movimientos'!$Q$5:$Q$1000, 0)), "") | H88: =IFERROR(INDEX('Detalles movimientos'!I$5:I$1000, MATCH(76, 'Detalles movimientos'!$Q$5:$Q$1000, 0)), "") | I88: =IFERROR(INDEX('Detalles movimientos'!J$5:J$1000, MATCH(76, 'Detalles movimientos'!$Q$5:$Q$1000, 0)), "") | ... L88: =IFERROR(INDEX('Detalles movimientos'!M$5:M$1000, MATCH(76, 'Detalles movimientos'!$Q$5:$Q$1000, 0)), "") | M88: =IFERROR(INDEX('Detalles movimientos'!P$5:P$1000, MATCH(76, 'Detalles movimientos'!$Q$5:$Q$1000, 0)), "")
B89: =IFERROR(INDEX('Detalles movimientos'!C$5:C$1000, MATCH(77, 'Detalles movimientos'!$Q$5:$Q$1000, 0)), "") | C89: =IFERROR(INDEX('Detalles movimientos'!D$5:D$1000, MATCH(77, 'Detalles movimientos'!$Q$5:$Q$1000, 0)), "") | D89: =IFERROR(INDEX('Detalles movimientos'!E$5:E$1000, MATCH(77, 'Detalles movimientos'!$Q$5:$Q$1000, 0)), "") | E89: =IFERROR(INDEX('Detalles movimientos'!F$5:F$1000, MATCH(77, 'Detalles movimientos'!$Q$5:$Q$1000, 0)), "") | F89: =IFERROR(INDEX('Detalles movimientos'!G$5:G$1000, MATCH(77, 'Detalles movimientos'!$Q$5:$Q$1000, 0)), "") | G89: =IFERROR(INDEX('Detalles movimientos'!H$5:H$1000, MATCH(77, 'Detalles movimientos'!$Q$5:$Q$1000, 0)), "") | H89: =IFERROR(INDEX('Detalles movimientos'!I$5:I$1000, MATCH(77, 'Detalles movimientos'!$Q$5:$Q$1000, 0)), "") | I89: =IFERROR(INDEX('Detalles movimientos'!J$5:J$1000, MATCH(77, 'Detalles movimientos'!$Q$5:$Q$1000, 0)), "") | ... L89: =IFERROR(INDEX('Detalles movimientos'!M$5:M$1000, MATCH(77, 'Detalles movimientos'!$Q$5:$Q$1000, 0)), "") | M89: =IFERROR(INDEX('Detalles movimientos'!P$5:P$1000, MATCH(77, 'Detalles movimientos'!$Q$5:$Q$1000, 0)), "")
B90: =IFERROR(INDEX('Detalles movimientos'!C$5:C$1000, MATCH(78, 'Detalles movimientos'!$Q$5:$Q$1000, 0)), "") | C90: =IFERROR(INDEX('Detalles movimientos'!D$5:D$1000, MATCH(78, 'Detalles movimientos'!$Q$5:$Q$1000, 0)), "") | D90: =IFERROR(INDEX('Detalles movimientos'!E$5:E$1000, MATCH(78, 'Detalles movimientos'!$Q$5:$Q$1000, 0)), "") | E90: =IFERROR(INDEX('Detalles movimientos'!F$5:F$1000, MATCH(78, 'Detalles movimientos'!$Q$5:$Q$1000, 0)), "") | F90: =IFERROR(INDEX('Detalles movimientos'!G$5:G$1000, MATCH(78, 'Detalles movimientos'!$Q$5:$Q$1000, 0)), "") | G90: =IFERROR(INDEX('Detalles movimientos'!H$5:H$1000, MATCH(78, 'Detalles movimientos'!$Q$5:$Q$1000, 0)), "") | H90: =IFERROR(INDEX('Detalles movimientos'!I$5:I$1000, MATCH(78, 'Detalles movimientos'!$Q$5:$Q$1000, 0)), "") | I90: =IFERROR(INDEX('Detalles movimientos'!J$5:J$1000, MATCH(78, 'Detalles movimientos'!$Q$5:$Q$1000, 0)), "") | ... L90: =IFERROR(INDEX('Detalles movimientos'!M$5:M$1000, MATCH(78, 'Detalles movimientos'!$Q$5:$Q$1000, 0)), "") | M90: =IFERROR(INDEX('Detalles movimientos'!P$5:P$1000, MATCH(78, 'Detalles movimientos'!$Q$5:$Q$1000, 0)), "")
B91: =IFERROR(INDEX('Detalles movimientos'!C$5:C$1000, MATCH(79, 'Detalles movimientos'!$Q$5:$Q$1000, 0)), "") | C91: =IFERROR(INDEX('Detalles movimientos'!D$5:D$1000, MATCH(79, 'Detalles movimientos'!$Q$5:$Q$1000, 0)), "") | D91: =IFERROR(INDEX('Detalles movimientos'!E$5:E$1000, MATCH(79, 'Detalles movimientos'!$Q$5:$Q$1000, 0)), "") | E91: =IFERROR(INDEX('Detalles movimientos'!F$5:F$1000, MATCH(79, 'Detalles movimientos'!$Q$5:$Q$1000, 0)), "") | F91: =IFERROR(INDEX('Detalles movimientos'!G$5:G$1000, MATCH(79, 'Detalles movimientos'!$Q$5:$Q$1000, 0)), "") | G91: =IFERROR(INDEX('Detalles movimientos'!H$5:H$1000, MATCH(79, 'Detalles movimientos'!$Q$5:$Q$1000, 0)), "") | H91: =IFERROR(INDEX('Detalles movimientos'!I$5:I$1000, MATCH(79, 'Detalles movimientos'!$Q$5:$Q$1000, 0)), "") | I91: =IFERROR(INDEX('Detalles movimientos'!J$5:J$1000, MATCH(79, 'Detalles movimientos'!$Q$5:$Q$1000, 0)), "") | ... L91: =IFERROR(INDEX('Detalles movimientos'!M$5:M$1000, MATCH(79, 'Detalles movimientos'!$Q$5:$Q$1000, 0)), "") | M91: =IFERROR(INDEX('Detalles movimientos'!P$5:P$1000, MATCH(79, 'Detalles movimientos'!$Q$5:$Q$1000, 0)), "")
B92: =IFERROR(INDEX('Detalles movimientos'!C$5:C$1000, MATCH(80, 'Detalles movimientos'!$Q$5:$Q$1000, 0)), "") | C92: =IFERROR(INDEX('Detalles movimientos'!D$5:D$1000, MATCH(80, 'Detalles movimientos'!$Q$5:$Q$1000, 0)), "") | D92: =IFERROR(INDEX('Detalles movimientos'!E$5:E$1000, MATCH(80, 'Detalles movimientos'!$Q$5:$Q$1000, 0)), "") | E92: =IFERROR(INDEX('Detalles movimientos'!F$5:F$1000, MATCH(80, 'Detalles movimientos'!$Q$5:$Q$1000, 0)), "") | F92: =IFERROR(INDEX('Detalles movimientos'!G$5:G$1000, MATCH(80, 'Detalles movimientos'!$Q$5:$Q$1000, 0)), "") | G92: =IFERROR(INDEX('Detalles movimientos'!H$5:H$1000, MATCH(80, 'Detalles movimientos'!$Q$5:$Q$1000, 0)), "") | H92: =IFERROR(INDEX('Detalles movimientos'!I$5:I$1000, MATCH(80, 'Detalles movimientos'!$Q$5:$Q$1000, 0)), "") | I92: =IFERROR(INDEX('Detalles movimientos'!J$5:J$1000, MATCH(80, 'Detalles movimientos'!$Q$5:$Q$1000, 0)), "") | ... L92: =IFERROR(INDEX('Detalles movimientos'!M$5:M$1000, MATCH(80, 'Detalles movimientos'!$Q$5:$Q$1000, 0)), "") | M92: =IFERROR(INDEX('Detalles movimientos'!P$5:P$1000, MATCH(80, 'Detalles movimientos'!$Q$5:$Q$1000, 0)), "")
B93: =IFERROR(INDEX('Detalles movimientos'!C$5:C$1000, MATCH(81, 'Detalles movimientos'!$Q$5:$Q$1000, 0)), "") | C93: =IFERROR(INDEX('Detalles movimientos'!D$5:D$1000, MATCH(81, 'Detalles movimientos'!$Q$5:$Q$1000, 0)), "") | D93: =IFERROR(INDEX('Detalles movimientos'!E$5:E$1000, MATCH(81, 'Detalles movimientos'!$Q$5:$Q$1000, 0)), "") | E93: =IFERROR(INDEX('Detalles movimientos'!F$5:F$1000, MATCH(81, 'Detalles movimientos'!$Q$5:$Q$1000, 0)), "") | F93: =IFERROR(INDEX('Detalles movimientos'!G$5:G$1000, MATCH(81, 'Detalles movimientos'!$Q$5:$Q$1000, 0)), "") | G93: =IFERROR(INDEX('Detalles movimientos'!H$5:H$1000, MATCH(81, 'Detalles movimientos'!$Q$5:$Q$1000, 0)), "") | H93: =IFERROR(INDEX('Detalles movimientos'!I$5:I$1000, MATCH(81, 'Detalles movimientos'!$Q$5:$Q$1000, 0)), "") | I93: =IFERROR(INDEX('Detalles movimientos'!J$5:J$1000, MATCH(81, 'Detalles movimientos'!$Q$5:$Q$1000, 0)), "") | ... L93: =IFERROR(INDEX('Detalles movimientos'!M$5:M$1000, MATCH(81, 'Detalles movimientos'!$Q$5:$Q$1000, 0)), "") | M93: =IFERROR(INDEX('Detalles movimientos'!P$5:P$1000, MATCH(81, 'Detalles movimientos'!$Q$5:$Q$1000, 0)), "")
B94: =IFERROR(INDEX('Detalles movimientos'!C$5:C$1000, MATCH(82, 'Detalles movimientos'!$Q$5:$Q$1000, 0)), "") | C94: =IFERROR(INDEX('Detalles movimientos'!D$5:D$1000, MATCH(82, 'Detalles movimientos'!$Q$5:$Q$1000, 0)), "") | D94: =IFERROR(INDEX('Detalles movimientos'!E$5:E$1000, MATCH(82, 'Detalles movimientos'!$Q$5:$Q$1000, 0)), "") | E94: =IFERROR(INDEX('Detalles movimientos'!F$5:F$1000, MATCH(82, 'Detalles movimientos'!$Q$5:$Q$1000, 0)), "") | F94: =IFERROR(INDEX('Detalles movimientos'!G$5:G$1000, MATCH(82, 'Detalles movimientos'!$Q$5:$Q$1000, 0)), "") | G94: =IFERROR(INDEX('Detalles movimientos'!H$5:H$1000, MATCH(82, 'Detalles movimientos'!$Q$5:$Q$1000, 0)), "") | H94: =IFERROR(INDEX('Detalles movimientos'!I$5:I$1000, MATCH(82, 'Detalles movimientos'!$Q$5:$Q$1000, 0)), "") | I94: =IFERROR(INDEX('Detalles movimientos'!J$5:J$1000, MATCH(82, 'Detalles movimientos'!$Q$5:$Q$1000, 0)), "") | ... L94: =IFERROR(INDEX('Detalles movimientos'!M$5:M$1000, MATCH(82, 'Detalles movimientos'!$Q$5:$Q$1000, 0)), "") | M94: =IFERROR(INDEX('Detalles movimientos'!P$5:P$1000, MATCH(82, 'Detalles movimientos'!$Q$5:$Q$1000, 0)), "")
B95: =IFERROR(INDEX('Detalles movimientos'!C$5:C$1000, MATCH(83, 'Detalles movimientos'!$Q$5:$Q$1000, 0)), "") | C95: =IFERROR(INDEX('Detalles movimientos'!D$5:D$1000, MATCH(83, 'Detalles movimientos'!$Q$5:$Q$1000, 0)), "") | D95: =IFERROR(INDEX('Detalles movimientos'!E$5:E$1000, MATCH(83, 'Detalles movimientos'!$Q$5:$Q$1000, 0)), "") | E95: =IFERROR(INDEX('Detalles movimientos'!F$5:F$1000, MATCH(83, 'Detalles movimientos'!$Q$5:$Q$1000, 0)), "") | F95: =IFERROR(INDEX('Detalles movimientos'!G$5:G$1000, MATCH(83, 'Detalles movimientos'!$Q$5:$Q$1000, 0)), "") | G95: =IFERROR(INDEX('Detalles movimientos'!H$5:H$1000, MATCH(83, 'Detalles movimientos'!$Q$5:$Q$1000, 0)), "") | H95: =IFERROR(INDEX('Detalles movimientos'!I$5:I$1000, MATCH(83, 'Detalles movimientos'!$Q$5:$Q$1000, 0)), "") | I95: =IFERROR(INDEX('Detalles movimientos'!J$5:J$1000, MATCH(83, 'Detalles movimientos'!$Q$5:$Q$1000, 0)), "") | ... L95: =IFERROR(INDEX('Detalles movimientos'!M$5:M$1000, MATCH(83, 'Detalles movimientos'!$Q$5:$Q$1000, 0)), "") | M95: =IFERROR(INDEX('Detalles movimientos'!P$5:P$1000, MATCH(83, 'Detalles movimientos'!$Q$5:$Q$1000, 0)), "")
B96: =IFERROR(INDEX('Detalles movimientos'!C$5:C$1000, MATCH(84, 'Detalles movimientos'!$Q$5:$Q$1000, 0)), "") | C96: =IFERROR(INDEX('Detalles movimientos'!D$5:D$1000, MATCH(84, 'Detalles movimientos'!$Q$5:$Q$1000, 0)), "") | D96: =IFERROR(INDEX('Detalles movimientos'!E$5:E$1000, MATCH(84, 'Detalles movimientos'!$Q$5:$Q$1000, 0)), "") | E96: =IFERROR(INDEX('Detalles movimientos'!F$5:F$1000, MATCH(84, 'Detalles movimientos'!$Q$5:$Q$1000, 0)), "") | F96: =IFERROR(INDEX('Detalles movimientos'!G$5:G$1000, MATCH(84, 'Detalles movimientos'!$Q$5:$Q$1000, 0)), "") | G96: =IFERROR(INDEX('Detalles movimientos'!H$5:H$1000, MATCH(84, 'Detalles movimientos'!$Q$5:$Q$1000, 0)), "") | H96: =IFERROR(INDEX('Detalles movimientos'!I$5:I$1000, MATCH(84, 'Detalles movimientos'!$Q$5:$Q$1000, 0)), "") | I96: =IFERROR(INDEX('Detalles movimientos'!J$5:J$1000, MATCH(84, 'Detalles movimientos'!$Q$5:$Q$1000, 0)), "") | ... L96: =IFERROR(INDEX('Detalles movimientos'!M$5:M$1000, MATCH(84, 'Detalles movimientos'!$Q$5:$Q$1000, 0)), "") | M96: =IFERROR(INDEX('Detalles movimientos'!P$5:P$1000, MATCH(84, 'Detalles movimientos'!$Q$5:$Q$1000, 0)), "")
B97: =IFERROR(INDEX('Detalles movimientos'!C$5:C$1000, MATCH(85, 'Detalles movimientos'!$Q$5:$Q$1000, 0)), "") | C97: =IFERROR(INDEX('Detalles movimientos'!D$5:D$1000, MATCH(85, 'Detalles movimientos'!$Q$5:$Q$1000, 0)), "") | D97: =IFERROR(INDEX('Detalles movimientos'!E$5:E$1000, MATCH(85, 'Detalles movimientos'!$Q$5:$Q$1000, 0)), "") | E97: =IFERROR(INDEX('Detalles movimientos'!F$5:F$1000, MATCH(85, 'Detalles movimientos'!$Q$5:$Q$1000, 0)), "") | F97: =IFERROR(INDEX('Detalles movimientos'!G$5:G$1000, MATCH(85, 'Detalles movimientos'!$Q$5:$Q$1000, 0)), "") | G97: =IFERROR(INDEX('Detalles movimientos'!H$5:H$1000, MATCH(85, 'Detalles movimientos'!$Q$5:$Q$1000, 0)), "") | H97: =IFERROR(INDEX('Detalles movimientos'!I$5:I$1000, MATCH(85, 'Detalles movimientos'!$Q$5:$Q$1000, 0)), "") | I97: =IFERROR(INDEX('Detalles movimientos'!J$5:J$1000, MATCH(85, 'Detalles movimientos'!$Q$5:$Q$1000, 0)), "") | ... L97: =IFERROR(INDEX('Detalles movimientos'!M$5:M$1000, MATCH(85, 'Detalles movimientos'!$Q$5:$Q$1000, 0)), "") | M97: =IFERROR(INDEX('Detalles movimientos'!P$5:P$1000, MATCH(85, 'Detalles movimientos'!$Q$5:$Q$1000, 0)), "")
B98: =IFERROR(INDEX('Detalles movimientos'!C$5:C$1000, MATCH(86, 'Detalles movimientos'!$Q$5:$Q$1000, 0)), "") | C98: =IFERROR(INDEX('Detalles movimientos'!D$5:D$1000, MATCH(86, 'Detalles movimientos'!$Q$5:$Q$1000, 0)), "") | D98: =IFERROR(INDEX('Detalles movimientos'!E$5:E$1000, MATCH(86, 'Detalles movimientos'!$Q$5:$Q$1000, 0)), "") | E98: =IFERROR(INDEX('Detalles movimientos'!F$5:F$1000, MATCH(86, 'Detalles movimientos'!$Q$5:$Q$1000, 0)), "") | F98: =IFERROR(INDEX('Detalles movimientos'!G$5:G$1000, MATCH(86, 'Detalles movimientos'!$Q$5:$Q$1000, 0)), "") | G98: =IFERROR(INDEX('Detalles movimientos'!H$5:H$1000, MATCH(86, 'Detalles movimientos'!$Q$5:$Q$1000, 0)), "") | H98: =IFERROR(INDEX('Detalles movimientos'!I$5:I$1000, MATCH(86, 'Detalles movimientos'!$Q$5:$Q$1000, 0)), "") | I98: =IFERROR(INDEX('Detalles movimientos'!J$5:J$1000, MATCH(86, 'Detalles movimientos'!$Q$5:$Q$1000, 0)), "") | ... L98: =IFERROR(INDEX('Detalles movimientos'!M$5:M$1000, MATCH(86, 'Detalles movimientos'!$Q$5:$Q$1000, 0)), "") | M98: =IFERROR(INDEX('Detalles movimientos'!P$5:P$1000, MATCH(86, 'Detalles movimientos'!$Q$5:$Q$1000, 0)), "")
B99: =IFERROR(INDEX('Detalles movimientos'!C$5:C$1000, MATCH(87, 'Detalles movimientos'!$Q$5:$Q$1000, 0)), "") | C99: =IFERROR(INDEX('Detalles movimientos'!D$5:D$1000, MATCH(87, 'Detalles movimientos'!$Q$5:$Q$1000, 0)), "") | D99: =IFERROR(INDEX('Detalles movimientos'!E$5:E$1000, MATCH(87, 'Detalles movimientos'!$Q$5:$Q$1000, 0)), "") | E99: =IFERROR(INDEX('Detalles movimientos'!F$5:F$1000, MATCH(87, 'Detalles movimientos'!$Q$5:$Q$1000, 0)), "") | F99: =IFERROR(INDEX('Detalles movimientos'!G$5:G$1000, MATCH(87, 'Detalles movimientos'!$Q$5:$Q$1000, 0)), "") | G99: =IFERROR(INDEX('Detalles movimientos'!H$5:H$1000, MATCH(87, 'Detalles movimientos'!$Q$5:$Q$1000, 0)), "") | H99: =IFERROR(INDEX('Detalles movimientos'!I$5:I$1000, MATCH(87, 'Detalles movimientos'!$Q$5:$Q$1000, 0)), "") | I99: =IFERROR(INDEX('Detalles movimientos'!J$5:J$1000, MATCH(87, 'Detalles movimientos'!$Q$5:$Q$1000, 0)), "") | ... L99: =IFERROR(INDEX('Detalles movimientos'!M$5:M$1000, MATCH(87, 'Detalles movimientos'!$Q$5:$Q$1000, 0)), "") | M99: =IFERROR(INDEX('Detalles movimientos'!P$5:P$1000, MATCH(87, 'Detalles movimientos'!$Q$5:$Q$1000, 0)), "")
B100: =IFERROR(INDEX('Detalles movimientos'!C$5:C$1000, MATCH(88, 'Detalles movimientos'!$Q$5:$Q$1000, 0)), "") | C100: =IFERROR(INDEX('Detalles movimientos'!D$5:D$1000, MATCH(88, 'Detalles movimientos'!$Q$5:$Q$1000, 0)), "") | D100: =IFERROR(INDEX('Detalles movimientos'!E$5:E$1000, MATCH(88, 'Detalles movimientos'!$Q$5:$Q$1000, 0)), "") | E100: =IFERROR(INDEX('Detalles movimientos'!F$5:F$1000, MATCH(88, 'Detalles movimientos'!$Q$5:$Q$1000, 0)), "") | F100: =IFERROR(INDEX('Detalles movimientos'!G$5:G$1000, MATCH(88, 'Detalles movimientos'!$Q$5:$Q$1000, 0)), "") | G100: =IFERROR(INDEX('Detalles movimientos'!H$5:H$1000, MATCH(88, 'Detalles movimientos'!$Q$5:$Q$1000, 0)), "") | H100: =IFERROR(INDEX('Detalles movimientos'!I$5:I$1000, MATCH(88, 'Detalles movimientos'!$Q$5:$Q$1000, 0)), "") | I100: =IFERROR(INDEX('Detalles movimientos'!J$5:J$1000, MATCH(88, 'Detalles movimientos'!$Q$5:$Q$1000, 0)), "") | ... L100: =IFERROR(INDEX('Detalles movimientos'!M$5:M$1000, MATCH(88, 'Detalles movimientos'!$Q$5:$Q$1000, 0)), "") | M100: =IFERROR(INDEX('Detalles movimientos'!P$5:P$1000, MATCH(88, 'Detalles movimientos'!$Q$5:$Q$1000, 0)), "")
B101: =IFERROR(INDEX('Detalles movimientos'!C$5:C$1000, MATCH(89, 'Detalles movimientos'!$Q$5:$Q$1000, 0)), "") | C101: =IFERROR(INDEX('Detalles movimientos'!D$5:D$1000, MATCH(89, 'Detalles movimientos'!$Q$5:$Q$1000, 0)), "") | D101: =IFERROR(INDEX('Detalles movimientos'!E$5:E$1000, MATCH(89, 'Detalles movimientos'!$Q$5:$Q$1000, 0)), "") | E101: =IFERROR(INDEX('Detalles movimientos'!F$5:F$1000, MATCH(89, 'Detalles movimientos'!$Q$5:$Q$1000, 0)), "") | F101: =IFERROR(INDEX('Detalles movimientos'!G$5:G$1000, MATCH(89, 'Detalles movimientos'!$Q$5:$Q$1000, 0)), "") | G101: =IFERROR(INDEX('Detalles movimientos'!H$5:H$1000, MATCH(89, 'Detalles movimientos'!$Q$5:$Q$1000, 0)), "") | H101: =IFERROR(INDEX('Detalles movimientos'!I$5:I$1000, MATCH(89, 'Detalles movimientos'!$Q$5:$Q$1000, 0)), "") | I101: =IFERROR(INDEX('Detalles movimientos'!J$5:J$1000, MATCH(89, 'Detalles movimientos'!$Q$5:$Q$1000, 0)), "") | ... L101: =IFERROR(INDEX('Detalles movimientos'!M$5:M$1000, MATCH(89, 'Detalles movimientos'!$Q$5:$Q$1000, 0)), "") | M101: =IFERROR(INDEX('Detalles movimientos'!P$5:P$1000, MATCH(89, 'Detalles movimientos'!$Q$5:$Q$1000, 0)), "")
B102: =IFERROR(INDEX('Detalles movimientos'!C$5:C$1000, MATCH(90, 'Detalles movimientos'!$Q$5:$Q$1000, 0)), "") | C102: =IFERROR(INDEX('Detalles movimientos'!D$5:D$1000, MATCH(90, 'Detalles movimientos'!$Q$5:$Q$1000, 0)), "") | D102: =IFERROR(INDEX('Detalles movimientos'!E$5:E$1000, MATCH(90, 'Detalles movimientos'!$Q$5:$Q$1000, 0)), "") | E102: =IFERROR(INDEX('Detalles movimientos'!F$5:F$1000, MATCH(90, 'Detalles movimientos'!$Q$5:$Q$1000, 0)), "") | F102: =IFERROR(INDEX('Detalles movimientos'!G$5:G$1000, MATCH(90, 'Detalles movimientos'!$Q$5:$Q$1000, 0)), "") | G102: =IFERROR(INDEX('Detalles movimientos'!H$5:H$1000, MATCH(90, 'Detalles movimientos'!$Q$5:$Q$1000, 0)), "") | H102: =IFERROR(INDEX('Detalles movimientos'!I$5:I$1000, MATCH(90, 'Detalles movimientos'!$Q$5:$Q$1000, 0)), "") | I102: =IFERROR(INDEX('Detalles movimientos'!J$5:J$1000, MATCH(90, 'Detalles movimientos'!$Q$5:$Q$1000, 0)), "") | ... L102: =IFERROR(INDEX('Detalles movimientos'!M$5:M$1000, MATCH(90, 'Detalles movimientos'!$Q$5:$Q$1000, 0)), "") | M102: =IFERROR(INDEX('Detalles movimientos'!P$5:P$1000, MATCH(90, 'Detalles movimientos'!$Q$5:$Q$1000, 0)), "")
B103: =IFERROR(INDEX('Detalles movimientos'!C$5:C$1000, MATCH(91, 'Detalles movimientos'!$Q$5:$Q$1000, 0)), "") | C103: =IFERROR(INDEX('Detalles movimientos'!D$5:D$1000, MATCH(91, 'Detalles movimientos'!$Q$5:$Q$1000, 0)), "") | D103: =IFERROR(INDEX('Detalles movimientos'!E$5:E$1000, MATCH(91, 'Detalles movimientos'!$Q$5:$Q$1000, 0)), "") | E103: =IFERROR(INDEX('Detalles movimientos'!F$5:F$1000, MATCH(91, 'Detalles movimientos'!$Q$5:$Q$1000, 0)), "") | F103: =IFERROR(INDEX('Detalles movimientos'!G$5:G$1000, MATCH(91, 'Detalles movimientos'!$Q$5:$Q$1000, 0)), "") | G103: =IFERROR(INDEX('Detalles movimientos'!H$5:H$1000, MATCH(91, 'Detalles movimientos'!$Q$5:$Q$1000, 0)), "") | H103: =IFERROR(INDEX('Detalles movimientos'!I$5:I$1000, MATCH(91, 'Detalles movimientos'!$Q$5:$Q$1000, 0)), "") | I103: =IFERROR(INDEX('Detalles movimientos'!J$5:J$1000, MATCH(91, 'Detalles movimientos'!$Q$5:$Q$1000, 0)), "") | ... L103: =IFERROR(INDEX('Detalles movimientos'!M$5:M$1000, MATCH(91, 'Detalles movimientos'!$Q$5:$Q$1000, 0)), "") | M103: =IFERROR(INDEX('Detalles movimientos'!P$5:P$1000, MATCH(91, 'Detalles movimientos'!$Q$5:$Q$1000, 0)), "")
B104: =IFERROR(INDEX('Detalles movimientos'!C$5:C$1000, MATCH(92, 'Detalles movimientos'!$Q$5:$Q$1000, 0)), "") | C104: =IFERROR(INDEX('Detalles movimientos'!D$5:D$1000, MATCH(92, 'Detalles movimientos'!$Q$5:$Q$1000, 0)), "") | D104: =IFERROR(INDEX('Detalles movimientos'!E$5:E$1000, MATCH(92, 'Detalles movimientos'!$Q$5:$Q$1000, 0)), "") | E104: =IFERROR(INDEX('Detalles movimientos'!F$5:F$1000, MATCH(92, 'Detalles movimientos'!$Q$5:$Q$1000, 0)), "") | F104: =IFERROR(INDEX('Detalles movimientos'!G$5:G$1000, MATCH(92, 'Detalles movimientos'!$Q$5:$Q$1000, 0)), "") | G104: =IFERROR(INDEX('Detalles movimientos'!H$5:H$1000, MATCH(92, 'Detalles movimientos'!$Q$5:$Q$1000, 0)), "") | H104: =IFERROR(INDEX('Detalles movimientos'!I$5:I$1000, MATCH(92, 'Detalles movimientos'!$Q$5:$Q$1000, 0)), "") | I104: =IFERROR(INDEX('Detalles movimientos'!J$5:J$1000, MATCH(92, 'Detalles movimientos'!$Q$5:$Q$1000, 0)), "") | ... L104: =IFERROR(INDEX('Detalles movimientos'!M$5:M$1000, MATCH(92, 'Detalles movimientos'!$Q$5:$Q$1000, 0)), "") | M104: =IFERROR(INDEX('Detalles movimientos'!P$5:P$1000, MATCH(92, 'Detalles movimientos'!$Q$5:$Q$1000, 0)), "")
B105: =IFERROR(INDEX('Detalles movimientos'!C$5:C$1000, MATCH(93, 'Detalles movimientos'!$Q$5:$Q$1000, 0)), "") | C105: =IFERROR(INDEX('Detalles movimientos'!D$5:D$1000, MATCH(93, 'Detalles movimientos'!$Q$5:$Q$1000, 0)), "") | D105: =IFERROR(INDEX('Detalles movimientos'!E$5:E$1000, MATCH(93, 'Detalles movimientos'!$Q$5:$Q$1000, 0)), "") | E105: =IFERROR(INDEX('Detalles movimientos'!F$5:F$1000, MATCH(93, 'Detalles movimientos'!$Q$5:$Q$1000, 0)), "") | F105: =IFERROR(INDEX('Detalles movimientos'!G$5:G$1000, MATCH(93, 'Detalles movimientos'!$Q$5:$Q$1000, 0)), "") | G105: =IFERROR(INDEX('Detalles movimientos'!H$5:H$1000, MATCH(93, 'Detalles movimientos'!$Q$5:$Q$1000, 0)), "") | H105: =IFERROR(INDEX('Detalles movimientos'!I$5:I$1000, MATCH(93, 'Detalles movimientos'!$Q$5:$Q$1000, 0)), "") | I105: =IFERROR(INDEX('Detalles movimientos'!J$5:J$1000, MATCH(93, 'Detalles movimientos'!$Q$5:$Q$1000, 0)), "") | ... L105: =IFERROR(INDEX('Detalles movimientos'!M$5:M$1000, MATCH(93, 'Detalles movimientos'!$Q$5:$Q$1000, 0)), "") | M105: =IFERROR(INDEX('Detalles movimientos'!P$5:P$1000, MATCH(93, 'Detalles movimientos'!$Q$5:$Q$1000, 0)), "")
B106: =IFERROR(INDEX('Detalles movimientos'!C$5:C$1000, MATCH(94, 'Detalles movimientos'!$Q$5:$Q$1000, 0)), "") | C106: =IFERROR(INDEX('Detalles movimientos'!D$5:D$1000, MATCH(94, 'Detalles movimientos'!$Q$5:$Q$1000, 0)), "") | D106: =IFERROR(INDEX('Detalles movimientos'!E$5:E$1000, MATCH(94, 'Detalles movimientos'!$Q$5:$Q$1000, 0)), "") | E106: =IFERROR(INDEX('Detalles movimientos'!F$5:F$1000, MATCH(94, 'Detalles movimientos'!$Q$5:$Q$1000, 0)), "") | F106: =IFERROR(INDEX('Detalles movimientos'!G$5:G$1000, MATCH(94, 'Detalles movimientos'!$Q$5:$Q$1000, 0)), "") | G106: =IFERROR(INDEX('Detalles movimientos'!H$5:H$1000, MATCH(94, 'Detalles movimientos'!$Q$5:$Q$1000, 0)), "") | H106: =IFERROR(INDEX('Detalles movimientos'!I$5:I$1000, MATCH(94, 'Detalles movimientos'!$Q$5:$Q$1000, 0)), "") | I106: =IFERROR(INDEX('Detalles movimientos'!J$5:J$1000, MATCH(94, 'Detalles movimientos'!$Q$5:$Q$1000, 0)), "") | ... L106: =IFERROR(INDEX('Detalles movimientos'!M$5:M$1000, MATCH(94, 'Detalles movimientos'!$Q$5:$Q$1000, 0)), "") | M106: =IFERROR(INDEX('Detalles movimientos'!P$5:P$1000, MATCH(94, 'Detalles movimientos'!$Q$5:$Q$1000, 0)), "")
...

Sheet Ignacio
B2: RESUMEN Y MOVIMIENTOS INDIVIDUALES: IGNACIO
B3: Sincronización en tiempo real con la pestaña 'Detalles movimientos'
B5: TOTAL LITROS | E5: TOTAL VENTAS ($) | H5: N° OPERACIONES | K5: PRECIO PROMEDIO ($/L)
B6: =SUMIFS('Detalles movimientos'!I$5:I$1000, 'Detalles movimientos'!F$5:F$1000, "Ignacio") -> 16564 | E6: =SUMIFS('Detalles movimientos'!J$5:J$1000, 'Detalles movimientos'!F$5:F$1000, "Ignacio") -> 0 | H6: =COUNTIFS('Detalles movimientos'!F$5:F$1000, "Ignacio") -> 4 | K6: =IFERROR(E6/B6, 0) -> 0
B9: Fecha | C9: Nombre Cliente | D9: Camión | E9: Vende | F9: Dirección | G9: Precio | H9: Litros | I9: Total | J9: Medio de pago | K9: Comisiones | L9: Observación | M9: Facturación / Detalles
B10: =IFERROR(INDEX('Detalles movimientos'!C$5:C$1000, MATCH(1, 'Detalles movimientos'!$R$5:$R$1000, 0)), "") -> 46230 | C10: =IFERROR(INDEX('Detalles movimientos'!D$5:D$1000, MATCH(1, 'Detalles movimientos'!$R$5:$R$1000, 0)), "") -> Ignacio Guerrero | D10: =IFERROR(INDEX('Detalles movimientos'!E$5:E$1000, MATCH(1, 'Detalles movimientos'!$R$5:$R$1000, 0)), "") -> VJYL61 | E10: =IFERROR(INDEX('Detalles movimientos'!F$5:F$1000, MATCH(1, 'Detalles movimientos'!$R$5:$R$1000, 0)), "") -> Ignacio | F10: =IFERROR(INDEX('Detalles movimientos'!G$5:G$1000, MATCH(1, 'Detalles movimientos'!$R$5:$R$1000, 0)), "") -> 0 | G10: =IFERROR(INDEX('Detalles movimientos'!H$5:H$1000, MATCH(1, 'Detalles movimientos'!$R$5:$R$1000, 0)), "") -> 0 | H10: =IFERROR(INDEX('Detalles movimientos'!I$5:I$1000, MATCH(1, 'Detalles movimientos'!$R$5:$R$1000, 0)), "") -> 1403 | I10: =IFERROR(INDEX('Detalles movimientos'!J$5:J$1000, MATCH(1, 'Detalles movimientos'!$R$5:$R$1000, 0)), "") -> 0 | ... L10: =IFERROR(INDEX('Detalles movimientos'!M$5:M$1000, MATCH(1, 'Detalles movimientos'!$R$5:$R$1000, 0)), "") -> Extraccion | M10: =IFERROR(INDEX('Detalles movimientos'!P$5:P$1000, MATCH(1, 'Detalles movimientos'!$R$5:$R$1000, 0)), "") -> 0
B11: =IFERROR(INDEX('Detalles movimientos'!C$5:C$1000, MATCH(2, 'Detalles movimientos'!$R$5:$R$1000, 0)), "") -> 46238 | C11: =IFERROR(INDEX('Detalles movimientos'!D$5:D$1000, MATCH(2, 'Detalles movimientos'!$R$5:$R$1000, 0)), "") -> Ignacio Guerrero | D11: =IFERROR(INDEX('Detalles movimientos'!E$5:E$1000, MATCH(2, 'Detalles movimientos'!$R$5:$R$1000, 0)), "") -> VJYL61 | E11: =IFERROR(INDEX('Detalles movimientos'!F$5:F$1000, MATCH(2, 'Detalles movimientos'!$R$5:$R$1000, 0)), "") -> Ignacio | F11: =IFERROR(INDEX('Detalles movimientos'!G$5:G$1000, MATCH(2, 'Detalles movimientos'!$R$5:$R$1000, 0)), "") -> 0 | G11: =IFERROR(INDEX('Detalles movimientos'!H$5:H$1000, MATCH(2, 'Detalles movimientos'!$R$5:$R$1000, 0)), "") -> 0 | H11: =IFERROR(INDEX('Detalles movimientos'!I$5:I$1000, MATCH(2, 'Detalles movimientos'!$R$5:$R$1000, 0)), "") -> 1403 | I11: =IFERROR(INDEX('Detalles movimientos'!J$5:J$1000, MATCH(2, 'Detalles movimientos'!$R$5:$R$1000, 0)), "") -> 0 | ... L11: =IFERROR(INDEX('Detalles movimientos'!M$5:M$1000, MATCH(2, 'Detalles movimientos'!$R$5:$R$1000, 0)), "") -> Extraccion | M11: =IFERROR(INDEX('Detalles movimientos'!P$5:P$1000, MATCH(2, 'Detalles movimientos'!$R$5:$R$1000, 0)), "") -> 0
B12: =IFERROR(INDEX('Detalles movimientos'!C$5:C$1000, MATCH(3, 'Detalles movimientos'!$R$5:$R$1000, 0)), "") -> 46242 | C12: =IFERROR(INDEX('Detalles movimientos'!D$5:D$1000, MATCH(3, 'Detalles movimientos'!$R$5:$R$1000, 0)), "") -> Ignacio Guerrero | D12: =IFERROR(INDEX('Detalles movimientos'!E$5:E$1000, MATCH(3, 'Detalles movimientos'!$R$5:$R$1000, 0)), "") -> VJYL61 | E12: =IFERROR(INDEX('Detalles movimientos'!F$5:F$1000, MATCH(3, 'Detalles movimientos'!$R$5:$R$1000, 0)), "") -> Ignacio | F12: =IFERROR(INDEX('Detalles movimientos'!G$5:G$1000, MATCH(3, 'Detalles movimientos'!$R$5:$R$1000, 0)), "") -> 0 | G12: =IFERROR(INDEX('Detalles movimientos'!H$5:H$1000, MATCH(3, 'Detalles movimientos'!$R$5:$R$1000, 0)), "") -> 0 | H12: =IFERROR(INDEX('Detalles movimientos'!I$5:I$1000, MATCH(3, 'Detalles movimientos'!$R$5:$R$1000, 0)), "") -> 2219 | I12: =IFERROR(INDEX('Detalles movimientos'!J$5:J$1000, MATCH(3, 'Detalles movimientos'!$R$5:$R$1000, 0)), "") -> 0 | ... L12: =IFERROR(INDEX('Detalles movimientos'!M$5:M$1000, MATCH(3, 'Detalles movimientos'!$R$5:$R$1000, 0)), "") -> Extraccion | M12: =IFERROR(INDEX('Detalles movimientos'!P$5:P$1000, MATCH(3, 'Detalles movimientos'!$R$5:$R$1000, 0)), "") -> 0
B13: =IFERROR(INDEX('Detalles movimientos'!C$5:C$1000, MATCH(4, 'Detalles movimientos'!$R$5:$R$1000, 0)), "") -> 46247 | C13: =IFERROR(INDEX('Detalles movimientos'!D$5:D$1000, MATCH(4, 'Detalles movimientos'!$R$5:$R$1000, 0)), "") -> Ignacio Guerrero | D13: =IFERROR(INDEX('Detalles movimientos'!E$5:E$1000, MATCH(4, 'Detalles movimientos'!$R$5:$R$1000, 0)), "") -> VJYL42 | E13: =IFERROR(INDEX('Detalles movimientos'!F$5:F$1000, MATCH(4, 'Detalles movimientos'!$R$5:$R$1000, 0)), "") -> Ignacio | F13: =IFERROR(INDEX('Detalles movimientos'!G$5:G$1000, MATCH(4, 'Detalles movimientos'!$R$5:$R$1000, 0)), "") -> 0 | G13: =IFERROR(INDEX('Detalles movimientos'!H$5:H$1000, MATCH(4, 'Detalles movimientos'!$R$5:$R$1000, 0)), "") -> 0 | H13: =IFERROR(INDEX('Detalles movimientos'!I$5:I$1000, MATCH(4, 'Detalles movimientos'!$R$5:$R$1000, 0)), "") -> 11539 | I13: =IFERROR(INDEX('Detalles movimientos'!J$5:J$1000, MATCH(4, 'Detalles movimientos'!$R$5:$R$1000, 0)), "") -> 0 | ... L13: =IFERROR(INDEX('Detalles movimientos'!M$5:M$1000, MATCH(4, 'Detalles movimientos'!$R$5:$R$1000, 0)), "") -> Extraccion | M13: =IFERROR(INDEX('Detalles movimientos'!P$5:P$1000, MATCH(4, 'Detalles movimientos'!$R$5:$R$1000, 0)), "") -> 0
B14: =IFERROR(INDEX('Detalles movimientos'!C$5:C$1000, MATCH(5, 'Detalles movimientos'!$R$5:$R$1000, 0)), "") | C14: =IFERROR(INDEX('Detalles movimientos'!D$5:D$1000, MATCH(5, 'Detalles movimientos'!$R$5:$R$1000, 0)), "") | D14: =IFERROR(INDEX('Detalles movimientos'!E$5:E$1000, MATCH(5, 'Detalles movimientos'!$R$5:$R$1000, 0)), "") | E14: =IFERROR(INDEX('Detalles movimientos'!F$5:F$1000, MATCH(5, 'Detalles movimientos'!$R$5:$R$1000, 0)), "") | F14: =IFERROR(INDEX('Detalles movimientos'!G$5:G$1000, MATCH(5, 'Detalles movimientos'!$R$5:$R$1000, 0)), "") | G14: =IFERROR(INDEX('Detalles movimientos'!H$5:H$1000, MATCH(5, 'Detalles movimientos'!$R$5:$R$1000, 0)), "") | H14: =IFERROR(INDEX('Detalles movimientos'!I$5:I$1000, MATCH(5, 'Detalles movimientos'!$R$5:$R$1000, 0)), "") | I14: =IFERROR(INDEX('Detalles movimientos'!J$5:J$1000, MATCH(5, 'Detalles movimientos'!$R$5:$R$1000, 0)), "") | ... L14: =IFERROR(INDEX('Detalles movimientos'!M$5:M$1000, MATCH(5, 'Detalles movimientos'!$R$5:$R$1000, 0)), "") | M14: =IFERROR(INDEX('Detalles movimientos'!P$5:P$1000, MATCH(5, 'Detalles movimientos'!$R$5:$R$1000, 0)), "")
B15: =IFERROR(INDEX('Detalles movimientos'!C$5:C$1000, MATCH(6, 'Detalles movimientos'!$R$5:$R$1000, 0)), "") | C15: =IFERROR(INDEX('Detalles movimientos'!D$5:D$1000, MATCH(6, 'Detalles movimientos'!$R$5:$R$1000, 0)), "") | D15: =IFERROR(INDEX('Detalles movimientos'!E$5:E$1000, MATCH(6, 'Detalles movimientos'!$R$5:$R$1000, 0)), "") | E15: =IFERROR(INDEX('Detalles movimientos'!F$5:F$1000, MATCH(6, 'Detalles movimientos'!$R$5:$R$1000, 0)), "") | F15: =IFERROR(INDEX('Detalles movimientos'!G$5:G$1000, MATCH(6, 'Detalles movimientos'!$R$5:$R$1000, 0)), "") | G15: =IFERROR(INDEX('Detalles movimientos'!H$5:H$1000, MATCH(6, 'Detalles movimientos'!$R$5:$R$1000, 0)), "") | H15: =IFERROR(INDEX('Detalles movimientos'!I$5:I$1000, MATCH(6, 'Detalles movimientos'!$R$5:$R$1000, 0)), "") | I15: =IFERROR(INDEX('Detalles movimientos'!J$5:J$1000, MATCH(6, 'Detalles movimientos'!$R$5:$R$1000, 0)), "") | ... L15: =IFERROR(INDEX('Detalles movimientos'!M$5:M$1000, MATCH(6, 'Detalles movimientos'!$R$5:$R$1000, 0)), "") | M15: =IFERROR(INDEX('Detalles movimientos'!P$5:P$1000, MATCH(6, 'Detalles movimientos'!$R$5:$R$1000, 0)), "")
B16: =IFERROR(INDEX('Detalles movimientos'!C$5:C$1000, MATCH(7, 'Detalles movimientos'!$R$5:$R$1000, 0)), "") | C16: =IFERROR(INDEX('Detalles movimientos'!D$5:D$1000, MATCH(7, 'Detalles movimientos'!$R$5:$R$1000, 0)), "") | D16: =IFERROR(INDEX('Detalles movimientos'!E$5:E$1000, MATCH(7, 'Detalles movimientos'!$R$5:$R$1000, 0)), "") | E16: =IFERROR(INDEX('Detalles movimientos'!F$5:F$1000, MATCH(7, 'Detalles movimientos'!$R$5:$R$1000, 0)), "") | F16: =IFERROR(INDEX('Detalles movimientos'!G$5:G$1000, MATCH(7, 'Detalles movimientos'!$R$5:$R$1000, 0)), "") | G16: =IFERROR(INDEX('Detalles movimientos'!H$5:H$1000, MATCH(7, 'Detalles movimientos'!$R$5:$R$1000, 0)), "") | H16: =IFERROR(INDEX('Detalles movimientos'!I$5:I$1000, MATCH(7, 'Detalles movimientos'!$R$5:$R$1000, 0)), "") | I16: =IFERROR(INDEX('Detalles movimientos'!J$5:J$1000, MATCH(7, 'Detalles movimientos'!$R$5:$R$1000, 0)), "") | ... L16: =IFERROR(INDEX('Detalles movimientos'!M$5:M$1000, MATCH(7, 'Detalles movimientos'!$R$5:$R$1000, 0)), "") | M16: =IFERROR(INDEX('Detalles movimientos'!P$5:P$1000, MATCH(7, 'Detalles movimientos'!$R$5:$R$1000, 0)), "")
B17: =IFERROR(INDEX('Detalles movimientos'!C$5:C$1000, MATCH(8, 'Detalles movimientos'!$R$5:$R$1000, 0)), "") | C17: =IFERROR(INDEX('Detalles movimientos'!D$5:D$1000, MATCH(8, 'Detalles movimientos'!$R$5:$R$1000, 0)), "") | D17: =IFERROR(INDEX('Detalles movimientos'!E$5:E$1000, MATCH(8, 'Detalles movimientos'!$R$5:$R$1000, 0)), "") | E17: =IFERROR(INDEX('Detalles movimientos'!F$5:F$1000, MATCH(8, 'Detalles movimientos'!$R$5:$R$1000, 0)), "") | F17: =IFERROR(INDEX('Detalles movimientos'!G$5:G$1000, MATCH(8, 'Detalles movimientos'!$R$5:$R$1000, 0)), "") | G17: =IFERROR(INDEX('Detalles movimientos'!H$5:H$1000, MATCH(8, 'Detalles movimientos'!$R$5:$R$1000, 0)), "") | H17: =IFERROR(INDEX('Detalles movimientos'!I$5:I$1000, MATCH(8, 'Detalles movimientos'!$R$5:$R$1000, 0)), "") | I17: =IFERROR(INDEX('Detalles movimientos'!J$5:J$1000, MATCH(8, 'Detalles movimientos'!$R$5:$R$1000, 0)), "") | ... L17: =IFERROR(INDEX('Detalles movimientos'!M$5:M$1000, MATCH(8, 'Detalles movimientos'!$R$5:$R$1000, 0)), "") | M17: =IFERROR(INDEX('Detalles movimientos'!P$5:P$1000, MATCH(8, 'Detalles movimientos'!$R$5:$R$1000, 0)), "")
B18: =IFERROR(INDEX('Detalles movimientos'!C$5:C$1000, MATCH(9, 'Detalles movimientos'!$R$5:$R$1000, 0)), "") | C18: =IFERROR(INDEX('Detalles movimientos'!D$5:D$1000, MATCH(9, 'Detalles movimientos'!$R$5:$R$1000, 0)), "") | D18: =IFERROR(INDEX('Detalles movimientos'!E$5:E$1000, MATCH(9, 'Detalles movimientos'!$R$5:$R$1000, 0)), "") | E18: =IFERROR(INDEX('Detalles movimientos'!F$5:F$1000, MATCH(9, 'Detalles movimientos'!$R$5:$R$1000, 0)), "") | F18: =IFERROR(INDEX('Detalles movimientos'!G$5:G$1000, MATCH(9, 'Detalles movimientos'!$R$5:$R$1000, 0)), "") | G18: =IFERROR(INDEX('Detalles movimientos'!H$5:H$1000, MATCH(9, 'Detalles movimientos'!$R$5:$R$1000, 0)), "") | H18: =IFERROR(INDEX('Detalles movimientos'!I$5:I$1000, MATCH(9, 'Detalles movimientos'!$R$5:$R$1000, 0)), "") | I18: =IFERROR(INDEX('Detalles movimientos'!J$5:J$1000, MATCH(9, 'Detalles movimientos'!$R$5:$R$1000, 0)), "") | ... L18: =IFERROR(INDEX('Detalles movimientos'!M$5:M$1000, MATCH(9, 'Detalles movimientos'!$R$5:$R$1000, 0)), "") | M18: =IFERROR(INDEX('Detalles movimientos'!P$5:P$1000, MATCH(9, 'Detalles movimientos'!$R$5:$R$1000, 0)), "")
B19: =IFERROR(INDEX('Detalles movimientos'!C$5:C$1000, MATCH(10, 'Detalles movimientos'!$R$5:$R$1000, 0)), "") | C19: =IFERROR(INDEX('Detalles movimientos'!D$5:D$1000, MATCH(10, 'Detalles movimientos'!$R$5:$R$1000, 0)), "") | D19: =IFERROR(INDEX('Detalles movimientos'!E$5:E$1000, MATCH(10, 'Detalles movimientos'!$R$5:$R$1000, 0)), "") | E19: =IFERROR(INDEX('Detalles movimientos'!F$5:F$1000, MATCH(10, 'Detalles movimientos'!$R$5:$R$1000, 0)), "") | F19: =IFERROR(INDEX('Detalles movimientos'!G$5:G$1000, MATCH(10, 'Detalles movimientos'!$R$5:$R$1000, 0)), "") | G19: =IFERROR(INDEX('Detalles movimientos'!H$5:H$1000, MATCH(10, 'Detalles movimientos'!$R$5:$R$1000, 0)), "") | H19: =IFERROR(INDEX('Detalles movimientos'!I$5:I$1000, MATCH(10, 'Detalles movimientos'!$R$5:$R$1000, 0)), "") | I19: =IFERROR(INDEX('Detalles movimientos'!J$5:J$1000, MATCH(10, 'Detalles movimientos'!$R$5:$R$1000, 0)), "") | ... L19: =IFERROR(INDEX('Detalles movimientos'!M$5:M$1000, MATCH(10, 'Detalles movimientos'!$R$5:$R$1000, 0)), "") | M19: =IFERROR(INDEX('Detalles movimientos'!P$5:P$1000, MATCH(10, 'Detalles movimientos'!$R$5:$R$1000, 0)), "")
B20: =IFERROR(INDEX('Detalles movimientos'!C$5:C$1000, MATCH(11, 'Detalles movimientos'!$R$5:$R$1000, 0)), "") | C20: =IFERROR(INDEX('Detalles movimientos'!D$5:D$1000, MATCH(11, 'Detalles movimientos'!$R$5:$R$1000, 0)), "") | D20: =IFERROR(INDEX('Detalles movimientos'!E$5:E$1000, MATCH(11, 'Detalles movimientos'!$R$5:$R$1000, 0)), "") | E20: =IFERROR(INDEX('Detalles movimientos'!F$5:F$1000, MATCH(11, 'Detalles movimientos'!$R$5:$R$1000, 0)), "") | F20: =IFERROR(INDEX('Detalles movimientos'!G$5:G$1000, MATCH(11, 'Detalles movimientos'!$R$5:$R$1000, 0)), "") | G20: =IFERROR(INDEX('Detalles movimientos'!H$5:H$1000, MATCH(11, 'Detalles movimientos'!$R$5:$R$1000, 0)), "") | H20: =IFERROR(INDEX('Detalles movimientos'!I$5:I$1000, MATCH(11, 'Detalles movimientos'!$R$5:$R$1000, 0)), "") | I20: =IFERROR(INDEX('Detalles movimientos'!J$5:J$1000, MATCH(11, 'Detalles movimientos'!$R$5:$R$1000, 0)), "") | ... L20: =IFERROR(INDEX('Detalles movimientos'!M$5:M$1000, MATCH(11, 'Detalles movimientos'!$R$5:$R$1000, 0)), "") | M20: =IFERROR(INDEX('Detalles movimientos'!P$5:P$1000, MATCH(11, 'Detalles movimientos'!$R$5:$R$1000, 0)), "")
B21: =IFERROR(INDEX('Detalles movimientos'!C$5:C$1000, MATCH(12, 'Detalles movimientos'!$R$5:$R$1000, 0)), "") | C21: =IFERROR(INDEX('Detalles movimientos'!D$5:D$1000, MATCH(12, 'Detalles movimientos'!$R$5:$R$1000, 0)), "") | D21: =IFERROR(INDEX('Detalles movimientos'!E$5:E$1000, MATCH(12, 'Detalles movimientos'!$R$5:$R$1000, 0)), "") | E21: =IFERROR(INDEX('Detalles movimientos'!F$5:F$1000, MATCH(12, 'Detalles movimientos'!$R$5:$R$1000, 0)), "") | F21: =IFERROR(INDEX('Detalles movimientos'!G$5:G$1000, MATCH(12, 'Detalles movimientos'!$R$5:$R$1000, 0)), "") | G21: =IFERROR(INDEX('Detalles movimientos'!H$5:H$1000, MATCH(12, 'Detalles movimientos'!$R$5:$R$1000, 0)), "") | H21: =IFERROR(INDEX('Detalles movimientos'!I$5:I$1000, MATCH(12, 'Detalles movimientos'!$R$5:$R$1000, 0)), "") | I21: =IFERROR(INDEX('Detalles movimientos'!J$5:J$1000, MATCH(12, 'Detalles movimientos'!$R$5:$R$1000, 0)), "") | ... L21: =IFERROR(INDEX('Detalles movimientos'!M$5:M$1000, MATCH(12, 'Detalles movimientos'!$R$5:$R$1000, 0)), "") | M21: =IFERROR(INDEX('Detalles movimientos'!P$5:P$1000, MATCH(12, 'Detalles movimientos'!$R$5:$R$1000, 0)), "")
B22: =IFERROR(INDEX('Detalles movimientos'!C$5:C$1000, MATCH(13, 'Detalles movimientos'!$R$5:$R$1000, 0)), "") | C22: =IFERROR(INDEX('Detalles movimientos'!D$5:D$1000, MATCH(13, 'Detalles movimientos'!$R$5:$R$1000, 0)), "") | D22: =IFERROR(INDEX('Detalles movimientos'!E$5:E$1000, MATCH(13, 'Detalles movimientos'!$R$5:$R$1000, 0)), "") | E22: =IFERROR(INDEX('Detalles movimientos'!F$5:F$1000, MATCH(13, 'Detalles movimientos'!$R$5:$R$1000, 0)), "") | F22: =IFERROR(INDEX('Detalles movimientos'!G$5:G$1000, MATCH(13, 'Detalles movimientos'!$R$5:$R$1000, 0)), "") | G22: =IFERROR(INDEX('Detalles movimientos'!H$5:H$1000, MATCH(13, 'Detalles movimientos'!$R$5:$R$1000, 0)), "") | H22: =IFERROR(INDEX('Detalles movimientos'!I$5:I$1000, MATCH(13, 'Detalles movimientos'!$R$5:$R$1000, 0)), "") | I22: =IFERROR(INDEX('Detalles movimientos'!J$5:J$1000, MATCH(13, 'Detalles movimientos'!$R$5:$R$1000, 0)), "") | ... L22: =IFERROR(INDEX('Detalles movimientos'!M$5:M$1000, MATCH(13, 'Detalles movimientos'!$R$5:$R$1000, 0)), "") | M22: =IFERROR(INDEX('Detalles movimientos'!P$5:P$1000, MATCH(13, 'Detalles movimientos'!$R$5:$R$1000, 0)), "")
B23: =IFERROR(INDEX('Detalles movimientos'!C$5:C$1000, MATCH(14, 'Detalles movimientos'!$R$5:$R$1000, 0)), "") | C23: =IFERROR(INDEX('Detalles movimientos'!D$5:D$1000, MATCH(14, 'Detalles movimientos'!$R$5:$R$1000, 0)), "") | D23: =IFERROR(INDEX('Detalles movimientos'!E$5:E$1000, MATCH(14, 'Detalles movimientos'!$R$5:$R$1000, 0)), "") | E23: =IFERROR(INDEX('Detalles movimientos'!F$5:F$1000, MATCH(14, 'Detalles movimientos'!$R$5:$R$1000, 0)), "") | F23: =IFERROR(INDEX('Detalles movimientos'!G$5:G$1000, MATCH(14, 'Detalles movimientos'!$R$5:$R$1000, 0)), "") | G23: =IFERROR(INDEX('Detalles movimientos'!H$5:H$1000, MATCH(14, 'Detalles movimientos'!$R$5:$R$1000, 0)), "") | H23: =IFERROR(INDEX('Detalles movimientos'!I$5:I$1000, MATCH(14, 'Detalles movimientos'!$R$5:$R$1000, 0)), "") | I23: =IFERROR(INDEX('Detalles movimientos'!J$5:J$1000, MATCH(14, 'Detalles movimientos'!$R$5:$R$1000, 0)), "") | ... L23: =IFERROR(INDEX('Detalles movimientos'!M$5:M$1000, MATCH(14, 'Detalles movimientos'!$R$5:$R$1000, 0)), "") | M23: =IFERROR(INDEX('Detalles movimientos'!P$5:P$1000, MATCH(14, 'Detalles movimientos'!$R$5:$R$1000, 0)), "")
B24: =IFERROR(INDEX('Detalles movimientos'!C$5:C$1000, MATCH(15, 'Detalles movimientos'!$R$5:$R$1000, 0)), "") | C24: =IFERROR(INDEX('Detalles movimientos'!D$5:D$1000, MATCH(15, 'Detalles movimientos'!$R$5:$R$1000, 0)), "") | D24: =IFERROR(INDEX('Detalles movimientos'!E$5:E$1000, MATCH(15, 'Detalles movimientos'!$R$5:$R$1000, 0)), "") | E24: =IFERROR(INDEX('Detalles movimientos'!F$5:F$1000, MATCH(15, 'Detalles movimientos'!$R$5:$R$1000, 0)), "") | F24: =IFERROR(INDEX('Detalles movimientos'!G$5:G$1000, MATCH(15, 'Detalles movimientos'!$R$5:$R$1000, 0)), "") | G24: =IFERROR(INDEX('Detalles movimientos'!H$5:H$1000, MATCH(15, 'Detalles movimientos'!$R$5:$R$1000, 0)), "") | H24: =IFERROR(INDEX('Detalles movimientos'!I$5:I$1000, MATCH(15, 'Detalles movimientos'!$R$5:$R$1000, 0)), "") | I24: =IFERROR(INDEX('Detalles movimientos'!J$5:J$1000, MATCH(15, 'Detalles movimientos'!$R$5:$R$1000, 0)), "") | ... L24: =IFERROR(INDEX('Detalles movimientos'!M$5:M$1000, MATCH(15, 'Detalles movimientos'!$R$5:$R$1000, 0)), "") | M24: =IFERROR(INDEX('Detalles movimientos'!P$5:P$1000, MATCH(15, 'Detalles movimientos'!$R$5:$R$1000, 0)), "")
B25: =IFERROR(INDEX('Detalles movimientos'!C$5:C$1000, MATCH(16, 'Detalles movimientos'!$R$5:$R$1000, 0)), "") | C25: =IFERROR(INDEX('Detalles movimientos'!D$5:D$1000, MATCH(16, 'Detalles movimientos'!$R$5:$R$1000, 0)), "") | D25: =IFERROR(INDEX('Detalles movimientos'!E$5:E$1000, MATCH(16, 'Detalles movimientos'!$R$5:$R$1000, 0)), "") | E25: =IFERROR(INDEX('Detalles movimientos'!F$5:F$1000, MATCH(16, 'Detalles movimientos'!$R$5:$R$1000, 0)), "") | F25: =IFERROR(INDEX('Detalles movimientos'!G$5:G$1000, MATCH(16, 'Detalles movimientos'!$R$5:$R$1000, 0)), "") | G25: =IFERROR(INDEX('Detalles movimientos'!H$5:H$1000, MATCH(16, 'Detalles movimientos'!$R$5:$R$1000, 0)), "") | H25: =IFERROR(INDEX('Detalles movimientos'!I$5:I$1000, MATCH(16, 'Detalles movimientos'!$R$5:$R$1000, 0)), "") | I25: =IFERROR(INDEX('Detalles movimientos'!J$5:J$1000, MATCH(16, 'Detalles movimientos'!$R$5:$R$1000, 0)), "") | ... L25: =IFERROR(INDEX('Detalles movimientos'!M$5:M$1000, MATCH(16, 'Detalles movimientos'!$R$5:$R$1000, 0)), "") | M25: =IFERROR(INDEX('Detalles movimientos'!P$5:P$1000, MATCH(16, 'Detalles movimientos'!$R$5:$R$1000, 0)), "")
B26: =IFERROR(INDEX('Detalles movimientos'!C$5:C$1000, MATCH(17, 'Detalles movimientos'!$R$5:$R$1000, 0)), "") | C26: =IFERROR(INDEX('Detalles movimientos'!D$5:D$1000, MATCH(17, 'Detalles movimientos'!$R$5:$R$1000, 0)), "") | D26: =IFERROR(INDEX('Detalles movimientos'!E$5:E$1000, MATCH(17, 'Detalles movimientos'!$R$5:$R$1000, 0)), "") | E26: =IFERROR(INDEX('Detalles movimientos'!F$5:F$1000, MATCH(17, 'Detalles movimientos'!$R$5:$R$1000, 0)), "") | F26: =IFERROR(INDEX('Detalles movimientos'!G$5:G$1000, MATCH(17, 'Detalles movimientos'!$R$5:$R$1000, 0)), "") | G26: =IFERROR(INDEX('Detalles movimientos'!H$5:H$1000, MATCH(17, 'Detalles movimientos'!$R$5:$R$1000, 0)), "") | H26: =IFERROR(INDEX('Detalles movimientos'!I$5:I$1000, MATCH(17, 'Detalles movimientos'!$R$5:$R$1000, 0)), "") | I26: =IFERROR(INDEX('Detalles movimientos'!J$5:J$1000, MATCH(17, 'Detalles movimientos'!$R$5:$R$1000, 0)), "") | ... L26: =IFERROR(INDEX('Detalles movimientos'!M$5:M$1000, MATCH(17, 'Detalles movimientos'!$R$5:$R$1000, 0)), "") | M26: =IFERROR(INDEX('Detalles movimientos'!P$5:P$1000, MATCH(17, 'Detalles movimientos'!$R$5:$R$1000, 0)), "")
B27: =IFERROR(INDEX('Detalles movimientos'!C$5:C$1000, MATCH(18, 'Detalles movimientos'!$R$5:$R$1000, 0)), "") | C27: =IFERROR(INDEX('Detalles movimientos'!D$5:D$1000, MATCH(18, 'Detalles movimientos'!$R$5:$R$1000, 0)), "") | D27: =IFERROR(INDEX('Detalles movimientos'!E$5:E$1000, MATCH(18, 'Detalles movimientos'!$R$5:$R$1000, 0)), "") | E27: =IFERROR(INDEX('Detalles movimientos'!F$5:F$1000, MATCH(18, 'Detalles movimientos'!$R$5:$R$1000, 0)), "") | F27: =IFERROR(INDEX('Detalles movimientos'!G$5:G$1000, MATCH(18, 'Detalles movimientos'!$R$5:$R$1000, 0)), "") | G27: =IFERROR(INDEX('Detalles movimientos'!H$5:H$1000, MATCH(18, 'Detalles movimientos'!$R$5:$R$1000, 0)), "") | H27: =IFERROR(INDEX('Detalles movimientos'!I$5:I$1000, MATCH(18, 'Detalles movimientos'!$R$5:$R$1000, 0)), "") | I27: =IFERROR(INDEX('Detalles movimientos'!J$5:J$1000, MATCH(18, 'Detalles movimientos'!$R$5:$R$1000, 0)), "") | ... L27: =IFERROR(INDEX('Detalles movimientos'!M$5:M$1000, MATCH(18, 'Detalles movimientos'!$R$5:$R$1000, 0)), "") | M27: =IFERROR(INDEX('Detalles movimientos'!P$5:P$1000, MATCH(18, 'Detalles movimientos'!$R$5:$R$1000, 0)), "")
B28: =IFERROR(INDEX('Detalles movimientos'!C$5:C$1000, MATCH(19, 'Detalles movimientos'!$R$5:$R$1000, 0)), "") | C28: =IFERROR(INDEX('Detalles movimientos'!D$5:D$1000, MATCH(19, 'Detalles movimientos'!$R$5:$R$1000, 0)), "") | D28: =IFERROR(INDEX('Detalles movimientos'!E$5:E$1000, MATCH(19, 'Detalles movimientos'!$R$5:$R$1000, 0)), "") | E28: =IFERROR(INDEX('Detalles movimientos'!F$5:F$1000, MATCH(19, 'Detalles movimientos'!$R$5:$R$1000, 0)), "") | F28: =IFERROR(INDEX('Detalles movimientos'!G$5:G$1000, MATCH(19, 'Detalles movimientos'!$R$5:$R$1000, 0)), "") | G28: =IFERROR(INDEX('Detalles movimientos'!H$5:H$1000, MATCH(19, 'Detalles movimientos'!$R$5:$R$1000, 0)), "") | H28: =IFERROR(INDEX('Detalles movimientos'!I$5:I$1000, MATCH(19, 'Detalles movimientos'!$R$5:$R$1000, 0)), "") | I28: =IFERROR(INDEX('Detalles movimientos'!J$5:J$1000, MATCH(19, 'Detalles movimientos'!$R$5:$R$1000, 0)), "") | ... L28: =IFERROR(INDEX('Detalles movimientos'!M$5:M$1000, MATCH(19, 'Detalles movimientos'!$R$5:$R$1000, 0)), "") | M28: =IFERROR(INDEX('Detalles movimientos'!P$5:P$1000, MATCH(19, 'Detalles movimientos'!$R$5:$R$1000, 0)), "")
B29: =IFERROR(INDEX('Detalles movimientos'!C$5:C$1000, MATCH(20, 'Detalles movimientos'!$R$5:$R$1000, 0)), "") | C29: =IFERROR(INDEX('Detalles movimientos'!D$5:D$1000, MATCH(20, 'Detalles movimientos'!$R$5:$R$1000, 0)), "") | D29: =IFERROR(INDEX('Detalles movimientos'!E$5:E$1000, MATCH(20, 'Detalles movimientos'!$R$5:$R$1000, 0)), "") | E29: =IFERROR(INDEX('Detalles movimientos'!F$5:F$1000, MATCH(20, 'Detalles movimientos'!$R$5:$R$1000, 0)), "") | F29: =IFERROR(INDEX('Detalles movimientos'!G$5:G$1000, MATCH(20, 'Detalles movimientos'!$R$5:$R$1000, 0)), "") | G29: =IFERROR(INDEX('Detalles movimientos'!H$5:H$1000, MATCH(20, 'Detalles movimientos'!$R$5:$R$1000, 0)), "") | H29: =IFERROR(INDEX('Detalles movimientos'!I$5:I$1000, MATCH(20, 'Detalles movimientos'!$R$5:$R$1000, 0)), "") | I29: =IFERROR(INDEX('Detalles movimientos'!J$5:J$1000, MATCH(20, 'Detalles movimientos'!$R$5:$R$1000, 0)), "") | ... L29: =IFERROR(INDEX('Detalles movimientos'!M$5:M$1000, MATCH(20, 'Detalles movimientos'!$R$5:$R$1000, 0)), "") | M29: =IFERROR(INDEX('Detalles movimientos'!P$5:P$1000, MATCH(20, 'Detalles movimientos'!$R$5:$R$1000, 0)), "")
B30: =IFERROR(INDEX('Detalles movimientos'!C$5:C$1000, MATCH(21, 'Detalles movimientos'!$R$5:$R$1000, 0)), "") | C30: =IFERROR(INDEX('Detalles movimientos'!D$5:D$1000, MATCH(21, 'Detalles movimientos'!$R$5:$R$1000, 0)), "") | D30: =IFERROR(INDEX('Detalles movimientos'!E$5:E$1000, MATCH(21, 'Detalles movimientos'!$R$5:$R$1000, 0)), "") | E30: =IFERROR(INDEX('Detalles movimientos'!F$5:F$1000, MATCH(21, 'Detalles movimientos'!$R$5:$R$1000, 0)), "") | F30: =IFERROR(INDEX('Detalles movimientos'!G$5:G$1000, MATCH(21, 'Detalles movimientos'!$R$5:$R$1000, 0)), "") | G30: =IFERROR(INDEX('Detalles movimientos'!H$5:H$1000, MATCH(21, 'Detalles movimientos'!$R$5:$R$1000, 0)), "") | H30: =IFERROR(INDEX('Detalles movimientos'!I$5:I$1000, MATCH(21, 'Detalles movimientos'!$R$5:$R$1000, 0)), "") | I30: =IFERROR(INDEX('Detalles movimientos'!J$5:J$1000, MATCH(21, 'Detalles movimientos'!$R$5:$R$1000, 0)), "") | ... L30: =IFERROR(INDEX('Detalles movimientos'!M$5:M$1000, MATCH(21, 'Detalles movimientos'!$R$5:$R$1000, 0)), "") | M30: =IFERROR(INDEX('Detalles movimientos'!P$5:P$1000, MATCH(21, 'Detalles movimientos'!$R$5:$R$1000, 0)), "")
B31: =IFERROR(INDEX('Detalles movimientos'!C$5:C$1000, MATCH(22, 'Detalles movimientos'!$R$5:$R$1000, 0)), "") | C31: =IFERROR(INDEX('Detalles movimientos'!D$5:D$1000, MATCH(22, 'Detalles movimientos'!$R$5:$R$1000, 0)), "") | D31: =IFERROR(INDEX('Detalles movimientos'!E$5:E$1000, MATCH(22, 'Detalles movimientos'!$R$5:$R$1000, 0)), "") | E31: =IFERROR(INDEX('Detalles movimientos'!F$5:F$1000, MATCH(22, 'Detalles movimientos'!$R$5:$R$1000, 0)), "") | F31: =IFERROR(INDEX('Detalles movimientos'!G$5:G$1000, MATCH(22, 'Detalles movimientos'!$R$5:$R$1000, 0)), "") | G31: =IFERROR(INDEX('Detalles movimientos'!H$5:H$1000, MATCH(22, 'Detalles movimientos'!$R$5:$R$1000, 0)), "") | H31: =IFERROR(INDEX('Detalles movimientos'!I$5:I$1000, MATCH(22, 'Detalles movimientos'!$R$5:$R$1000, 0)), "") | I31: =IFERROR(INDEX('Detalles movimientos'!J$5:J$1000, MATCH(22, 'Detalles movimientos'!$R$5:$R$1000, 0)), "") | ... L31: =IFERROR(INDEX('Detalles movimientos'!M$5:M$1000, MATCH(22, 'Detalles movimientos'!$R$5:$R$1000, 0)), "") | M31: =IFERROR(INDEX('Detalles movimientos'!P$5:P$1000, MATCH(22, 'Detalles movimientos'!$R$5:$R$1000, 0)), "")
B32: =IFERROR(INDEX('Detalles movimientos'!C$5:C$1000, MATCH(23, 'Detalles movimientos'!$R$5:$R$1000, 0)), "") | C32: =IFERROR(INDEX('Detalles movimientos'!D$5:D$1000, MATCH(23, 'Detalles movimientos'!$R$5:$R$1000, 0)), "") | D32: =IFERROR(INDEX('Detalles movimientos'!E$5:E$1000, MATCH(23, 'Detalles movimientos'!$R$5:$R$1000, 0)), "") | E32: =IFERROR(INDEX('Detalles movimientos'!F$5:F$1000, MATCH(23, 'Detalles movimientos'!$R$5:$R$1000, 0)), "") | F32: =IFERROR(INDEX('Detalles movimientos'!G$5:G$1000, MATCH(23, 'Detalles movimientos'!$R$5:$R$1000, 0)), "") | G32: =IFERROR(INDEX('Detalles movimientos'!H$5:H$1000, MATCH(23, 'Detalles movimientos'!$R$5:$R$1000, 0)), "") | H32: =IFERROR(INDEX('Detalles movimientos'!I$5:I$1000, MATCH(23, 'Detalles movimientos'!$R$5:$R$1000, 0)), "") | I32: =IFERROR(INDEX('Detalles movimientos'!J$5:J$1000, MATCH(23, 'Detalles movimientos'!$R$5:$R$1000, 0)), "") | ... L32: =IFERROR(INDEX('Detalles movimientos'!M$5:M$1000, MATCH(23, 'Detalles movimientos'!$R$5:$R$1000, 0)), "") | M32: =IFERROR(INDEX('Detalles movimientos'!P$5:P$1000, MATCH(23, 'Detalles movimientos'!$R$5:$R$1000, 0)), "")
B33: =IFERROR(INDEX('Detalles movimientos'!C$5:C$1000, MATCH(24, 'Detalles movimientos'!$R$5:$R$1000, 0)), "") | C33: =IFERROR(INDEX('Detalles movimientos'!D$5:D$1000, MATCH(24, 'Detalles movimientos'!$R$5:$R$1000, 0)), "") | D33: =IFERROR(INDEX('Detalles movimientos'!E$5:E$1000, MATCH(24, 'Detalles movimientos'!$R$5:$R$1000, 0)), "") | E33: =IFERROR(INDEX('Detalles movimientos'!F$5:F$1000, MATCH(24, 'Detalles movimientos'!$R$5:$R$1000, 0)), "") | F33: =IFERROR(INDEX('Detalles movimientos'!G$5:G$1000, MATCH(24, 'Detalles movimientos'!$R$5:$R$1000, 0)), "") | G33: =IFERROR(INDEX('Detalles movimientos'!H$5:H$1000, MATCH(24, 'Detalles movimientos'!$R$5:$R$1000, 0)), "") | H33: =IFERROR(INDEX('Detalles movimientos'!I$5:I$1000, MATCH(24, 'Detalles movimientos'!$R$5:$R$1000, 0)), "") | I33: =IFERROR(INDEX('Detalles movimientos'!J$5:J$1000, MATCH(24, 'Detalles movimientos'!$R$5:$R$1000, 0)), "") | ... L33: =IFERROR(INDEX('Detalles movimientos'!M$5:M$1000, MATCH(24, 'Detalles movimientos'!$R$5:$R$1000, 0)), "") | M33: =IFERROR(INDEX('Detalles movimientos'!P$5:P$1000, MATCH(24, 'Detalles movimientos'!$R$5:$R$1000, 0)), "")
B34: =IFERROR(INDEX('Detalles movimientos'!C$5:C$1000, MATCH(25, 'Detalles movimientos'!$R$5:$R$1000, 0)), "") | C34: =IFERROR(INDEX('Detalles movimientos'!D$5:D$1000, MATCH(25, 'Detalles movimientos'!$R$5:$R$1000, 0)), "") | D34: =IFERROR(INDEX('Detalles movimientos'!E$5:E$1000, MATCH(25, 'Detalles movimientos'!$R$5:$R$1000, 0)), "") | E34: =IFERROR(INDEX('Detalles movimientos'!F$5:F$1000, MATCH(25, 'Detalles movimientos'!$R$5:$R$1000, 0)), "") | F34: =IFERROR(INDEX('Detalles movimientos'!G$5:G$1000, MATCH(25, 'Detalles movimientos'!$R$5:$R$1000, 0)), "") | G34: =IFERROR(INDEX('Detalles movimientos'!H$5:H$1000, MATCH(25, 'Detalles movimientos'!$R$5:$R$1000, 0)), "") | H34: =IFERROR(INDEX('Detalles movimientos'!I$5:I$1000, MATCH(25, 'Detalles movimientos'!$R$5:$R$1000, 0)), "") | I34: =IFERROR(INDEX('Detalles movimientos'!J$5:J$1000, MATCH(25, 'Detalles movimientos'!$R$5:$R$1000, 0)), "") | ... L34: =IFERROR(INDEX('Detalles movimientos'!M$5:M$1000, MATCH(25, 'Detalles movimientos'!$R$5:$R$1000, 0)), "") | M34: =IFERROR(INDEX('Detalles movimientos'!P$5:P$1000, MATCH(25, 'Detalles movimientos'!$R$5:$R$1000, 0)), "")
B35: =IFERROR(INDEX('Detalles movimientos'!C$5:C$1000, MATCH(26, 'Detalles movimientos'!$R$5:$R$1000, 0)), "") | C35: =IFERROR(INDEX('Detalles movimientos'!D$5:D$1000, MATCH(26, 'Detalles movimientos'!$R$5:$R$1000, 0)), "") | D35: =IFERROR(INDEX('Detalles movimientos'!E$5:E$1000, MATCH(26, 'Detalles movimientos'!$R$5:$R$1000, 0)), "") | E35: =IFERROR(INDEX('Detalles movimientos'!F$5:F$1000, MATCH(26, 'Detalles movimientos'!$R$5:$R$1000, 0)), "") | F35: =IFERROR(INDEX('Detalles movimientos'!G$5:G$1000, MATCH(26, 'Detalles movimientos'!$R$5:$R$1000, 0)), "") | G35: =IFERROR(INDEX('Detalles movimientos'!H$5:H$1000, MATCH(26, 'Detalles movimientos'!$R$5:$R$1000, 0)), "") | H35: =IFERROR(INDEX('Detalles movimientos'!I$5:I$1000, MATCH(26, 'Detalles movimientos'!$R$5:$R$1000, 0)), "") | I35: =IFERROR(INDEX('Detalles movimientos'!J$5:J$1000, MATCH(26, 'Detalles movimientos'!$R$5:$R$1000, 0)), "") | ... L35: =IFERROR(INDEX('Detalles movimientos'!M$5:M$1000, MATCH(26, 'Detalles movimientos'!$R$5:$R$1000, 0)), "") | M35: =IFERROR(INDEX('Detalles movimientos'!P$5:P$1000, MATCH(26, 'Detalles movimientos'!$R$5:$R$1000, 0)), "")
B36: =IFERROR(INDEX('Detalles movimientos'!C$5:C$1000, MATCH(27, 'Detalles movimientos'!$R$5:$R$1000, 0)), "") | C36: =IFERROR(INDEX('Detalles movimientos'!D$5:D$1000, MATCH(27, 'Detalles movimientos'!$R$5:$R$1000, 0)), "") | D36: =IFERROR(INDEX('Detalles movimientos'!E$5:E$1000, MATCH(27, 'Detalles movimientos'!$R$5:$R$1000, 0)), "") | E36: =IFERROR(INDEX('Detalles movimientos'!F$5:F$1000, MATCH(27, 'Detalles movimientos'!$R$5:$R$1000, 0)), "") | F36: =IFERROR(INDEX('Detalles movimientos'!G$5:G$1000, MATCH(27, 'Detalles movimientos'!$R$5:$R$1000, 0)), "") | G36: =IFERROR(INDEX('Detalles movimientos'!H$5:H$1000, MATCH(27, 'Detalles movimientos'!$R$5:$R$1000, 0)), "") | H36: =IFERROR(INDEX('Detalles movimientos'!I$5:I$1000, MATCH(27, 'Detalles movimientos'!$R$5:$R$1000, 0)), "") | I36: =IFERROR(INDEX('Detalles movimientos'!J$5:J$1000, MATCH(27, 'Detalles movimientos'!$R$5:$R$1000, 0)), "") | ... L36: =IFERROR(INDEX('Detalles movimientos'!M$5:M$1000, MATCH(27, 'Detalles movimientos'!$R$5:$R$1000, 0)), "") | M36: =IFERROR(INDEX('Detalles movimientos'!P$5:P$1000, MATCH(27, 'Detalles movimientos'!$R$5:$R$1000, 0)), "")
B37: =IFERROR(INDEX('Detalles movimientos'!C$5:C$1000, MATCH(28, 'Detalles movimientos'!$R$5:$R$1000, 0)), "") | C37: =IFERROR(INDEX('Detalles movimientos'!D$5:D$1000, MATCH(28, 'Detalles movimientos'!$R$5:$R$1000, 0)), "") | D37: =IFERROR(INDEX('Detalles movimientos'!E$5:E$1000, MATCH(28, 'Detalles movimientos'!$R$5:$R$1000, 0)), "") | E37: =IFERROR(INDEX('Detalles movimientos'!F$5:F$1000, MATCH(28, 'Detalles movimientos'!$R$5:$R$1000, 0)), "") | F37: =IFERROR(INDEX('Detalles movimientos'!G$5:G$1000, MATCH(28, 'Detalles movimientos'!$R$5:$R$1000, 0)), "") | G37: =IFERROR(INDEX('Detalles movimientos'!H$5:H$1000, MATCH(28, 'Detalles movimientos'!$R$5:$R$1000, 0)), "") | H37: =IFERROR(INDEX('Detalles movimientos'!I$5:I$1000, MATCH(28, 'Detalles movimientos'!$R$5:$R$1000, 0)), "") | I37: =IFERROR(INDEX('Detalles movimientos'!J$5:J$1000, MATCH(28, 'Detalles movimientos'!$R$5:$R$1000, 0)), "") | ... L37: =IFERROR(INDEX('Detalles movimientos'!M$5:M$1000, MATCH(28, 'Detalles movimientos'!$R$5:$R$1000, 0)), "") | M37: =IFERROR(INDEX('Detalles movimientos'!P$5:P$1000, MATCH(28, 'Detalles movimientos'!$R$5:$R$1000, 0)), "")
B38: =IFERROR(INDEX('Detalles movimientos'!C$5:C$1000, MATCH(29, 'Detalles movimientos'!$R$5:$R$1000, 0)), "") | C38: =IFERROR(INDEX('Detalles movimientos'!D$5:D$1000, MATCH(29, 'Detalles movimientos'!$R$5:$R$1000, 0)), "") | D38: =IFERROR(INDEX('Detalles movimientos'!E$5:E$1000, MATCH(29, 'Detalles movimientos'!$R$5:$R$1000, 0)), "") | E38: =IFERROR(INDEX('Detalles movimientos'!F$5:F$1000, MATCH(29, 'Detalles movimientos'!$R$5:$R$1000, 0)), "") | F38: =IFERROR(INDEX('Detalles movimientos'!G$5:G$1000, MATCH(29, 'Detalles movimientos'!$R$5:$R$1000, 0)), "") | G38: =IFERROR(INDEX('Detalles movimientos'!H$5:H$1000, MATCH(29, 'Detalles movimientos'!$R$5:$R$1000, 0)), "") | H38: =IFERROR(INDEX('Detalles movimientos'!I$5:I$1000, MATCH(29, 'Detalles movimientos'!$R$5:$R$1000, 0)), "") | I38: =IFERROR(INDEX('Detalles movimientos'!J$5:J$1000, MATCH(29, 'Detalles movimientos'!$R$5:$R$1000, 0)), "") | ... L38: =IFERROR(INDEX('Detalles movimientos'!M$5:M$1000, MATCH(29, 'Detalles movimientos'!$R$5:$R$1000, 0)), "") | M38: =IFERROR(INDEX('Detalles movimientos'!P$5:P$1000, MATCH(29, 'Detalles movimientos'!$R$5:$R$1000, 0)), "")
B39: =IFERROR(INDEX('Detalles movimientos'!C$5:C$1000, MATCH(30, 'Detalles movimientos'!$R$5:$R$1000, 0)), "") | C39: =IFERROR(INDEX('Detalles movimientos'!D$5:D$1000, MATCH(30, 'Detalles movimientos'!$R$5:$R$1000, 0)), "") | D39: =IFERROR(INDEX('Detalles movimientos'!E$5:E$1000, MATCH(30, 'Detalles movimientos'!$R$5:$R$1000, 0)), "") | E39: =IFERROR(INDEX('Detalles movimientos'!F$5:F$1000, MATCH(30, 'Detalles movimientos'!$R$5:$R$1000, 0)), "") | F39: =IFERROR(INDEX('Detalles movimientos'!G$5:G$1000, MATCH(30, 'Detalles movimientos'!$R$5:$R$1000, 0)), "") | G39: =IFERROR(INDEX('Detalles movimientos'!H$5:H$1000, MATCH(30, 'Detalles movimientos'!$R$5:$R$1000, 0)), "") | H39: =IFERROR(INDEX('Detalles movimientos'!I$5:I$1000, MATCH(30, 'Detalles movimientos'!$R$5:$R$1000, 0)), "") | I39: =IFERROR(INDEX('Detalles movimientos'!J$5:J$1000, MATCH(30, 'Detalles movimientos'!$R$5:$R$1000, 0)), "") | ... L39: =IFERROR(INDEX('Detalles movimientos'!M$5:M$1000, MATCH(30, 'Detalles movimientos'!$R$5:$R$1000, 0)), "") | M39: =IFERROR(INDEX('Detalles movimientos'!P$5:P$1000, MATCH(30, 'Detalles movimientos'!$R$5:$R$1000, 0)), "")
B40: =IFERROR(INDEX('Detalles movimientos'!C$5:C$1000, MATCH(31, 'Detalles movimientos'!$R$5:$R$1000, 0)), "") | C40: =IFERROR(INDEX('Detalles movimientos'!D$5:D$1000, MATCH(31, 'Detalles movimientos'!$R$5:$R$1000, 0)), "") | D40: =IFERROR(INDEX('Detalles movimientos'!E$5:E$1000, MATCH(31, 'Detalles movimientos'!$R$5:$R$1000, 0)), "") | E40: =IFERROR(INDEX('Detalles movimientos'!F$5:F$1000, MATCH(31, 'Detalles movimientos'!$R$5:$R$1000, 0)), "") | F40: =IFERROR(INDEX('Detalles movimientos'!G$5:G$1000, MATCH(31, 'Detalles movimientos'!$R$5:$R$1000, 0)), "") | G40: =IFERROR(INDEX('Detalles movimientos'!H$5:H$1000, MATCH(31, 'Detalles movimientos'!$R$5:$R$1000, 0)), "") | H40: =IFERROR(INDEX('Detalles movimientos'!I$5:I$1000, MATCH(31, 'Detalles movimientos'!$R$5:$R$1000, 0)), "") | I40: =IFERROR(INDEX('Detalles movimientos'!J$5:J$1000, MATCH(31, 'Detalles movimientos'!$R$5:$R$1000, 0)), "") | ... L40: =IFERROR(INDEX('Detalles movimientos'!M$5:M$1000, MATCH(31, 'Detalles movimientos'!$R$5:$R$1000, 0)), "") | M40: =IFERROR(INDEX('Detalles movimientos'!P$5:P$1000, MATCH(31, 'Detalles movimientos'!$R$5:$R$1000, 0)), "")
B41: =IFERROR(INDEX('Detalles movimientos'!C$5:C$1000, MATCH(32, 'Detalles movimientos'!$R$5:$R$1000, 0)), "") | C41: =IFERROR(INDEX('Detalles movimientos'!D$5:D$1000, MATCH(32, 'Detalles movimientos'!$R$5:$R$1000, 0)), "") | D41: =IFERROR(INDEX('Detalles movimientos'!E$5:E$1000, MATCH(32, 'Detalles movimientos'!$R$5:$R$1000, 0)), "") | E41: =IFERROR(INDEX('Detalles movimientos'!F$5:F$1000, MATCH(32, 'Detalles movimientos'!$R$5:$R$1000, 0)), "") | F41: =IFERROR(INDEX('Detalles movimientos'!G$5:G$1000, MATCH(32, 'Detalles movimientos'!$R$5:$R$1000, 0)), "") | G41: =IFERROR(INDEX('Detalles movimientos'!H$5:H$1000, MATCH(32, 'Detalles movimientos'!$R$5:$R$1000, 0)), "") | H41: =IFERROR(INDEX('Detalles movimientos'!I$5:I$1000, MATCH(32, 'Detalles movimientos'!$R$5:$R$1000, 0)), "") | I41: =IFERROR(INDEX('Detalles movimientos'!J$5:J$1000, MATCH(32, 'Detalles movimientos'!$R$5:$R$1000, 0)), "") | ... L41: =IFERROR(INDEX('Detalles movimientos'!M$5:M$1000, MATCH(32, 'Detalles movimientos'!$R$5:$R$1000, 0)), "") | M41: =IFERROR(INDEX('Detalles movimientos'!P$5:P$1000, MATCH(32, 'Detalles movimientos'!$R$5:$R$1000, 0)), "")
B42: =IFERROR(INDEX('Detalles movimientos'!C$5:C$1000, MATCH(33, 'Detalles movimientos'!$R$5:$R$1000, 0)), "") | C42: =IFERROR(INDEX('Detalles movimientos'!D$5:D$1000, MATCH(33, 'Detalles movimientos'!$R$5:$R$1000, 0)), "") | D42: =IFERROR(INDEX('Detalles movimientos'!E$5:E$1000, MATCH(33, 'Detalles movimientos'!$R$5:$R$1000, 0)), "") | E42: =IFERROR(INDEX('Detalles movimientos'!F$5:F$1000, MATCH(33, 'Detalles movimientos'!$R$5:$R$1000, 0)), "") | F42: =IFERROR(INDEX('Detalles movimientos'!G$5:G$1000, MATCH(33, 'Detalles movimientos'!$R$5:$R$1000, 0)), "") | G42: =IFERROR(INDEX('Detalles movimientos'!H$5:H$1000, MATCH(33, 'Detalles movimientos'!$R$5:$R$1000, 0)), "") | H42: =IFERROR(INDEX('Detalles movimientos'!I$5:I$1000, MATCH(33, 'Detalles movimientos'!$R$5:$R$1000, 0)), "") | I42: =IFERROR(INDEX('Detalles movimientos'!J$5:J$1000, MATCH(33, 'Detalles movimientos'!$R$5:$R$1000, 0)), "") | ... L42: =IFERROR(INDEX('Detalles movimientos'!M$5:M$1000, MATCH(33, 'Detalles movimientos'!$R$5:$R$1000, 0)), "") | M42: =IFERROR(INDEX('Detalles movimientos'!P$5:P$1000, MATCH(33, 'Detalles movimientos'!$R$5:$R$1000, 0)), "")
B43: =IFERROR(INDEX('Detalles movimientos'!C$5:C$1000, MATCH(34, 'Detalles movimientos'!$R$5:$R$1000, 0)), "") | C43: =IFERROR(INDEX('Detalles movimientos'!D$5:D$1000, MATCH(34, 'Detalles movimientos'!$R$5:$R$1000, 0)), "") | D43: =IFERROR(INDEX('Detalles movimientos'!E$5:E$1000, MATCH(34, 'Detalles movimientos'!$R$5:$R$1000, 0)), "") | E43: =IFERROR(INDEX('Detalles movimientos'!F$5:F$1000, MATCH(34, 'Detalles movimientos'!$R$5:$R$1000, 0)), "") | F43: =IFERROR(INDEX('Detalles movimientos'!G$5:G$1000, MATCH(34, 'Detalles movimientos'!$R$5:$R$1000, 0)), "") | G43: =IFERROR(INDEX('Detalles movimientos'!H$5:H$1000, MATCH(34, 'Detalles movimientos'!$R$5:$R$1000, 0)), "") | H43: =IFERROR(INDEX('Detalles movimientos'!I$5:I$1000, MATCH(34, 'Detalles movimientos'!$R$5:$R$1000, 0)), "") | I43: =IFERROR(INDEX('Detalles movimientos'!J$5:J$1000, MATCH(34, 'Detalles movimientos'!$R$5:$R$1000, 0)), "") | ... L43: =IFERROR(INDEX('Detalles movimientos'!M$5:M$1000, MATCH(34, 'Detalles movimientos'!$R$5:$R$1000, 0)), "") | M43: =IFERROR(INDEX('Detalles movimientos'!P$5:P$1000, MATCH(34, 'Detalles movimientos'!$R$5:$R$1000, 0)), "")
B44: =IFERROR(INDEX('Detalles movimientos'!C$5:C$1000, MATCH(35, 'Detalles movimientos'!$R$5:$R$1000, 0)), "") | C44: =IFERROR(INDEX('Detalles movimientos'!D$5:D$1000, MATCH(35, 'Detalles movimientos'!$R$5:$R$1000, 0)), "") | D44: =IFERROR(INDEX('Detalles movimientos'!E$5:E$1000, MATCH(35, 'Detalles movimientos'!$R$5:$R$1000, 0)), "") | E44: =IFERROR(INDEX('Detalles movimientos'!F$5:F$1000, MATCH(35, 'Detalles movimientos'!$R$5:$R$1000, 0)), "") | F44: =IFERROR(INDEX('Detalles movimientos'!G$5:G$1000, MATCH(35, 'Detalles movimientos'!$R$5:$R$1000, 0)), "") | G44: =IFERROR(INDEX('Detalles movimientos'!H$5:H$1000, MATCH(35, 'Detalles movimientos'!$R$5:$R$1000, 0)), "") | H44: =IFERROR(INDEX('Detalles movimientos'!I$5:I$1000, MATCH(35, 'Detalles movimientos'!$R$5:$R$1000, 0)), "") | I44: =IFERROR(INDEX('Detalles movimientos'!J$5:J$1000, MATCH(35, 'Detalles movimientos'!$R$5:$R$1000, 0)), "") | ... L44: =IFERROR(INDEX('Detalles movimientos'!M$5:M$1000, MATCH(35, 'Detalles movimientos'!$R$5:$R$1000, 0)), "") | M44: =IFERROR(INDEX('Detalles movimientos'!P$5:P$1000, MATCH(35, 'Detalles movimientos'!$R$5:$R$1000, 0)), "")
B45: =IFERROR(INDEX('Detalles movimientos'!C$5:C$1000, MATCH(36, 'Detalles movimientos'!$R$5:$R$1000, 0)), "") | C45: =IFERROR(INDEX('Detalles movimientos'!D$5:D$1000, MATCH(36, 'Detalles movimientos'!$R$5:$R$1000, 0)), "") | D45: =IFERROR(INDEX('Detalles movimientos'!E$5:E$1000, MATCH(36, 'Detalles movimientos'!$R$5:$R$1000, 0)), "") | E45: =IFERROR(INDEX('Detalles movimientos'!F$5:F$1000, MATCH(36, 'Detalles movimientos'!$R$5:$R$1000, 0)), "") | F45: =IFERROR(INDEX('Detalles movimientos'!G$5:G$1000, MATCH(36, 'Detalles movimientos'!$R$5:$R$1000, 0)), "") | G45: =IFERROR(INDEX('Detalles movimientos'!H$5:H$1000, MATCH(36, 'Detalles movimientos'!$R$5:$R$1000, 0)), "") | H45: =IFERROR(INDEX('Detalles movimientos'!I$5:I$1000, MATCH(36, 'Detalles movimientos'!$R$5:$R$1000, 0)), "") | I45: =IFERROR(INDEX('Detalles movimientos'!J$5:J$1000, MATCH(36, 'Detalles movimientos'!$R$5:$R$1000, 0)), "") | ... L45: =IFERROR(INDEX('Detalles movimientos'!M$5:M$1000, MATCH(36, 'Detalles movimientos'!$R$5:$R$1000, 0)), "") | M45: =IFERROR(INDEX('Detalles movimientos'!P$5:P$1000, MATCH(36, 'Detalles movimientos'!$R$5:$R$1000, 0)), "")
B46: =IFERROR(INDEX('Detalles movimientos'!C$5:C$1000, MATCH(37, 'Detalles movimientos'!$R$5:$R$1000, 0)), "") | C46: =IFERROR(INDEX('Detalles movimientos'!D$5:D$1000, MATCH(37, 'Detalles movimientos'!$R$5:$R$1000, 0)), "") | D46: =IFERROR(INDEX('Detalles movimientos'!E$5:E$1000, MATCH(37, 'Detalles movimientos'!$R$5:$R$1000, 0)), "") | E46: =IFERROR(INDEX('Detalles movimientos'!F$5:F$1000, MATCH(37, 'Detalles movimientos'!$R$5:$R$1000, 0)), "") | F46: =IFERROR(INDEX('Detalles movimientos'!G$5:G$1000, MATCH(37, 'Detalles movimientos'!$R$5:$R$1000, 0)), "") | G46: =IFERROR(INDEX('Detalles movimientos'!H$5:H$1000, MATCH(37, 'Detalles movimientos'!$R$5:$R$1000, 0)), "") | H46: =IFERROR(INDEX('Detalles movimientos'!I$5:I$1000, MATCH(37, 'Detalles movimientos'!$R$5:$R$1000, 0)), "") | I46: =IFERROR(INDEX('Detalles movimientos'!J$5:J$1000, MATCH(37, 'Detalles movimientos'!$R$5:$R$1000, 0)), "") | ... L46: =IFERROR(INDEX('Detalles movimientos'!M$5:M$1000, MATCH(37, 'Detalles movimientos'!$R$5:$R$1000, 0)), "") | M46: =IFERROR(INDEX('Detalles movimientos'!P$5:P$1000, MATCH(37, 'Detalles movimientos'!$R$5:$R$1000, 0)), "")
B47: =IFERROR(INDEX('Detalles movimientos'!C$5:C$1000, MATCH(38, 'Detalles movimientos'!$R$5:$R$1000, 0)), "") | C47: =IFERROR(INDEX('Detalles movimientos'!D$5:D$1000, MATCH(38, 'Detalles movimientos'!$R$5:$R$1000, 0)), "") | D47: =IFERROR(INDEX('Detalles movimientos'!E$5:E$1000, MATCH(38, 'Detalles movimientos'!$R$5:$R$1000, 0)), "") | E47: =IFERROR(INDEX('Detalles movimientos'!F$5:F$1000, MATCH(38, 'Detalles movimientos'!$R$5:$R$1000, 0)), "") | F47: =IFERROR(INDEX('Detalles movimientos'!G$5:G$1000, MATCH(38, 'Detalles movimientos'!$R$5:$R$1000, 0)), "") | G47: =IFERROR(INDEX('Detalles movimientos'!H$5:H$1000, MATCH(38, 'Detalles movimientos'!$R$5:$R$1000, 0)), "") | H47: =IFERROR(INDEX('Detalles movimientos'!I$5:I$1000, MATCH(38, 'Detalles movimientos'!$R$5:$R$1000, 0)), "") | I47: =IFERROR(INDEX('Detalles movimientos'!J$5:J$1000, MATCH(38, 'Detalles movimientos'!$R$5:$R$1000, 0)), "") | ... L47: =IFERROR(INDEX('Detalles movimientos'!M$5:M$1000, MATCH(38, 'Detalles movimientos'!$R$5:$R$1000, 0)), "") | M47: =IFERROR(INDEX('Detalles movimientos'!P$5:P$1000, MATCH(38, 'Detalles movimientos'!$R$5:$R$1000, 0)), "")
B48: =IFERROR(INDEX('Detalles movimientos'!C$5:C$1000, MATCH(39, 'Detalles movimientos'!$R$5:$R$1000, 0)), "") | C48: =IFERROR(INDEX('Detalles movimientos'!D$5:D$1000, MATCH(39, 'Detalles movimientos'!$R$5:$R$1000, 0)), "") | D48: =IFERROR(INDEX('Detalles movimientos'!E$5:E$1000, MATCH(39, 'Detalles movimientos'!$R$5:$R$1000, 0)), "") | E48: =IFERROR(INDEX('Detalles movimientos'!F$5:F$1000, MATCH(39, 'Detalles movimientos'!$R$5:$R$1000, 0)), "") | F48: =IFERROR(INDEX('Detalles movimientos'!G$5:G$1000, MATCH(39, 'Detalles movimientos'!$R$5:$R$1000, 0)), "") | G48: =IFERROR(INDEX('Detalles movimientos'!H$5:H$1000, MATCH(39, 'Detalles movimientos'!$R$5:$R$1000, 0)), "") | H48: =IFERROR(INDEX('Detalles movimientos'!I$5:I$1000, MATCH(39, 'Detalles movimientos'!$R$5:$R$1000, 0)), "") | I48: =IFERROR(INDEX('Detalles movimientos'!J$5:J$1000, MATCH(39, 'Detalles movimientos'!$R$5:$R$1000, 0)), "") | ... L48: =IFERROR(INDEX('Detalles movimientos'!M$5:M$1000, MATCH(39, 'Detalles movimientos'!$R$5:$R$1000, 0)), "") | M48: =IFERROR(INDEX('Detalles movimientos'!P$5:P$1000, MATCH(39, 'Detalles movimientos'!$R$5:$R$1000, 0)), "")
B49: =IFERROR(INDEX('Detalles movimientos'!C$5:C$1000, MATCH(40, 'Detalles movimientos'!$R$5:$R$1000, 0)), "") | C49: =IFERROR(INDEX('Detalles movimientos'!D$5:D$1000, MATCH(40, 'Detalles movimientos'!$R$5:$R$1000, 0)), "") | D49: =IFERROR(INDEX('Detalles movimientos'!E$5:E$1000, MATCH(40, 'Detalles movimientos'!$R$5:$R$1000, 0)), "") | E49: =IFERROR(INDEX('Detalles movimientos'!F$5:F$1000, MATCH(40, 'Detalles movimientos'!$R$5:$R$1000, 0)), "") | F49: =IFERROR(INDEX('Detalles movimientos'!G$5:G$1000, MATCH(40, 'Detalles movimientos'!$R$5:$R$1000, 0)), "") | G49: =IFERROR(INDEX('Detalles movimientos'!H$5:H$1000, MATCH(40, 'Detalles movimientos'!$R$5:$R$1000, 0)), "") | H49: =IFERROR(INDEX('Detalles movimientos'!I$5:I$1000, MATCH(40, 'Detalles movimientos'!$R$5:$R$1000, 0)), "") | I49: =IFERROR(INDEX('Detalles movimientos'!J$5:J$1000, MATCH(40, 'Detalles movimientos'!$R$5:$R$1000, 0)), "") | ... L49: =IFERROR(INDEX('Detalles movimientos'!M$5:M$1000, MATCH(40, 'Detalles movimientos'!$R$5:$R$1000, 0)), "") | M49: =IFERROR(INDEX('Detalles movimientos'!P$5:P$1000, MATCH(40, 'Detalles movimientos'!$R$5:$R$1000, 0)), "")
B50: =IFERROR(INDEX('Detalles movimientos'!C$5:C$1000, MATCH(41, 'Detalles movimientos'!$R$5:$R$1000, 0)), "") | C50: =IFERROR(INDEX('Detalles movimientos'!D$5:D$1000, MATCH(41, 'Detalles movimientos'!$R$5:$R$1000, 0)), "") | D50: =IFERROR(INDEX('Detalles movimientos'!E$5:E$1000, MATCH(41, 'Detalles movimientos'!$R$5:$R$1000, 0)), "") | E50: =IFERROR(INDEX('Detalles movimientos'!F$5:F$1000, MATCH(41, 'Detalles movimientos'!$R$5:$R$1000, 0)), "") | F50: =IFERROR(INDEX('Detalles movimientos'!G$5:G$1000, MATCH(41, 'Detalles movimientos'!$R$5:$R$1000, 0)), "") | G50: =IFERROR(INDEX('Detalles movimientos'!H$5:H$1000, MATCH(41, 'Detalles movimientos'!$R$5:$R$1000, 0)), "") | H50: =IFERROR(INDEX('Detalles movimientos'!I$5:I$1000, MATCH(41, 'Detalles movimientos'!$R$5:$R$1000, 0)), "") | I50: =IFERROR(INDEX('Detalles movimientos'!J$5:J$1000, MATCH(41, 'Detalles movimientos'!$R$5:$R$1000, 0)), "") | ... L50: =IFERROR(INDEX('Detalles movimientos'!M$5:M$1000, MATCH(41, 'Detalles movimientos'!$R$5:$R$1000, 0)), "") | M50: =IFERROR(INDEX('Detalles movimientos'!P$5:P$1000, MATCH(41, 'Detalles movimientos'!$R$5:$R$1000, 0)), "")
B51: =IFERROR(INDEX('Detalles movimientos'!C$5:C$1000, MATCH(42, 'Detalles movimientos'!$R$5:$R$1000, 0)), "") | C51: =IFERROR(INDEX('Detalles movimientos'!D$5:D$1000, MATCH(42, 'Detalles movimientos'!$R$5:$R$1000, 0)), "") | D51: =IFERROR(INDEX('Detalles movimientos'!E$5:E$1000, MATCH(42, 'Detalles movimientos'!$R$5:$R$1000, 0)), "") | E51: =IFERROR(INDEX('Detalles movimientos'!F$5:F$1000, MATCH(42, 'Detalles movimientos'!$R$5:$R$1000, 0)), "") | F51: =IFERROR(INDEX('Detalles movimientos'!G$5:G$1000, MATCH(42, 'Detalles movimientos'!$R$5:$R$1000, 0)), "") | G51: =IFERROR(INDEX('Detalles movimientos'!H$5:H$1000, MATCH(42, 'Detalles movimientos'!$R$5:$R$1000, 0)), "") | H51: =IFERROR(INDEX('Detalles movimientos'!I$5:I$1000, MATCH(42, 'Detalles movimientos'!$R$5:$R$1000, 0)), "") | I51: =IFERROR(INDEX('Detalles movimientos'!J$5:J$1000, MATCH(42, 'Detalles movimientos'!$R$5:$R$1000, 0)), "") | ... L51: =IFERROR(INDEX('Detalles movimientos'!M$5:M$1000, MATCH(42, 'Detalles movimientos'!$R$5:$R$1000, 0)), "") | M51: =IFERROR(INDEX('Detalles movimientos'!P$5:P$1000, MATCH(42, 'Detalles movimientos'!$R$5:$R$1000, 0)), "")
B52: =IFERROR(INDEX('Detalles movimientos'!C$5:C$1000, MATCH(43, 'Detalles movimientos'!$R$5:$R$1000, 0)), "") | C52: =IFERROR(INDEX('Detalles movimientos'!D$5:D$1000, MATCH(43, 'Detalles movimientos'!$R$5:$R$1000, 0)), "") | D52: =IFERROR(INDEX('Detalles movimientos'!E$5:E$1000, MATCH(43, 'Detalles movimientos'!$R$5:$R$1000, 0)), "") | E52: =IFERROR(INDEX('Detalles movimientos'!F$5:F$1000, MATCH(43, 'Detalles movimientos'!$R$5:$R$1000, 0)), "") | F52: =IFERROR(INDEX('Detalles movimientos'!G$5:G$1000, MATCH(43, 'Detalles movimientos'!$R$5:$R$1000, 0)), "") | G52: =IFERROR(INDEX('Detalles movimientos'!H$5:H$1000, MATCH(43, 'Detalles movimientos'!$R$5:$R$1000, 0)), "") | H52: =IFERROR(INDEX('Detalles movimientos'!I$5:I$1000, MATCH(43, 'Detalles movimientos'!$R$5:$R$1000, 0)), "") | I52: =IFERROR(INDEX('Detalles movimientos'!J$5:J$1000, MATCH(43, 'Detalles movimientos'!$R$5:$R$1000, 0)), "") | ... L52: =IFERROR(INDEX('Detalles movimientos'!M$5:M$1000, MATCH(43, 'Detalles movimientos'!$R$5:$R$1000, 0)), "") | M52: =IFERROR(INDEX('Detalles movimientos'!P$5:P$1000, MATCH(43, 'Detalles movimientos'!$R$5:$R$1000, 0)), "")
B53: =IFERROR(INDEX('Detalles movimientos'!C$5:C$1000, MATCH(44, 'Detalles movimientos'!$R$5:$R$1000, 0)), "") | C53: =IFERROR(INDEX('Detalles movimientos'!D$5:D$1000, MATCH(44, 'Detalles movimientos'!$R$5:$R$1000, 0)), "") | D53: =IFERROR(INDEX('Detalles movimientos'!E$5:E$1000, MATCH(44, 'Detalles movimientos'!$R$5:$R$1000, 0)), "") | E53: =IFERROR(INDEX('Detalles movimientos'!F$5:F$1000, MATCH(44, 'Detalles movimientos'!$R$5:$R$1000, 0)), "") | F53: =IFERROR(INDEX('Detalles movimientos'!G$5:G$1000, MATCH(44, 'Detalles movimientos'!$R$5:$R$1000, 0)), "") | G53: =IFERROR(INDEX('Detalles movimientos'!H$5:H$1000, MATCH(44, 'Detalles movimientos'!$R$5:$R$1000, 0)), "") | H53: =IFERROR(INDEX('Detalles movimientos'!I$5:I$1000, MATCH(44, 'Detalles movimientos'!$R$5:$R$1000, 0)), "") | I53: =IFERROR(INDEX('Detalles movimientos'!J$5:J$1000, MATCH(44, 'Detalles movimientos'!$R$5:$R$1000, 0)), "") | ... L53: =IFERROR(INDEX('Detalles movimientos'!M$5:M$1000, MATCH(44, 'Detalles movimientos'!$R$5:$R$1000, 0)), "") | M53: =IFERROR(INDEX('Detalles movimientos'!P$5:P$1000, MATCH(44, 'Detalles movimientos'!$R$5:$R$1000, 0)), "")
B54: =IFERROR(INDEX('Detalles movimientos'!C$5:C$1000, MATCH(45, 'Detalles movimientos'!$R$5:$R$1000, 0)), "") | C54: =IFERROR(INDEX('Detalles movimientos'!D$5:D$1000, MATCH(45, 'Detalles movimientos'!$R$5:$R$1000, 0)), "") | D54: =IFERROR(INDEX('Detalles movimientos'!E$5:E$1000, MATCH(45, 'Detalles movimientos'!$R$5:$R$1000, 0)), "") | E54: =IFERROR(INDEX('Detalles movimientos'!F$5:F$1000, MATCH(45, 'Detalles movimientos'!$R$5:$R$1000, 0)), "") | F54: =IFERROR(INDEX('Detalles movimientos'!G$5:G$1000, MATCH(45, 'Detalles movimientos'!$R$5:$R$1000, 0)), "") | G54: =IFERROR(INDEX('Detalles movimientos'!H$5:H$1000, MATCH(45, 'Detalles movimientos'!$R$5:$R$1000, 0)), "") | H54: =IFERROR(INDEX('Detalles movimientos'!I$5:I$1000, MATCH(45, 'Detalles movimientos'!$R$5:$R$1000, 0)), "") | I54: =IFERROR(INDEX('Detalles movimientos'!J$5:J$1000, MATCH(45, 'Detalles movimientos'!$R$5:$R$1000, 0)), "") | ... L54: =IFERROR(INDEX('Detalles movimientos'!M$5:M$1000, MATCH(45, 'Detalles movimientos'!$R$5:$R$1000, 0)), "") | M54: =IFERROR(INDEX('Detalles movimientos'!P$5:P$1000, MATCH(45, 'Detalles movimientos'!$R$5:$R$1000, 0)), "")
B55: =IFERROR(INDEX('Detalles movimientos'!C$5:C$1000, MATCH(46, 'Detalles movimientos'!$R$5:$R$1000, 0)), "") | C55: =IFERROR(INDEX('Detalles movimientos'!D$5:D$1000, MATCH(46, 'Detalles movimientos'!$R$5:$R$1000, 0)), "") | D55: =IFERROR(INDEX('Detalles movimientos'!E$5:E$1000, MATCH(46, 'Detalles movimientos'!$R$5:$R$1000, 0)), "") | E55: =IFERROR(INDEX('Detalles movimientos'!F$5:F$1000, MATCH(46, 'Detalles movimientos'!$R$5:$R$1000, 0)), "") | F55: =IFERROR(INDEX('Detalles movimientos'!G$5:G$1000, MATCH(46, 'Detalles movimientos'!$R$5:$R$1000, 0)), "") | G55: =IFERROR(INDEX('Detalles movimientos'!H$5:H$1000, MATCH(46, 'Detalles movimientos'!$R$5:$R$1000, 0)), "") | H55: =IFERROR(INDEX('Detalles movimientos'!I$5:I$1000, MATCH(46, 'Detalles movimientos'!$R$5:$R$1000, 0)), "") | I55: =IFERROR(INDEX('Detalles movimientos'!J$5:J$1000, MATCH(46, 'Detalles movimientos'!$R$5:$R$1000, 0)), "") | ... L55: =IFERROR(INDEX('Detalles movimientos'!M$5:M$1000, MATCH(46, 'Detalles movimientos'!$R$5:$R$1000, 0)), "") | M55: =IFERROR(INDEX('Detalles movimientos'!P$5:P$1000, MATCH(46, 'Detalles movimientos'!$R$5:$R$1000, 0)), "")
B56: =IFERROR(INDEX('Detalles movimientos'!C$5:C$1000, MATCH(47, 'Detalles movimientos'!$R$5:$R$1000, 0)), "") | C56: =IFERROR(INDEX('Detalles movimientos'!D$5:D$1000, MATCH(47, 'Detalles movimientos'!$R$5:$R$1000, 0)), "") | D56: =IFERROR(INDEX('Detalles movimientos'!E$5:E$1000, MATCH(47, 'Detalles movimientos'!$R$5:$R$1000, 0)), "") | E56: =IFERROR(INDEX('Detalles movimientos'!F$5:F$1000, MATCH(47, 'Detalles movimientos'!$R$5:$R$1000, 0)), "") | F56: =IFERROR(INDEX('Detalles movimientos'!G$5:G$1000, MATCH(47, 'Detalles movimientos'!$R$5:$R$1000, 0)), "") | G56: =IFERROR(INDEX('Detalles movimientos'!H$5:H$1000, MATCH(47, 'Detalles movimientos'!$R$5:$R$1000, 0)), "") | H56: =IFERROR(INDEX('Detalles movimientos'!I$5:I$1000, MATCH(47, 'Detalles movimientos'!$R$5:$R$1000, 0)), "") | I56: =IFERROR(INDEX('Detalles movimientos'!J$5:J$1000, MATCH(47, 'Detalles movimientos'!$R$5:$R$1000, 0)), "") | ... L56: =IFERROR(INDEX('Detalles movimientos'!M$5:M$1000, MATCH(47, 'Detalles movimientos'!$R$5:$R$1000, 0)), "") | M56: =IFERROR(INDEX('Detalles movimientos'!P$5:P$1000, MATCH(47, 'Detalles movimientos'!$R$5:$R$1000, 0)), "")
B57: =IFERROR(INDEX('Detalles movimientos'!C$5:C$1000, MATCH(48, 'Detalles movimientos'!$R$5:$R$1000, 0)), "") | C57: =IFERROR(INDEX('Detalles movimientos'!D$5:D$1000, MATCH(48, 'Detalles movimientos'!$R$5:$R$1000, 0)), "") | D57: =IFERROR(INDEX('Detalles movimientos'!E$5:E$1000, MATCH(48, 'Detalles movimientos'!$R$5:$R$1000, 0)), "") | E57: =IFERROR(INDEX('Detalles movimientos'!F$5:F$1000, MATCH(48, 'Detalles movimientos'!$R$5:$R$1000, 0)), "") | F57: =IFERROR(INDEX('Detalles movimientos'!G$5:G$1000, MATCH(48, 'Detalles movimientos'!$R$5:$R$1000, 0)), "") | G57: =IFERROR(INDEX('Detalles movimientos'!H$5:H$1000, MATCH(48, 'Detalles movimientos'!$R$5:$R$1000, 0)), "") | H57: =IFERROR(INDEX('Detalles movimientos'!I$5:I$1000, MATCH(48, 'Detalles movimientos'!$R$5:$R$1000, 0)), "") | I57: =IFERROR(INDEX('Detalles movimientos'!J$5:J$1000, MATCH(48, 'Detalles movimientos'!$R$5:$R$1000, 0)), "") | ... L57: =IFERROR(INDEX('Detalles movimientos'!M$5:M$1000, MATCH(48, 'Detalles movimientos'!$R$5:$R$1000, 0)), "") | M57: =IFERROR(INDEX('Detalles movimientos'!P$5:P$1000, MATCH(48, 'Detalles movimientos'!$R$5:$R$1000, 0)), "")
B58: =IFERROR(INDEX('Detalles movimientos'!C$5:C$1000, MATCH(49, 'Detalles movimientos'!$R$5:$R$1000, 0)), "") | C58: =IFERROR(INDEX('Detalles movimientos'!D$5:D$1000, MATCH(49, 'Detalles movimientos'!$R$5:$R$1000, 0)), "") | D58: =IFERROR(INDEX('Detalles movimientos'!E$5:E$1000, MATCH(49, 'Detalles movimientos'!$R$5:$R$1000, 0)), "") | E58: =IFERROR(INDEX('Detalles movimientos'!F$5:F$1000, MATCH(49, 'Detalles movimientos'!$R$5:$R$1000, 0)), "") | F58: =IFERROR(INDEX('Detalles movimientos'!G$5:G$1000, MATCH(49, 'Detalles movimientos'!$R$5:$R$1000, 0)), "") | G58: =IFERROR(INDEX('Detalles movimientos'!H$5:H$1000, MATCH(49, 'Detalles movimientos'!$R$5:$R$1000, 0)), "") | H58: =IFERROR(INDEX('Detalles movimientos'!I$5:I$1000, MATCH(49, 'Detalles movimientos'!$R$5:$R$1000, 0)), "") | I58: =IFERROR(INDEX('Detalles movimientos'!J$5:J$1000, MATCH(49, 'Detalles movimientos'!$R$5:$R$1000, 0)), "") | ... L58: =IFERROR(INDEX('Detalles movimientos'!M$5:M$1000, MATCH(49, 'Detalles movimientos'!$R$5:$R$1000, 0)), "") | M58: =IFERROR(INDEX('Detalles movimientos'!P$5:P$1000, MATCH(49, 'Detalles movimientos'!$R$5:$R$1000, 0)), "")
B59: =IFERROR(INDEX('Detalles movimientos'!C$5:C$1000, MATCH(50, 'Detalles movimientos'!$R$5:$R$1000, 0)), "") | C59: =IFERROR(INDEX('Detalles movimientos'!D$5:D$1000, MATCH(50, 'Detalles movimientos'!$R$5:$R$1000, 0)), "") | D59: =IFERROR(INDEX('Detalles movimientos'!E$5:E$1000, MATCH(50, 'Detalles movimientos'!$R$5:$R$1000, 0)), "") | E59: =IFERROR(INDEX('Detalles movimientos'!F$5:F$1000, MATCH(50, 'Detalles movimientos'!$R$5:$R$1000, 0)), "") | F59: =IFERROR(INDEX('Detalles movimientos'!G$5:G$1000, MATCH(50, 'Detalles movimientos'!$R$5:$R$1000, 0)), "") | G59: =IFERROR(INDEX('Detalles movimientos'!H$5:H$1000, MATCH(50, 'Detalles movimientos'!$R$5:$R$1000, 0)), "") | H59: =IFERROR(INDEX('Detalles movimientos'!I$5:I$1000, MATCH(50, 'Detalles movimientos'!$R$5:$R$1000, 0)), "") | I59: =IFERROR(INDEX('Detalles movimientos'!J$5:J$1000, MATCH(50, 'Detalles movimientos'!$R$5:$R$1000, 0)), "") | ... L59: =IFERROR(INDEX('Detalles movimientos'!M$5:M$1000, MATCH(50, 'Detalles movimientos'!$R$5:$R$1000, 0)), "") | M59: =IFERROR(INDEX('Detalles movimientos'!P$5:P$1000, MATCH(50, 'Detalles movimientos'!$R$5:$R$1000, 0)), "")
B60: =IFERROR(INDEX('Detalles movimientos'!C$5:C$1000, MATCH(51, 'Detalles movimientos'!$R$5:$R$1000, 0)), "") | C60: =IFERROR(INDEX('Detalles movimientos'!D$5:D$1000, MATCH(51, 'Detalles movimientos'!$R$5:$R$1000, 0)), "") | D60: =IFERROR(INDEX('Detalles movimientos'!E$5:E$1000, MATCH(51, 'Detalles movimientos'!$R$5:$R$1000, 0)), "") | E60: =IFERROR(INDEX('Detalles movimientos'!F$5:F$1000, MATCH(51, 'Detalles movimientos'!$R$5:$R$1000, 0)), "") | F60: =IFERROR(INDEX('Detalles movimientos'!G$5:G$1000, MATCH(51, 'Detalles movimientos'!$R$5:$R$1000, 0)), "") | G60: =IFERROR(INDEX('Detalles movimientos'!H$5:H$1000, MATCH(51, 'Detalles movimientos'!$R$5:$R$1000, 0)), "") | H60: =IFERROR(INDEX('Detalles movimientos'!I$5:I$1000, MATCH(51, 'Detalles movimientos'!$R$5:$R$1000, 0)), "") | I60: =IFERROR(INDEX('Detalles movimientos'!J$5:J$1000, MATCH(51, 'Detalles movimientos'!$R$5:$R$1000, 0)), "") | ... L60: =IFERROR(INDEX('Detalles movimientos'!M$5:M$1000, MATCH(51, 'Detalles movimientos'!$R$5:$R$1000, 0)), "") | M60: =IFERROR(INDEX('Detalles movimientos'!P$5:P$1000, MATCH(51, 'Detalles movimientos'!$R$5:$R$1000, 0)), "")
B61: =IFERROR(INDEX('Detalles movimientos'!C$5:C$1000, MATCH(52, 'Detalles movimientos'!$R$5:$R$1000, 0)), "") | C61: =IFERROR(INDEX('Detalles movimientos'!D$5:D$1000, MATCH(52, 'Detalles movimientos'!$R$5:$R$1000, 0)), "") | D61: =IFERROR(INDEX('Detalles movimientos'!E$5:E$1000, MATCH(52, 'Detalles movimientos'!$R$5:$R$1000, 0)), "") | E61: =IFERROR(INDEX('Detalles movimientos'!F$5:F$1000, MATCH(52, 'Detalles movimientos'!$R$5:$R$1000, 0)), "") | F61: =IFERROR(INDEX('Detalles movimientos'!G$5:G$1000, MATCH(52, 'Detalles movimientos'!$R$5:$R$1000, 0)), "") | G61: =IFERROR(INDEX('Detalles movimientos'!H$5:H$1000, MATCH(52, 'Detalles movimientos'!$R$5:$R$1000, 0)), "") | H61: =IFERROR(INDEX('Detalles movimientos'!I$5:I$1000, MATCH(52, 'Detalles movimientos'!$R$5:$R$1000, 0)), "") | I61: =IFERROR(INDEX('Detalles movimientos'!J$5:J$1000, MATCH(52, 'Detalles movimientos'!$R$5:$R$1000, 0)), "") | ... L61: =IFERROR(INDEX('Detalles movimientos'!M$5:M$1000, MATCH(52, 'Detalles movimientos'!$R$5:$R$1000, 0)), "") | M61: =IFERROR(INDEX('Detalles movimientos'!P$5:P$1000, MATCH(52, 'Detalles movimientos'!$R$5:$R$1000, 0)), "")
B62: =IFERROR(INDEX('Detalles movimientos'!C$5:C$1000, MATCH(53, 'Detalles movimientos'!$R$5:$R$1000, 0)), "") | C62: =IFERROR(INDEX('Detalles movimientos'!D$5:D$1000, MATCH(53, 'Detalles movimientos'!$R$5:$R$1000, 0)), "") | D62: =IFERROR(INDEX('Detalles movimientos'!E$5:E$1000, MATCH(53, 'Detalles movimientos'!$R$5:$R$1000, 0)), "") | E62: =IFERROR(INDEX('Detalles movimientos'!F$5:F$1000, MATCH(53, 'Detalles movimientos'!$R$5:$R$1000, 0)), "") | F62: =IFERROR(INDEX('Detalles movimientos'!G$5:G$1000, MATCH(53, 'Detalles movimientos'!$R$5:$R$1000, 0)), "") | G62: =IFERROR(INDEX('Detalles movimientos'!H$5:H$1000, MATCH(53, 'Detalles movimientos'!$R$5:$R$1000, 0)), "") | H62: =IFERROR(INDEX('Detalles movimientos'!I$5:I$1000, MATCH(53, 'Detalles movimientos'!$R$5:$R$1000, 0)), "") | I62: =IFERROR(INDEX('Detalles movimientos'!J$5:J$1000, MATCH(53, 'Detalles movimientos'!$R$5:$R$1000, 0)), "") | ... L62: =IFERROR(INDEX('Detalles movimientos'!M$5:M$1000, MATCH(53, 'Detalles movimientos'!$R$5:$R$1000, 0)), "") | M62: =IFERROR(INDEX('Detalles movimientos'!P$5:P$1000, MATCH(53, 'Detalles movimientos'!$R$5:$R$1000, 0)), "")
B63: =IFERROR(INDEX('Detalles movimientos'!C$5:C$1000, MATCH(54, 'Detalles movimientos'!$R$5:$R$1000, 0)), "") | C63: =IFERROR(INDEX('Detalles movimientos'!D$5:D$1000, MATCH(54, 'Detalles movimientos'!$R$5:$R$1000, 0)), "") | D63: =IFERROR(INDEX('Detalles movimientos'!E$5:E$1000, MATCH(54, 'Detalles movimientos'!$R$5:$R$1000, 0)), "") | E63: =IFERROR(INDEX('Detalles movimientos'!F$5:F$1000, MATCH(54, 'Detalles movimientos'!$R$5:$R$1000, 0)), "") | F63: =IFERROR(INDEX('Detalles movimientos'!G$5:G$1000, MATCH(54, 'Detalles movimientos'!$R$5:$R$1000, 0)), "") | G63: =IFERROR(INDEX('Detalles movimientos'!H$5:H$1000, MATCH(54, 'Detalles movimientos'!$R$5:$R$1000, 0)), "") | H63: =IFERROR(INDEX('Detalles movimientos'!I$5:I$1000, MATCH(54, 'Detalles movimientos'!$R$5:$R$1000, 0)), "") | I63: =IFERROR(INDEX('Detalles movimientos'!J$5:J$1000, MATCH(54, 'Detalles movimientos'!$R$5:$R$1000, 0)), "") | ... L63: =IFERROR(INDEX('Detalles movimientos'!M$5:M$1000, MATCH(54, 'Detalles movimientos'!$R$5:$R$1000, 0)), "") | M63: =IFERROR(INDEX('Detalles movimientos'!P$5:P$1000, MATCH(54, 'Detalles movimientos'!$R$5:$R$1000, 0)), "")
B64: =IFERROR(INDEX('Detalles movimientos'!C$5:C$1000, MATCH(55, 'Detalles movimientos'!$R$5:$R$1000, 0)), "") | C64: =IFERROR(INDEX('Detalles movimientos'!D$5:D$1000, MATCH(55, 'Detalles movimientos'!$R$5:$R$1000, 0)), "") | D64: =IFERROR(INDEX('Detalles movimientos'!E$5:E$1000, MATCH(55, 'Detalles movimientos'!$R$5:$R$1000, 0)), "") | E64: =IFERROR(INDEX('Detalles movimientos'!F$5:F$1000, MATCH(55, 'Detalles movimientos'!$R$5:$R$1000, 0)), "") | F64: =IFERROR(INDEX('Detalles movimientos'!G$5:G$1000, MATCH(55, 'Detalles movimientos'!$R$5:$R$1000, 0)), "") | G64: =IFERROR(INDEX('Detalles movimientos'!H$5:H$1000, MATCH(55, 'Detalles movimientos'!$R$5:$R$1000, 0)), "") | H64: =IFERROR(INDEX('Detalles movimientos'!I$5:I$1000, MATCH(55, 'Detalles movimientos'!$R$5:$R$1000, 0)), "") | I64: =IFERROR(INDEX('Detalles movimientos'!J$5:J$1000, MATCH(55, 'Detalles movimientos'!$R$5:$R$1000, 0)), "") | ... L64: =IFERROR(INDEX('Detalles movimientos'!M$5:M$1000, MATCH(55, 'Detalles movimientos'!$R$5:$R$1000, 0)), "") | M64: =IFERROR(INDEX('Detalles movimientos'!P$5:P$1000, MATCH(55, 'Detalles movimientos'!$R$5:$R$1000, 0)), "")
B65: =IFERROR(INDEX('Detalles movimientos'!C$5:C$1000, MATCH(56, 'Detalles movimientos'!$R$5:$R$1000, 0)), "") | C65: =IFERROR(INDEX('Detalles movimientos'!D$5:D$1000, MATCH(56, 'Detalles movimientos'!$R$5:$R$1000, 0)), "") | D65: =IFERROR(INDEX('Detalles movimientos'!E$5:E$1000, MATCH(56, 'Detalles movimientos'!$R$5:$R$1000, 0)), "") | E65: =IFERROR(INDEX('Detalles movimientos'!F$5:F$1000, MATCH(56, 'Detalles movimientos'!$R$5:$R$1000, 0)), "") | F65: =IFERROR(INDEX('Detalles movimientos'!G$5:G$1000, MATCH(56, 'Detalles movimientos'!$R$5:$R$1000, 0)), "") | G65: =IFERROR(INDEX('Detalles movimientos'!H$5:H$1000, MATCH(56, 'Detalles movimientos'!$R$5:$R$1000, 0)), "") | H65: =IFERROR(INDEX('Detalles movimientos'!I$5:I$1000, MATCH(56, 'Detalles movimientos'!$R$5:$R$1000, 0)), "") | I65: =IFERROR(INDEX('Detalles movimientos'!J$5:J$1000, MATCH(56, 'Detalles movimientos'!$R$5:$R$1000, 0)), "") | ... L65: =IFERROR(INDEX('Detalles movimientos'!M$5:M$1000, MATCH(56, 'Detalles movimientos'!$R$5:$R$1000, 0)), "") | M65: =IFERROR(INDEX('Detalles movimientos'!P$5:P$1000, MATCH(56, 'Detalles movimientos'!$R$5:$R$1000, 0)), "")
B66: =IFERROR(INDEX('Detalles movimientos'!C$5:C$1000, MATCH(57, 'Detalles movimientos'!$R$5:$R$1000, 0)), "") | C66: =IFERROR(INDEX('Detalles movimientos'!D$5:D$1000, MATCH(57, 'Detalles movimientos'!$R$5:$R$1000, 0)), "") | D66: =IFERROR(INDEX('Detalles movimientos'!E$5:E$1000, MATCH(57, 'Detalles movimientos'!$R$5:$R$1000, 0)), "") | E66: =IFERROR(INDEX('Detalles movimientos'!F$5:F$1000, MATCH(57, 'Detalles movimientos'!$R$5:$R$1000, 0)), "") | F66: =IFERROR(INDEX('Detalles movimientos'!G$5:G$1000, MATCH(57, 'Detalles movimientos'!$R$5:$R$1000, 0)), "") | G66: =IFERROR(INDEX('Detalles movimientos'!H$5:H$1000, MATCH(57, 'Detalles movimientos'!$R$5:$R$1000, 0)), "") | H66: =IFERROR(INDEX('Detalles movimientos'!I$5:I$1000, MATCH(57, 'Detalles movimientos'!$R$5:$R$1000, 0)), "") | I66: =IFERROR(INDEX('Detalles movimientos'!J$5:J$1000, MATCH(57, 'Detalles movimientos'!$R$5:$R$1000, 0)), "") | ... L66: =IFERROR(INDEX('Detalles movimientos'!M$5:M$1000, MATCH(57, 'Detalles movimientos'!$R$5:$R$1000, 0)), "") | M66: =IFERROR(INDEX('Detalles movimientos'!P$5:P$1000, MATCH(57, 'Detalles movimientos'!$R$5:$R$1000, 0)), "")
B67: =IFERROR(INDEX('Detalles movimientos'!C$5:C$1000, MATCH(58, 'Detalles movimientos'!$R$5:$R$1000, 0)), "") | C67: =IFERROR(INDEX('Detalles movimientos'!D$5:D$1000, MATCH(58, 'Detalles movimientos'!$R$5:$R$1000, 0)), "") | D67: =IFERROR(INDEX('Detalles movimientos'!E$5:E$1000, MATCH(58, 'Detalles movimientos'!$R$5:$R$1000, 0)), "") | E67: =IFERROR(INDEX('Detalles movimientos'!F$5:F$1000, MATCH(58, 'Detalles movimientos'!$R$5:$R$1000, 0)), "") | F67: =IFERROR(INDEX('Detalles movimientos'!G$5:G$1000, MATCH(58, 'Detalles movimientos'!$R$5:$R$1000, 0)), "") | G67: =IFERROR(INDEX('Detalles movimientos'!H$5:H$1000, MATCH(58, 'Detalles movimientos'!$R$5:$R$1000, 0)), "") | H67: =IFERROR(INDEX('Detalles movimientos'!I$5:I$1000, MATCH(58, 'Detalles movimientos'!$R$5:$R$1000, 0)), "") | I67: =IFERROR(INDEX('Detalles movimientos'!J$5:J$1000, MATCH(58, 'Detalles movimientos'!$R$5:$R$1000, 0)), "") | ... L67: =IFERROR(INDEX('Detalles movimientos'!M$5:M$1000, MATCH(58, 'Detalles movimientos'!$R$5:$R$1000, 0)), "") | M67: =IFERROR(INDEX('Detalles movimientos'!P$5:P$1000, MATCH(58, 'Detalles movimientos'!$R$5:$R$1000, 0)), "")
B68: =IFERROR(INDEX('Detalles movimientos'!C$5:C$1000, MATCH(59, 'Detalles movimientos'!$R$5:$R$1000, 0)), "") | C68: =IFERROR(INDEX('Detalles movimientos'!D$5:D$1000, MATCH(59, 'Detalles movimientos'!$R$5:$R$1000, 0)), "") | D68: =IFERROR(INDEX('Detalles movimientos'!E$5:E$1000, MATCH(59, 'Detalles movimientos'!$R$5:$R$1000, 0)), "") | E68: =IFERROR(INDEX('Detalles movimientos'!F$5:F$1000, MATCH(59, 'Detalles movimientos'!$R$5:$R$1000, 0)), "") | F68: =IFERROR(INDEX('Detalles movimientos'!G$5:G$1000, MATCH(59, 'Detalles movimientos'!$R$5:$R$1000, 0)), "") | G68: =IFERROR(INDEX('Detalles movimientos'!H$5:H$1000, MATCH(59, 'Detalles movimientos'!$R$5:$R$1000, 0)), "") | H68: =IFERROR(INDEX('Detalles movimientos'!I$5:I$1000, MATCH(59, 'Detalles movimientos'!$R$5:$R$1000, 0)), "") | I68: =IFERROR(INDEX('Detalles movimientos'!J$5:J$1000, MATCH(59, 'Detalles movimientos'!$R$5:$R$1000, 0)), "") | ... L68: =IFERROR(INDEX('Detalles movimientos'!M$5:M$1000, MATCH(59, 'Detalles movimientos'!$R$5:$R$1000, 0)), "") | M68: =IFERROR(INDEX('Detalles movimientos'!P$5:P$1000, MATCH(59, 'Detalles movimientos'!$R$5:$R$1000, 0)), "")
B69: =IFERROR(INDEX('Detalles movimientos'!C$5:C$1000, MATCH(60, 'Detalles movimientos'!$R$5:$R$1000, 0)), "") | C69: =IFERROR(INDEX('Detalles movimientos'!D$5:D$1000, MATCH(60, 'Detalles movimientos'!$R$5:$R$1000, 0)), "") | D69: =IFERROR(INDEX('Detalles movimientos'!E$5:E$1000, MATCH(60, 'Detalles movimientos'!$R$5:$R$1000, 0)), "") | E69: =IFERROR(INDEX('Detalles movimientos'!F$5:F$1000, MATCH(60, 'Detalles movimientos'!$R$5:$R$1000, 0)), "") | F69: =IFERROR(INDEX('Detalles movimientos'!G$5:G$1000, MATCH(60, 'Detalles movimientos'!$R$5:$R$1000, 0)), "") | G69: =IFERROR(INDEX('Detalles movimientos'!H$5:H$1000, MATCH(60, 'Detalles movimientos'!$R$5:$R$1000, 0)), "") | H69: =IFERROR(INDEX('Detalles movimientos'!I$5:I$1000, MATCH(60, 'Detalles movimientos'!$R$5:$R$1000, 0)), "") | I69: =IFERROR(INDEX('Detalles movimientos'!J$5:J$1000, MATCH(60, 'Detalles movimientos'!$R$5:$R$1000, 0)), "") | ... L69: =IFERROR(INDEX('Detalles movimientos'!M$5:M$1000, MATCH(60, 'Detalles movimientos'!$R$5:$R$1000, 0)), "") | M69: =IFERROR(INDEX('Detalles movimientos'!P$5:P$1000, MATCH(60, 'Detalles movimientos'!$R$5:$R$1000, 0)), "")
B70: =IFERROR(INDEX('Detalles movimientos'!C$5:C$1000, MATCH(61, 'Detalles movimientos'!$R$5:$R$1000, 0)), "") | C70: =IFERROR(INDEX('Detalles movimientos'!D$5:D$1000, MATCH(61, 'Detalles movimientos'!$R$5:$R$1000, 0)), "") | D70: =IFERROR(INDEX('Detalles movimientos'!E$5:E$1000, MATCH(61, 'Detalles movimientos'!$R$5:$R$1000, 0)), "") | E70: =IFERROR(INDEX('Detalles movimientos'!F$5:F$1000, MATCH(61, 'Detalles movimientos'!$R$5:$R$1000, 0)), "") | F70: =IFERROR(INDEX('Detalles movimientos'!G$5:G$1000, MATCH(61, 'Detalles movimientos'!$R$5:$R$1000, 0)), "") | G70: =IFERROR(INDEX('Detalles movimientos'!H$5:H$1000, MATCH(61, 'Detalles movimientos'!$R$5:$R$1000, 0)), "") | H70: =IFERROR(INDEX('Detalles movimientos'!I$5:I$1000, MATCH(61, 'Detalles movimientos'!$R$5:$R$1000, 0)), "") | I70: =IFERROR(INDEX('Detalles movimientos'!J$5:J$1000, MATCH(61, 'Detalles movimientos'!$R$5:$R$1000, 0)), "") | ... L70: =IFERROR(INDEX('Detalles movimientos'!M$5:M$1000, MATCH(61, 'Detalles movimientos'!$R$5:$R$1000, 0)), "") | M70: =IFERROR(INDEX('Detalles movimientos'!P$5:P$1000, MATCH(61, 'Detalles movimientos'!$R$5:$R$1000, 0)), "")
B71: =IFERROR(INDEX('Detalles movimientos'!C$5:C$1000, MATCH(62, 'Detalles movimientos'!$R$5:$R$1000, 0)), "") | C71: =IFERROR(INDEX('Detalles movimientos'!D$5:D$1000, MATCH(62, 'Detalles movimientos'!$R$5:$R$1000, 0)), "") | D71: =IFERROR(INDEX('Detalles movimientos'!E$5:E$1000, MATCH(62, 'Detalles movimientos'!$R$5:$R$1000, 0)), "") | E71: =IFERROR(INDEX('Detalles movimientos'!F$5:F$1000, MATCH(62, 'Detalles movimientos'!$R$5:$R$1000, 0)), "") | F71: =IFERROR(INDEX('Detalles movimientos'!G$5:G$1000, MATCH(62, 'Detalles movimientos'!$R$5:$R$1000, 0)), "") | G71: =IFERROR(INDEX('Detalles movimientos'!H$5:H$1000, MATCH(62, 'Detalles movimientos'!$R$5:$R$1000, 0)), "") | H71: =IFERROR(INDEX('Detalles movimientos'!I$5:I$1000, MATCH(62, 'Detalles movimientos'!$R$5:$R$1000, 0)), "") | I71: =IFERROR(INDEX('Detalles movimientos'!J$5:J$1000, MATCH(62, 'Detalles movimientos'!$R$5:$R$1000, 0)), "") | ... L71: =IFERROR(INDEX('Detalles movimientos'!M$5:M$1000, MATCH(62, 'Detalles movimientos'!$R$5:$R$1000, 0)), "") | M71: =IFERROR(INDEX('Detalles movimientos'!P$5:P$1000, MATCH(62, 'Detalles movimientos'!$R$5:$R$1000, 0)), "")
B72: =IFERROR(INDEX('Detalles movimientos'!C$5:C$1000, MATCH(63, 'Detalles movimientos'!$R$5:$R$1000, 0)), "") | C72: =IFERROR(INDEX('Detalles movimientos'!D$5:D$1000, MATCH(63, 'Detalles movimientos'!$R$5:$R$1000, 0)), "") | D72: =IFERROR(INDEX('Detalles movimientos'!E$5:E$1000, MATCH(63, 'Detalles movimientos'!$R$5:$R$1000, 0)), "") | E72: =IFERROR(INDEX('Detalles movimientos'!F$5:F$1000, MATCH(63, 'Detalles movimientos'!$R$5:$R$1000, 0)), "") | F72: =IFERROR(INDEX('Detalles movimientos'!G$5:G$1000, MATCH(63, 'Detalles movimientos'!$R$5:$R$1000, 0)), "") | G72: =IFERROR(INDEX('Detalles movimientos'!H$5:H$1000, MATCH(63, 'Detalles movimientos'!$R$5:$R$1000, 0)), "") | H72: =IFERROR(INDEX('Detalles movimientos'!I$5:I$1000, MATCH(63, 'Detalles movimientos'!$R$5:$R$1000, 0)), "") | I72: =IFERROR(INDEX('Detalles movimientos'!J$5:J$1000, MATCH(63, 'Detalles movimientos'!$R$5:$R$1000, 0)), "") | ... L72: =IFERROR(INDEX('Detalles movimientos'!M$5:M$1000, MATCH(63, 'Detalles movimientos'!$R$5:$R$1000, 0)), "") | M72: =IFERROR(INDEX('Detalles movimientos'!P$5:P$1000, MATCH(63, 'Detalles movimientos'!$R$5:$R$1000, 0)), "")
B73: =IFERROR(INDEX('Detalles movimientos'!C$5:C$1000, MATCH(64, 'Detalles movimientos'!$R$5:$R$1000, 0)), "") | C73: =IFERROR(INDEX('Detalles movimientos'!D$5:D$1000, MATCH(64, 'Detalles movimientos'!$R$5:$R$1000, 0)), "") | D73: =IFERROR(INDEX('Detalles movimientos'!E$5:E$1000, MATCH(64, 'Detalles movimientos'!$R$5:$R$1000, 0)), "") | E73: =IFERROR(INDEX('Detalles movimientos'!F$5:F$1000, MATCH(64, 'Detalles movimientos'!$R$5:$R$1000, 0)), "") | F73: =IFERROR(INDEX('Detalles movimientos'!G$5:G$1000, MATCH(64, 'Detalles movimientos'!$R$5:$R$1000, 0)), "") | G73: =IFERROR(INDEX('Detalles movimientos'!H$5:H$1000, MATCH(64, 'Detalles movimientos'!$R$5:$R$1000, 0)), "") | H73: =IFERROR(INDEX('Detalles movimientos'!I$5:I$1000, MATCH(64, 'Detalles movimientos'!$R$5:$R$1000, 0)), "") | I73: =IFERROR(INDEX('Detalles movimientos'!J$5:J$1000, MATCH(64, 'Detalles movimientos'!$R$5:$R$1000, 0)), "") | ... L73: =IFERROR(INDEX('Detalles movimientos'!M$5:M$1000, MATCH(64, 'Detalles movimientos'!$R$5:$R$1000, 0)), "") | M73: =IFERROR(INDEX('Detalles movimientos'!P$5:P$1000, MATCH(64, 'Detalles movimientos'!$R$5:$R$1000, 0)), "")
B74: =IFERROR(INDEX('Detalles movimientos'!C$5:C$1000, MATCH(65, 'Detalles movimientos'!$R$5:$R$1000, 0)), "") | C74: =IFERROR(INDEX('Detalles movimientos'!D$5:D$1000, MATCH(65, 'Detalles movimientos'!$R$5:$R$1000, 0)), "") | D74: =IFERROR(INDEX('Detalles movimientos'!E$5:E$1000, MATCH(65, 'Detalles movimientos'!$R$5:$R$1000, 0)), "") | E74: =IFERROR(INDEX('Detalles movimientos'!F$5:F$1000, MATCH(65, 'Detalles movimientos'!$R$5:$R$1000, 0)), "") | F74: =IFERROR(INDEX('Detalles movimientos'!G$5:G$1000, MATCH(65, 'Detalles movimientos'!$R$5:$R$1000, 0)), "") | G74: =IFERROR(INDEX('Detalles movimientos'!H$5:H$1000, MATCH(65, 'Detalles movimientos'!$R$5:$R$1000, 0)), "") | H74: =IFERROR(INDEX('Detalles movimientos'!I$5:I$1000, MATCH(65, 'Detalles movimientos'!$R$5:$R$1000, 0)), "") | I74: =IFERROR(INDEX('Detalles movimientos'!J$5:J$1000, MATCH(65, 'Detalles movimientos'!$R$5:$R$1000, 0)), "") | ... L74: =IFERROR(INDEX('Detalles movimientos'!M$5:M$1000, MATCH(65, 'Detalles movimientos'!$R$5:$R$1000, 0)), "") | M74: =IFERROR(INDEX('Detalles movimientos'!P$5:P$1000, MATCH(65, 'Detalles movimientos'!$R$5:$R$1000, 0)), "")
