Workbook

Sheet Detalles movimientos
C2: VENTAS GRANEL ECOGAS SPA
C4: Fecha | D4: Nombre Cliente | E4: Camión | F4: Vende | G4: Dirección | H4: Precio | I4: Litros Vendidos | K4: Cuenta litros | L4: Extraccion | M4: Total Recaudado | N4: Medio de pago | O4: Comisiones | P4: Observación | Q4: COMPRA ENAP | R4: Litros Comprados | T4: _Idx_CJ | U4: _Idx_Ignacio | V4: _Idx_Tripulacion | W4: _Idx_ENAP carga
C5: 46226 | D5: ENAP carga | E5: VJYL61 | F5: ENAP carga | N5: ENAP carga | O5: =IF(F5="CJ", I5*200, "") | P5: Guía N° xxxxx | Q5: 3836889 | R5: 11481 | T5: =IF(F5="CJ", COUNTIF(F$5:F5, "CJ"), "") | U5: =IF(F5="Ignacio", COUNTIF(F$5:F5, "Ignacio"), "") | V5: =IF(F5="Tripulacion", COUNTIF(F$5:F5, "Tripulacion"), "") | W5: =IF(F5="ENAP carga", COUNTIF(F$5:F5, "ENAP carga"), "")
C6: 46230 | D6: Ignacio Guerrero | E6: VJYL61 | F6: Ignacio | L6: 1403 | N6: Extraccion | O6: =IF(F6="CJ", I6*200, "") | P6: Extraccion | T6: =IF(F6="CJ", COUNTIF(F$5:F6, "CJ"), "") | U6: =IF(F6="Ignacio", COUNTIF(F$5:F6, "Ignacio"), "") | V6: =IF(F6="Tripulacion", COUNTIF(F$5:F6, "Tripulacion"), "") | W6: =IF(F6="ENAP carga", COUNTIF(F$5:F6, "ENAP carga"), "")
C7: 46230 | D7: Ricardo Brisas del Raco | E7: VJYL61 | F7: CJ | G7: Brisas del Raco | H7: 1000 | I7: 179.2 | M7: =H7*I7 | N7: Tarjeta | O7: =I7*200 | P7: Comision Pagada | T7: =IF(F7="CJ", COUNTIF(F$5:F7, "CJ"), "") | U7: =IF(F7="Ignacio", COUNTIF(F$5:F7, "Ignacio"), "") | V7: =IF(F7="Tripulacion", COUNTIF(F$5:F7, "Tripulacion"), "") | W7: =IF(F7="ENAP carga", COUNTIF(F$5:F7, "ENAP carga"), "")
C8: 46230 | D8: Ale Turko | E8: VJYL61 | F8: CJ | H8: 1000 | I8: 518.1 | M8: =H8*I8 | N8: Pendiente de pago | O8: =I8*200 | P8: Comision Pagada | T8: =IF(F8="CJ", COUNTIF(F$5:F8, "CJ"), "") | U8: =IF(F8="Ignacio", COUNTIF(F$5:F8, "Ignacio"), "") | V8: =IF(F8="Tripulacion", COUNTIF(F$5:F8, "Tripulacion"), "") | W8: =IF(F8="ENAP carga", COUNTIF(F$5:F8, "ENAP carga"), "")
C9: 46230 | D9: Tirua | E9: VJYL61 | F9: CJ | H9: 1000 | I9: 488.2 | M9: =H9*I9 | N9: Pagado | O9: =I9*200 | P9: Comision Pagada | T9: =IF(F9="CJ", COUNTIF(F$5:F9, "CJ"), "") | U9: =IF(F9="Ignacio", COUNTIF(F$5:F9, "Ignacio"), "") | V9: =IF(F9="Tripulacion", COUNTIF(F$5:F9, "Tripulacion"), "") | W9: =IF(F9="ENAP carga", COUNTIF(F$5:F9, "ENAP carga"), "")
C10: 46230 | D10: Ciao Italia | E10: VJYL61 | F10: CJ | H10: 1000 | I10: 500.3 | M10: =H10*I10 | N10: Pagado | O10: =I10*200 | P10: Comision Pagada | T10: =IF(F10="CJ", COUNTIF(F$5:F10, "CJ"), "") | U10: =IF(F10="Ignacio", COUNTIF(F$5:F10, "Ignacio"), "") | V10: =IF(F10="Tripulacion", COUNTIF(F$5:F10, "Tripulacion"), "") | W10: =IF(F10="ENAP carga", COUNTIF(F$5:F10, "ENAP carga"), "")
C11: 46230 | D11: Claudio Ulloa | E11: VJYL61 | F11: CJ | H11: 1000 | I11: 237.9 | M11: =H11*I11 | N11: Pagado | O11: =I11*200 | P11: Comision Pagada | T11: =IF(F11="CJ", COUNTIF(F$5:F11, "CJ"), "") | U11: =IF(F11="Ignacio", COUNTIF(F$5:F11, "Ignacio"), "") | V11: =IF(F11="Tripulacion", COUNTIF(F$5:F11, "Tripulacion"), "") | W11: =IF(F11="ENAP carga", COUNTIF(F$5:F11, "ENAP carga"), "")
C12: 46230 | D12: Francisco Ulloa | E12: VJYL61 | F12: CJ | H12: 1000 | I12: 205.1 | M12: =H12*I12 | N12: Pagado | O12: =I12*200 | P12: Comision Pagada | T12: =IF(F12="CJ", COUNTIF(F$5:F12, "CJ"), "") | U12: =IF(F12="Ignacio", COUNTIF(F$5:F12, "Ignacio"), "") | V12: =IF(F12="Tripulacion", COUNTIF(F$5:F12, "Tripulacion"), "") | W12: =IF(F12="ENAP carga", COUNTIF(F$5:F12, "ENAP carga"), "")
C13: 46230 | D13: Alicia Pavez | E13: VJYL61 | F13: CJ | H13: 1000 | I13: 300 | M13: =H13*I13 | N13: Pendiente de pago | O13: =I13*200 | P13: Comision Pagada | S13: =SUM(I7:I13) | T13: =IF(F13="CJ", COUNTIF(F$5:F13, "CJ"), "") | U13: =IF(F13="Ignacio", COUNTIF(F$5:F13, "Ignacio"), "") | V13: =IF(F13="Tripulacion", COUNTIF(F$5:F13, "Tripulacion"), "") | W13: =IF(F13="ENAP carga", COUNTIF(F$5:F13, "ENAP carga"), "")
C14: 46231 | D14: Vanessa | E14: VJYL61 | F14: CJ | H14: 1000 | I14: 200 | M14: =H14*I14 | N14: Transferencia | O14: =IF(F14="CJ", I14*200, "") | T14: =IF(F14="CJ", COUNTIF(F$5:F14, "CJ"), "") | U14: =IF(F14="Ignacio", COUNTIF(F$5:F14, "Ignacio"), "") | V14: =IF(F14="Tripulacion", COUNTIF(F$5:F14, "Tripulacion"), "") | W14: =IF(F14="ENAP carga", COUNTIF(F$5:F14, "ENAP carga"), "")
C15: 46231 | D15: Franco Garcia | E15: VJYL61 | F15: Tripulacion | G15: Santa Rita 1177 parcela 14 Pirque | H15: 0 | I15: 912 | K15: 13789 | M15: =H15*I15 | O15: =IF(F15="CJ", I15*200, "") | T15: =IF(F15="CJ", COUNTIF(F$5:F15, "CJ"), "") | U15: =IF(F15="Ignacio", COUNTIF(F$5:F15, "Ignacio"), "") | V15: =IF(F15="Tripulacion", COUNTIF(F$5:F15, "Tripulacion"), "") | W15: =IF(F15="ENAP carga", COUNTIF(F$5:F15, "ENAP carga"), "")
C16: 46233 | D16: Simon | E16: VJYL61 | F16: CJ | G16: Camino el Chalaco 66B | H16: 1000 | I16: 747 | J16: =K16-K15 | K16: 14535 | M16: =H16*I16 | N16: Transferencia | O16: =IF(F16="CJ", I16*200, "") | P16: Factura | S16: Ebal spa - RUT: 77.625.623-4 - Av Gabriela 3264 La Pintana - Giro Construccion | T16: =IF(F16="CJ", COUNTIF(F$5:F16, "CJ"), "") | U16: =IF(F16="Ignacio", COUNTIF(F$5:F16, "Ignacio"), "") | V16: =IF(F16="Tripulacion", COUNTIF(F$5:F16, "Tripulacion"), "") | W16: =IF(F16="ENAP carga", COUNTIF(F$5:F16, "ENAP carga"), "")
C17: 46237 | D17: Manuel Vergara Ricci | E17: VJYL61 | F17: CJ | G17: Avenida Virginia subercaseaux 4175 (parcela 15) | H17: 1100 | I17: 200 | J17: =K17-K16 | K17: 14735 | M17: =H17*I17 | N17: Transferencia | O17: =IF(F17="CJ", I17*200, "") | T17: =IF(F17="CJ", COUNTIF(F$5:F17, "CJ"), "") | U17: =IF(F17="Ignacio", COUNTIF(F$5:F17, "Ignacio"), "") | V17: =IF(F17="Tripulacion", COUNTIF(F$5:F17, "Tripulacion"), "") | W17: =IF(F17="ENAP carga", COUNTIF(F$5:F17, "ENAP carga"), "")
C18: 46237 | D18: Gabriela Rojas | E18: VJYL61 | F18: CJ | G18: Camino de las flores 1262 Pirque | H18: 1100 | I18: 350 | J18: =K18-K17 | K18: 16490 | M18: =H18*I18 | N18: Transferencia en dos | O18: =IF(F18="CJ", I18*200, "") | P18: Quedó saldo de $35 mil para mañana | T18: =IF(F18="CJ", COUNTIF(F$5:F18, "CJ"), "") | U18: =IF(F18="Ignacio", COUNTIF(F$5:F18, "Ignacio"), "") | V18: =IF(F18="Tripulacion", COUNTIF(F$5:F18, "Tripulacion"), "") | W18: =IF(F18="ENAP carga", COUNTIF(F$5:F18, "ENAP carga"), "")
C19: 46238 | D19: Ignacio Guerrero | E19: VJYL61 | F19: Ignacio | L19: 1403 | N19: Extraccion | O19: =IF(F19="CJ", L19*200, "") | P19: Extraccion | T19: =IF(F19="CJ", COUNTIF(F$5:F19, "CJ"), "") | U19: =IF(F19="Ignacio", COUNTIF(F$5:F19, "Ignacio"), "") | V19: =IF(F19="Tripulacion", COUNTIF(F$5:F19, "Tripulacion"), "") | W19: =IF(F19="ENAP carga", COUNTIF(F$5:F19, "ENAP carga"), "")
C20: 46239 | D20: Casa de Reposo Brisas | E20: VJYL61 | F20: CJ | G20: Brisas del raco parcela 36 Pirque | H20: 1100 | I20: 270 | J20: =K20-K18 | K20: 16760 | M20: =H20*I20 | N20: Transferencia | O20: =IF(F20="CJ", I20*200, "") | P20: Factura | S20: Residencia Adulto Mayor Amor Eterno SpA - Rut 76.699.397-4 - Los Almendros Parcela2B Pirque | T20: =IF(F20="CJ", COUNTIF(F$5:F20, "CJ"), "") | U20: =IF(F20="Ignacio", COUNTIF(F$5:F20, "Ignacio"), "") | V20: =IF(F20="Tripulacion", COUNTIF(F$5:F20, "Tripulacion"), "") | W20: =IF(F20="ENAP carga", COUNTIF(F$5:F20, "ENAP carga"), "")
C21: 46241 | D21: Gastronomca Exquisite | E21: VJYL61 | F21: Tripulacion | G21: JP Alesaandri 114 Nuñoa | H21: 1000 | I21: 350 | J21: =K21-K20 | K21: 17110 | M21: =H21*I21 | N21: Transferencia | O21: =IF(F21="CJ", I21*200, "") | P21: Factura | S21: Gastronomica Exquisite SpA - Rut: 77.714.318-2 - JP alessandri 114 Nuñoa | T21: =IF(F21="CJ", COUNTIF(F$5:F21, "CJ"), "") | U21: =IF(F21="Ignacio", COUNTIF(F$5:F21, "Ignacio"), "") | V21: =IF(F21="Tripulacion", COUNTIF(F$5:F21, "Tripulacion"), "") | W21: =IF(F21="ENAP carga", COUNTIF(F$5:F21, "ENAP carga"), "")
C22: 46241 | D22: Panaderia Maipu | E22: VJYL61 | F22: Tripulacion | G22: Av los carreras 706B, plaza de los porotos | H22: 1000 | I22: 109 | J22: =K22-K21 | K22: 17219 | M22: =H22*I22 | N22: Transferencia | O22: =IF(F22="CJ", I22*200, "") | T22: =IF(F22="CJ", COUNTIF(F$5:F22, "CJ"), "") | U22: =IF(F22="Ignacio", COUNTIF(F$5:F22, "Ignacio"), "") | V22: =IF(F22="Tripulacion", COUNTIF(F$5:F22, "Tripulacion"), "") | W22: =IF(F22="ENAP carga", COUNTIF(F$5:F22, "ENAP carga"), "")
C23: 46242 | D23: Ignacio Guerrero | E23: VJYL61 | F23: Ignacio | L23: 2219 | N23: Extraccion | O23: =IF(F23="CJ", L23*200, "") | P23: Extraccion | T23: =IF(F23="CJ", COUNTIF(F$5:F23, "CJ"), "") | U23: =IF(F23="Ignacio", COUNTIF(F$5:F23, "Ignacio"), "") | V23: =IF(F23="Tripulacion", COUNTIF(F$5:F23, "Tripulacion"), "") | W23: =IF(F23="ENAP carga", COUNTIF(F$5:F23, "ENAP carga"), "")
C24: 46245 | D24: Eli Ciao Italia | E24: VJYL61 | F24: CJ | G24: Camino rinconada san Vicente parcela 38 | H24: 1100 | I24: 404 | J24: =K24-K22 | K24: 19834 | M24: =H24*I24 | N24: Transferencia | O24: =IF(F24="CJ", I24*200, "") | T24: =IF(F24="CJ", COUNTIF(F$5:F24, "CJ"), "") | U24: =IF(F24="Ignacio", COUNTIF(F$5:F24, "Ignacio"), "") | V24: =IF(F24="Tripulacion", COUNTIF(F$5:F24, "Tripulacion"), "") | W24: =IF(F24="ENAP carga", COUNTIF(F$5:F24, "ENAP carga"), "")
C25: 46245 | D25: Javier Quiroz | E25: VJYL61 | F25: CJ | G25: Condominio majadas C parcela 5 | H25: 1100 | I25: 509 | J25: =K25-K24 | K25: 20343 | M25: =H25*I25 | N25: Transferencia | O25: =IF(F25="CJ", I25*200, "") | T25: =IF(F25="CJ", COUNTIF(F$5:F25, "CJ"), "") | U25: =IF(F25="Ignacio", COUNTIF(F$5:F25, "Ignacio"), "") | V25: =IF(F25="Tripulacion", COUNTIF(F$5:F25, "Tripulacion"), "") | W25: =IF(F25="ENAP carga", COUNTIF(F$5:F25, "ENAP carga"), "")
C26: 46246 | D26: ENAP carga | E26: VJYL42 | F26: ENAP carga | M26: =H26*I26 | N26: ENAP carga | O26: =IF(F26="CJ", I26*200, "") | P26: Guía N° 2356186 | Q26: 3882182 | R26: 11617 | T26: =IF(F26="CJ", COUNTIF(F$5:F26, "CJ"), "") | U26: =IF(F26="Ignacio", COUNTIF(F$5:F26, "Ignacio"), "") | V26: =IF(F26="Tripulacion", COUNTIF(F$5:F26, "Tripulacion"), "") | W26: =IF(F26="ENAP carga", COUNTIF(F$5:F26, "ENAP carga"), "")
C27: 46247 | D27: Ignacio Guerrero | E27: VJYL42 | F27: Ignacio | L27: 11539 | M27: =H27*I27 | N27: Extraccion | O27: =IF(F27="CJ", I27*200, "") | P27: Extraccion | T27: =IF(F27="CJ", COUNTIF(F$5:F27, "CJ"), "") | U27: =IF(F27="Ignacio", COUNTIF(F$5:F27, "Ignacio"), "") | V27: =IF(F27="Tripulacion", COUNTIF(F$5:F27, "Tripulacion"), "") | W27: =IF(F27="ENAP carga", COUNTIF(F$5:F27, "ENAP carga"), "")
C28: 46247 | D28: ENAP carga | E28: VJYL61 | F28: ENAP carga | M28: =H28*I28 | N28: ENAP carga | O28: =IF(F28="CJ", I28*200, "") | P28: Guía N° 2356453 | Q28: 3836889 | R28: 11481 | T28: =IF(F28="CJ", COUNTIF(F$5:F28, "CJ"), "") | U28: =IF(F28="Ignacio", COUNTIF(F$5:F28, "Ignacio"), "") | V28: =IF(F28="Tripulacion", COUNTIF(F$5:F28, "Tripulacion"), "") | W28: =IF(F28="ENAP carga", COUNTIF(F$5:F28, "ENAP carga"), "")
C29: 46247 | D29: Mister Guss SpA | E29: VJYL61 | F29: Tripulacion | G29: PRIMERA TRANSVERSAL 828 PADRE HURTADO | H29: 1000 | I29: 256 | K29: 22615 | M29: =H29*I29 | N29: Transferencia | O29: =IF(F29="CJ", I29*200, "") | P29: Factura | S29: MISTER GUSS SPA - RUT 78.060.801-3 - PRIMERA TRANSVERSAL 828 PADRE HURTADO - RESTOBAR | T29: =IF(F29="CJ", COUNTIF(F$5:F29, "CJ"), "") | U29: =IF(F29="Ignacio", COUNTIF(F$5:F29, "Ignacio"), "") | V29: =IF(F29="Tripulacion", COUNTIF(F$5:F29, "Tripulacion"), "") | W29: =IF(F29="ENAP carga", COUNTIF(F$5:F29, "ENAP carga"), "")
C30: 46248 | D30: ENAP carga | E30: VJYL42 | F30: ENAP carga | N30: ENAP carga | O30: =IF(F30="CJ", I30*200, "") | P30: Guía N° 2356889 | Q30: 3955528 | R30: 11656 | T30: =IF(F30="CJ", COUNTIF(F$5:F30, "CJ"), "") | U30: =IF(F30="Ignacio", COUNTIF(F$5:F30, "Ignacio"), "") | V30: =IF(F30="Tripulacion", COUNTIF(F$5:F30, "Tripulacion"), "") | W30: =IF(F30="ENAP carga", COUNTIF(F$5:F30, "ENAP carga"), "")
C31: 46251 | D31: Ignacio Guerrero | E31: VJYL42 | F31: Ignacio | L31: 11344 | N31: Extraccion | P31: Extraccion
C32: 46252 | D32: ENAP carga | E32: VJYL42 | F32: ENAP carga | N32: ENAP carga | O32: =IF(F32="CJ", I32*200, "") | P32: Guía N° 2358078 | Q32: 3889821 | R32: 11462 | T32: =IF(F32="CJ", COUNTIF(F$5:F32, "CJ"), "") | U32: =IF(F32="Ignacio", COUNTIF(F$5:F32, "Ignacio"), "") | V32: =IF(F32="Tripulacion", COUNTIF(F$5:F32, "Tripulacion"), "") | W32: =IF(F32="ENAP carga", COUNTIF(F$5:F32, "ENAP carga"), "")
C33: 46253 | D33: ENAP carga | E33: VJYL42 | F33: ENAP carga | N33: ENAP carga | O33: =IF(F33="CJ", I33*200, "") | P33: Guía N° 2358522 | Q33: 3830686 | R33: 11288 | T33: =IF(F33="CJ", COUNTIF(F$5:F33, "CJ"), "") | U33: =IF(F33="Ignacio", COUNTIF(F$5:F33, "Ignacio"), "") | V33: =IF(F33="Tripulacion", COUNTIF(F$5:F33, "Tripulacion"), "") | W33: =IF(F33="ENAP carga", COUNTIF(F$5:F33, "ENAP carga"), "")
C34: 46253 | D34: Ignacio Guerrero | E34: VJYL42 | F34: Ignacio | L34: 11225 | N34: Extraccion | P34: Extraccion
C35: 46254 | D35: Ignacio Guerrero | E35: VJYL42 | F35: Ignacio | L35: 11088 | N35: Extraccion | P35: Extraccion
C36: 46254 | D36: Bar Barrio Alto | E36: VJYL61 | F36: CJ | G36: El Peñón 335 Puente Alto | H36: 1000 | I36: 294 | J36: =K36-K29 | K36: 22909 | M36: =H36*I36 | N36: Transferencia dos | O36: =IF(F36="CJ", I36*200, "") | P36: Factura | S36: Centro de eventos Barrio Alto SpA - RUT 78.467.844-K - EL PENON CHICO 0335 PUENTE ALTO | T36: =IF(F36="CJ", COUNTIF(F$5:F36, "CJ"), "") | U36: =IF(F36="Ignacio", COUNTIF(F$5:F36, "Ignacio"), "") | V36: =IF(F36="Tripulacion", COUNTIF(F$5:F36, "Tripulacion"), "") | W36: =IF(F36="ENAP carga", COUNTIF(F$5:F36, "ENAP carga"), "")
C37: 46254 | D37: BAR Tirua | E37: VJYL61 | F37: CJ | G37: Pirque | H37: 1100 | I37: 500 | J37: =K37-K36 | K37: 23409 | M37: =H37*I37 | N37: Pendiente de pago | O37: =IF(F37="CJ", I37*200, "") | T37: =IF(F37="CJ", COUNTIF(F$5:F37, "CJ"), "") | U37: =IF(F37="Ignacio", COUNTIF(F$5:F37, "Ignacio"), "") | V37: =IF(F37="Tripulacion", COUNTIF(F$5:F37, "Tripulacion"), "") | W37: =IF(F37="ENAP carga", COUNTIF(F$5:F37, "ENAP carga"), "")
C38: 46254 | D38: Brasas y Sabor SpA | E38: VJYL61 | F38: Tripulacion | G38: Puente Alto | H38: 1100 | I38: 100 | J38: =K38-K37 | K38: 23509 | M38: =H38*I38 | N38: Transferencia | O38: =IF(F38="CJ", I38*200, "") | P38: Factura | S38: Brasas y Sabor SpA - RUT 76.378-704-4 - Av Concha y Toro #11 Puente Alto | T38: =IF(F38="CJ", COUNTIF(F$5:F38, "CJ"), "") | U38: =IF(F38="Ignacio", COUNTIF(F$5:F38, "Ignacio"), "") | V38: =IF(F38="Tripulacion", COUNTIF(F$5:F38, "Tripulacion"), "") | W38: =IF(F38="ENAP carga", COUNTIF(F$5:F38, "ENAP carga"), "")
C39: 46258 | D39: Franco Garcia | E39: VJYL61 | F39: Tripulacion | G39: Santa Rita 1177 parcela 14 Pirque | H39: 0 | I39: 1120 | J39: =K39-K38 | K39: 24630 | M39: =H39*I39 | O39: =IF(F39="CJ", I39*200, "") | T39: =IF(F39="CJ", COUNTIF(F$5:F39, "CJ"), "") | U39: =IF(F39="Ignacio", COUNTIF(F$5:F39, "Ignacio"), "") | V39: =IF(F39="Tripulacion", COUNTIF(F$5:F39, "Tripulacion"), "") | W39: =IF(F39="ENAP carga", COUNTIF(F$5:F39, "ENAP carga"), "")
C40: 46258 | D40: Centro de Eventos Barrio Alto SpA | E40: VJYL61 | F40: Tripulacion | G40: El Peñón 335 Puente Alto | H40: 1000 | I40: 449 | J40: =K40-K39 | K40: 25078 | M40: =H40*I40 | N40: Transferencia | O40: =IF(F40="CJ", I40*200, "") | P40: Factura | S40: Centro de eventos Barrio Alto SpA - RUT 78.467.844-K - EL PENON CHICO 0335 PUENTE ALTO | T40: =IF(F40="CJ", COUNTIF(F$5:F40, "CJ"), "") | U40: =IF(F40="Ignacio", COUNTIF(F$5:F40, "Ignacio"), "") | V40: =IF(F40="Tripulacion", COUNTIF(F$5:F40, "Tripulacion"), "") | W40: =IF(F40="ENAP carga", COUNTIF(F$5:F40, "ENAP carga"), "")
C41: 46259 | D41: ENAP carga | E41: VJYL42 | F41: ENAP carga | N41: ENAP carga | O41: =IF(F41="CJ", I41*200, "") | P41: Guía N° 2360214 | Q41: 3772187 | R41: 11288 | T41: =IF(F41="CJ", COUNTIF(F$5:F41, "CJ"), "") | U41: =IF(F41="Ignacio", COUNTIF(F$5:F41, "Ignacio"), "") | V41: =IF(F41="Tripulacion", COUNTIF(F$5:F41, "Tripulacion"), "") | W41: =IF(F41="ENAP carga", COUNTIF(F$5:F41, "ENAP carga"), "")
C42: 46260 | D42: ENAP carga | E42: VJYL42 | F42: ENAP carga | N42: ENAP carga | O42: =IF(F42="CJ", I42*200, "") | P42: Guía N° 2360596 | Q42: 3571608 | R42: 10688 | T42: =IF(F42="CJ", COUNTIF(F$5:F42, "CJ"), "") | U42: =IF(F42="Ignacio", COUNTIF(F$5:F42, "Ignacio"), "") | V42: =IF(F42="Tripulacion", COUNTIF(F$5:F42, "Tripulacion"), "") | W42: =IF(F42="ENAP carga", COUNTIF(F$5:F42, "ENAP carga"), "")
C43: 46261 | D43: Comercializadora Lavin | E43: VJYL61 | F43: Tripulacion | G43: Ignacio Carrera Pinto 693 Padre Hurtado | H43: 1000 | I43: 313 | J43: =K43-K40 | K43: 25391 | M43: =H43*I43 | N43: Transferencia | O43: =IF(F43="CJ", I43*200, "") | T43: =IF(F43="CJ", COUNTIF(F$5:F43, "CJ"), "") | U43: =IF(F43="Ignacio", COUNTIF(F$5:F43, "Ignacio"), "") | V43: =IF(F43="Tripulacion", COUNTIF(F$5:F43, "Tripulacion"), "") | W43: =IF(F43="ENAP carga", COUNTIF(F$5:F43, "ENAP carga"), "")
C44: 46261 | D44: El Toro Manso | E44: VJYL61 | F44: CJ | G44: Virginia Subercaso Pirque | H44: 1000 | I44: 300 | M44: =H44*I44 | N44: Transferencia | O44: =IF(F44="CJ", I44*200, "") | T44: =IF(F44="CJ", COUNTIF(F$5:F44, "CJ"), "") | U44: =IF(F44="Ignacio", COUNTIF(F$5:F44, "Ignacio"), "") | V44: =IF(F44="Tripulacion", COUNTIF(F$5:F44, "Tripulacion"), "") | W44: =IF(F44="ENAP carga", COUNTIF(F$5:F44, "ENAP carga"), "")
C45: 46262 | D45: ENAP carga | E45: VJYL42 | F45: ENAP carga | O45: =IF(F45="CJ", I45*200, "") | P45: Guía N° 2361274 | Q45: 3843361 | R45: 11501 | T45: =IF(F45="CJ", COUNTIF(F$5:F45, "CJ"), "") | U45: =IF(F45="Ignacio", COUNTIF(F$5:F45, "Ignacio"), "") | V45: =IF(F45="Tripulacion", COUNTIF(F$5:F45, "Tripulacion"), "") | W45: =IF(F45="ENAP carga", COUNTIF(F$5:F45, "ENAP carga"), "")
C46: 46262 | D46: Gastronomca Exquisite | E46: VJYL61 | F46: Tripulacion | G46: JP Alesaandri 114 Nuñoa | H46: 1000 | I46: 300 | J46: =K46-K43 | K46: 25691 | M46: =H46*I46 | N46: Transferencia | O46: =IF(F46="CJ", I46*200, "") | T46: =IF(F46="CJ", COUNTIF(F$5:F46, "CJ"), "") | U46: =IF(F46="Ignacio", COUNTIF(F$5:F46, "Ignacio"), "") | V46: =IF(F46="Tripulacion", COUNTIF(F$5:F46, "Tripulacion"), "") | W46: =IF(F46="ENAP carga", COUNTIF(F$5:F46, "ENAP carga"), "")
C47: 46262 | D47: Cuco¨s Pollo | E47: VJYL42 | F47: Tripulacion | G47: Av Observatorio 1088 El Bosque | H47: 1000 | I47: 253 | M47: =H47*I47 | N47: Deposito efectivo | O47: =IF(F47="CJ", I47*200, "") | T47: =IF(F47="CJ", COUNTIF(F$5:F47, "CJ"), "") | U47: =IF(F47="Ignacio", COUNTIF(F$5:F47, "Ignacio"), "") | V47: =IF(F47="Tripulacion", COUNTIF(F$5:F47, "Tripulacion"), "") | W47: =IF(F47="ENAP carga", COUNTIF(F$5:F47, "ENAP carga"), "")
C48: 46265 | D48: ENAP carga | E48: VJYL42 | F48: ENAP carga | N48: ENAP carga | O48: =IF(F48="CJ", I48*200, "") | P48: Guía N° 2361941 | Q48: 3890396 | R48: 11462 | T48: =IF(F48="CJ", COUNTIF(F$5:F48, "CJ"), "") | U48: =IF(F48="Ignacio", COUNTIF(F$5:F48, "Ignacio"), "") | V48: =IF(F48="Tripulacion", COUNTIF(F$5:F48, "Tripulacion"), "") | W48: =IF(F48="ENAP carga", COUNTIF(F$5:F48, "ENAP carga"), "")
C49: 46267 | D49: Cristobal Bravo | E49: VJYL61 | F49: Tripulacion | G49: Pirque | H49: 850 | I49: 1000 | J49: =K49-K46 | K49: 26691 | M49: =H49*I49 | N49: Pagado | O49: =IF(F49="CJ", I49*200, "") | T49: =IF(F49="CJ", COUNTIF(F$5:F49, "CJ"), "") | U49: =IF(F49="Ignacio", COUNTIF(F$5:F49, "Ignacio"), "") | V49: =IF(F49="Tripulacion", COUNTIF(F$5:F49, "Tripulacion"), "") | W49: =IF(F49="ENAP carga", COUNTIF(F$5:F49, "ENAP carga"), "")
C50: 46268 | E50: VJYL61 | F50: Tripulacion | G50: Pirque | H50: 1000 | I50: 342.7 | J50: =K50-K49 | K50: 27034 | M50: =H50*I50 | N50: Transferencia | O50: =IF(F50="CJ", I50*200, "") | T50: =IF(F50="CJ", COUNTIF(F$5:F50, "CJ"), "") | U50: =IF(F50="Ignacio", COUNTIF(F$5:F50, "Ignacio"), "") | V50: =IF(F50="Tripulacion", COUNTIF(F$5:F50, "Tripulacion"), "") | W50: =IF(F50="ENAP carga", COUNTIF(F$5:F50, "ENAP carga"), "")
C51: 46270 | D51: ENAP carga | E51: VJYL42 | F51: ENAP carga | N51: ENAP carga | P51: Guía N° 2363973 | Q51: 3890396 | R51: 11481
C52: 46271 | D52: Casa de Reposo Brisas | E52: VJYL61 | F52: Tripulacion | G52: Pirque | H52: 1100 | I52: 300 | J52: =K52-K50 | K52: 27334 | M52: =H52*I52 | N52: Transferencia | O52: =IF(F52="CJ", I52*200, "") | T52: =IF(F52="CJ", COUNTIF(F$5:F52, "CJ"), "") | U52: =IF(F52="Ignacio", COUNTIF(F$5:F52, "Ignacio"), "") | V52: =IF(F52="Tripulacion", COUNTIF(F$5:F52, "Tripulacion"), "") | W52: =IF(F52="ENAP carga", COUNTIF(F$5:F52, "ENAP carga"), "")
C53: 46271 | D53: Jazmin Sunko | E53: VJYL61 | F53: Tripulacion | G53: Pirque | H53: 1100 | I53: 254 | J53: =K53-K52 | K53: 27588.7 | M53: =H53*I53 | N53: Transferencia | O53: =IF(F53="CJ", I53*200, "") | T53: =IF(F53="CJ", COUNTIF(F$5:F53, "CJ"), "") | U53: =IF(F53="Ignacio", COUNTIF(F$5:F53, "Ignacio"), "") | V53: =IF(F53="Tripulacion", COUNTIF(F$5:F53, "Tripulacion"), "") | W53: =IF(F53="ENAP carga", COUNTIF(F$5:F53, "ENAP carga"), "")
C54: 46272 | D54: ENAP carga | E54: VJYL42 | F54: ENAP carga | N54: ENAP carga | O54: =IF(F54="CJ", I54*200, "") | P54: Guía N° 2364285 | Q54: 3706813 | R54: 11288 | T54: =IF(F54="CJ", COUNTIF(F$5:F54, "CJ"), "") | U54: =IF(F54="Ignacio", COUNTIF(F$5:F54, "Ignacio"), "") | V54: =IF(F54="Tripulacion", COUNTIF(F$5:F54, "Tripulacion"), "") | W54: =IF(F54="ENAP carga", COUNTIF(F$5:F54, "ENAP carga"), "")
C55: 46273 | D55: ENAP carga | E55: VJYL42 | F55: ENAP carga | N55: ENAP carga | O55: =IF(F55="CJ", I55*200, "") | P55: Guía N° 2364754 | Q55: 3675022 | R55: 11307 | T55: =IF(F55="CJ", COUNTIF(F$5:F55, "CJ"), "") | U55: =IF(F55="Ignacio", COUNTIF(F$5:F55, "Ignacio"), "") | V55: =IF(F55="Tripulacion", COUNTIF(F$5:F55, "Tripulacion"), "") | W55: =IF(F55="ENAP carga", COUNTIF(F$5:F55, "ENAP carga"), "")
C56: 46274 | D56: ENAP carga | E56: VJYL42 | F56: ENAP carga | N56: ENAP carga | O56: =IF(F56="CJ", I56*200, "") | P56: Guía N° 2365221 | Q56: 3725888 | R56: 11346 | T56: =IF(F56="CJ", COUNTIF(F$5:F56, "CJ"), "") | U56: =IF(F56="Ignacio", COUNTIF(F$5:F56, "Ignacio"), "") | V56: =IF(F56="Tripulacion", COUNTIF(F$5:F56, "Tripulacion"), "") | W56: =IF(F56="ENAP carga", COUNTIF(F$5:F56, "ENAP carga"), "")
C57: 46275 | D57: ENAP carga | E57: VJYL42 | F57: ENAP carga | N57: ENAP carga | O57: =IF(F57="CJ", I57*200, "") | P57: Guía N° 2365840 | Q57: 3706813 | R57: 11288 | T57: =IF(F57="CJ", COUNTIF(F$5:F57, "CJ"), "") | U57: =IF(F57="Ignacio", COUNTIF(F$5:F57, "Ignacio"), "") | V57: =IF(F57="Tripulacion", COUNTIF(F$5:F57, "Tripulacion"), "") | W57: =IF(F57="ENAP carga", COUNTIF(F$5:F57, "ENAP carga"), "")
C58: 46276 | D58: ENAP carga | E58: VJYL42 | F58: ENAP carga | N58: ENAP carga | O58: =IF(F58="CJ", I58*200, "") | P58: Guía N° 2366189 | Q58: 3675022 | R58: 11191 | T58: =IF(F58="CJ", COUNTIF(F$5:F58, "CJ"), "") | U58: =IF(F58="Ignacio", COUNTIF(F$5:F58, "Ignacio"), "") | V58: =IF(F58="Tripulacion", COUNTIF(F$5:F58, "Tripulacion"), "") | W58: =IF(F58="ENAP carga", COUNTIF(F$5:F58, "ENAP carga"), "")
C59: 46277 | D59: ENAP carga | E59: VJYL42 | F59: ENAP carga | N59: ENAP carga | O59: =IF(F59="CJ", I59*200, "") | P59: Guía N° 2366535 | Q59: 3725888 | R59: 11346 | T59: =IF(F59="CJ", COUNTIF(F$5:F59, "CJ"), "") | U59: =IF(F59="Ignacio", COUNTIF(F$5:F59, "Ignacio"), "") | V59: =IF(F59="Tripulacion", COUNTIF(F$5:F59, "Tripulacion"), "") | W59: =IF(F59="ENAP carga", COUNTIF(F$5:F59, "ENAP carga"), "")
C60: 46279 | D60: ENAP carga | E60: VJYL42 | F60: ENAP carga | N60: ENAP carga | O60: =IF(F60="CJ", I60*200, "") | P60: Guía N° 2366964 | Q60: 3675022 | R60: 11191 | T60: =IF(F60="CJ", COUNTIF(F$5:F60, "CJ"), "") | U60: =IF(F60="Ignacio", COUNTIF(F$5:F60, "Ignacio"), "") | V60: =IF(F60="Tripulacion", COUNTIF(F$5:F60, "Tripulacion"), "") | W60: =IF(F60="ENAP carga", COUNTIF(F$5:F60, "ENAP carga"), "")
C61: 46281 | D61: ENAP carga | E61: VJYL42 | F61: ENAP carga | N61: ENAP carga | O61: =IF(F61="CJ", I61*200, "") | P61: Guía N° 2367767 | Q61: 3630515 | R61: 11055 | T61: =IF(F61="CJ", COUNTIF(F$5:F61, "CJ"), "") | U61: =IF(F61="Ignacio", COUNTIF(F$5:F61, "Ignacio"), "") | V61: =IF(F61="Tripulacion", COUNTIF(F$5:F61, "Tripulacion"), "") | W61: =IF(F61="ENAP carga", COUNTIF(F$5:F61, "ENAP carga"), "")
C62: 46281 | D62: ENAP carga | E62: VJYL61 | F62: ENAP carga | N62: ENAP carga | P62: Guía N° 2367813 | Q62: 3624157 | R62: 11036
C63: 46282 | D63: ENAP carga | E63: VJYL61 | F63: ENAP carga | N63: ENAP carga | P63: Guía N° 2368175 | Q63: 3636873 | R63: 11075
C64: 46282 | D64: ENAP carga | E64: VJYL42 | F64: ENAP carga | N64: ENAP carga | P64: Guía N° 2368199 | Q64: 3630515 | R64: 11055
C65: 46283 | D65: ENAP carga | E65: VJYL42 | F65: ENAP carga | N65: ENAP carga | P65: Guía N° 2368296 | Q65: 3687739 | R65: 11230
C66: 46283 | D66: ENAP carga | E66: VJYL61 | F66: ENAP carga | N66: ENAP carga | P66: Guía N° 2368302 | Q66: 3700455 | R66: 11268
C67: 46286 | D67: ENAP carga | E67: VJYL42 | F67: ENAP carga | N67: ENAP carga | P67: Guía N° 2368758 | Q67: 3643231 | R67: 11094
C68: 46287 | D68: ENAP carga | E68: VJYL61 | F68: ENAP carga | N68: ENAP carga | P68: Guía N° 2369174 | Q68: 3687739 | R68: 11230
C69: 46288 | D69: ENAP carga | E69: VJYL42 | F69: ENAP carga | N69: ENAP carga | P69: Guía N° 2369529 | Q69: 3649590 | R69: 11113
C70: 46288 | D70: ENAP carga | E70: VJYL61 | F70: ENAP carga | N70: ENAP carga | P70: Guía N° 2369600 | Q70: 3668664 | R70: 11172 | T70: =IF(F70="CJ", COUNTIF(F$5:F70, "CJ"), "") | U70: =IF(F70="Ignacio", COUNTIF(F$5:F70, "Ignacio"), "") | V70: =IF(F70="Tripulacion", COUNTIF(F$5:F70, "Tripulacion"), "") | W70: =IF(F70="ENAP carga", COUNTIF(F$5:F70, "ENAP carga"), "")
C71: 46289 | D71: ENAP carga | E71: VJYL42 | F71: ENAP carga | N71: ENAP carga | P71: Guía N° 2369880 | Q71: 3675022 | R71: 11191
C72: 46290 | D72: ENAP carga | E72: VJYL61 | F72: ENAP carga | N72: ENAP carga | P72: Guía N° 2370275 | Q72: 3681380 | R72: 11210
C73: 46290 | D73: Ciao Italia | E73: VJYL61 | H73: 1000 | I73: 400 | M73: 400000 | N73: Transferencia | O73: =IF(F73="CJ", I74*200, "") | T73: =IF(F73="CJ", COUNTIF(F$5:F73, "CJ"), "") | U73: =IF(F73="Ignacio", COUNTIF(F$5:F73, "Ignacio"), "") | V73: =IF(F73="Tripulacion", COUNTIF(F$5:F73, "Tripulacion"), "") | W73: =IF(F73="ENAP carga", COUNTIF(F$5:F73, "ENAP carga"), "")
C74: 46290 | D74: Franco Garcia | E74: VJYL61 | I74: 606 | O74: =IF(F74="CJ",#REF!* 200, "") | T74: =IF(F74="CJ", COUNTIF(F$5:F74, "CJ"), "") | U74: =IF(F74="Ignacio", COUNTIF(F$5:F74, "Ignacio"), "") | V74: =IF(F74="Tripulacion", COUNTIF(F$5:F74, "Tripulacion"), "") | W74: =IF(F74="ENAP carga", COUNTIF(F$5:F74, "ENAP carga"), "")
C75: 46290 | D75: JC | E75: VJYL61 | I75: 453
C76: 46291 | D76: ENAP carga | E76: VJYL61 | F76: ENAP carga | N76: ENAP carga | P76: Guía N° 2370601 | Q76: 3668664 | R76: 11172
C77: 46291 | D77: ENAP carga | E77: VJYL42 | F77: ENAP carga | N77: ENAP carga | P77: Guía N° 2370615 | Q77: 3643231 | R77: 11094
C78: 46293 | D78: ENAP carga | E78: VJYL42 | F78: ENAP carga | N78: ENAP carga | P78: Guía N° 2370973 | Q78: 3605082 | R78: 10978
C79: 46293 | D79: Mister Guss SpA | E79: VJYL42 | H79: 1000 | I79: 916 | M79: 916000
C80: 46295 | D80: ENAP carga | E80: VJYL61 | F80: ENAP carga | N80: ENAP carga | P80: Guía N° 2371924 | Q80: 3681380 | R80: 11210
C81: 46297 | D81: ENAP carga | E81: VJYL42 | F81: ENAP carga | N81: ENAP carga | P81: Guía N° 2372734 | Q81: 4124127 | R81: 11172
C82: 46297 | D82: ENAP carga | E82: VJYL61 | F82: ENAP carga | N82: ENAP carga | P82: Guía N° 2372742 | Q82: 4124127 | R82: 11172 | T82: =IF(F82="CJ", COUNTIF(F$5:F82, "CJ"), "") | U82: =IF(F82="Ignacio", COUNTIF(F$5:F82, "Ignacio"), "") | V82: =IF(F82="Tripulacion", COUNTIF(F$5:F82, "Tripulacion"), "") | W82: =IF(F82="ENAP carga", COUNTIF(F$5:F82, "ENAP carga"), "")
C83: 46298 | D83: ENAP carga | E83: VJYL42 | F83: ENAP carga | N83: ENAP carga | P83: Guía N° 2372987 | Q83: 4145568 | R83: 11230
C84: 46300 | D84: ENAP carga | E84: VJYL42 | F84: ENAP carga | N84: ENAP carga | P84: Guía N° 2373313 | Q84: 4131274 | R84: 11191
C85: 46301 | D85: ENAP carga | E85: VJYL61 | F85: ENAP carga | N85: ENAP carga | P85: Guía N° 2373685 | Q85: 4131274 | R85: 11191 | T85: =IF(F85="CJ", COUNTIF(F$5:F85, "CJ"), "") | U85: =IF(F85="Ignacio", COUNTIF(F$5:F85, "Ignacio"), "") | V85: =IF(F85="Tripulacion", COUNTIF(F$5:F85, "Tripulacion"), "") | W85: =IF(F85="ENAP carga", COUNTIF(F$5:F85, "ENAP carga"), "")
C86: 46303 | D86: ENAP carga | E86: VJYL61 | F86: ENAP carga | N86: ENAP carga | P86: Guía N° 2374399 | Q86: 4131274 | R86: 11191
C87: 46304 | D87: ENAP carga | E87: VJYL42 | F87: ENAP carga | N87: ENAP carga | P87: Guía N° 2374704 | Q87: 4081242 | R87: 11055
C88: 46305 | D88: ENAP carga | E88: VJYL42 | F88: ENAP carga | N88: ENAP carga | P88: Guía N° 2375047 | Q88: 4116979 | R88: 11152 | T88: =IF(F88="CJ", COUNTIF(F$5:F88, "CJ"), "") | U88: =IF(F88="Ignacio", COUNTIF(F$5:F88, "Ignacio"), "") | V88: =IF(F88="Tripulacion", COUNTIF(F$5:F88, "Tripulacion"), "") | W88: =IF(F88="ENAP carga", COUNTIF(F$5:F88, "ENAP carga"), "")
C89: 46305 | D89: ENAP carga | E89: VJYL61 | F89: ENAP carga | N89: ENAP carga | P89: Guía N° 2375063 | Q89: 4109832 | R89: 11133
C90: 46307 | D90: ENAP carga | E90: VJYL42 | F90: ENAP carga | N90: ENAP carga | P90: Guía N° 2375303 | Q90: 4109832 | R90: 11133
C91: 46307 | D91: ENAP carga | E91: VJYL61 | F91: ENAP carga | N91: ENAP carga | P91: Guía N° 2375310 | Q91: 4109832 | R91: 11133 | T91: =IF(F91="CJ", COUNTIF(F$5:F91, "CJ"), "") | U91: =IF(F91="Ignacio", COUNTIF(F$5:F91, "Ignacio"), "") | V91: =IF(F91="Tripulacion", COUNTIF(F$5:F91, "Tripulacion"), "") | W91: =IF(F91="ENAP carga", COUNTIF(F$5:F91, "ENAP carga"), "")
C92: 46308 | D92: ENAP carga | E92: VJYL61 | F92: ENAP carga | N92: ENAP carga | P92: Guía N° 2375632 | Q92: 4116979 | R92: 11152
C93: 46310 | D93: ENAP carga | E93: VJYL61 | F93: ENAP carga | N93: ENAP carga | P93: Guía N° 2376368 | Q93: 4095536 | R93: 11094 | T93: =IF(F93="CJ", COUNTIF(F$5:F93, "CJ"), "") | U93: =IF(F93="Ignacio", COUNTIF(F$5:F93, "Ignacio"), "") | V93: =IF(F93="Tripulacion", COUNTIF(F$5:F93, "Tripulacion"), "") | W93: =IF(F93="ENAP carga", COUNTIF(F$5:F93, "ENAP carga"), "")
C94: 46310 | D94: ENAP carga | E94: VJYL42 | F94: ENAP carga | N94: ENAP carga | P94: Guía N° 2376392 | Q94: 4102683 | R94: 11113
C95: 46311 | D95: ENAP carga | E95: VJYL42 | F95: ENAP carga | N95: ENAP carga | P95: Guía N° 2376802 | Q95: 4116979 | R95: 11152 | T95: =IF(F95="CJ", COUNTIF(F$5:F95, "CJ"), "") | U95: =IF(F95="Ignacio", COUNTIF(F$5:F95, "Ignacio"), "") | V95: =IF(F95="Tripulacion", COUNTIF(F$5:F95, "Tripulacion"), "") | W95: =IF(F95="ENAP carga", COUNTIF(F$5:F95, "ENAP carga"), "")
C96: 46311 | D96: ENAP carga | E96: VJYL61 | F96: ENAP carga | N96: ENAP carga | P96: Guía N° 2376794 | Q96: 4102683 | R96: 11113
C97: 46312 | D97: ENAP carga | E97: VJYL42 | F97: ENAP carga | N97: ENAP carga | P97: Guía N° 2377115 | Q97: 4109832 | R97: 11133 | T97: =IF(F97="CJ", COUNTIF(F$5:F97, "CJ"), "") | U97: =IF(F97="Ignacio", COUNTIF(F$5:F97, "Ignacio"), "") | V97: =IF(F97="Tripulacion", COUNTIF(F$5:F97, "Tripulacion"), "") | W97: =IF(F97="ENAP carga", COUNTIF(F$5:F97, "ENAP carga"), "")
C98: 46314 | D98: ENAP carga | E98: VJYL61 | F98: ENAP carga | N98: ENAP carga | P98: Guía N° 2377567 | Q98: 4074094 | R98: 11036 | W98: =IF(F98="ENAP carga", COUNTIF(F$5:F98, "ENAP carga"), "")
C99: 46315 | D99: ENAP carga | E99: VJYL61 | F99: ENAP carga | N99: ENAP carga | P99: Guía N° 2377964 | Q99: 4088388 | R99: 11075 | T99: =IF(F99="CJ", COUNTIF(F$5:F99, "CJ"), "") | U99: =IF(F99="Ignacio", COUNTIF(F$5:F99, "Ignacio"), "") | V99: =IF(F99="Tripulacion", COUNTIF(F$5:F99, "Tripulacion"), "") | W99: =IF(F99="ENAP carga", COUNTIF(F$5:F99, "ENAP carga"), "")
C100: 46315 | D100: ENAP carga | E100: VJYL42 | F100: ENAP carga | N100: ENAP carga | P100: Guía N° 2377979 | Q100: 4066946 | R100: 11017 | W100: =IF(F100="ENAP carga", COUNTIF(F$5:F100, "ENAP carga"), "")
T101: =IF(F101="CJ", COUNTIF(F$5:F101, "CJ"), "") | U101: =IF(F101="Ignacio", COUNTIF(F$5:F101, "Ignacio"), "") | V101: =IF(F101="Tripulacion", COUNTIF(F$5:F101, "Tripulacion"), "") | W101: =IF(F101="ENAP carga", COUNTIF(F$5:F101, "ENAP carga"), "")
T103: =IF(F103="CJ", COUNTIF(F$5:F103, "CJ"), "") | U103: =IF(F103="Ignacio", COUNTIF(F$5:F103, "Ignacio"), "") | V103: =IF(F103="Tripulacion", COUNTIF(F$5:F103, "Tripulacion"), "") | W103: =IF(F103="ENAP carga", COUNTIF(F$5:F103, "ENAP carga"), "")
...

Sheet ENAP
B2: RESUMEN Y MOVIMIENTOS INDIVIDUALES: ENAP CARGA
B3: Sincronización en tiempo real con la pestaña 'Detalles movimientos'
B5: LITROS VENDIDOS | C5: LITROS COMPRADOS | D5: STOCK ACTUAL | E5: TOTAL VENTAS ($) | F5: N° OPERACIONES
B6: =SUMIFS('Detalles movimientos'!I$5:I$1021, 'Detalles movimientos'!F$5:F$1021, "ENAP carga") | C6: =SUMIFS('Detalles movimientos'!R$5:R$1021, 'Detalles movimientos'!F$5:F$1021, "ENAP carga") | D6: =C6-B6 | E6: =SUMIFS('Detalles movimientos'!M$5:M$1021, 'Detalles movimientos'!F$5:F$1021, "ENAP carga") | F6: =COUNTIFS('Detalles movimientos'!F$5:F$1021, "ENAP carga")
B9: Fecha | C9: Nombre Cliente | D9: Camión | E9: Vende | F9: Dirección | G9: Precio | H9: Litros | I9: Total | J9: Medio de pago | K9: Comisiones | L9: Observación | M9: Facturación / Detalles
B10: =IFERROR(INDEX('Detalles movimientos'!C$5:C$1021, MATCH(1, 'Detalles movimientos'!$W$5:$W$1021, 0)), "") | C10: =IFERROR(INDEX('Detalles movimientos'!D$5:D$1021, MATCH(1, 'Detalles movimientos'!$W$5:$W$1021, 0)), "") | D10: =IFERROR(INDEX('Detalles movimientos'!E$5:E$1021, MATCH(1, 'Detalles movimientos'!$W$5:$W$1021, 0)), "") | E10: =IFERROR(INDEX('Detalles movimientos'!F$5:F$1021, MATCH(1, 'Detalles movimientos'!$W$5:$W$1021, 0)), "") | F10: =IFERROR(INDEX('Detalles movimientos'!G$5:G$1021, MATCH(1, 'Detalles movimientos'!$W$5:$W$1021, 0)), "") | G10: =IFERROR(INDEX('Detalles movimientos'!H$5:H$1021, MATCH(1, 'Detalles movimientos'!$W$5:$W$1021, 0)), "") | H10: =IFERROR(INDEX('Detalles movimientos'!I$5:I$1021, MATCH(1, 'Detalles movimientos'!$W$5:$W$1021, 0)), "") | I10: =IFERROR(INDEX('Detalles movimientos'!M$5:M$1021, MATCH(1, 'Detalles movimientos'!$W$5:$W$1021, 0)), "") | J10: =IFERROR(INDEX('Detalles movimientos'!N$5:N$1021, MATCH(1, 'Detalles movimientos'!$W$5:$W$1021, 0)), "") | K10: =IFERROR(INDEX('Detalles movimientos'!O$5:O$1021, MATCH(1, 'Detalles movimientos'!$W$5:$W$1021, 0)), "") | L10: =IFERROR(INDEX('Detalles movimientos'!P$5:P$1021, MATCH(1, 'Detalles movimientos'!$W$5:$W$1021, 0)), "") | M10: =IFERROR(INDEX('Detalles movimientos'!S$5:S$1021, MATCH(1, 'Detalles movimientos'!$W$5:$W$1021, 0)), "")
B11: =IFERROR(INDEX('Detalles movimientos'!C$5:C$1021, MATCH(2, 'Detalles movimientos'!$W$5:$W$1021, 0)), "") | C11: =IFERROR(INDEX('Detalles movimientos'!D$5:D$1021, MATCH(2, 'Detalles movimientos'!$W$5:$W$1021, 0)), "") | D11: =IFERROR(INDEX('Detalles movimientos'!E$5:E$1021, MATCH(2, 'Detalles movimientos'!$W$5:$W$1021, 0)), "") | E11: =IFERROR(INDEX('Detalles movimientos'!F$5:F$1021, MATCH(2, 'Detalles movimientos'!$W$5:$W$1021, 0)), "") | F11: =IFERROR(INDEX('Detalles movimientos'!G$5:G$1021, MATCH(2, 'Detalles movimientos'!$W$5:$W$1021, 0)), "") | G11: =IFERROR(INDEX('Detalles movimientos'!H$5:H$1021, MATCH(2, 'Detalles movimientos'!$W$5:$W$1021, 0)), "") | H11: =IFERROR(INDEX('Detalles movimientos'!I$5:I$1021, MATCH(2, 'Detalles movimientos'!$W$5:$W$1021, 0)), "") | I11: =IFERROR(INDEX('Detalles movimientos'!M$5:M$1021, MATCH(2, 'Detalles movimientos'!$W$5:$W$1021, 0)), "") | J11: =IFERROR(INDEX('Detalles movimientos'!N$5:N$1021, MATCH(2, 'Detalles movimientos'!$W$5:$W$1021, 0)), "") | K11: =IFERROR(INDEX('Detalles movimientos'!O$5:O$1021, MATCH(2, 'Detalles movimientos'!$W$5:$W$1021, 0)), "") | L11: =IFERROR(INDEX('Detalles movimientos'!P$5:P$1021, MATCH(2, 'Detalles movimientos'!$W$5:$W$1021, 0)), "") | M11: =IFERROR(INDEX('Detalles movimientos'!S$5:S$1021, MATCH(2, 'Detalles movimientos'!$W$5:$W$1021, 0)), "")
B12: =IFERROR(INDEX('Detalles movimientos'!C$5:C$1021, MATCH(3, 'Detalles movimientos'!$W$5:$W$1021, 0)), "") | C12: =IFERROR(INDEX('Detalles movimientos'!D$5:D$1021, MATCH(3, 'Detalles movimientos'!$W$5:$W$1021, 0)), "") | D12: =IFERROR(INDEX('Detalles movimientos'!E$5:E$1021, MATCH(3, 'Detalles movimientos'!$W$5:$W$1021, 0)), "") | E12: =IFERROR(INDEX('Detalles movimientos'!F$5:F$1021, MATCH(3, 'Detalles movimientos'!$W$5:$W$1021, 0)), "") | F12: =IFERROR(INDEX('Detalles movimientos'!G$5:G$1021, MATCH(3, 'Detalles movimientos'!$W$5:$W$1021, 0)), "") | G12: =IFERROR(INDEX('Detalles movimientos'!H$5:H$1021, MATCH(3, 'Detalles movimientos'!$W$5:$W$1021, 0)), "") | H12: =IFERROR(INDEX('Detalles movimientos'!I$5:I$1021, MATCH(3, 'Detalles movimientos'!$W$5:$W$1021, 0)), "") | I12: =IFERROR(INDEX('Detalles movimientos'!M$5:M$1021, MATCH(3, 'Detalles movimientos'!$W$5:$W$1021, 0)), "") | J12: =IFERROR(INDEX('Detalles movimientos'!N$5:N$1021, MATCH(3, 'Detalles movimientos'!$W$5:$W$1021, 0)), "") | K12: =IFERROR(INDEX('Detalles movimientos'!O$5:O$1021, MATCH(3, 'Detalles movimientos'!$W$5:$W$1021, 0)), "") | L12: =IFERROR(INDEX('Detalles movimientos'!P$5:P$1021, MATCH(3, 'Detalles movimientos'!$W$5:$W$1021, 0)), "") | M12: =IFERROR(INDEX('Detalles movimientos'!S$5:S$1021, MATCH(3, 'Detalles movimientos'!$W$5:$W$1021, 0)), "")
B13: =IFERROR(INDEX('Detalles movimientos'!C$5:C$1021, MATCH(4, 'Detalles movimientos'!$W$5:$W$1021, 0)), "") | C13: =IFERROR(INDEX('Detalles movimientos'!D$5:D$1021, MATCH(4, 'Detalles movimientos'!$W$5:$W$1021, 0)), "") | D13: =IFERROR(INDEX('Detalles movimientos'!E$5:E$1021, MATCH(4, 'Detalles movimientos'!$W$5:$W$1021, 0)), "") | E13: =IFERROR(INDEX('Detalles movimientos'!F$5:F$1021, MATCH(4, 'Detalles movimientos'!$W$5:$W$1021, 0)), "") | F13: =IFERROR(INDEX('Detalles movimientos'!G$5:G$1021, MATCH(4, 'Detalles movimientos'!$W$5:$W$1021, 0)), "") | G13: =IFERROR(INDEX('Detalles movimientos'!H$5:H$1021, MATCH(4, 'Detalles movimientos'!$W$5:$W$1021, 0)), "") | H13: =IFERROR(INDEX('Detalles movimientos'!I$5:I$1021, MATCH(4, 'Detalles movimientos'!$W$5:$W$1021, 0)), "") | I13: =IFERROR(INDEX('Detalles movimientos'!M$5:M$1021, MATCH(4, 'Detalles movimientos'!$W$5:$W$1021, 0)), "") | J13: =IFERROR(INDEX('Detalles movimientos'!N$5:N$1021, MATCH(4, 'Detalles movimientos'!$W$5:$W$1021, 0)), "") | K13: =IFERROR(INDEX('Detalles movimientos'!O$5:O$1021, MATCH(4, 'Detalles movimientos'!$W$5:$W$1021, 0)), "") | L13: =IFERROR(INDEX('Detalles movimientos'!P$5:P$1021, MATCH(4, 'Detalles movimientos'!$W$5:$W$1021, 0)), "") | M13: =IFERROR(INDEX('Detalles movimientos'!S$5:S$1021, MATCH(4, 'Detalles movimientos'!$W$5:$W$1021, 0)), "")
B14: =IFERROR(INDEX('Detalles movimientos'!C$5:C$1021, MATCH(5, 'Detalles movimientos'!$W$5:$W$1021, 0)), "") | C14: =IFERROR(INDEX('Detalles movimientos'!D$5:D$1021, MATCH(5, 'Detalles movimientos'!$W$5:$W$1021, 0)), "") | D14: =IFERROR(INDEX('Detalles movimientos'!E$5:E$1021, MATCH(5, 'Detalles movimientos'!$W$5:$W$1021, 0)), "") | E14: =IFERROR(INDEX('Detalles movimientos'!F$5:F$1021, MATCH(5, 'Detalles movimientos'!$W$5:$W$1021, 0)), "") | F14: =IFERROR(INDEX('Detalles movimientos'!G$5:G$1021, MATCH(5, 'Detalles movimientos'!$W$5:$W$1021, 0)), "") | G14: =IFERROR(INDEX('Detalles movimientos'!H$5:H$1021, MATCH(5, 'Detalles movimientos'!$W$5:$W$1021, 0)), "") | H14: =IFERROR(INDEX('Detalles movimientos'!I$5:I$1021, MATCH(5, 'Detalles movimientos'!$W$5:$W$1021, 0)), "") | I14: =IFERROR(INDEX('Detalles movimientos'!M$5:M$1021, MATCH(5, 'Detalles movimientos'!$W$5:$W$1021, 0)), "") | J14: =IFERROR(INDEX('Detalles movimientos'!N$5:N$1021, MATCH(5, 'Detalles movimientos'!$W$5:$W$1021, 0)), "") | K14: =IFERROR(INDEX('Detalles movimientos'!O$5:O$1021, MATCH(5, 'Detalles movimientos'!$W$5:$W$1021, 0)), "") | L14: =IFERROR(INDEX('Detalles movimientos'!P$5:P$1021, MATCH(5, 'Detalles movimientos'!$W$5:$W$1021, 0)), "") | M14: =IFERROR(INDEX('Detalles movimientos'!S$5:S$1021, MATCH(5, 'Detalles movimientos'!$W$5:$W$1021, 0)), "")
B15: =IFERROR(INDEX('Detalles movimientos'!C$5:C$1021, MATCH(6, 'Detalles movimientos'!$W$5:$W$1021, 0)), "") | C15: =IFERROR(INDEX('Detalles movimientos'!D$5:D$1021, MATCH(6, 'Detalles movimientos'!$W$5:$W$1021, 0)), "") | D15: =IFERROR(INDEX('Detalles movimientos'!E$5:E$1021, MATCH(6, 'Detalles movimientos'!$W$5:$W$1021, 0)), "") | E15: =IFERROR(INDEX('Detalles movimientos'!F$5:F$1021, MATCH(6, 'Detalles movimientos'!$W$5:$W$1021, 0)), "") | F15: =IFERROR(INDEX('Detalles movimientos'!G$5:G$1021, MATCH(6, 'Detalles movimientos'!$W$5:$W$1021, 0)), "") | G15: =IFERROR(INDEX('Detalles movimientos'!H$5:H$1021, MATCH(6, 'Detalles movimientos'!$W$5:$W$1021, 0)), "") | H15: =IFERROR(INDEX('Detalles movimientos'!I$5:I$1021, MATCH(6, 'Detalles movimientos'!$W$5:$W$1021, 0)), "") | I15: =IFERROR(INDEX('Detalles movimientos'!M$5:M$1021, MATCH(6, 'Detalles movimientos'!$W$5:$W$1021, 0)), "") | J15: =IFERROR(INDEX('Detalles movimientos'!N$5:N$1021, MATCH(6, 'Detalles movimientos'!$W$5:$W$1021, 0)), "") | K15: =IFERROR(INDEX('Detalles movimientos'!O$5:O$1021, MATCH(6, 'Detalles movimientos'!$W$5:$W$1021, 0)), "") | L15: =IFERROR(INDEX('Detalles movimientos'!P$5:P$1021, MATCH(6, 'Detalles movimientos'!$W$5:$W$1021, 0)), "") | M15: =IFERROR(INDEX('Detalles movimientos'!S$5:S$1021, MATCH(6, 'Detalles movimientos'!$W$5:$W$1021, 0)), "")
B16: =IFERROR(INDEX('Detalles movimientos'!C$5:C$1021, MATCH(7, 'Detalles movimientos'!$W$5:$W$1021, 0)), "") | C16: =IFERROR(INDEX('Detalles movimientos'!D$5:D$1021, MATCH(7, 'Detalles movimientos'!$W$5:$W$1021, 0)), "") | D16: =IFERROR(INDEX('Detalles movimientos'!E$5:E$1021, MATCH(7, 'Detalles movimientos'!$W$5:$W$1021, 0)), "") | E16: =IFERROR(INDEX('Detalles movimientos'!F$5:F$1021, MATCH(7, 'Detalles movimientos'!$W$5:$W$1021, 0)), "") | F16: =IFERROR(INDEX('Detalles movimientos'!G$5:G$1021, MATCH(7, 'Detalles movimientos'!$W$5:$W$1021, 0)), "") | G16: =IFERROR(INDEX('Detalles movimientos'!H$5:H$1021, MATCH(7, 'Detalles movimientos'!$W$5:$W$1021, 0)), "") | H16: =IFERROR(INDEX('Detalles movimientos'!I$5:I$1021, MATCH(7, 'Detalles movimientos'!$W$5:$W$1021, 0)), "") | I16: =IFERROR(INDEX('Detalles movimientos'!M$5:M$1021, MATCH(7, 'Detalles movimientos'!$W$5:$W$1021, 0)), "") | J16: =IFERROR(INDEX('Detalles movimientos'!N$5:N$1021, MATCH(7, 'Detalles movimientos'!$W$5:$W$1021, 0)), "") | K16: =IFERROR(INDEX('Detalles movimientos'!O$5:O$1021, MATCH(7, 'Detalles movimientos'!$W$5:$W$1021, 0)), "") | L16: =IFERROR(INDEX('Detalles movimientos'!P$5:P$1021, MATCH(7, 'Detalles movimientos'!$W$5:$W$1021, 0)), "") | M16: =IFERROR(INDEX('Detalles movimientos'!S$5:S$1021, MATCH(7, 'Detalles movimientos'!$W$5:$W$1021, 0)), "")
B17: =IFERROR(INDEX('Detalles movimientos'!C$5:C$1021, MATCH(8, 'Detalles movimientos'!$W$5:$W$1021, 0)), "") | C17: =IFERROR(INDEX('Detalles movimientos'!D$5:D$1021, MATCH(8, 'Detalles movimientos'!$W$5:$W$1021, 0)), "") | D17: =IFERROR(INDEX('Detalles movimientos'!E$5:E$1021, MATCH(8, 'Detalles movimientos'!$W$5:$W$1021, 0)), "") | E17: =IFERROR(INDEX('Detalles movimientos'!F$5:F$1021, MATCH(8, 'Detalles movimientos'!$W$5:$W$1021, 0)), "") | F17: =IFERROR(INDEX('Detalles movimientos'!G$5:G$1021, MATCH(8, 'Detalles movimientos'!$W$5:$W$1021, 0)), "") | G17: =IFERROR(INDEX('Detalles movimientos'!H$5:H$1021, MATCH(8, 'Detalles movimientos'!$W$5:$W$1021, 0)), "") | H17: =IFERROR(INDEX('Detalles movimientos'!I$5:I$1021, MATCH(8, 'Detalles movimientos'!$W$5:$W$1021, 0)), "") | I17: =IFERROR(INDEX('Detalles movimientos'!M$5:M$1021, MATCH(8, 'Detalles movimientos'!$W$5:$W$1021, 0)), "") | J17: =IFERROR(INDEX('Detalles movimientos'!N$5:N$1021, MATCH(8, 'Detalles movimientos'!$W$5:$W$1021, 0)), "") | K17: =IFERROR(INDEX('Detalles movimientos'!O$5:O$1021, MATCH(8, 'Detalles movimientos'!$W$5:$W$1021, 0)), "") | L17: =IFERROR(INDEX('Detalles movimientos'!P$5:P$1021, MATCH(8, 'Detalles movimientos'!$W$5:$W$1021, 0)), "") | M17: =IFERROR(INDEX('Detalles movimientos'!S$5:S$1021, MATCH(8, 'Detalles movimientos'!$W$5:$W$1021, 0)), "")
B18: =IFERROR(INDEX('Detalles movimientos'!C$5:C$1021, MATCH(9, 'Detalles movimientos'!$W$5:$W$1021, 0)), "") | C18: =IFERROR(INDEX('Detalles movimientos'!D$5:D$1021, MATCH(9, 'Detalles movimientos'!$W$5:$W$1021, 0)), "") | D18: =IFERROR(INDEX('Detalles movimientos'!E$5:E$1021, MATCH(9, 'Detalles movimientos'!$W$5:$W$1021, 0)), "") | E18: =IFERROR(INDEX('Detalles movimientos'!F$5:F$1021, MATCH(9, 'Detalles movimientos'!$W$5:$W$1021, 0)), "") | F18: =IFERROR(INDEX('Detalles movimientos'!G$5:G$1021, MATCH(9, 'Detalles movimientos'!$W$5:$W$1021, 0)), "") | G18: =IFERROR(INDEX('Detalles movimientos'!H$5:H$1021, MATCH(9, 'Detalles movimientos'!$W$5:$W$1021, 0)), "") | H18: =IFERROR(INDEX('Detalles movimientos'!I$5:I$1021, MATCH(9, 'Detalles movimientos'!$W$5:$W$1021, 0)), "") | I18: =IFERROR(INDEX('Detalles movimientos'!M$5:M$1021, MATCH(9, 'Detalles movimientos'!$W$5:$W$1021, 0)), "") | J18: =IFERROR(INDEX('Detalles movimientos'!N$5:N$1021, MATCH(9, 'Detalles movimientos'!$W$5:$W$1021, 0)), "") | K18: =IFERROR(INDEX('Detalles movimientos'!O$5:O$1021, MATCH(9, 'Detalles movimientos'!$W$5:$W$1021, 0)), "") | L18: =IFERROR(INDEX('Detalles movimientos'!P$5:P$1021, MATCH(9, 'Detalles movimientos'!$W$5:$W$1021, 0)), "") | M18: =IFERROR(INDEX('Detalles movimientos'!S$5:S$1021, MATCH(9, 'Detalles movimientos'!$W$5:$W$1021, 0)), "")
B19: =IFERROR(INDEX('Detalles movimientos'!C$5:C$1021, MATCH(10, 'Detalles movimientos'!$W$5:$W$1021, 0)), "") | C19: =IFERROR(INDEX('Detalles movimientos'!D$5:D$1021, MATCH(10, 'Detalles movimientos'!$W$5:$W$1021, 0)), "") | D19: =IFERROR(INDEX('Detalles movimientos'!E$5:E$1021, MATCH(10, 'Detalles movimientos'!$W$5:$W$1021, 0)), "") | E19: =IFERROR(INDEX('Detalles movimientos'!F$5:F$1021, MATCH(10, 'Detalles movimientos'!$W$5:$W$1021, 0)), "") | F19: =IFERROR(INDEX('Detalles movimientos'!G$5:G$1021, MATCH(10, 'Detalles movimientos'!$W$5:$W$1021, 0)), "") | G19: =IFERROR(INDEX('Detalles movimientos'!H$5:H$1021, MATCH(10, 'Detalles movimientos'!$W$5:$W$1021, 0)), "") | H19: =IFERROR(INDEX('Detalles movimientos'!I$5:I$1021, MATCH(10, 'Detalles movimientos'!$W$5:$W$1021, 0)), "") | I19: =IFERROR(INDEX('Detalles movimientos'!M$5:M$1021, MATCH(10, 'Detalles movimientos'!$W$5:$W$1021, 0)), "") | J19: =IFERROR(INDEX('Detalles movimientos'!N$5:N$1021, MATCH(10, 'Detalles movimientos'!$W$5:$W$1021, 0)), "") | K19: =IFERROR(INDEX('Detalles movimientos'!O$5:O$1021, MATCH(10, 'Detalles movimientos'!$W$5:$W$1021, 0)), "") | L19: =IFERROR(INDEX('Detalles movimientos'!P$5:P$1021, MATCH(10, 'Detalles movimientos'!$W$5:$W$1021, 0)), "") | M19: =IFERROR(INDEX('Detalles movimientos'!S$5:S$1021, MATCH(10, 'Detalles movimientos'!$W$5:$W$1021, 0)), "")
B20: =IFERROR(INDEX('Detalles movimientos'!C$5:C$1021, MATCH(11, 'Detalles movimientos'!$W$5:$W$1021, 0)), "") | C20: =IFERROR(INDEX('Detalles movimientos'!D$5:D$1021, MATCH(11, 'Detalles movimientos'!$W$5:$W$1021, 0)), "") | D20: =IFERROR(INDEX('Detalles movimientos'!E$5:E$1021, MATCH(11, 'Detalles movimientos'!$W$5:$W$1021, 0)), "") | E20: =IFERROR(INDEX('Detalles movimientos'!F$5:F$1021, MATCH(11, 'Detalles movimientos'!$W$5:$W$1021, 0)), "") | F20: =IFERROR(INDEX('Detalles movimientos'!G$5:G$1021, MATCH(11, 'Detalles movimientos'!$W$5:$W$1021, 0)), "") | G20: =IFERROR(INDEX('Detalles movimientos'!H$5:H$1021, MATCH(11, 'Detalles movimientos'!$W$5:$W$1021, 0)), "") | H20: =IFERROR(INDEX('Detalles movimientos'!I$5:I$1021, MATCH(11, 'Detalles movimientos'!$W$5:$W$1021, 0)), "") | I20: =IFERROR(INDEX('Detalles movimientos'!M$5:M$1021, MATCH(11, 'Detalles movimientos'!$W$5:$W$1021, 0)), "") | J20: =IFERROR(INDEX('Detalles movimientos'!N$5:N$1021, MATCH(11, 'Detalles movimientos'!$W$5:$W$1021, 0)), "") | K20: =IFERROR(INDEX('Detalles movimientos'!O$5:O$1021, MATCH(11, 'Detalles movimientos'!$W$5:$W$1021, 0)), "") | L20: =IFERROR(INDEX('Detalles movimientos'!P$5:P$1021, MATCH(11, 'Detalles movimientos'!$W$5:$W$1021, 0)), "") | M20: =IFERROR(INDEX('Detalles movimientos'!S$5:S$1021, MATCH(11, 'Detalles movimientos'!$W$5:$W$1021, 0)), "")
B21: =IFERROR(INDEX('Detalles movimientos'!C$5:C$1021, MATCH(12, 'Detalles movimientos'!$W$5:$W$1021, 0)), "") | C21: =IFERROR(INDEX('Detalles movimientos'!D$5:D$1021, MATCH(12, 'Detalles movimientos'!$W$5:$W$1021, 0)), "") | D21: =IFERROR(INDEX('Detalles movimientos'!E$5:E$1021, MATCH(12, 'Detalles movimientos'!$W$5:$W$1021, 0)), "") | E21: =IFERROR(INDEX('Detalles movimientos'!F$5:F$1021, MATCH(12, 'Detalles movimientos'!$W$5:$W$1021, 0)), "") | F21: =IFERROR(INDEX('Detalles movimientos'!G$5:G$1021, MATCH(12, 'Detalles movimientos'!$W$5:$W$1021, 0)), "") | G21: =IFERROR(INDEX('Detalles movimientos'!H$5:H$1021, MATCH(12, 'Detalles movimientos'!$W$5:$W$1021, 0)), "") | H21: =IFERROR(INDEX('Detalles movimientos'!I$5:I$1021, MATCH(12, 'Detalles movimientos'!$W$5:$W$1021, 0)), "") | I21: =IFERROR(INDEX('Detalles movimientos'!M$5:M$1021, MATCH(12, 'Detalles movimientos'!$W$5:$W$1021, 0)), "") | J21: =IFERROR(INDEX('Detalles movimientos'!N$5:N$1021, MATCH(12, 'Detalles movimientos'!$W$5:$W$1021, 0)), "") | K21: =IFERROR(INDEX('Detalles movimientos'!O$5:O$1021, MATCH(12, 'Detalles movimientos'!$W$5:$W$1021, 0)), "") | L21: =IFERROR(INDEX('Detalles movimientos'!P$5:P$1021, MATCH(12, 'Detalles movimientos'!$W$5:$W$1021, 0)), "") | M21: =IFERROR(INDEX('Detalles movimientos'!S$5:S$1021, MATCH(12, 'Detalles movimientos'!$W$5:$W$1021, 0)), "")
B22: =IFERROR(INDEX('Detalles movimientos'!C$5:C$1021, MATCH(13, 'Detalles movimientos'!$W$5:$W$1021, 0)), "") | C22: =IFERROR(INDEX('Detalles movimientos'!D$5:D$1021, MATCH(13, 'Detalles movimientos'!$W$5:$W$1021, 0)), "") | D22: =IFERROR(INDEX('Detalles movimientos'!E$5:E$1021, MATCH(13, 'Detalles movimientos'!$W$5:$W$1021, 0)), "") | E22: =IFERROR(INDEX('Detalles movimientos'!F$5:F$1021, MATCH(13, 'Detalles movimientos'!$W$5:$W$1021, 0)), "") | F22: =IFERROR(INDEX('Detalles movimientos'!G$5:G$1021, MATCH(13, 'Detalles movimientos'!$W$5:$W$1021, 0)), "") | G22: =IFERROR(INDEX('Detalles movimientos'!H$5:H$1021, MATCH(13, 'Detalles movimientos'!$W$5:$W$1021, 0)), "") | H22: =IFERROR(INDEX('Detalles movimientos'!I$5:I$1021, MATCH(13, 'Detalles movimientos'!$W$5:$W$1021, 0)), "") | I22: =IFERROR(INDEX('Detalles movimientos'!M$5:M$1021, MATCH(13, 'Detalles movimientos'!$W$5:$W$1021, 0)), "") | J22: =IFERROR(INDEX('Detalles movimientos'!N$5:N$1021, MATCH(13, 'Detalles movimientos'!$W$5:$W$1021, 0)), "") | K22: =IFERROR(INDEX('Detalles movimientos'!O$5:O$1021, MATCH(13, 'Detalles movimientos'!$W$5:$W$1021, 0)), "") | L22: =IFERROR(INDEX('Detalles movimientos'!P$5:P$1021, MATCH(13, 'Detalles movimientos'!$W$5:$W$1021, 0)), "") | M22: =IFERROR(INDEX('Detalles movimientos'!S$5:S$1021, MATCH(13, 'Detalles movimientos'!$W$5:$W$1021, 0)), "")
B23: =IFERROR(INDEX('Detalles movimientos'!C$5:C$1021, MATCH(14, 'Detalles movimientos'!$W$5:$W$1021, 0)), "") | C23: =IFERROR(INDEX('Detalles movimientos'!D$5:D$1021, MATCH(14, 'Detalles movimientos'!$W$5:$W$1021, 0)), "") | D23: =IFERROR(INDEX('Detalles movimientos'!E$5:E$1021, MATCH(14, 'Detalles movimientos'!$W$5:$W$1021, 0)), "") | E23: =IFERROR(INDEX('Detalles movimientos'!F$5:F$1021, MATCH(14, 'Detalles movimientos'!$W$5:$W$1021, 0)), "") | F23: =IFERROR(INDEX('Detalles movimientos'!G$5:G$1021, MATCH(14, 'Detalles movimientos'!$W$5:$W$1021, 0)), "") | G23: =IFERROR(INDEX('Detalles movimientos'!H$5:H$1021, MATCH(14, 'Detalles movimientos'!$W$5:$W$1021, 0)), "") | H23: =IFERROR(INDEX('Detalles movimientos'!I$5:I$1021, MATCH(14, 'Detalles movimientos'!$W$5:$W$1021, 0)), "") | I23: =IFERROR(INDEX('Detalles movimientos'!M$5:M$1021, MATCH(14, 'Detalles movimientos'!$W$5:$W$1021, 0)), "") | J23: =IFERROR(INDEX('Detalles movimientos'!N$5:N$1021, MATCH(14, 'Detalles movimientos'!$W$5:$W$1021, 0)), "") | K23: =IFERROR(INDEX('Detalles movimientos'!O$5:O$1021, MATCH(14, 'Detalles movimientos'!$W$5:$W$1021, 0)), "") | L23: =IFERROR(INDEX('Detalles movimientos'!P$5:P$1021, MATCH(14, 'Detalles movimientos'!$W$5:$W$1021, 0)), "") | M23: =IFERROR(INDEX('Detalles movimientos'!S$5:S$1021, MATCH(14, 'Detalles movimientos'!$W$5:$W$1021, 0)), "")
B24: =IFERROR(INDEX('Detalles movimientos'!C$5:C$1021, MATCH(15, 'Detalles movimientos'!$W$5:$W$1021, 0)), "") | C24: =IFERROR(INDEX('Detalles movimientos'!D$5:D$1021, MATCH(15, 'Detalles movimientos'!$W$5:$W$1021, 0)), "") | D24: =IFERROR(INDEX('Detalles movimientos'!E$5:E$1021, MATCH(15, 'Detalles movimientos'!$W$5:$W$1021, 0)), "") | E24: =IFERROR(INDEX('Detalles movimientos'!F$5:F$1021, MATCH(15, 'Detalles movimientos'!$W$5:$W$1021, 0)), "") | F24: =IFERROR(INDEX('Detalles movimientos'!G$5:G$1021, MATCH(15, 'Detalles movimientos'!$W$5:$W$1021, 0)), "") | G24: =IFERROR(INDEX('Detalles movimientos'!H$5:H$1021, MATCH(15, 'Detalles movimientos'!$W$5:$W$1021, 0)), "") | H24: =IFERROR(INDEX('Detalles movimientos'!I$5:I$1021, MATCH(15, 'Detalles movimientos'!$W$5:$W$1021, 0)), "") | I24: =IFERROR(INDEX('Detalles movimientos'!M$5:M$1021, MATCH(15, 'Detalles movimientos'!$W$5:$W$1021, 0)), "") | J24: =IFERROR(INDEX('Detalles movimientos'!N$5:N$1021, MATCH(15, 'Detalles movimientos'!$W$5:$W$1021, 0)), "") | K24: =IFERROR(INDEX('Detalles movimientos'!O$5:O$1021, MATCH(15, 'Detalles movimientos'!$W$5:$W$1021, 0)), "") | L24: =IFERROR(INDEX('Detalles movimientos'!P$5:P$1021, MATCH(15, 'Detalles movimientos'!$W$5:$W$1021, 0)), "") | M24: =IFERROR(INDEX('Detalles movimientos'!S$5:S$1021, MATCH(15, 'Detalles movimientos'!$W$5:$W$1021, 0)), "")
B25: =IFERROR(INDEX('Detalles movimientos'!C$5:C$1021, MATCH(16, 'Detalles movimientos'!$W$5:$W$1021, 0)), "") | C25: =IFERROR(INDEX('Detalles movimientos'!D$5:D$1021, MATCH(16, 'Detalles movimientos'!$W$5:$W$1021, 0)), "") | D25: =IFERROR(INDEX('Detalles movimientos'!E$5:E$1021, MATCH(16, 'Detalles movimientos'!$W$5:$W$1021, 0)), "") | E25: =IFERROR(INDEX('Detalles movimientos'!F$5:F$1021, MATCH(16, 'Detalles movimientos'!$W$5:$W$1021, 0)), "") | F25: =IFERROR(INDEX('Detalles movimientos'!G$5:G$1021, MATCH(16, 'Detalles movimientos'!$W$5:$W$1021, 0)), "") | G25: =IFERROR(INDEX('Detalles movimientos'!H$5:H$1021, MATCH(16, 'Detalles movimientos'!$W$5:$W$1021, 0)), "") | H25: =IFERROR(INDEX('Detalles movimientos'!I$5:I$1021, MATCH(16, 'Detalles movimientos'!$W$5:$W$1021, 0)), "") | I25: =IFERROR(INDEX('Detalles movimientos'!M$5:M$1021, MATCH(16, 'Detalles movimientos'!$W$5:$W$1021, 0)), "") | J25: =IFERROR(INDEX('Detalles movimientos'!N$5:N$1021, MATCH(16, 'Detalles movimientos'!$W$5:$W$1021, 0)), "") | K25: =IFERROR(INDEX('Detalles movimientos'!O$5:O$1021, MATCH(16, 'Detalles movimientos'!$W$5:$W$1021, 0)), "") | L25: =IFERROR(INDEX('Detalles movimientos'!P$5:P$1021, MATCH(16, 'Detalles movimientos'!$W$5:$W$1021, 0)), "") | M25: =IFERROR(INDEX('Detalles movimientos'!S$5:S$1021, MATCH(16, 'Detalles movimientos'!$W$5:$W$1021, 0)), "")
B26: =IFERROR(INDEX('Detalles movimientos'!C$5:C$1021, MATCH(17, 'Detalles movimientos'!$W$5:$W$1021, 0)), "") | C26: =IFERROR(INDEX('Detalles movimientos'!D$5:D$1021, MATCH(17, 'Detalles movimientos'!$W$5:$W$1021, 0)), "") | D26: =IFERROR(INDEX('Detalles movimientos'!E$5:E$1021, MATCH(17, 'Detalles movimientos'!$W$5:$W$1021, 0)), "") | E26: =IFERROR(INDEX('Detalles movimientos'!F$5:F$1021, MATCH(17, 'Detalles movimientos'!$W$5:$W$1021, 0)), "") | F26: =IFERROR(INDEX('Detalles movimientos'!G$5:G$1021, MATCH(17, 'Detalles movimientos'!$W$5:$W$1021, 0)), "") | G26: =IFERROR(INDEX('Detalles movimientos'!H$5:H$1021, MATCH(17, 'Detalles movimientos'!$W$5:$W$1021, 0)), "") | H26: =IFERROR(INDEX('Detalles movimientos'!I$5:I$1021, MATCH(17, 'Detalles movimientos'!$W$5:$W$1021, 0)), "") | I26: =IFERROR(INDEX('Detalles movimientos'!M$5:M$1021, MATCH(17, 'Detalles movimientos'!$W$5:$W$1021, 0)), "") | J26: =IFERROR(INDEX('Detalles movimientos'!N$5:N$1021, MATCH(17, 'Detalles movimientos'!$W$5:$W$1021, 0)), "") | K26: =IFERROR(INDEX('Detalles movimientos'!O$5:O$1021, MATCH(17, 'Detalles movimientos'!$W$5:$W$1021, 0)), "") | L26: =IFERROR(INDEX('Detalles movimientos'!P$5:P$1021, MATCH(17, 'Detalles movimientos'!$W$5:$W$1021, 0)), "") | M26: =IFERROR(INDEX('Detalles movimientos'!S$5:S$1021, MATCH(17, 'Detalles movimientos'!$W$5:$W$1021, 0)), "")
B27: =IFERROR(INDEX('Detalles movimientos'!C$5:C$1021, MATCH(18, 'Detalles movimientos'!$W$5:$W$1021, 0)), "") | C27: =IFERROR(INDEX('Detalles movimientos'!D$5:D$1021, MATCH(18, 'Detalles movimientos'!$W$5:$W$1021, 0)), "") | D27: =IFERROR(INDEX('Detalles movimientos'!E$5:E$1021, MATCH(18, 'Detalles movimientos'!$W$5:$W$1021, 0)), "") | E27: =IFERROR(INDEX('Detalles movimientos'!F$5:F$1021, MATCH(18, 'Detalles movimientos'!$W$5:$W$1021, 0)), "") | F27: =IFERROR(INDEX('Detalles movimientos'!G$5:G$1021, MATCH(18, 'Detalles movimientos'!$W$5:$W$1021, 0)), "") | G27: =IFERROR(INDEX('Detalles movimientos'!H$5:H$1021, MATCH(18, 'Detalles movimientos'!$W$5:$W$1021, 0)), "") | H27: =IFERROR(INDEX('Detalles movimientos'!I$5:I$1021, MATCH(18, 'Detalles movimientos'!$W$5:$W$1021, 0)), "") | I27: =IFERROR(INDEX('Detalles movimientos'!M$5:M$1021, MATCH(18, 'Detalles movimientos'!$W$5:$W$1021, 0)), "") | J27: =IFERROR(INDEX('Detalles movimientos'!N$5:N$1021, MATCH(18, 'Detalles movimientos'!$W$5:$W$1021, 0)), "") | K27: =IFERROR(INDEX('Detalles movimientos'!O$5:O$1021, MATCH(18, 'Detalles movimientos'!$W$5:$W$1021, 0)), "") | L27: =IFERROR(INDEX('Detalles movimientos'!P$5:P$1021, MATCH(18, 'Detalles movimientos'!$W$5:$W$1021, 0)), "") | M27: =IFERROR(INDEX('Detalles movimientos'!S$5:S$1021, MATCH(18, 'Detalles movimientos'!$W$5:$W$1021, 0)), "")
B28: =IFERROR(INDEX('Detalles movimientos'!C$5:C$1021, MATCH(19, 'Detalles movimientos'!$W$5:$W$1021, 0)), "") | C28: =IFERROR(INDEX('Detalles movimientos'!D$5:D$1021, MATCH(19, 'Detalles movimientos'!$W$5:$W$1021, 0)), "") | D28: =IFERROR(INDEX('Detalles movimientos'!E$5:E$1021, MATCH(19, 'Detalles movimientos'!$W$5:$W$1021, 0)), "") | E28: =IFERROR(INDEX('Detalles movimientos'!F$5:F$1021, MATCH(19, 'Detalles movimientos'!$W$5:$W$1021, 0)), "") | F28: =IFERROR(INDEX('Detalles movimientos'!G$5:G$1021, MATCH(19, 'Detalles movimientos'!$W$5:$W$1021, 0)), "") | G28: =IFERROR(INDEX('Detalles movimientos'!H$5:H$1021, MATCH(19, 'Detalles movimientos'!$W$5:$W$1021, 0)), "") | H28: =IFERROR(INDEX('Detalles movimientos'!I$5:I$1021, MATCH(19, 'Detalles movimientos'!$W$5:$W$1021, 0)), "") | I28: =IFERROR(INDEX('Detalles movimientos'!M$5:M$1021, MATCH(19, 'Detalles movimientos'!$W$5:$W$1021, 0)), "") | J28: =IFERROR(INDEX('Detalles movimientos'!N$5:N$1021, MATCH(19, 'Detalles movimientos'!$W$5:$W$1021, 0)), "") | K28: =IFERROR(INDEX('Detalles movimientos'!O$5:O$1021, MATCH(19, 'Detalles movimientos'!$W$5:$W$1021, 0)), "") | L28: =IFERROR(INDEX('Detalles movimientos'!P$5:P$1021, MATCH(19, 'Detalles movimientos'!$W$5:$W$1021, 0)), "") | M28: =IFERROR(INDEX('Detalles movimientos'!S$5:S$1021, MATCH(19, 'Detalles movimientos'!$W$5:$W$1021, 0)), "")
B29: =IFERROR(INDEX('Detalles movimientos'!C$5:C$1021, MATCH(20, 'Detalles movimientos'!$W$5:$W$1021, 0)), "") | C29: =IFERROR(INDEX('Detalles movimientos'!D$5:D$1021, MATCH(20, 'Detalles movimientos'!$W$5:$W$1021, 0)), "") | D29: =IFERROR(INDEX('Detalles movimientos'!E$5:E$1021, MATCH(20, 'Detalles movimientos'!$W$5:$W$1021, 0)), "") | E29: =IFERROR(INDEX('Detalles movimientos'!F$5:F$1021, MATCH(20, 'Detalles movimientos'!$W$5:$W$1021, 0)), "") | F29: =IFERROR(INDEX('Detalles movimientos'!G$5:G$1021, MATCH(20, 'Detalles movimientos'!$W$5:$W$1021, 0)), "") | G29: =IFERROR(INDEX('Detalles movimientos'!H$5:H$1021, MATCH(20, 'Detalles movimientos'!$W$5:$W$1021, 0)), "") | H29: =IFERROR(INDEX('Detalles movimientos'!I$5:I$1021, MATCH(20, 'Detalles movimientos'!$W$5:$W$1021, 0)), "") | I29: =IFERROR(INDEX('Detalles movimientos'!M$5:M$1021, MATCH(20, 'Detalles movimientos'!$W$5:$W$1021, 0)), "") | J29: =IFERROR(INDEX('Detalles movimientos'!N$5:N$1021, MATCH(20, 'Detalles movimientos'!$W$5:$W$1021, 0)), "") | K29: =IFERROR(INDEX('Detalles movimientos'!O$5:O$1021, MATCH(20, 'Detalles movimientos'!$W$5:$W$1021, 0)), "") | L29: =IFERROR(INDEX('Detalles movimientos'!P$5:P$1021, MATCH(20, 'Detalles movimientos'!$W$5:$W$1021, 0)), "") | M29: =IFERROR(INDEX('Detalles movimientos'!S$5:S$1021, MATCH(20, 'Detalles movimientos'!$W$5:$W$1021, 0)), "")
B30: =IFERROR(INDEX('Detalles movimientos'!C$5:C$1021, MATCH(21, 'Detalles movimientos'!$W$5:$W$1021, 0)), "") | C30: =IFERROR(INDEX('Detalles movimientos'!D$5:D$1021, MATCH(21, 'Detalles movimientos'!$W$5:$W$1021, 0)), "") | D30: =IFERROR(INDEX('Detalles movimientos'!E$5:E$1021, MATCH(21, 'Detalles movimientos'!$W$5:$W$1021, 0)), "") | E30: =IFERROR(INDEX('Detalles movimientos'!F$5:F$1021, MATCH(21, 'Detalles movimientos'!$W$5:$W$1021, 0)), "") | F30: =IFERROR(INDEX('Detalles movimientos'!G$5:G$1021, MATCH(21, 'Detalles movimientos'!$W$5:$W$1021, 0)), "") | G30: =IFERROR(INDEX('Detalles movimientos'!H$5:H$1021, MATCH(21, 'Detalles movimientos'!$W$5:$W$1021, 0)), "") | H30: =IFERROR(INDEX('Detalles movimientos'!I$5:I$1021, MATCH(21, 'Detalles movimientos'!$W$5:$W$1021, 0)), "") | I30: =IFERROR(INDEX('Detalles movimientos'!M$5:M$1021, MATCH(21, 'Detalles movimientos'!$W$5:$W$1021, 0)), "") | J30: =IFERROR(INDEX('Detalles movimientos'!N$5:N$1021, MATCH(21, 'Detalles movimientos'!$W$5:$W$1021, 0)), "") | K30: =IFERROR(INDEX('Detalles movimientos'!O$5:O$1021, MATCH(21, 'Detalles movimientos'!$W$5:$W$1021, 0)), "") | L30: =IFERROR(INDEX('Detalles movimientos'!P$5:P$1021, MATCH(21, 'Detalles movimientos'!$W$5:$W$1021, 0)), "") | M30: =IFERROR(INDEX('Detalles movimientos'!S$5:S$1021, MATCH(21, 'Detalles movimientos'!$W$5:$W$1021, 0)), "")
B31: =IFERROR(INDEX('Detalles movimientos'!C$5:C$1021, MATCH(22, 'Detalles movimientos'!$W$5:$W$1021, 0)), "") | C31: =IFERROR(INDEX('Detalles movimientos'!D$5:D$1021, MATCH(22, 'Detalles movimientos'!$W$5:$W$1021, 0)), "") | D31: =IFERROR(INDEX('Detalles movimientos'!E$5:E$1021, MATCH(22, 'Detalles movimientos'!$W$5:$W$1021, 0)), "") | E31: =IFERROR(INDEX('Detalles movimientos'!F$5:F$1021, MATCH(22, 'Detalles movimientos'!$W$5:$W$1021, 0)), "") | F31: =IFERROR(INDEX('Detalles movimientos'!G$5:G$1021, MATCH(22, 'Detalles movimientos'!$W$5:$W$1021, 0)), "") | G31: =IFERROR(INDEX('Detalles movimientos'!H$5:H$1021, MATCH(22, 'Detalles movimientos'!$W$5:$W$1021, 0)), "") | H31: =IFERROR(INDEX('Detalles movimientos'!I$5:I$1021, MATCH(22, 'Detalles movimientos'!$W$5:$W$1021, 0)), "") | I31: =IFERROR(INDEX('Detalles movimientos'!M$5:M$1021, MATCH(22, 'Detalles movimientos'!$W$5:$W$1021, 0)), "") | J31: =IFERROR(INDEX('Detalles movimientos'!N$5:N$1021, MATCH(22, 'Detalles movimientos'!$W$5:$W$1021, 0)), "") | K31: =IFERROR(INDEX('Detalles movimientos'!O$5:O$1021, MATCH(22, 'Detalles movimientos'!$W$5:$W$1021, 0)), "") | L31: =IFERROR(INDEX('Detalles movimientos'!P$5:P$1021, MATCH(22, 'Detalles movimientos'!$W$5:$W$1021, 0)), "") | M31: =IFERROR(INDEX('Detalles movimientos'!S$5:S$1021, MATCH(22, 'Detalles movimientos'!$W$5:$W$1021, 0)), "")
B32: =IFERROR(INDEX('Detalles movimientos'!C$5:C$1021, MATCH(23, 'Detalles movimientos'!$W$5:$W$1021, 0)), "") | C32: =IFERROR(INDEX('Detalles movimientos'!D$5:D$1021, MATCH(23, 'Detalles movimientos'!$W$5:$W$1021, 0)), "") | D32: =IFERROR(INDEX('Detalles movimientos'!E$5:E$1021, MATCH(23, 'Detalles movimientos'!$W$5:$W$1021, 0)), "") | E32: =IFERROR(INDEX('Detalles movimientos'!F$5:F$1021, MATCH(23, 'Detalles movimientos'!$W$5:$W$1021, 0)), "") | F32: =IFERROR(INDEX('Detalles movimientos'!G$5:G$1021, MATCH(23, 'Detalles movimientos'!$W$5:$W$1021, 0)), "") | G32: =IFERROR(INDEX('Detalles movimientos'!H$5:H$1021, MATCH(23, 'Detalles movimientos'!$W$5:$W$1021, 0)), "") | H32: =IFERROR(INDEX('Detalles movimientos'!I$5:I$1021, MATCH(23, 'Detalles movimientos'!$W$5:$W$1021, 0)), "") | I32: =IFERROR(INDEX('Detalles movimientos'!M$5:M$1021, MATCH(23, 'Detalles movimientos'!$W$5:$W$1021, 0)), "") | J32: =IFERROR(INDEX('Detalles movimientos'!N$5:N$1021, MATCH(23, 'Detalles movimientos'!$W$5:$W$1021, 0)), "") | K32: =IFERROR(INDEX('Detalles movimientos'!O$5:O$1021, MATCH(23, 'Detalles movimientos'!$W$5:$W$1021, 0)), "") | L32: =IFERROR(INDEX('Detalles movimientos'!P$5:P$1021, MATCH(23, 'Detalles movimientos'!$W$5:$W$1021, 0)), "") | M32: =IFERROR(INDEX('Detalles movimientos'!S$5:S$1021, MATCH(23, 'Detalles movimientos'!$W$5:$W$1021, 0)), "")
B33: =IFERROR(INDEX('Detalles movimientos'!C$5:C$1021, MATCH(24, 'Detalles movimientos'!$W$5:$W$1021, 0)), "") | C33: =IFERROR(INDEX('Detalles movimientos'!D$5:D$1021, MATCH(24, 'Detalles movimientos'!$W$5:$W$1021, 0)), "") | D33: =IFERROR(INDEX('Detalles movimientos'!E$5:E$1021, MATCH(24, 'Detalles movimientos'!$W$5:$W$1021, 0)), "") | E33: =IFERROR(INDEX('Detalles movimientos'!F$5:F$1021, MATCH(24, 'Detalles movimientos'!$W$5:$W$1021, 0)), "") | F33: =IFERROR(INDEX('Detalles movimientos'!G$5:G$1021, MATCH(24, 'Detalles movimientos'!$W$5:$W$1021, 0)), "") | G33: =IFERROR(INDEX('Detalles movimientos'!H$5:H$1021, MATCH(24, 'Detalles movimientos'!$W$5:$W$1021, 0)), "") | H33: =IFERROR(INDEX('Detalles movimientos'!I$5:I$1021, MATCH(24, 'Detalles movimientos'!$W$5:$W$1021, 0)), "") | I33: =IFERROR(INDEX('Detalles movimientos'!M$5:M$1021, MATCH(24, 'Detalles movimientos'!$W$5:$W$1021, 0)), "") | J33: =IFERROR(INDEX('Detalles movimientos'!N$5:N$1021, MATCH(24, 'Detalles movimientos'!$W$5:$W$1021, 0)), "") | K33: =IFERROR(INDEX('Detalles movimientos'!O$5:O$1021, MATCH(24, 'Detalles movimientos'!$W$5:$W$1021, 0)), "") | L33: =IFERROR(INDEX('Detalles movimientos'!P$5:P$1021, MATCH(24, 'Detalles movimientos'!$W$5:$W$1021, 0)), "") | M33: =IFERROR(INDEX('Detalles movimientos'!S$5:S$1021, MATCH(24, 'Detalles movimientos'!$W$5:$W$1021, 0)), "")
B34: =IFERROR(INDEX('Detalles movimientos'!C$5:C$1021, MATCH(25, 'Detalles movimientos'!$W$5:$W$1021, 0)), "") | C34: =IFERROR(INDEX('Detalles movimientos'!D$5:D$1021, MATCH(25, 'Detalles movimientos'!$W$5:$W$1021, 0)), "") | D34: =IFERROR(INDEX('Detalles movimientos'!E$5:E$1021, MATCH(25, 'Detalles movimientos'!$W$5:$W$1021, 0)), "") | E34: =IFERROR(INDEX('Detalles movimientos'!F$5:F$1021, MATCH(25, 'Detalles movimientos'!$W$5:$W$1021, 0)), "") | F34: =IFERROR(INDEX('Detalles movimientos'!G$5:G$1021, MATCH(25, 'Detalles movimientos'!$W$5:$W$1021, 0)), "") | G34: =IFERROR(INDEX('Detalles movimientos'!H$5:H$1021, MATCH(25, 'Detalles movimientos'!$W$5:$W$1021, 0)), "") | H34: =IFERROR(INDEX('Detalles movimientos'!I$5:I$1021, MATCH(25, 'Detalles movimientos'!$W$5:$W$1021, 0)), "") | I34: =IFERROR(INDEX('Detalles movimientos'!M$5:M$1021, MATCH(25, 'Detalles movimientos'!$W$5:$W$1021, 0)), "") | J34: =IFERROR(INDEX('Detalles movimientos'!N$5:N$1021, MATCH(25, 'Detalles movimientos'!$W$5:$W$1021, 0)), "") | K34: =IFERROR(INDEX('Detalles movimientos'!O$5:O$1021, MATCH(25, 'Detalles movimientos'!$W$5:$W$1021, 0)), "") | L34: =IFERROR(INDEX('Detalles movimientos'!P$5:P$1021, MATCH(25, 'Detalles movimientos'!$W$5:$W$1021, 0)), "") | M34: =IFERROR(INDEX('Detalles movimientos'!S$5:S$1021, MATCH(25, 'Detalles movimientos'!$W$5:$W$1021, 0)), "")
B35: =IFERROR(INDEX('Detalles movimientos'!C$5:C$1021, MATCH(26, 'Detalles movimientos'!$W$5:$W$1021, 0)), "") | C35: =IFERROR(INDEX('Detalles movimientos'!D$5:D$1021, MATCH(26, 'Detalles movimientos'!$W$5:$W$1021, 0)), "") | D35: =IFERROR(INDEX('Detalles movimientos'!E$5:E$1021, MATCH(26, 'Detalles movimientos'!$W$5:$W$1021, 0)), "") | E35: =IFERROR(INDEX('Detalles movimientos'!F$5:F$1021, MATCH(26, 'Detalles movimientos'!$W$5:$W$1021, 0)), "") | F35: =IFERROR(INDEX('Detalles movimientos'!G$5:G$1021, MATCH(26, 'Detalles movimientos'!$W$5:$W$1021, 0)), "") | G35: =IFERROR(INDEX('Detalles movimientos'!H$5:H$1021, MATCH(26, 'Detalles movimientos'!$W$5:$W$1021, 0)), "") | H35: =IFERROR(INDEX('Detalles movimientos'!I$5:I$1021, MATCH(26, 'Detalles movimientos'!$W$5:$W$1021, 0)), "") | I35: =IFERROR(INDEX('Detalles movimientos'!M$5:M$1021, MATCH(26, 'Detalles movimientos'!$W$5:$W$1021, 0)), "") | J35: =IFERROR(INDEX('Detalles movimientos'!N$5:N$1021, MATCH(26, 'Detalles movimientos'!$W$5:$W$1021, 0)), "") | K35: =IFERROR(INDEX('Detalles movimientos'!O$5:O$1021, MATCH(26, 'Detalles movimientos'!$W$5:$W$1021, 0)), "") | L35: =IFERROR(INDEX('Detalles movimientos'!P$5:P$1021, MATCH(26, 'Detalles movimientos'!$W$5:$W$1021, 0)), "") | M35: =IFERROR(INDEX('Detalles movimientos'!S$5:S$1021, MATCH(26, 'Detalles movimientos'!$W$5:$W$1021, 0)), "")
B36: =IFERROR(INDEX('Detalles movimientos'!C$5:C$1021, MATCH(27, 'Detalles movimientos'!$W$5:$W$1021, 0)), "") | C36: =IFERROR(INDEX('Detalles movimientos'!D$5:D$1021, MATCH(27, 'Detalles movimientos'!$W$5:$W$1021, 0)), "") | D36: =IFERROR(INDEX('Detalles movimientos'!E$5:E$1021, MATCH(27, 'Detalles movimientos'!$W$5:$W$1021, 0)), "") | E36: =IFERROR(INDEX('Detalles movimientos'!F$5:F$1021, MATCH(27, 'Detalles movimientos'!$W$5:$W$1021, 0)), "") | F36: =IFERROR(INDEX('Detalles movimientos'!G$5:G$1021, MATCH(27, 'Detalles movimientos'!$W$5:$W$1021, 0)), "") | G36: =IFERROR(INDEX('Detalles movimientos'!H$5:H$1021, MATCH(27, 'Detalles movimientos'!$W$5:$W$1021, 0)), "") | H36: =IFERROR(INDEX('Detalles movimientos'!I$5:I$1021, MATCH(27, 'Detalles movimientos'!$W$5:$W$1021, 0)), "") | I36: =IFERROR(INDEX('Detalles movimientos'!M$5:M$1021, MATCH(27, 'Detalles movimientos'!$W$5:$W$1021, 0)), "") | J36: =IFERROR(INDEX('Detalles movimientos'!N$5:N$1021, MATCH(27, 'Detalles movimientos'!$W$5:$W$1021, 0)), "") | K36: =IFERROR(INDEX('Detalles movimientos'!O$5:O$1021, MATCH(27, 'Detalles movimientos'!$W$5:$W$1021, 0)), "") | L36: =IFERROR(INDEX('Detalles movimientos'!P$5:P$1021, MATCH(27, 'Detalles movimientos'!$W$5:$W$1021, 0)), "") | M36: =IFERROR(INDEX('Detalles movimientos'!S$5:S$1021, MATCH(27, 'Detalles movimientos'!$W$5:$W$1021, 0)), "")
B37: =IFERROR(INDEX('Detalles movimientos'!C$5:C$1021, MATCH(28, 'Detalles movimientos'!$W$5:$W$1021, 0)), "") | C37: =IFERROR(INDEX('Detalles movimientos'!D$5:D$1021, MATCH(28, 'Detalles movimientos'!$W$5:$W$1021, 0)), "") | D37: =IFERROR(INDEX('Detalles movimientos'!E$5:E$1021, MATCH(28, 'Detalles movimientos'!$W$5:$W$1021, 0)), "") | E37: =IFERROR(INDEX('Detalles movimientos'!F$5:F$1021, MATCH(28, 'Detalles movimientos'!$W$5:$W$1021, 0)), "") | F37: =IFERROR(INDEX('Detalles movimientos'!G$5:G$1021, MATCH(28, 'Detalles movimientos'!$W$5:$W$1021, 0)), "") | G37: =IFERROR(INDEX('Detalles movimientos'!H$5:H$1021, MATCH(28, 'Detalles movimientos'!$W$5:$W$1021, 0)), "") | H37: =IFERROR(INDEX('Detalles movimientos'!I$5:I$1021, MATCH(28, 'Detalles movimientos'!$W$5:$W$1021, 0)), "") | I37: =IFERROR(INDEX('Detalles movimientos'!M$5:M$1021, MATCH(28, 'Detalles movimientos'!$W$5:$W$1021, 0)), "") | J37: =IFERROR(INDEX('Detalles movimientos'!N$5:N$1021, MATCH(28, 'Detalles movimientos'!$W$5:$W$1021, 0)), "") | K37: =IFERROR(INDEX('Detalles movimientos'!O$5:O$1021, MATCH(28, 'Detalles movimientos'!$W$5:$W$1021, 0)), "") | L37: =IFERROR(INDEX('Detalles movimientos'!P$5:P$1021, MATCH(28, 'Detalles movimientos'!$W$5:$W$1021, 0)), "") | M37: =IFERROR(INDEX('Detalles movimientos'!S$5:S$1021, MATCH(28, 'Detalles movimientos'!$W$5:$W$1021, 0)), "")
B38: =IFERROR(INDEX('Detalles movimientos'!C$5:C$1021, MATCH(29, 'Detalles movimientos'!$W$5:$W$1021, 0)), "") | C38: =IFERROR(INDEX('Detalles movimientos'!D$5:D$1021, MATCH(29, 'Detalles movimientos'!$W$5:$W$1021, 0)), "") | D38: =IFERROR(INDEX('Detalles movimientos'!E$5:E$1021, MATCH(29, 'Detalles movimientos'!$W$5:$W$1021, 0)), "") | E38: =IFERROR(INDEX('Detalles movimientos'!F$5:F$1021, MATCH(29, 'Detalles movimientos'!$W$5:$W$1021, 0)), "") | F38: =IFERROR(INDEX('Detalles movimientos'!G$5:G$1021, MATCH(29, 'Detalles movimientos'!$W$5:$W$1021, 0)), "") | G38: =IFERROR(INDEX('Detalles movimientos'!H$5:H$1021, MATCH(29, 'Detalles movimientos'!$W$5:$W$1021, 0)), "") | H38: =IFERROR(INDEX('Detalles movimientos'!I$5:I$1021, MATCH(29, 'Detalles movimientos'!$W$5:$W$1021, 0)), "") | I38: =IFERROR(INDEX('Detalles movimientos'!M$5:M$1021, MATCH(29, 'Detalles movimientos'!$W$5:$W$1021, 0)), "") | J38: =IFERROR(INDEX('Detalles movimientos'!N$5:N$1021, MATCH(29, 'Detalles movimientos'!$W$5:$W$1021, 0)), "") | K38: =IFERROR(INDEX('Detalles movimientos'!O$5:O$1021, MATCH(29, 'Detalles movimientos'!$W$5:$W$1021, 0)), "") | L38: =IFERROR(INDEX('Detalles movimientos'!P$5:P$1021, MATCH(29, 'Detalles movimientos'!$W$5:$W$1021, 0)), "") | M38: =IFERROR(INDEX('Detalles movimientos'!S$5:S$1021, MATCH(29, 'Detalles movimientos'!$W$5:$W$1021, 0)), "")
B39: =IFERROR(INDEX('Detalles movimientos'!C$5:C$1021, MATCH(30, 'Detalles movimientos'!$W$5:$W$1021, 0)), "") | C39: =IFERROR(INDEX('Detalles movimientos'!D$5:D$1021, MATCH(30, 'Detalles movimientos'!$W$5:$W$1021, 0)), "") | D39: =IFERROR(INDEX('Detalles movimientos'!E$5:E$1021, MATCH(30, 'Detalles movimientos'!$W$5:$W$1021, 0)), "") | E39: =IFERROR(INDEX('Detalles movimientos'!F$5:F$1021, MATCH(30, 'Detalles movimientos'!$W$5:$W$1021, 0)), "") | F39: =IFERROR(INDEX('Detalles movimientos'!G$5:G$1021, MATCH(30, 'Detalles movimientos'!$W$5:$W$1021, 0)), "") | G39: =IFERROR(INDEX('Detalles movimientos'!H$5:H$1021, MATCH(30, 'Detalles movimientos'!$W$5:$W$1021, 0)), "") | H39: =IFERROR(INDEX('Detalles movimientos'!I$5:I$1021, MATCH(30, 'Detalles movimientos'!$W$5:$W$1021, 0)), "") | I39: =IFERROR(INDEX('Detalles movimientos'!M$5:M$1021, MATCH(30, 'Detalles movimientos'!$W$5:$W$1021, 0)), "") | J39: =IFERROR(INDEX('Detalles movimientos'!N$5:N$1021, MATCH(30, 'Detalles movimientos'!$W$5:$W$1021, 0)), "") | K39: =IFERROR(INDEX('Detalles movimientos'!O$5:O$1021, MATCH(30, 'Detalles movimientos'!$W$5:$W$1021, 0)), "") | L39: =IFERROR(INDEX('Detalles movimientos'!P$5:P$1021, MATCH(30, 'Detalles movimientos'!$W$5:$W$1021, 0)), "") | M39: =IFERROR(INDEX('Detalles movimientos'!S$5:S$1021, MATCH(30, 'Detalles movimientos'!$W$5:$W$1021, 0)), "")
B40: =IFERROR(INDEX('Detalles movimientos'!C$5:C$1021, MATCH(31, 'Detalles movimientos'!$W$5:$W$1021, 0)), "") | C40: =IFERROR(INDEX('Detalles movimientos'!D$5:D$1021, MATCH(31, 'Detalles movimientos'!$W$5:$W$1021, 0)), "") | D40: =IFERROR(INDEX('Detalles movimientos'!E$5:E$1021, MATCH(31, 'Detalles movimientos'!$W$5:$W$1021, 0)), "") | E40: =IFERROR(INDEX('Detalles movimientos'!F$5:F$1021, MATCH(31, 'Detalles movimientos'!$W$5:$W$1021, 0)), "") | F40: =IFERROR(INDEX('Detalles movimientos'!G$5:G$1021, MATCH(31, 'Detalles movimientos'!$W$5:$W$1021, 0)), "") | G40: =IFERROR(INDEX('Detalles movimientos'!H$5:H$1021, MATCH(31, 'Detalles movimientos'!$W$5:$W$1021, 0)), "") | H40: =IFERROR(INDEX('Detalles movimientos'!I$5:I$1021, MATCH(31, 'Detalles movimientos'!$W$5:$W$1021, 0)), "") | I40: =IFERROR(INDEX('Detalles movimientos'!M$5:M$1021, MATCH(31, 'Detalles movimientos'!$W$5:$W$1021, 0)), "") | J40: =IFERROR(INDEX('Detalles movimientos'!N$5:N$1021, MATCH(31, 'Detalles movimientos'!$W$5:$W$1021, 0)), "") | K40: =IFERROR(INDEX('Detalles movimientos'!O$5:O$1021, MATCH(31, 'Detalles movimientos'!$W$5:$W$1021, 0)), "") | L40: =IFERROR(INDEX('Detalles movimientos'!P$5:P$1021, MATCH(31, 'Detalles movimientos'!$W$5:$W$1021, 0)), "") | M40: =IFERROR(INDEX('Detalles movimientos'!S$5:S$1021, MATCH(31, 'Detalles movimientos'!$W$5:$W$1021, 0)), "")
B41: =IFERROR(INDEX('Detalles movimientos'!C$5:C$1021, MATCH(32, 'Detalles movimientos'!$W$5:$W$1021, 0)), "") | C41: =IFERROR(INDEX('Detalles movimientos'!D$5:D$1021, MATCH(32, 'Detalles movimientos'!$W$5:$W$1021, 0)), "") | D41: =IFERROR(INDEX('Detalles movimientos'!E$5:E$1021, MATCH(32, 'Detalles movimientos'!$W$5:$W$1021, 0)), "") | E41: =IFERROR(INDEX('Detalles movimientos'!F$5:F$1021, MATCH(32, 'Detalles movimientos'!$W$5:$W$1021, 0)), "") | F41: =IFERROR(INDEX('Detalles movimientos'!G$5:G$1021, MATCH(32, 'Detalles movimientos'!$W$5:$W$1021, 0)), "") | G41: =IFERROR(INDEX('Detalles movimientos'!H$5:H$1021, MATCH(32, 'Detalles movimientos'!$W$5:$W$1021, 0)), "") | H41: =IFERROR(INDEX('Detalles movimientos'!I$5:I$1021, MATCH(32, 'Detalles movimientos'!$W$5:$W$1021, 0)), "") | I41: =IFERROR(INDEX('Detalles movimientos'!M$5:M$1021, MATCH(32, 'Detalles movimientos'!$W$5:$W$1021, 0)), "") | J41: =IFERROR(INDEX('Detalles movimientos'!N$5:N$1021, MATCH(32, 'Detalles movimientos'!$W$5:$W$1021, 0)), "") | K41: =IFERROR(INDEX('Detalles movimientos'!O$5:O$1021, MATCH(32, 'Detalles movimientos'!$W$5:$W$1021, 0)), "") | L41: =IFERROR(INDEX('Detalles movimientos'!P$5:P$1021, MATCH(32, 'Detalles movimientos'!$W$5:$W$1021, 0)), "") | M41: =IFERROR(INDEX('Detalles movimientos'!S$5:S$1021, MATCH(32, 'Detalles movimientos'!$W$5:$W$1021, 0)), "")
B42: =IFERROR(INDEX('Detalles movimientos'!C$5:C$1021, MATCH(33, 'Detalles movimientos'!$W$5:$W$1021, 0)), "") | C42: =IFERROR(INDEX('Detalles movimientos'!D$5:D$1021, MATCH(33, 'Detalles movimientos'!$W$5:$W$1021, 0)), "") | D42: =IFERROR(INDEX('Detalles movimientos'!E$5:E$1021, MATCH(33, 'Detalles movimientos'!$W$5:$W$1021, 0)), "") | E42: =IFERROR(INDEX('Detalles movimientos'!F$5:F$1021, MATCH(33, 'Detalles movimientos'!$W$5:$W$1021, 0)), "") | F42: =IFERROR(INDEX('Detalles movimientos'!G$5:G$1021, MATCH(33, 'Detalles movimientos'!$W$5:$W$1021, 0)), "") | G42: =IFERROR(INDEX('Detalles movimientos'!H$5:H$1021, MATCH(33, 'Detalles movimientos'!$W$5:$W$1021, 0)), "") | H42: =IFERROR(INDEX('Detalles movimientos'!I$5:I$1021, MATCH(33, 'Detalles movimientos'!$W$5:$W$1021, 0)), "") | I42: =IFERROR(INDEX('Detalles movimientos'!M$5:M$1021, MATCH(33, 'Detalles movimientos'!$W$5:$W$1021, 0)), "") | J42: =IFERROR(INDEX('Detalles movimientos'!N$5:N$1021, MATCH(33, 'Detalles movimientos'!$W$5:$W$1021, 0)), "") | K42: =IFERROR(INDEX('Detalles movimientos'!O$5:O$1021, MATCH(33, 'Detalles movimientos'!$W$5:$W$1021, 0)), "") | L42: =IFERROR(INDEX('Detalles movimientos'!P$5:P$1021, MATCH(33, 'Detalles movimientos'!$W$5:$W$1021, 0)), "") | M42: =IFERROR(INDEX('Detalles movimientos'!S$5:S$1021, MATCH(33, 'Detalles movimientos'!$W$5:$W$1021, 0)), "")
B43: =IFERROR(INDEX('Detalles movimientos'!C$5:C$1021, MATCH(34, 'Detalles movimientos'!$W$5:$W$1021, 0)), "") | C43: =IFERROR(INDEX('Detalles movimientos'!D$5:D$1021, MATCH(34, 'Detalles movimientos'!$W$5:$W$1021, 0)), "") | D43: =IFERROR(INDEX('Detalles movimientos'!E$5:E$1021, MATCH(34, 'Detalles movimientos'!$W$5:$W$1021, 0)), "") | E43: =IFERROR(INDEX('Detalles movimientos'!F$5:F$1021, MATCH(34, 'Detalles movimientos'!$W$5:$W$1021, 0)), "") | F43: =IFERROR(INDEX('Detalles movimientos'!G$5:G$1021, MATCH(34, 'Detalles movimientos'!$W$5:$W$1021, 0)), "") | G43: =IFERROR(INDEX('Detalles movimientos'!H$5:H$1021, MATCH(34, 'Detalles movimientos'!$W$5:$W$1021, 0)), "") | H43: =IFERROR(INDEX('Detalles movimientos'!I$5:I$1021, MATCH(34, 'Detalles movimientos'!$W$5:$W$1021, 0)), "") | I43: =IFERROR(INDEX('Detalles movimientos'!M$5:M$1021, MATCH(34, 'Detalles movimientos'!$W$5:$W$1021, 0)), "") | J43: =IFERROR(INDEX('Detalles movimientos'!N$5:N$1021, MATCH(34, 'Detalles movimientos'!$W$5:$W$1021, 0)), "") | K43: =IFERROR(INDEX('Detalles movimientos'!O$5:O$1021, MATCH(34, 'Detalles movimientos'!$W$5:$W$1021, 0)), "") | L43: =IFERROR(INDEX('Detalles movimientos'!P$5:P$1021, MATCH(34, 'Detalles movimientos'!$W$5:$W$1021, 0)), "") | M43: =IFERROR(INDEX('Detalles movimientos'!S$5:S$1021, MATCH(34, 'Detalles movimientos'!$W$5:$W$1021, 0)), "")
B44: =IFERROR(INDEX('Detalles movimientos'!C$5:C$1021, MATCH(35, 'Detalles movimientos'!$W$5:$W$1021, 0)), "") | C44: =IFERROR(INDEX('Detalles movimientos'!D$5:D$1021, MATCH(35, 'Detalles movimientos'!$W$5:$W$1021, 0)), "") | D44: =IFERROR(INDEX('Detalles movimientos'!E$5:E$1021, MATCH(35, 'Detalles movimientos'!$W$5:$W$1021, 0)), "") | E44: =IFERROR(INDEX('Detalles movimientos'!F$5:F$1021, MATCH(35, 'Detalles movimientos'!$W$5:$W$1021, 0)), "") | F44: =IFERROR(INDEX('Detalles movimientos'!G$5:G$1021, MATCH(35, 'Detalles movimientos'!$W$5:$W$1021, 0)), "") | G44: =IFERROR(INDEX('Detalles movimientos'!H$5:H$1021, MATCH(35, 'Detalles movimientos'!$W$5:$W$1021, 0)), "") | H44: =IFERROR(INDEX('Detalles movimientos'!I$5:I$1021, MATCH(35, 'Detalles movimientos'!$W$5:$W$1021, 0)), "") | I44: =IFERROR(INDEX('Detalles movimientos'!M$5:M$1021, MATCH(35, 'Detalles movimientos'!$W$5:$W$1021, 0)), "") | J44: =IFERROR(INDEX('Detalles movimientos'!N$5:N$1021, MATCH(35, 'Detalles movimientos'!$W$5:$W$1021, 0)), "") | K44: =IFERROR(INDEX('Detalles movimientos'!O$5:O$1021, MATCH(35, 'Detalles movimientos'!$W$5:$W$1021, 0)), "") | L44: =IFERROR(INDEX('Detalles movimientos'!P$5:P$1021, MATCH(35, 'Detalles movimientos'!$W$5:$W$1021, 0)), "") | M44: =IFERROR(INDEX('Detalles movimientos'!S$5:S$1021, MATCH(35, 'Detalles movimientos'!$W$5:$W$1021, 0)), "")
B45: =IFERROR(INDEX('Detalles movimientos'!C$5:C$1021, MATCH(36, 'Detalles movimientos'!$W$5:$W$1021, 0)), "") | C45: =IFERROR(INDEX('Detalles movimientos'!D$5:D$1021, MATCH(36, 'Detalles movimientos'!$W$5:$W$1021, 0)), "") | D45: =IFERROR(INDEX('Detalles movimientos'!E$5:E$1021, MATCH(36, 'Detalles movimientos'!$W$5:$W$1021, 0)), "") | E45: =IFERROR(INDEX('Detalles movimientos'!F$5:F$1021, MATCH(36, 'Detalles movimientos'!$W$5:$W$1021, 0)), "") | F45: =IFERROR(INDEX('Detalles movimientos'!G$5:G$1021, MATCH(36, 'Detalles movimientos'!$W$5:$W$1021, 0)), "") | G45: =IFERROR(INDEX('Detalles movimientos'!H$5:H$1021, MATCH(36, 'Detalles movimientos'!$W$5:$W$1021, 0)), "") | H45: =IFERROR(INDEX('Detalles movimientos'!I$5:I$1021, MATCH(36, 'Detalles movimientos'!$W$5:$W$1021, 0)), "") | I45: =IFERROR(INDEX('Detalles movimientos'!M$5:M$1021, MATCH(36, 'Detalles movimientos'!$W$5:$W$1021, 0)), "") | J45: =IFERROR(INDEX('Detalles movimientos'!N$5:N$1021, MATCH(36, 'Detalles movimientos'!$W$5:$W$1021, 0)), "") | K45: =IFERROR(INDEX('Detalles movimientos'!O$5:O$1021, MATCH(36, 'Detalles movimientos'!$W$5:$W$1021, 0)), "") | L45: =IFERROR(INDEX('Detalles movimientos'!P$5:P$1021, MATCH(36, 'Detalles movimientos'!$W$5:$W$1021, 0)), "") | M45: =IFERROR(INDEX('Detalles movimientos'!S$5:S$1021, MATCH(36, 'Detalles movimientos'!$W$5:$W$1021, 0)), "")
B46: =IFERROR(INDEX('Detalles movimientos'!C$5:C$1021, MATCH(37, 'Detalles movimientos'!$W$5:$W$1021, 0)), "") | C46: =IFERROR(INDEX('Detalles movimientos'!D$5:D$1021, MATCH(37, 'Detalles movimientos'!$W$5:$W$1021, 0)), "") | D46: =IFERROR(INDEX('Detalles movimientos'!E$5:E$1021, MATCH(37, 'Detalles movimientos'!$W$5:$W$1021, 0)), "") | E46: =IFERROR(INDEX('Detalles movimientos'!F$5:F$1021, MATCH(37, 'Detalles movimientos'!$W$5:$W$1021, 0)), "") | F46: =IFERROR(INDEX('Detalles movimientos'!G$5:G$1021, MATCH(37, 'Detalles movimientos'!$W$5:$W$1021, 0)), "") | G46: =IFERROR(INDEX('Detalles movimientos'!H$5:H$1021, MATCH(37, 'Detalles movimientos'!$W$5:$W$1021, 0)), "") | H46: =IFERROR(INDEX('Detalles movimientos'!I$5:I$1021, MATCH(37, 'Detalles movimientos'!$W$5:$W$1021, 0)), "") | I46: =IFERROR(INDEX('Detalles movimientos'!M$5:M$1021, MATCH(37, 'Detalles movimientos'!$W$5:$W$1021, 0)), "") | J46: =IFERROR(INDEX('Detalles movimientos'!N$5:N$1021, MATCH(37, 'Detalles movimientos'!$W$5:$W$1021, 0)), "") | K46: =IFERROR(INDEX('Detalles movimientos'!O$5:O$1021, MATCH(37, 'Detalles movimientos'!$W$5:$W$1021, 0)), "") | L46: =IFERROR(INDEX('Detalles movimientos'!P$5:P$1021, MATCH(37, 'Detalles movimientos'!$W$5:$W$1021, 0)), "") | M46: =IFERROR(INDEX('Detalles movimientos'!S$5:S$1021, MATCH(37, 'Detalles movimientos'!$W$5:$W$1021, 0)), "")
B47: =IFERROR(INDEX('Detalles movimientos'!C$5:C$1021, MATCH(38, 'Detalles movimientos'!$W$5:$W$1021, 0)), "") | C47: =IFERROR(INDEX('Detalles movimientos'!D$5:D$1021, MATCH(38, 'Detalles movimientos'!$W$5:$W$1021, 0)), "") | D47: =IFERROR(INDEX('Detalles movimientos'!E$5:E$1021, MATCH(38, 'Detalles movimientos'!$W$5:$W$1021, 0)), "") | E47: =IFERROR(INDEX('Detalles movimientos'!F$5:F$1021, MATCH(38, 'Detalles movimientos'!$W$5:$W$1021, 0)), "") | F47: =IFERROR(INDEX('Detalles movimientos'!G$5:G$1021, MATCH(38, 'Detalles movimientos'!$W$5:$W$1021, 0)), "") | G47: =IFERROR(INDEX('Detalles movimientos'!H$5:H$1021, MATCH(38, 'Detalles movimientos'!$W$5:$W$1021, 0)), "") | H47: =IFERROR(INDEX('Detalles movimientos'!I$5:I$1021, MATCH(38, 'Detalles movimientos'!$W$5:$W$1021, 0)), "") | I47: =IFERROR(INDEX('Detalles movimientos'!M$5:M$1021, MATCH(38, 'Detalles movimientos'!$W$5:$W$1021, 0)), "") | J47: =IFERROR(INDEX('Detalles movimientos'!N$5:N$1021, MATCH(38, 'Detalles movimientos'!$W$5:$W$1021, 0)), "") | K47: =IFERROR(INDEX('Detalles movimientos'!O$5:O$1021, MATCH(38, 'Detalles movimientos'!$W$5:$W$1021, 0)), "") | L47: =IFERROR(INDEX('Detalles movimientos'!P$5:P$1021, MATCH(38, 'Detalles movimientos'!$W$5:$W$1021, 0)), "") | M47: =IFERROR(INDEX('Detalles movimientos'!S$5:S$1021, MATCH(38, 'Detalles movimientos'!$W$5:$W$1021, 0)), "")
B48: =IFERROR(INDEX('Detalles movimientos'!C$5:C$1021, MATCH(39, 'Detalles movimientos'!$W$5:$W$1021, 0)), "") | C48: =IFERROR(INDEX('Detalles movimientos'!D$5:D$1021, MATCH(39, 'Detalles movimientos'!$W$5:$W$1021, 0)), "") | D48: =IFERROR(INDEX('Detalles movimientos'!E$5:E$1021, MATCH(39, 'Detalles movimientos'!$W$5:$W$1021, 0)), "") | E48: =IFERROR(INDEX('Detalles movimientos'!F$5:F$1021, MATCH(39, 'Detalles movimientos'!$W$5:$W$1021, 0)), "") | F48: =IFERROR(INDEX('Detalles movimientos'!G$5:G$1021, MATCH(39, 'Detalles movimientos'!$W$5:$W$1021, 0)), "") | G48: =IFERROR(INDEX('Detalles movimientos'!H$5:H$1021, MATCH(39, 'Detalles movimientos'!$W$5:$W$1021, 0)), "") | H48: =IFERROR(INDEX('Detalles movimientos'!I$5:I$1021, MATCH(39, 'Detalles movimientos'!$W$5:$W$1021, 0)), "") | I48: =IFERROR(INDEX('Detalles movimientos'!M$5:M$1021, MATCH(39, 'Detalles movimientos'!$W$5:$W$1021, 0)), "") | J48: =IFERROR(INDEX('Detalles movimientos'!N$5:N$1021, MATCH(39, 'Detalles movimientos'!$W$5:$W$1021, 0)), "") | K48: =IFERROR(INDEX('Detalles movimientos'!O$5:O$1021, MATCH(39, 'Detalles movimientos'!$W$5:$W$1021, 0)), "") | L48: =IFERROR(INDEX('Detalles movimientos'!P$5:P$1021, MATCH(39, 'Detalles movimientos'!$W$5:$W$1021, 0)), "") | M48: =IFERROR(INDEX('Detalles movimientos'!S$5:S$1021, MATCH(39, 'Detalles movimientos'!$W$5:$W$1021, 0)), "")
B49: =IFERROR(INDEX('Detalles movimientos'!C$5:C$1021, MATCH(40, 'Detalles movimientos'!$W$5:$W$1021, 0)), "") | C49: =IFERROR(INDEX('Detalles movimientos'!D$5:D$1021, MATCH(40, 'Detalles movimientos'!$W$5:$W$1021, 0)), "") | D49: =IFERROR(INDEX('Detalles movimientos'!E$5:E$1021, MATCH(40, 'Detalles movimientos'!$W$5:$W$1021, 0)), "") | E49: =IFERROR(INDEX('Detalles movimientos'!F$5:F$1021, MATCH(40, 'Detalles movimientos'!$W$5:$W$1021, 0)), "") | F49: =IFERROR(INDEX('Detalles movimientos'!G$5:G$1021, MATCH(40, 'Detalles movimientos'!$W$5:$W$1021, 0)), "") | G49: =IFERROR(INDEX('Detalles movimientos'!H$5:H$1021, MATCH(40, 'Detalles movimientos'!$W$5:$W$1021, 0)), "") | H49: =IFERROR(INDEX('Detalles movimientos'!I$5:I$1021, MATCH(40, 'Detalles movimientos'!$W$5:$W$1021, 0)), "") | I49: =IFERROR(INDEX('Detalles movimientos'!M$5:M$1021, MATCH(40, 'Detalles movimientos'!$W$5:$W$1021, 0)), "") | J49: =IFERROR(INDEX('Detalles movimientos'!N$5:N$1021, MATCH(40, 'Detalles movimientos'!$W$5:$W$1021, 0)), "") | K49: =IFERROR(INDEX('Detalles movimientos'!O$5:O$1021, MATCH(40, 'Detalles movimientos'!$W$5:$W$1021, 0)), "") | L49: =IFERROR(INDEX('Detalles movimientos'!P$5:P$1021, MATCH(40, 'Detalles movimientos'!$W$5:$W$1021, 0)), "") | M49: =IFERROR(INDEX('Detalles movimientos'!S$5:S$1021, MATCH(40, 'Detalles movimientos'!$W$5:$W$1021, 0)), "")
B50: =IFERROR(INDEX('Detalles movimientos'!C$5:C$1021, MATCH(41, 'Detalles movimientos'!$W$5:$W$1021, 0)), "") | C50: =IFERROR(INDEX('Detalles movimientos'!D$5:D$1021, MATCH(41, 'Detalles movimientos'!$W$5:$W$1021, 0)), "") | D50: =IFERROR(INDEX('Detalles movimientos'!E$5:E$1021, MATCH(41, 'Detalles movimientos'!$W$5:$W$1021, 0)), "") | E50: =IFERROR(INDEX('Detalles movimientos'!F$5:F$1021, MATCH(41, 'Detalles movimientos'!$W$5:$W$1021, 0)), "") | F50: =IFERROR(INDEX('Detalles movimientos'!G$5:G$1021, MATCH(41, 'Detalles movimientos'!$W$5:$W$1021, 0)), "") | G50: =IFERROR(INDEX('Detalles movimientos'!H$5:H$1021, MATCH(41, 'Detalles movimientos'!$W$5:$W$1021, 0)), "") | H50: =IFERROR(INDEX('Detalles movimientos'!I$5:I$1021, MATCH(41, 'Detalles movimientos'!$W$5:$W$1021, 0)), "") | I50: =IFERROR(INDEX('Detalles movimientos'!M$5:M$1021, MATCH(41, 'Detalles movimientos'!$W$5:$W$1021, 0)), "") | J50: =IFERROR(INDEX('Detalles movimientos'!N$5:N$1021, MATCH(41, 'Detalles movimientos'!$W$5:$W$1021, 0)), "") | K50: =IFERROR(INDEX('Detalles movimientos'!O$5:O$1021, MATCH(41, 'Detalles movimientos'!$W$5:$W$1021, 0)), "") | L50: =IFERROR(INDEX('Detalles movimientos'!P$5:P$1021, MATCH(41, 'Detalles movimientos'!$W$5:$W$1021, 0)), "") | M50: =IFERROR(INDEX('Detalles movimientos'!S$5:S$1021, MATCH(41, 'Detalles movimientos'!$W$5:$W$1021, 0)), "")
B51: =IFERROR(INDEX('Detalles movimientos'!C$5:C$1021, MATCH(42, 'Detalles movimientos'!$W$5:$W$1021, 0)), "") | C51: =IFERROR(INDEX('Detalles movimientos'!D$5:D$1021, MATCH(42, 'Detalles movimientos'!$W$5:$W$1021, 0)), "") | D51: =IFERROR(INDEX('Detalles movimientos'!E$5:E$1021, MATCH(42, 'Detalles movimientos'!$W$5:$W$1021, 0)), "") | E51: =IFERROR(INDEX('Detalles movimientos'!F$5:F$1021, MATCH(42, 'Detalles movimientos'!$W$5:$W$1021, 0)), "") | F51: =IFERROR(INDEX('Detalles movimientos'!G$5:G$1021, MATCH(42, 'Detalles movimientos'!$W$5:$W$1021, 0)), "") | G51: =IFERROR(INDEX('Detalles movimientos'!H$5:H$1021, MATCH(42, 'Detalles movimientos'!$W$5:$W$1021, 0)), "") | H51: =IFERROR(INDEX('Detalles movimientos'!I$5:I$1021, MATCH(42, 'Detalles movimientos'!$W$5:$W$1021, 0)), "") | I51: =IFERROR(INDEX('Detalles movimientos'!M$5:M$1021, MATCH(42, 'Detalles movimientos'!$W$5:$W$1021, 0)), "") | J51: =IFERROR(INDEX('Detalles movimientos'!N$5:N$1021, MATCH(42, 'Detalles movimientos'!$W$5:$W$1021, 0)), "") | K51: =IFERROR(INDEX('Detalles movimientos'!O$5:O$1021, MATCH(42, 'Detalles movimientos'!$W$5:$W$1021, 0)), "") | L51: =IFERROR(INDEX('Detalles movimientos'!P$5:P$1021, MATCH(42, 'Detalles movimientos'!$W$5:$W$1021, 0)), "") | M51: =IFERROR(INDEX('Detalles movimientos'!S$5:S$1021, MATCH(42, 'Detalles movimientos'!$W$5:$W$1021, 0)), "")
B52: =IFERROR(INDEX('Detalles movimientos'!C$5:C$1021, MATCH(43, 'Detalles movimientos'!$W$5:$W$1021, 0)), "") | C52: =IFERROR(INDEX('Detalles movimientos'!D$5:D$1021, MATCH(43, 'Detalles movimientos'!$W$5:$W$1021, 0)), "") | D52: =IFERROR(INDEX('Detalles movimientos'!E$5:E$1021, MATCH(43, 'Detalles movimientos'!$W$5:$W$1021, 0)), "") | E52: =IFERROR(INDEX('Detalles movimientos'!F$5:F$1021, MATCH(43, 'Detalles movimientos'!$W$5:$W$1021, 0)), "") | F52: =IFERROR(INDEX('Detalles movimientos'!G$5:G$1021, MATCH(43, 'Detalles movimientos'!$W$5:$W$1021, 0)), "") | G52: =IFERROR(INDEX('Detalles movimientos'!H$5:H$1021, MATCH(43, 'Detalles movimientos'!$W$5:$W$1021, 0)), "") | H52: =IFERROR(INDEX('Detalles movimientos'!I$5:I$1021, MATCH(43, 'Detalles movimientos'!$W$5:$W$1021, 0)), "") | I52: =IFERROR(INDEX('Detalles movimientos'!M$5:M$1021, MATCH(43, 'Detalles movimientos'!$W$5:$W$1021, 0)), "") | J52: =IFERROR(INDEX('Detalles movimientos'!N$5:N$1021, MATCH(43, 'Detalles movimientos'!$W$5:$W$1021, 0)), "") | K52: =IFERROR(INDEX('Detalles movimientos'!O$5:O$1021, MATCH(43, 'Detalles movimientos'!$W$5:$W$1021, 0)), "") | L52: =IFERROR(INDEX('Detalles movimientos'!P$5:P$1021, MATCH(43, 'Detalles movimientos'!$W$5:$W$1021, 0)), "") | M52: =IFERROR(INDEX('Detalles movimientos'!S$5:S$1021, MATCH(43, 'Detalles movimientos'!$W$5:$W$1021, 0)), "")
B53: =IFERROR(INDEX('Detalles movimientos'!C$5:C$1021, MATCH(44, 'Detalles movimientos'!$W$5:$W$1021, 0)), "") | C53: =IFERROR(INDEX('Detalles movimientos'!D$5:D$1021, MATCH(44, 'Detalles movimientos'!$W$5:$W$1021, 0)), "") | D53: =IFERROR(INDEX('Detalles movimientos'!E$5:E$1021, MATCH(44, 'Detalles movimientos'!$W$5:$W$1021, 0)), "") | E53: =IFERROR(INDEX('Detalles movimientos'!F$5:F$1021, MATCH(44, 'Detalles movimientos'!$W$5:$W$1021, 0)), "") | F53: =IFERROR(INDEX('Detalles movimientos'!G$5:G$1021, MATCH(44, 'Detalles movimientos'!$W$5:$W$1021, 0)), "") | G53: =IFERROR(INDEX('Detalles movimientos'!H$5:H$1021, MATCH(44, 'Detalles movimientos'!$W$5:$W$1021, 0)), "") | H53: =IFERROR(INDEX('Detalles movimientos'!I$5:I$1021, MATCH(44, 'Detalles movimientos'!$W$5:$W$1021, 0)), "") | I53: =IFERROR(INDEX('Detalles movimientos'!M$5:M$1021, MATCH(44, 'Detalles movimientos'!$W$5:$W$1021, 0)), "") | J53: =IFERROR(INDEX('Detalles movimientos'!N$5:N$1021, MATCH(44, 'Detalles movimientos'!$W$5:$W$1021, 0)), "") | K53: =IFERROR(INDEX('Detalles movimientos'!O$5:O$1021, MATCH(44, 'Detalles movimientos'!$W$5:$W$1021, 0)), "") | L53: =IFERROR(INDEX('Detalles movimientos'!P$5:P$1021, MATCH(44, 'Detalles movimientos'!$W$5:$W$1021, 0)), "") | M53: =IFERROR(INDEX('Detalles movimientos'!S$5:S$1021, MATCH(44, 'Detalles movimientos'!$W$5:$W$1021, 0)), "")
B54: =IFERROR(INDEX('Detalles movimientos'!C$5:C$1021, MATCH(45, 'Detalles movimientos'!$W$5:$W$1021, 0)), "") | C54: =IFERROR(INDEX('Detalles movimientos'!D$5:D$1021, MATCH(45, 'Detalles movimientos'!$W$5:$W$1021, 0)), "") | D54: =IFERROR(INDEX('Detalles movimientos'!E$5:E$1021, MATCH(45, 'Detalles movimientos'!$W$5:$W$1021, 0)), "") | E54: =IFERROR(INDEX('Detalles movimientos'!F$5:F$1021, MATCH(45, 'Detalles movimientos'!$W$5:$W$1021, 0)), "") | F54: =IFERROR(INDEX('Detalles movimientos'!G$5:G$1021, MATCH(45, 'Detalles movimientos'!$W$5:$W$1021, 0)), "") | G54: =IFERROR(INDEX('Detalles movimientos'!H$5:H$1021, MATCH(45, 'Detalles movimientos'!$W$5:$W$1021, 0)), "") | H54: =IFERROR(INDEX('Detalles movimientos'!I$5:I$1021, MATCH(45, 'Detalles movimientos'!$W$5:$W$1021, 0)), "") | I54: =IFERROR(INDEX('Detalles movimientos'!M$5:M$1021, MATCH(45, 'Detalles movimientos'!$W$5:$W$1021, 0)), "") | J54: =IFERROR(INDEX('Detalles movimientos'!N$5:N$1021, MATCH(45, 'Detalles movimientos'!$W$5:$W$1021, 0)), "") | K54: =IFERROR(INDEX('Detalles movimientos'!O$5:O$1021, MATCH(45, 'Detalles movimientos'!$W$5:$W$1021, 0)), "") | L54: =IFERROR(INDEX('Detalles movimientos'!P$5:P$1021, MATCH(45, 'Detalles movimientos'!$W$5:$W$1021, 0)), "") | M54: =IFERROR(INDEX('Detalles movimientos'!S$5:S$1021, MATCH(45, 'Detalles movimientos'!$W$5:$W$1021, 0)), "")
B55: =IFERROR(INDEX('Detalles movimientos'!C$5:C$1021, MATCH(46, 'Detalles movimientos'!$W$5:$W$1021, 0)), "") | C55: =IFERROR(INDEX('Detalles movimientos'!D$5:D$1021, MATCH(46, 'Detalles movimientos'!$W$5:$W$1021, 0)), "") | D55: =IFERROR(INDEX('Detalles movimientos'!E$5:E$1021, MATCH(46, 'Detalles movimientos'!$W$5:$W$1021, 0)), "") | E55: =IFERROR(INDEX('Detalles movimientos'!F$5:F$1021, MATCH(46, 'Detalles movimientos'!$W$5:$W$1021, 0)), "") | F55: =IFERROR(INDEX('Detalles movimientos'!G$5:G$1021, MATCH(46, 'Detalles movimientos'!$W$5:$W$1021, 0)), "") | G55: =IFERROR(INDEX('Detalles movimientos'!H$5:H$1021, MATCH(46, 'Detalles movimientos'!$W$5:$W$1021, 0)), "") | H55: =IFERROR(INDEX('Detalles movimientos'!I$5:I$1021, MATCH(46, 'Detalles movimientos'!$W$5:$W$1021, 0)), "") | I55: =IFERROR(INDEX('Detalles movimientos'!M$5:M$1021, MATCH(46, 'Detalles movimientos'!$W$5:$W$1021, 0)), "") | J55: =IFERROR(INDEX('Detalles movimientos'!N$5:N$1021, MATCH(46, 'Detalles movimientos'!$W$5:$W$1021, 0)), "") | K55: =IFERROR(INDEX('Detalles movimientos'!O$5:O$1021, MATCH(46, 'Detalles movimientos'!$W$5:$W$1021, 0)), "") | L55: =IFERROR(INDEX('Detalles movimientos'!P$5:P$1021, MATCH(46, 'Detalles movimientos'!$W$5:$W$1021, 0)), "") | M55: =IFERROR(INDEX('Detalles movimientos'!S$5:S$1021, MATCH(46, 'Detalles movimientos'!$W$5:$W$1021, 0)), "")
B56: =IFERROR(INDEX('Detalles movimientos'!C$5:C$1021, MATCH(47, 'Detalles movimientos'!$W$5:$W$1021, 0)), "") | C56: =IFERROR(INDEX('Detalles movimientos'!D$5:D$1021, MATCH(47, 'Detalles movimientos'!$W$5:$W$1021, 0)), "") | D56: =IFERROR(INDEX('Detalles movimientos'!E$5:E$1021, MATCH(47, 'Detalles movimientos'!$W$5:$W$1021, 0)), "") | E56: =IFERROR(INDEX('Detalles movimientos'!F$5:F$1021, MATCH(47, 'Detalles movimientos'!$W$5:$W$1021, 0)), "") | F56: =IFERROR(INDEX('Detalles movimientos'!G$5:G$1021, MATCH(47, 'Detalles movimientos'!$W$5:$W$1021, 0)), "") | G56: =IFERROR(INDEX('Detalles movimientos'!H$5:H$1021, MATCH(47, 'Detalles movimientos'!$W$5:$W$1021, 0)), "") | H56: =IFERROR(INDEX('Detalles movimientos'!I$5:I$1021, MATCH(47, 'Detalles movimientos'!$W$5:$W$1021, 0)), "") | I56: =IFERROR(INDEX('Detalles movimientos'!M$5:M$1021, MATCH(47, 'Detalles movimientos'!$W$5:$W$1021, 0)), "") | J56: =IFERROR(INDEX('Detalles movimientos'!N$5:N$1021, MATCH(47, 'Detalles movimientos'!$W$5:$W$1021, 0)), "") | K56: =IFERROR(INDEX('Detalles movimientos'!O$5:O$1021, MATCH(47, 'Detalles movimientos'!$W$5:$W$1021, 0)), "") | L56: =IFERROR(INDEX('Detalles movimientos'!P$5:P$1021, MATCH(47, 'Detalles movimientos'!$W$5:$W$1021, 0)), "") | M56: =IFERROR(INDEX('Detalles movimientos'!S$5:S$1021, MATCH(47, 'Detalles movimientos'!$W$5:$W$1021, 0)), "")
B57: =IFERROR(INDEX('Detalles movimientos'!C$5:C$1021, MATCH(48, 'Detalles movimientos'!$W$5:$W$1021, 0)), "") | C57: =IFERROR(INDEX('Detalles movimientos'!D$5:D$1021, MATCH(48, 'Detalles movimientos'!$W$5:$W$1021, 0)), "") | D57: =IFERROR(INDEX('Detalles movimientos'!E$5:E$1021, MATCH(48, 'Detalles movimientos'!$W$5:$W$1021, 0)), "") | E57: =IFERROR(INDEX('Detalles movimientos'!F$5:F$1021, MATCH(48, 'Detalles movimientos'!$W$5:$W$1021, 0)), "") | F57: =IFERROR(INDEX('Detalles movimientos'!G$5:G$1021, MATCH(48, 'Detalles movimientos'!$W$5:$W$1021, 0)), "") | G57: =IFERROR(INDEX('Detalles movimientos'!H$5:H$1021, MATCH(48, 'Detalles movimientos'!$W$5:$W$1021, 0)), "") | H57: =IFERROR(INDEX('Detalles movimientos'!I$5:I$1021, MATCH(48, 'Detalles movimientos'!$W$5:$W$1021, 0)), "") | I57: =IFERROR(INDEX('Detalles movimientos'!M$5:M$1021, MATCH(48, 'Detalles movimientos'!$W$5:$W$1021, 0)), "") | J57: =IFERROR(INDEX('Detalles movimientos'!N$5:N$1021, MATCH(48, 'Detalles movimientos'!$W$5:$W$1021, 0)), "") | K57: =IFERROR(INDEX('Detalles movimientos'!O$5:O$1021, MATCH(48, 'Detalles movimientos'!$W$5:$W$1021, 0)), "") | L57: =IFERROR(INDEX('Detalles movimientos'!P$5:P$1021, MATCH(48, 'Detalles movimientos'!$W$5:$W$1021, 0)), "") | M57: =IFERROR(INDEX('Detalles movimientos'!S$5:S$1021, MATCH(48, 'Detalles movimientos'!$W$5:$W$1021, 0)), "")
B58: =IFERROR(INDEX('Detalles movimientos'!C$5:C$1021, MATCH(49, 'Detalles movimientos'!$W$5:$W$1021, 0)), "") | C58: =IFERROR(INDEX('Detalles movimientos'!D$5:D$1021, MATCH(49, 'Detalles movimientos'!$W$5:$W$1021, 0)), "") | D58: =IFERROR(INDEX('Detalles movimientos'!E$5:E$1021, MATCH(49, 'Detalles movimientos'!$W$5:$W$1021, 0)), "") | E58: =IFERROR(INDEX('Detalles movimientos'!F$5:F$1021, MATCH(49, 'Detalles movimientos'!$W$5:$W$1021, 0)), "") | F58: =IFERROR(INDEX('Detalles movimientos'!G$5:G$1021, MATCH(49, 'Detalles movimientos'!$W$5:$W$1021, 0)), "") | G58: =IFERROR(INDEX('Detalles movimientos'!H$5:H$1021, MATCH(49, 'Detalles movimientos'!$W$5:$W$1021, 0)), "") | H58: =IFERROR(INDEX('Detalles movimientos'!I$5:I$1021, MATCH(49, 'Detalles movimientos'!$W$5:$W$1021, 0)), "") | I58: =IFERROR(INDEX('Detalles movimientos'!M$5:M$1021, MATCH(49, 'Detalles movimientos'!$W$5:$W$1021, 0)), "") | J58: =IFERROR(INDEX('Detalles movimientos'!N$5:N$1021, MATCH(49, 'Detalles movimientos'!$W$5:$W$1021, 0)), "") | K58: =IFERROR(INDEX('Detalles movimientos'!O$5:O$1021, MATCH(49, 'Detalles movimientos'!$W$5:$W$1021, 0)), "") | L58: =IFERROR(INDEX('Detalles movimientos'!P$5:P$1021, MATCH(49, 'Detalles movimientos'!$W$5:$W$1021, 0)), "") | M58: =IFERROR(INDEX('Detalles movimientos'!S$5:S$1021, MATCH(49, 'Detalles movimientos'!$W$5:$W$1021, 0)), "")
B59: =IFERROR(INDEX('Detalles movimientos'!C$5:C$1021, MATCH(50, 'Detalles movimientos'!$W$5:$W$1021, 0)), "") | C59: =IFERROR(INDEX('Detalles movimientos'!D$5:D$1021, MATCH(50, 'Detalles movimientos'!$W$5:$W$1021, 0)), "") | D59: =IFERROR(INDEX('Detalles movimientos'!E$5:E$1021, MATCH(50, 'Detalles movimientos'!$W$5:$W$1021, 0)), "") | E59: =IFERROR(INDEX('Detalles movimientos'!F$5:F$1021, MATCH(50, 'Detalles movimientos'!$W$5:$W$1021, 0)), "") | F59: =IFERROR(INDEX('Detalles movimientos'!G$5:G$1021, MATCH(50, 'Detalles movimientos'!$W$5:$W$1021, 0)), "") | G59: =IFERROR(INDEX('Detalles movimientos'!H$5:H$1021, MATCH(50, 'Detalles movimientos'!$W$5:$W$1021, 0)), "") | H59: =IFERROR(INDEX('Detalles movimientos'!I$5:I$1021, MATCH(50, 'Detalles movimientos'!$W$5:$W$1021, 0)), "") | I59: =IFERROR(INDEX('Detalles movimientos'!M$5:M$1021, MATCH(50, 'Detalles movimientos'!$W$5:$W$1021, 0)), "") | J59: =IFERROR(INDEX('Detalles movimientos'!N$5:N$1021, MATCH(50, 'Detalles movimientos'!$W$5:$W$1021, 0)), "") | K59: =IFERROR(INDEX('Detalles movimientos'!O$5:O$1021, MATCH(50, 'Detalles movimientos'!$W$5:$W$1021, 0)), "") | L59: =IFERROR(INDEX('Detalles movimientos'!P$5:P$1021, MATCH(50, 'Detalles movimientos'!$W$5:$W$1021, 0)), "") | M59: =IFERROR(INDEX('Detalles movimientos'!S$5:S$1021, MATCH(50, 'Detalles movimientos'!$W$5:$W$1021, 0)), "")
B60: =IFERROR(INDEX('Detalles movimientos'!C$5:C$1021, MATCH(51, 'Detalles movimientos'!$W$5:$W$1021, 0)), "") | C60: =IFERROR(INDEX('Detalles movimientos'!D$5:D$1021, MATCH(51, 'Detalles movimientos'!$W$5:$W$1021, 0)), "") | D60: =IFERROR(INDEX('Detalles movimientos'!E$5:E$1021, MATCH(51, 'Detalles movimientos'!$W$5:$W$1021, 0)), "") | E60: =IFERROR(INDEX('Detalles movimientos'!F$5:F$1021, MATCH(51, 'Detalles movimientos'!$W$5:$W$1021, 0)), "") | F60: =IFERROR(INDEX('Detalles movimientos'!G$5:G$1021, MATCH(51, 'Detalles movimientos'!$W$5:$W$1021, 0)), "") | G60: =IFERROR(INDEX('Detalles movimientos'!H$5:H$1021, MATCH(51, 'Detalles movimientos'!$W$5:$W$1021, 0)), "") | H60: =IFERROR(INDEX('Detalles movimientos'!I$5:I$1021, MATCH(51, 'Detalles movimientos'!$W$5:$W$1021, 0)), "") | I60: =IFERROR(INDEX('Detalles movimientos'!M$5:M$1021, MATCH(51, 'Detalles movimientos'!$W$5:$W$1021, 0)), "") | J60: =IFERROR(INDEX('Detalles movimientos'!N$5:N$1021, MATCH(51, 'Detalles movimientos'!$W$5:$W$1021, 0)), "") | K60: =IFERROR(INDEX('Detalles movimientos'!O$5:O$1021, MATCH(51, 'Detalles movimientos'!$W$5:$W$1021, 0)), "") | L60: =IFERROR(INDEX('Detalles movimientos'!P$5:P$1021, MATCH(51, 'Detalles movimientos'!$W$5:$W$1021, 0)), "") | M60: =IFERROR(INDEX('Detalles movimientos'!S$5:S$1021, MATCH(51, 'Detalles movimientos'!$W$5:$W$1021, 0)), "")
B61: =IFERROR(INDEX('Detalles movimientos'!C$5:C$1021, MATCH(52, 'Detalles movimientos'!$W$5:$W$1021, 0)), "") | C61: =IFERROR(INDEX('Detalles movimientos'!D$5:D$1021, MATCH(52, 'Detalles movimientos'!$W$5:$W$1021, 0)), "") | D61: =IFERROR(INDEX('Detalles movimientos'!E$5:E$1021, MATCH(52, 'Detalles movimientos'!$W$5:$W$1021, 0)), "") | E61: =IFERROR(INDEX('Detalles movimientos'!F$5:F$1021, MATCH(52, 'Detalles movimientos'!$W$5:$W$1021, 0)), "") | F61: =IFERROR(INDEX('Detalles movimientos'!G$5:G$1021, MATCH(52, 'Detalles movimientos'!$W$5:$W$1021, 0)), "") | G61: =IFERROR(INDEX('Detalles movimientos'!H$5:H$1021, MATCH(52, 'Detalles movimientos'!$W$5:$W$1021, 0)), "") | H61: =IFERROR(INDEX('Detalles movimientos'!I$5:I$1021, MATCH(52, 'Detalles movimientos'!$W$5:$W$1021, 0)), "") | I61: =IFERROR(INDEX('Detalles movimientos'!M$5:M$1021, MATCH(52, 'Detalles movimientos'!$W$5:$W$1021, 0)), "") | J61: =IFERROR(INDEX('Detalles movimientos'!N$5:N$1021, MATCH(52, 'Detalles movimientos'!$W$5:$W$1021, 0)), "") | K61: =IFERROR(INDEX('Detalles movimientos'!O$5:O$1021, MATCH(52, 'Detalles movimientos'!$W$5:$W$1021, 0)), "") | L61: =IFERROR(INDEX('Detalles movimientos'!P$5:P$1021, MATCH(52, 'Detalles movimientos'!$W$5:$W$1021, 0)), "") | M61: =IFERROR(INDEX('Detalles movimientos'!S$5:S$1021, MATCH(52, 'Detalles movimientos'!$W$5:$W$1021, 0)), "")
B62: =IFERROR(INDEX('Detalles movimientos'!C$5:C$1021, MATCH(53, 'Detalles movimientos'!$W$5:$W$1021, 0)), "") | C62: =IFERROR(INDEX('Detalles movimientos'!D$5:D$1021, MATCH(53, 'Detalles movimientos'!$W$5:$W$1021, 0)), "") | D62: =IFERROR(INDEX('Detalles movimientos'!E$5:E$1021, MATCH(53, 'Detalles movimientos'!$W$5:$W$1021, 0)), "") | E62: =IFERROR(INDEX('Detalles movimientos'!F$5:F$1021, MATCH(53, 'Detalles movimientos'!$W$5:$W$1021, 0)), "") | F62: =IFERROR(INDEX('Detalles movimientos'!G$5:G$1021, MATCH(53, 'Detalles movimientos'!$W$5:$W$1021, 0)), "") | G62: =IFERROR(INDEX('Detalles movimientos'!H$5:H$1021, MATCH(53, 'Detalles movimientos'!$W$5:$W$1021, 0)), "") | H62: =IFERROR(INDEX('Detalles movimientos'!I$5:I$1021, MATCH(53, 'Detalles movimientos'!$W$5:$W$1021, 0)), "") | I62: =IFERROR(INDEX('Detalles movimientos'!M$5:M$1021, MATCH(53, 'Detalles movimientos'!$W$5:$W$1021, 0)), "") | J62: =IFERROR(INDEX('Detalles movimientos'!N$5:N$1021, MATCH(53, 'Detalles movimientos'!$W$5:$W$1021, 0)), "") | K62: =IFERROR(INDEX('Detalles movimientos'!O$5:O$1021, MATCH(53, 'Detalles movimientos'!$W$5:$W$1021, 0)), "") | L62: =IFERROR(INDEX('Detalles movimientos'!P$5:P$1021, MATCH(53, 'Detalles movimientos'!$W$5:$W$1021, 0)), "") | M62: =IFERROR(INDEX('Detalles movimientos'!S$5:S$1021, MATCH(53, 'Detalles movimientos'!$W$5:$W$1021, 0)), "")
B63: =IFERROR(INDEX('Detalles movimientos'!C$5:C$1021, MATCH(54, 'Detalles movimientos'!$W$5:$W$1021, 0)), "") | C63: =IFERROR(INDEX('Detalles movimientos'!D$5:D$1021, MATCH(54, 'Detalles movimientos'!$W$5:$W$1021, 0)), "") | D63: =IFERROR(INDEX('Detalles movimientos'!E$5:E$1021, MATCH(54, 'Detalles movimientos'!$W$5:$W$1021, 0)), "") | E63: =IFERROR(INDEX('Detalles movimientos'!F$5:F$1021, MATCH(54, 'Detalles movimientos'!$W$5:$W$1021, 0)), "") | F63: =IFERROR(INDEX('Detalles movimientos'!G$5:G$1021, MATCH(54, 'Detalles movimientos'!$W$5:$W$1021, 0)), "") | G63: =IFERROR(INDEX('Detalles movimientos'!H$5:H$1021, MATCH(54, 'Detalles movimientos'!$W$5:$W$1021, 0)), "") | H63: =IFERROR(INDEX('Detalles movimientos'!I$5:I$1021, MATCH(54, 'Detalles movimientos'!$W$5:$W$1021, 0)), "") | I63: =IFERROR(INDEX('Detalles movimientos'!M$5:M$1021, MATCH(54, 'Detalles movimientos'!$W$5:$W$1021, 0)), "") | J63: =IFERROR(INDEX('Detalles movimientos'!N$5:N$1021, MATCH(54, 'Detalles movimientos'!$W$5:$W$1021, 0)), "") | K63: =IFERROR(INDEX('Detalles movimientos'!O$5:O$1021, MATCH(54, 'Detalles movimientos'!$W$5:$W$1021, 0)), "") | L63: =IFERROR(INDEX('Detalles movimientos'!P$5:P$1021, MATCH(54, 'Detalles movimientos'!$W$5:$W$1021, 0)), "") | M63: =IFERROR(INDEX('Detalles movimientos'!S$5:S$1021, MATCH(54, 'Detalles movimientos'!$W$5:$W$1021, 0)), "")
B64: =IFERROR(INDEX('Detalles movimientos'!C$5:C$1021, MATCH(55, 'Detalles movimientos'!$W$5:$W$1021, 0)), "") | C64: =IFERROR(INDEX('Detalles movimientos'!D$5:D$1021, MATCH(55, 'Detalles movimientos'!$W$5:$W$1021, 0)), "") | D64: =IFERROR(INDEX('Detalles movimientos'!E$5:E$1021, MATCH(55, 'Detalles movimientos'!$W$5:$W$1021, 0)), "") | E64: =IFERROR(INDEX('Detalles movimientos'!F$5:F$1021, MATCH(55, 'Detalles movimientos'!$W$5:$W$1021, 0)), "") | F64: =IFERROR(INDEX('Detalles movimientos'!G$5:G$1021, MATCH(55, 'Detalles movimientos'!$W$5:$W$1021, 0)), "") | G64: =IFERROR(INDEX('Detalles movimientos'!H$5:H$1021, MATCH(55, 'Detalles movimientos'!$W$5:$W$1021, 0)), "") | H64: =IFERROR(INDEX('Detalles movimientos'!I$5:I$1021, MATCH(55, 'Detalles movimientos'!$W$5:$W$1021, 0)), "") | I64: =IFERROR(INDEX('Detalles movimientos'!M$5:M$1021, MATCH(55, 'Detalles movimientos'!$W$5:$W$1021, 0)), "") | J64: =IFERROR(INDEX('Detalles movimientos'!N$5:N$1021, MATCH(55, 'Detalles movimientos'!$W$5:$W$1021, 0)), "") | K64: =IFERROR(INDEX('Detalles movimientos'!O$5:O$1021, MATCH(55, 'Detalles movimientos'!$W$5:$W$1021, 0)), "") | L64: =IFERROR(INDEX('Detalles movimientos'!P$5:P$1021, MATCH(55, 'Detalles movimientos'!$W$5:$W$1021, 0)), "") | M64: =IFERROR(INDEX('Detalles movimientos'!S$5:S$1021, MATCH(55, 'Detalles movimientos'!$W$5:$W$1021, 0)), "")
B65: =IFERROR(INDEX('Detalles movimientos'!C$5:C$1021, MATCH(56, 'Detalles movimientos'!$W$5:$W$1021, 0)), "") | C65: =IFERROR(INDEX('Detalles movimientos'!D$5:D$1021, MATCH(56, 'Detalles movimientos'!$W$5:$W$1021, 0)), "") | D65: =IFERROR(INDEX('Detalles movimientos'!E$5:E$1021, MATCH(56, 'Detalles movimientos'!$W$5:$W$1021, 0)), "") | E65: =IFERROR(INDEX('Detalles movimientos'!F$5:F$1021, MATCH(56, 'Detalles movimientos'!$W$5:$W$1021, 0)), "") | F65: =IFERROR(INDEX('Detalles movimientos'!G$5:G$1021, MATCH(56, 'Detalles movimientos'!$W$5:$W$1021, 0)), "") | G65: =IFERROR(INDEX('Detalles movimientos'!H$5:H$1021, MATCH(56, 'Detalles movimientos'!$W$5:$W$1021, 0)), "") | H65: =IFERROR(INDEX('Detalles movimientos'!I$5:I$1021, MATCH(56, 'Detalles movimientos'!$W$5:$W$1021, 0)), "") | I65: =IFERROR(INDEX('Detalles movimientos'!M$5:M$1021, MATCH(56, 'Detalles movimientos'!$W$5:$W$1021, 0)), "") | J65: =IFERROR(INDEX('Detalles movimientos'!N$5:N$1021, MATCH(56, 'Detalles movimientos'!$W$5:$W$1021, 0)), "") | K65: =IFERROR(INDEX('Detalles movimientos'!O$5:O$1021, MATCH(56, 'Detalles movimientos'!$W$5:$W$1021, 0)), "") | L65: =IFERROR(INDEX('Detalles movimientos'!P$5:P$1021, MATCH(56, 'Detalles movimientos'!$W$5:$W$1021, 0)), "") | M65: =IFERROR(INDEX('Detalles movimientos'!S$5:S$1021, MATCH(56, 'Detalles movimientos'!$W$5:$W$1021, 0)), "")
B66: =IFERROR(INDEX('Detalles movimientos'!C$5:C$1021, MATCH(57, 'Detalles movimientos'!$W$5:$W$1021, 0)), "") | C66: =IFERROR(INDEX('Detalles movimientos'!D$5:D$1021, MATCH(57, 'Detalles movimientos'!$W$5:$W$1021, 0)), "") | D66: =IFERROR(INDEX('Detalles movimientos'!E$5:E$1021, MATCH(57, 'Detalles movimientos'!$W$5:$W$1021, 0)), "") | E66: =IFERROR(INDEX('Detalles movimientos'!F$5:F$1021, MATCH(57, 'Detalles movimientos'!$W$5:$W$1021, 0)), "") | F66: =IFERROR(INDEX('Detalles movimientos'!G$5:G$1021, MATCH(57, 'Detalles movimientos'!$W$5:$W$1021, 0)), "") | G66: =IFERROR(INDEX('Detalles movimientos'!H$5:H$1021, MATCH(57, 'Detalles movimientos'!$W$5:$W$1021, 0)), "") | H66: =IFERROR(INDEX('Detalles movimientos'!I$5:I$1021, MATCH(57, 'Detalles movimientos'!$W$5:$W$1021, 0)), "") | I66: =IFERROR(INDEX('Detalles movimientos'!M$5:M$1021, MATCH(57, 'Detalles movimientos'!$W$5:$W$1021, 0)), "") | J66: =IFERROR(INDEX('Detalles movimientos'!N$5:N$1021, MATCH(57, 'Detalles movimientos'!$W$5:$W$1021, 0)), "") | K66: =IFERROR(INDEX('Detalles movimientos'!O$5:O$1021, MATCH(57, 'Detalles movimientos'!$W$5:$W$1021, 0)), "") | L66: =IFERROR(INDEX('Detalles movimientos'!P$5:P$1021, MATCH(57, 'Detalles movimientos'!$W$5:$W$1021, 0)), "") | M66: =IFERROR(INDEX('Detalles movimientos'!S$5:S$1021, MATCH(57, 'Detalles movimientos'!$W$5:$W$1021, 0)), "")
B67: =IFERROR(INDEX('Detalles movimientos'!C$5:C$1021, MATCH(58, 'Detalles movimientos'!$W$5:$W$1021, 0)), "") | C67: =IFERROR(INDEX('Detalles movimientos'!D$5:D$1021, MATCH(58, 'Detalles movimientos'!$W$5:$W$1021, 0)), "") | D67: =IFERROR(INDEX('Detalles movimientos'!E$5:E$1021, MATCH(58, 'Detalles movimientos'!$W$5:$W$1021, 0)), "") | E67: =IFERROR(INDEX('Detalles movimientos'!F$5:F$1021, MATCH(58, 'Detalles movimientos'!$W$5:$W$1021, 0)), "") | F67: =IFERROR(INDEX('Detalles movimientos'!G$5:G$1021, MATCH(58, 'Detalles movimientos'!$W$5:$W$1021, 0)), "") | G67: =IFERROR(INDEX('Detalles movimientos'!H$5:H$1021, MATCH(58, 'Detalles movimientos'!$W$5:$W$1021, 0)), "") | H67: =IFERROR(INDEX('Detalles movimientos'!I$5:I$1021, MATCH(58, 'Detalles movimientos'!$W$5:$W$1021, 0)), "") | I67: =IFERROR(INDEX('Detalles movimientos'!M$5:M$1021, MATCH(58, 'Detalles movimientos'!$W$5:$W$1021, 0)), "") | J67: =IFERROR(INDEX('Detalles movimientos'!N$5:N$1021, MATCH(58, 'Detalles movimientos'!$W$5:$W$1021, 0)), "") | K67: =IFERROR(INDEX('Detalles movimientos'!O$5:O$1021, MATCH(58, 'Detalles movimientos'!$W$5:$W$1021, 0)), "") | L67: =IFERROR(INDEX('Detalles movimientos'!P$5:P$1021, MATCH(58, 'Detalles movimientos'!$W$5:$W$1021, 0)), "") | M67: =IFERROR(INDEX('Detalles movimientos'!S$5:S$1021, MATCH(58, 'Detalles movimientos'!$W$5:$W$1021, 0)), "")
B68: =IFERROR(INDEX('Detalles movimientos'!C$5:C$1021, MATCH(59, 'Detalles movimientos'!$W$5:$W$1021, 0)), "") | C68: =IFERROR(INDEX('Detalles movimientos'!D$5:D$1021, MATCH(59, 'Detalles movimientos'!$W$5:$W$1021, 0)), "") | D68: =IFERROR(INDEX('Detalles movimientos'!E$5:E$1021, MATCH(59, 'Detalles movimientos'!$W$5:$W$1021, 0)), "") | E68: =IFERROR(INDEX('Detalles movimientos'!F$5:F$1021, MATCH(59, 'Detalles movimientos'!$W$5:$W$1021, 0)), "") | F68: =IFERROR(INDEX('Detalles movimientos'!G$5:G$1021, MATCH(59, 'Detalles movimientos'!$W$5:$W$1021, 0)), "") | G68: =IFERROR(INDEX('Detalles movimientos'!H$5:H$1021, MATCH(59, 'Detalles movimientos'!$W$5:$W$1021, 0)), "") | H68: =IFERROR(INDEX('Detalles movimientos'!I$5:I$1021, MATCH(59, 'Detalles movimientos'!$W$5:$W$1021, 0)), "") | I68: =IFERROR(INDEX('Detalles movimientos'!M$5:M$1021, MATCH(59, 'Detalles movimientos'!$W$5:$W$1021, 0)), "") | J68: =IFERROR(INDEX('Detalles movimientos'!N$5:N$1021, MATCH(59, 'Detalles movimientos'!$W$5:$W$1021, 0)), "") | K68: =IFERROR(INDEX('Detalles movimientos'!O$5:O$1021, MATCH(59, 'Detalles movimientos'!$W$5:$W$1021, 0)), "") | L68: =IFERROR(INDEX('Detalles movimientos'!P$5:P$1021, MATCH(59, 'Detalles movimientos'!$W$5:$W$1021, 0)), "") | M68: =IFERROR(INDEX('Detalles movimientos'!S$5:S$1021, MATCH(59, 'Detalles movimientos'!$W$5:$W$1021, 0)), "")
B69: =IFERROR(INDEX('Detalles movimientos'!C$5:C$1021, MATCH(60, 'Detalles movimientos'!$W$5:$W$1021, 0)), "") | C69: =IFERROR(INDEX('Detalles movimientos'!D$5:D$1021, MATCH(60, 'Detalles movimientos'!$W$5:$W$1021, 0)), "") | D69: =IFERROR(INDEX('Detalles movimientos'!E$5:E$1021, MATCH(60, 'Detalles movimientos'!$W$5:$W$1021, 0)), "") | E69: =IFERROR(INDEX('Detalles movimientos'!F$5:F$1021, MATCH(60, 'Detalles movimientos'!$W$5:$W$1021, 0)), "") | F69: =IFERROR(INDEX('Detalles movimientos'!G$5:G$1021, MATCH(60, 'Detalles movimientos'!$W$5:$W$1021, 0)), "") | G69: =IFERROR(INDEX('Detalles movimientos'!H$5:H$1021, MATCH(60, 'Detalles movimientos'!$W$5:$W$1021, 0)), "") | H69: =IFERROR(INDEX('Detalles movimientos'!I$5:I$1021, MATCH(60, 'Detalles movimientos'!$W$5:$W$1021, 0)), "") | I69: =IFERROR(INDEX('Detalles movimientos'!M$5:M$1021, MATCH(60, 'Detalles movimientos'!$W$5:$W$1021, 0)), "") | J69: =IFERROR(INDEX('Detalles movimientos'!N$5:N$1021, MATCH(60, 'Detalles movimientos'!$W$5:$W$1021, 0)), "") | K69: =IFERROR(INDEX('Detalles movimientos'!O$5:O$1021, MATCH(60, 'Detalles movimientos'!$W$5:$W$1021, 0)), "") | L69: =IFERROR(INDEX('Detalles movimientos'!P$5:P$1021, MATCH(60, 'Detalles movimientos'!$W$5:$W$1021, 0)), "") | M69: =IFERROR(INDEX('Detalles movimientos'!S$5:S$1021, MATCH(60, 'Detalles movimientos'!$W$5:$W$1021, 0)), "")
B70: =IFERROR(INDEX('Detalles movimientos'!C$5:C$1021, MATCH(61, 'Detalles movimientos'!$W$5:$W$1021, 0)), "") | C70: =IFERROR(INDEX('Detalles movimientos'!D$5:D$1021, MATCH(61, 'Detalles movimientos'!$W$5:$W$1021, 0)), "") | D70: =IFERROR(INDEX('Detalles movimientos'!E$5:E$1021, MATCH(61, 'Detalles movimientos'!$W$5:$W$1021, 0)), "") | E70: =IFERROR(INDEX('Detalles movimientos'!F$5:F$1021, MATCH(61, 'Detalles movimientos'!$W$5:$W$1021, 0)), "") | F70: =IFERROR(INDEX('Detalles movimientos'!G$5:G$1021, MATCH(61, 'Detalles movimientos'!$W$5:$W$1021, 0)), "") | G70: =IFERROR(INDEX('Detalles movimientos'!H$5:H$1021, MATCH(61, 'Detalles movimientos'!$W$5:$W$1021, 0)), "") | H70: =IFERROR(INDEX('Detalles movimientos'!I$5:I$1021, MATCH(61, 'Detalles movimientos'!$W$5:$W$1021, 0)), "") | I70: =IFERROR(INDEX('Detalles movimientos'!M$5:M$1021, MATCH(61, 'Detalles movimientos'!$W$5:$W$1021, 0)), "") | J70: =IFERROR(INDEX('Detalles movimientos'!N$5:N$1021, MATCH(61, 'Detalles movimientos'!$W$5:$W$1021, 0)), "") | K70: =IFERROR(INDEX('Detalles movimientos'!O$5:O$1021, MATCH(61, 'Detalles movimientos'!$W$5:$W$1021, 0)), "") | L70: =IFERROR(INDEX('Detalles movimientos'!P$5:P$1021, MATCH(61, 'Detalles movimientos'!$W$5:$W$1021, 0)), "") | M70: =IFERROR(INDEX('Detalles movimientos'!S$5:S$1021, MATCH(61, 'Detalles movimientos'!$W$5:$W$1021, 0)), "")
B71: =IFERROR(INDEX('Detalles movimientos'!C$5:C$1021, MATCH(62, 'Detalles movimientos'!$W$5:$W$1021, 0)), "") | C71: =IFERROR(INDEX('Detalles movimientos'!D$5:D$1021, MATCH(62, 'Detalles movimientos'!$W$5:$W$1021, 0)), "") | D71: =IFERROR(INDEX('Detalles movimientos'!E$5:E$1021, MATCH(62, 'Detalles movimientos'!$W$5:$W$1021, 0)), "") | E71: =IFERROR(INDEX('Detalles movimientos'!F$5:F$1021, MATCH(62, 'Detalles movimientos'!$W$5:$W$1021, 0)), "") | F71: =IFERROR(INDEX('Detalles movimientos'!G$5:G$1021, MATCH(62, 'Detalles movimientos'!$W$5:$W$1021, 0)), "") | G71: =IFERROR(INDEX('Detalles movimientos'!H$5:H$1021, MATCH(62, 'Detalles movimientos'!$W$5:$W$1021, 0)), "") | H71: =IFERROR(INDEX('Detalles movimientos'!I$5:I$1021, MATCH(62, 'Detalles movimientos'!$W$5:$W$1021, 0)), "") | I71: =IFERROR(INDEX('Detalles movimientos'!M$5:M$1021, MATCH(62, 'Detalles movimientos'!$W$5:$W$1021, 0)), "") | J71: =IFERROR(INDEX('Detalles movimientos'!N$5:N$1021, MATCH(62, 'Detalles movimientos'!$W$5:$W$1021, 0)), "") | K71: =IFERROR(INDEX('Detalles movimientos'!O$5:O$1021, MATCH(62, 'Detalles movimientos'!$W$5:$W$1021, 0)), "") | L71: =IFERROR(INDEX('Detalles movimientos'!P$5:P$1021, MATCH(62, 'Detalles movimientos'!$W$5:$W$1021, 0)), "") | M71: =IFERROR(INDEX('Detalles movimientos'!S$5:S$1021, MATCH(62, 'Detalles movimientos'!$W$5:$W$1021, 0)), "")
B72: =IFERROR(INDEX('Detalles movimientos'!C$5:C$1021, MATCH(63, 'Detalles movimientos'!$W$5:$W$1021, 0)), "") | C72: =IFERROR(INDEX('Detalles movimientos'!D$5:D$1021, MATCH(63, 'Detalles movimientos'!$W$5:$W$1021, 0)), "") | D72: =IFERROR(INDEX('Detalles movimientos'!E$5:E$1021, MATCH(63, 'Detalles movimientos'!$W$5:$W$1021, 0)), "") | E72: =IFERROR(INDEX('Detalles movimientos'!F$5:F$1021, MATCH(63, 'Detalles movimientos'!$W$5:$W$1021, 0)), "") | F72: =IFERROR(INDEX('Detalles movimientos'!G$5:G$1021, MATCH(63, 'Detalles movimientos'!$W$5:$W$1021, 0)), "") | G72: =IFERROR(INDEX('Detalles movimientos'!H$5:H$1021, MATCH(63, 'Detalles movimientos'!$W$5:$W$1021, 0)), "") | H72: =IFERROR(INDEX('Detalles movimientos'!I$5:I$1021, MATCH(63, 'Detalles movimientos'!$W$5:$W$1021, 0)), "") | I72: =IFERROR(INDEX('Detalles movimientos'!M$5:M$1021, MATCH(63, 'Detalles movimientos'!$W$5:$W$1021, 0)), "") | J72: =IFERROR(INDEX('Detalles movimientos'!N$5:N$1021, MATCH(63, 'Detalles movimientos'!$W$5:$W$1021, 0)), "") | K72: =IFERROR(INDEX('Detalles movimientos'!O$5:O$1021, MATCH(63, 'Detalles movimientos'!$W$5:$W$1021, 0)), "") | L72: =IFERROR(INDEX('Detalles movimientos'!P$5:P$1021, MATCH(63, 'Detalles movimientos'!$W$5:$W$1021, 0)), "") | M72: =IFERROR(INDEX('Detalles movimientos'!S$5:S$1021, MATCH(63, 'Detalles movimientos'!$W$5:$W$1021, 0)), "")
B73: =IFERROR(INDEX('Detalles movimientos'!C$5:C$1021, MATCH(64, 'Detalles movimientos'!$W$5:$W$1021, 0)), "") | C73: =IFERROR(INDEX('Detalles movimientos'!D$5:D$1021, MATCH(64, 'Detalles movimientos'!$W$5:$W$1021, 0)), "") | D73: =IFERROR(INDEX('Detalles movimientos'!E$5:E$1021, MATCH(64, 'Detalles movimientos'!$W$5:$W$1021, 0)), "") | E73: =IFERROR(INDEX('Detalles movimientos'!F$5:F$1021, MATCH(64, 'Detalles movimientos'!$W$5:$W$1021, 0)), "") | F73: =IFERROR(INDEX('Detalles movimientos'!G$5:G$1021, MATCH(64, 'Detalles movimientos'!$W$5:$W$1021, 0)), "") | G73: =IFERROR(INDEX('Detalles movimientos'!H$5:H$1021, MATCH(64, 'Detalles movimientos'!$W$5:$W$1021, 0)), "") | H73: =IFERROR(INDEX('Detalles movimientos'!I$5:I$1021, MATCH(64, 'Detalles movimientos'!$W$5:$W$1021, 0)), "") | I73: =IFERROR(INDEX('Detalles movimientos'!M$5:M$1021, MATCH(64, 'Detalles movimientos'!$W$5:$W$1021, 0)), "") | J73: =IFERROR(INDEX('Detalles movimientos'!N$5:N$1021, MATCH(64, 'Detalles movimientos'!$W$5:$W$1021, 0)), "") | K73: =IFERROR(INDEX('Detalles movimientos'!O$5:O$1021, MATCH(64, 'Detalles movimientos'!$W$5:$W$1021, 0)), "") | L73: =IFERROR(INDEX('Detalles movimientos'!P$5:P$1021, MATCH(64, 'Detalles movimientos'!$W$5:$W$1021, 0)), "") | M73: =IFERROR(INDEX('Detalles movimientos'!S$5:S$1021, MATCH(64, 'Detalles movimientos'!$W$5:$W$1021, 0)), "")
B74: =IFERROR(INDEX('Detalles movimientos'!C$5:C$1021, MATCH(65, 'Detalles movimientos'!$W$5:$W$1021, 0)), "") | C74: =IFERROR(INDEX('Detalles movimientos'!D$5:D$1021, MATCH(65, 'Detalles movimientos'!$W$5:$W$1021, 0)), "") | D74: =IFERROR(INDEX('Detalles movimientos'!E$5:E$1021, MATCH(65, 'Detalles movimientos'!$W$5:$W$1021, 0)), "") | E74: =IFERROR(INDEX('Detalles movimientos'!F$5:F$1021, MATCH(65, 'Detalles movimientos'!$W$5:$W$1021, 0)), "") | F74: =IFERROR(INDEX('Detalles movimientos'!G$5:G$1021, MATCH(65, 'Detalles movimientos'!$W$5:$W$1021, 0)), "") | G74: =IFERROR(INDEX('Detalles movimientos'!H$5:H$1021, MATCH(65, 'Detalles movimientos'!$W$5:$W$1021, 0)), "") | H74: =IFERROR(INDEX('Detalles movimientos'!I$5:I$1021, MATCH(65, 'Detalles movimientos'!$W$5:$W$1021, 0)), "") | I74: =IFERROR(INDEX('Detalles movimientos'!M$5:M$1021, MATCH(65, 'Detalles movimientos'!$W$5:$W$1021, 0)), "") | J74: =IFERROR(INDEX('Detalles movimientos'!N$5:N$1021, MATCH(65, 'Detalles movimientos'!$W$5:$W$1021, 0)), "") | K74: =IFERROR(INDEX('Detalles movimientos'!O$5:O$1021, MATCH(65, 'Detalles movimientos'!$W$5:$W$1021, 0)), "") | L74: =IFERROR(INDEX('Detalles movimientos'!P$5:P$1021, MATCH(65, 'Detalles movimientos'!$W$5:$W$1021, 0)), "") | M74: =IFERROR(INDEX('Detalles movimientos'!S$5:S$1021, MATCH(65, 'Detalles movimientos'!$W$5:$W$1021, 0)), "")
B75: =IFERROR(INDEX('Detalles movimientos'!C$5:C$1021, MATCH(66, 'Detalles movimientos'!$W$5:$W$1021, 0)), "") | C75: =IFERROR(INDEX('Detalles movimientos'!D$5:D$1021, MATCH(66, 'Detalles movimientos'!$W$5:$W$1021, 0)), "") | D75: =IFERROR(INDEX('Detalles movimientos'!E$5:E$1021, MATCH(66, 'Detalles movimientos'!$W$5:$W$1021, 0)), "") | E75: =IFERROR(INDEX('Detalles movimientos'!F$5:F$1021, MATCH(66, 'Detalles movimientos'!$W$5:$W$1021, 0)), "") | F75: =IFERROR(INDEX('Detalles movimientos'!G$5:G$1021, MATCH(66, 'Detalles movimientos'!$W$5:$W$1021, 0)), "") | G75: =IFERROR(INDEX('Detalles movimientos'!H$5:H$1021, MATCH(66, 'Detalles movimientos'!$W$5:$W$1021, 0)), "") | H75: =IFERROR(INDEX('Detalles movimientos'!I$5:I$1021, MATCH(66, 'Detalles movimientos'!$W$5:$W$1021, 0)), "") | I75: =IFERROR(INDEX('Detalles movimientos'!M$5:M$1021, MATCH(66, 'Detalles movimientos'!$W$5:$W$1021, 0)), "") | J75: =IFERROR(INDEX('Detalles movimientos'!N$5:N$1021, MATCH(66, 'Detalles movimientos'!$W$5:$W$1021, 0)), "") | K75: =IFERROR(INDEX('Detalles movimientos'!O$5:O$1021, MATCH(66, 'Detalles movimientos'!$W$5:$W$1021, 0)), "") | L75: =IFERROR(INDEX('Detalles movimientos'!P$5:P$1021, MATCH(66, 'Detalles movimientos'!$W$5:$W$1021, 0)), "") | M75: =IFERROR(INDEX('Detalles movimientos'!S$5:S$1021, MATCH(66, 'Detalles movimientos'!$W$5:$W$1021, 0)), "")
B76: =IFERROR(INDEX('Detalles movimientos'!C$5:C$1021, MATCH(67, 'Detalles movimientos'!$W$5:$W$1021, 0)), "") | C76: =IFERROR(INDEX('Detalles movimientos'!D$5:D$1021, MATCH(67, 'Detalles movimientos'!$W$5:$W$1021, 0)), "") | D76: =IFERROR(INDEX('Detalles movimientos'!E$5:E$1021, MATCH(67, 'Detalles movimientos'!$W$5:$W$1021, 0)), "") | E76: =IFERROR(INDEX('Detalles movimientos'!F$5:F$1021, MATCH(67, 'Detalles movimientos'!$W$5:$W$1021, 0)), "") | F76: =IFERROR(INDEX('Detalles movimientos'!G$5:G$1021, MATCH(67, 'Detalles movimientos'!$W$5:$W$1021, 0)), "") | G76: =IFERROR(INDEX('Detalles movimientos'!H$5:H$1021, MATCH(67, 'Detalles movimientos'!$W$5:$W$1021, 0)), "") | H76: =IFERROR(INDEX('Detalles movimientos'!I$5:I$1021, MATCH(67, 'Detalles movimientos'!$W$5:$W$1021, 0)), "") | I76: =IFERROR(INDEX('Detalles movimientos'!M$5:M$1021, MATCH(67, 'Detalles movimientos'!$W$5:$W$1021, 0)), "") | J76: =IFERROR(INDEX('Detalles movimientos'!N$5:N$1021, MATCH(67, 'Detalles movimientos'!$W$5:$W$1021, 0)), "") | K76: =IFERROR(INDEX('Detalles movimientos'!O$5:O$1021, MATCH(67, 'Detalles movimientos'!$W$5:$W$1021, 0)), "") | L76: =IFERROR(INDEX('Detalles movimientos'!P$5:P$1021, MATCH(67, 'Detalles movimientos'!$W$5:$W$1021, 0)), "") | M76: =IFERROR(INDEX('Detalles movimientos'!S$5:S$1021, MATCH(67, 'Detalles movimientos'!$W$5:$W$1021, 0)), "")
B77: =IFERROR(INDEX('Detalles movimientos'!C$5:C$1021, MATCH(68, 'Detalles movimientos'!$W$5:$W$1021, 0)), "") | C77: =IFERROR(INDEX('Detalles movimientos'!D$5:D$1021, MATCH(68, 'Detalles movimientos'!$W$5:$W$1021, 0)), "") | D77: =IFERROR(INDEX('Detalles movimientos'!E$5:E$1021, MATCH(68, 'Detalles movimientos'!$W$5:$W$1021, 0)), "") | E77: =IFERROR(INDEX('Detalles movimientos'!F$5:F$1021, MATCH(68, 'Detalles movimientos'!$W$5:$W$1021, 0)), "") | F77: =IFERROR(INDEX('Detalles movimientos'!G$5:G$1021, MATCH(68, 'Detalles movimientos'!$W$5:$W$1021, 0)), "") | G77: =IFERROR(INDEX('Detalles movimientos'!H$5:H$1021, MATCH(68, 'Detalles movimientos'!$W$5:$W$1021, 0)), "") | H77: =IFERROR(INDEX('Detalles movimientos'!I$5:I$1021, MATCH(68, 'Detalles movimientos'!$W$5:$W$1021, 0)), "") | I77: =IFERROR(INDEX('Detalles movimientos'!M$5:M$1021, MATCH(68, 'Detalles movimientos'!$W$5:$W$1021, 0)), "") | J77: =IFERROR(INDEX('Detalles movimientos'!N$5:N$1021, MATCH(68, 'Detalles movimientos'!$W$5:$W$1021, 0)), "") | K77: =IFERROR(INDEX('Detalles movimientos'!O$5:O$1021, MATCH(68, 'Detalles movimientos'!$W$5:$W$1021, 0)), "") | L77: =IFERROR(INDEX('Detalles movimientos'!P$5:P$1021, MATCH(68, 'Detalles movimientos'!$W$5:$W$1021, 0)), "") | M77: =IFERROR(INDEX('Detalles movimientos'!S$5:S$1021, MATCH(68, 'Detalles movimientos'!$W$5:$W$1021, 0)), "")
B78: =IFERROR(INDEX('Detalles movimientos'!C$5:C$1021, MATCH(69, 'Detalles movimientos'!$W$5:$W$1021, 0)), "") | C78: =IFERROR(INDEX('Detalles movimientos'!D$5:D$1021, MATCH(69, 'Detalles movimientos'!$W$5:$W$1021, 0)), "") | D78: =IFERROR(INDEX('Detalles movimientos'!E$5:E$1021, MATCH(69, 'Detalles movimientos'!$W$5:$W$1021, 0)), "") | E78: =IFERROR(INDEX('Detalles movimientos'!F$5:F$1021, MATCH(69, 'Detalles movimientos'!$W$5:$W$1021, 0)), "") | F78: =IFERROR(INDEX('Detalles movimientos'!G$5:G$1021, MATCH(69, 'Detalles movimientos'!$W$5:$W$1021, 0)), "") | G78: =IFERROR(INDEX('Detalles movimientos'!H$5:H$1021, MATCH(69, 'Detalles movimientos'!$W$5:$W$1021, 0)), "") | H78: =IFERROR(INDEX('Detalles movimientos'!I$5:I$1021, MATCH(69, 'Detalles movimientos'!$W$5:$W$1021, 0)), "") | I78: =IFERROR(INDEX('Detalles movimientos'!M$5:M$1021, MATCH(69, 'Detalles movimientos'!$W$5:$W$1021, 0)), "") | J78: =IFERROR(INDEX('Detalles movimientos'!N$5:N$1021, MATCH(69, 'Detalles movimientos'!$W$5:$W$1021, 0)), "") | K78: =IFERROR(INDEX('Detalles movimientos'!O$5:O$1021, MATCH(69, 'Detalles movimientos'!$W$5:$W$1021, 0)), "") | L78: =IFERROR(INDEX('Detalles movimientos'!P$5:P$1021, MATCH(69, 'Detalles movimientos'!$W$5:$W$1021, 0)), "") | M78: =IFERROR(INDEX('Detalles movimientos'!S$5:S$1021, MATCH(69, 'Detalles movimientos'!$W$5:$W$1021, 0)), "")
B79: =IFERROR(INDEX('Detalles movimientos'!C$5:C$1021, MATCH(70, 'Detalles movimientos'!$W$5:$W$1021, 0)), "") | C79: =IFERROR(INDEX('Detalles movimientos'!D$5:D$1021, MATCH(70, 'Detalles movimientos'!$W$5:$W$1021, 0)), "") | D79: =IFERROR(INDEX('Detalles movimientos'!E$5:E$1021, MATCH(70, 'Detalles movimientos'!$W$5:$W$1021, 0)), "") | E79: =IFERROR(INDEX('Detalles movimientos'!F$5:F$1021, MATCH(70, 'Detalles movimientos'!$W$5:$W$1021, 0)), "") | F79: =IFERROR(INDEX('Detalles movimientos'!G$5:G$1021, MATCH(70, 'Detalles movimientos'!$W$5:$W$1021, 0)), "") | G79: =IFERROR(INDEX('Detalles movimientos'!H$5:H$1021, MATCH(70, 'Detalles movimientos'!$W$5:$W$1021, 0)), "") | H79: =IFERROR(INDEX('Detalles movimientos'!I$5:I$1021, MATCH(70, 'Detalles movimientos'!$W$5:$W$1021, 0)), "") | I79: =IFERROR(INDEX('Detalles movimientos'!M$5:M$1021, MATCH(70, 'Detalles movimientos'!$W$5:$W$1021, 0)), "") | J79: =IFERROR(INDEX('Detalles movimientos'!N$5:N$1021, MATCH(70, 'Detalles movimientos'!$W$5:$W$1021, 0)), "") | K79: =IFERROR(INDEX('Detalles movimientos'!O$5:O$1021, MATCH(70, 'Detalles movimientos'!$W$5:$W$1021, 0)), "") | L79: =IFERROR(INDEX('Detalles movimientos'!P$5:P$1021, MATCH(70, 'Detalles movimientos'!$W$5:$W$1021, 0)), "") | M79: =IFERROR(INDEX('Detalles movimientos'!S$5:S$1021, MATCH(70, 'Detalles movimientos'!$W$5:$W$1021, 0)), "")
B80: =IFERROR(INDEX('Detalles movimientos'!C$5:C$1021, MATCH(71, 'Detalles movimientos'!$W$5:$W$1021, 0)), "") | C80: =IFERROR(INDEX('Detalles movimientos'!D$5:D$1021, MATCH(71, 'Detalles movimientos'!$W$5:$W$1021, 0)), "") | D80: =IFERROR(INDEX('Detalles movimientos'!E$5:E$1021, MATCH(71, 'Detalles movimientos'!$W$5:$W$1021, 0)), "") | E80: =IFERROR(INDEX('Detalles movimientos'!F$5:F$1021, MATCH(71, 'Detalles movimientos'!$W$5:$W$1021, 0)), "") | F80: =IFERROR(INDEX('Detalles movimientos'!G$5:G$1021, MATCH(71, 'Detalles movimientos'!$W$5:$W$1021, 0)), "") | G80: =IFERROR(INDEX('Detalles movimientos'!H$5:H$1021, MATCH(71, 'Detalles movimientos'!$W$5:$W$1021, 0)), "") | H80: =IFERROR(INDEX('Detalles movimientos'!I$5:I$1021, MATCH(71, 'Detalles movimientos'!$W$5:$W$1021, 0)), "") | I80: =IFERROR(INDEX('Detalles movimientos'!M$5:M$1021, MATCH(71, 'Detalles movimientos'!$W$5:$W$1021, 0)), "") | J80: =IFERROR(INDEX('Detalles movimientos'!N$5:N$1021, MATCH(71, 'Detalles movimientos'!$W$5:$W$1021, 0)), "") | K80: =IFERROR(INDEX('Detalles movimientos'!O$5:O$1021, MATCH(71, 'Detalles movimientos'!$W$5:$W$1021, 0)), "") | L80: =IFERROR(INDEX('Detalles movimientos'!P$5:P$1021, MATCH(71, 'Detalles movimientos'!$W$5:$W$1021, 0)), "") | M80: =IFERROR(INDEX('Detalles movimientos'!S$5:S$1021, MATCH(71, 'Detalles movimientos'!$W$5:$W$1021, 0)), "")
B81: =IFERROR(INDEX('Detalles movimientos'!C$5:C$1021, MATCH(72, 'Detalles movimientos'!$W$5:$W$1021, 0)), "") | C81: =IFERROR(INDEX('Detalles movimientos'!D$5:D$1021, MATCH(72, 'Detalles movimientos'!$W$5:$W$1021, 0)), "") | D81: =IFERROR(INDEX('Detalles movimientos'!E$5:E$1021, MATCH(72, 'Detalles movimientos'!$W$5:$W$1021, 0)), "") | E81: =IFERROR(INDEX('Detalles movimientos'!F$5:F$1021, MATCH(72, 'Detalles movimientos'!$W$5:$W$1021, 0)), "") | F81: =IFERROR(INDEX('Detalles movimientos'!G$5:G$1021, MATCH(72, 'Detalles movimientos'!$W$5:$W$1021, 0)), "") | G81: =IFERROR(INDEX('Detalles movimientos'!H$5:H$1021, MATCH(72, 'Detalles movimientos'!$W$5:$W$1021, 0)), "") | H81: =IFERROR(INDEX('Detalles movimientos'!I$5:I$1021, MATCH(72, 'Detalles movimientos'!$W$5:$W$1021, 0)), "") | I81: =IFERROR(INDEX('Detalles movimientos'!M$5:M$1021, MATCH(72, 'Detalles movimientos'!$W$5:$W$1021, 0)), "") | J81: =IFERROR(INDEX('Detalles movimientos'!N$5:N$1021, MATCH(72, 'Detalles movimientos'!$W$5:$W$1021, 0)), "") | K81: =IFERROR(INDEX('Detalles movimientos'!O$5:O$1021, MATCH(72, 'Detalles movimientos'!$W$5:$W$1021, 0)), "") | L81: =IFERROR(INDEX('Detalles movimientos'!P$5:P$1021, MATCH(72, 'Detalles movimientos'!$W$5:$W$1021, 0)), "") | M81: =IFERROR(INDEX('Detalles movimientos'!S$5:S$1021, MATCH(72, 'Detalles movimientos'!$W$5:$W$1021, 0)), "")
B82: =IFERROR(INDEX('Detalles movimientos'!C$5:C$1021, MATCH(73, 'Detalles movimientos'!$W$5:$W$1021, 0)), "") | C82: =IFERROR(INDEX('Detalles movimientos'!D$5:D$1021, MATCH(73, 'Detalles movimientos'!$W$5:$W$1021, 0)), "") | D82: =IFERROR(INDEX('Detalles movimientos'!E$5:E$1021, MATCH(73, 'Detalles movimientos'!$W$5:$W$1021, 0)), "") | E82: =IFERROR(INDEX('Detalles movimientos'!F$5:F$1021, MATCH(73, 'Detalles movimientos'!$W$5:$W$1021, 0)), "") | F82: =IFERROR(INDEX('Detalles movimientos'!G$5:G$1021, MATCH(73, 'Detalles movimientos'!$W$5:$W$1021, 0)), "") | G82: =IFERROR(INDEX('Detalles movimientos'!H$5:H$1021, MATCH(73, 'Detalles movimientos'!$W$5:$W$1021, 0)), "") | H82: =IFERROR(INDEX('Detalles movimientos'!I$5:I$1021, MATCH(73, 'Detalles movimientos'!$W$5:$W$1021, 0)), "") | I82: =IFERROR(INDEX('Detalles movimientos'!M$5:M$1021, MATCH(73, 'Detalles movimientos'!$W$5:$W$1021, 0)), "") | J82: =IFERROR(INDEX('Detalles movimientos'!N$5:N$1021, MATCH(73, 'Detalles movimientos'!$W$5:$W$1021, 0)), "") | K82: =IFERROR(INDEX('Detalles movimientos'!O$5:O$1021, MATCH(73, 'Detalles movimientos'!$W$5:$W$1021, 0)), "") | L82: =IFERROR(INDEX('Detalles movimientos'!P$5:P$1021, MATCH(73, 'Detalles movimientos'!$W$5:$W$1021, 0)), "") | M82: =IFERROR(INDEX('Detalles movimientos'!S$5:S$1021, MATCH(73, 'Detalles movimientos'!$W$5:$W$1021, 0)), "")
B83: =IFERROR(INDEX('Detalles movimientos'!C$5:C$1021, MATCH(74, 'Detalles movimientos'!$W$5:$W$1021, 0)), "") | C83: =IFERROR(INDEX('Detalles movimientos'!D$5:D$1021, MATCH(74, 'Detalles movimientos'!$W$5:$W$1021, 0)), "") | D83: =IFERROR(INDEX('Detalles movimientos'!E$5:E$1021, MATCH(74, 'Detalles movimientos'!$W$5:$W$1021, 0)), "") | E83: =IFERROR(INDEX('Detalles movimientos'!F$5:F$1021, MATCH(74, 'Detalles movimientos'!$W$5:$W$1021, 0)), "") | F83: =IFERROR(INDEX('Detalles movimientos'!G$5:G$1021, MATCH(74, 'Detalles movimientos'!$W$5:$W$1021, 0)), "") | G83: =IFERROR(INDEX('Detalles movimientos'!H$5:H$1021, MATCH(74, 'Detalles movimientos'!$W$5:$W$1021, 0)), "") | H83: =IFERROR(INDEX('Detalles movimientos'!I$5:I$1021, MATCH(74, 'Detalles movimientos'!$W$5:$W$1021, 0)), "") | I83: =IFERROR(INDEX('Detalles movimientos'!M$5:M$1021, MATCH(74, 'Detalles movimientos'!$W$5:$W$1021, 0)), "") | J83: =IFERROR(INDEX('Detalles movimientos'!N$5:N$1021, MATCH(74, 'Detalles movimientos'!$W$5:$W$1021, 0)), "") | K83: =IFERROR(INDEX('Detalles movimientos'!O$5:O$1021, MATCH(74, 'Detalles movimientos'!$W$5:$W$1021, 0)), "") | L83: =IFERROR(INDEX('Detalles movimientos'!P$5:P$1021, MATCH(74, 'Detalles movimientos'!$W$5:$W$1021, 0)), "") | M83: =IFERROR(INDEX('Detalles movimientos'!S$5:S$1021, MATCH(74, 'Detalles movimientos'!$W$5:$W$1021, 0)), "")
B84: =IFERROR(INDEX('Detalles movimientos'!C$5:C$1021, MATCH(75, 'Detalles movimientos'!$W$5:$W$1021, 0)), "") | C84: =IFERROR(INDEX('Detalles movimientos'!D$5:D$1021, MATCH(75, 'Detalles movimientos'!$W$5:$W$1021, 0)), "") | D84: =IFERROR(INDEX('Detalles movimientos'!E$5:E$1021, MATCH(75, 'Detalles movimientos'!$W$5:$W$1021, 0)), "") | E84: =IFERROR(INDEX('Detalles movimientos'!F$5:F$1021, MATCH(75, 'Detalles movimientos'!$W$5:$W$1021, 0)), "") | F84: =IFERROR(INDEX('Detalles movimientos'!G$5:G$1021, MATCH(75, 'Detalles movimientos'!$W$5:$W$1021, 0)), "") | G84: =IFERROR(INDEX('Detalles movimientos'!H$5:H$1021, MATCH(75, 'Detalles movimientos'!$W$5:$W$1021, 0)), "") | H84: =IFERROR(INDEX('Detalles movimientos'!I$5:I$1021, MATCH(75, 'Detalles movimientos'!$W$5:$W$1021, 0)), "") | I84: =IFERROR(INDEX('Detalles movimientos'!M$5:M$1021, MATCH(75, 'Detalles movimientos'!$W$5:$W$1021, 0)), "") | J84: =IFERROR(INDEX('Detalles movimientos'!N$5:N$1021, MATCH(75, 'Detalles movimientos'!$W$5:$W$1021, 0)), "") | K84: =IFERROR(INDEX('Detalles movimientos'!O$5:O$1021, MATCH(75, 'Detalles movimientos'!$W$5:$W$1021, 0)), "") | L84: =IFERROR(INDEX('Detalles movimientos'!P$5:P$1021, MATCH(75, 'Detalles movimientos'!$W$5:$W$1021, 0)), "") | M84: =IFERROR(INDEX('Detalles movimientos'!S$5:S$1021, MATCH(75, 'Detalles movimientos'!$W$5:$W$1021, 0)), "")
B85: =IFERROR(INDEX('Detalles movimientos'!C$5:C$1021, MATCH(76, 'Detalles movimientos'!$W$5:$W$1021, 0)), "") | C85: =IFERROR(INDEX('Detalles movimientos'!D$5:D$1021, MATCH(76, 'Detalles movimientos'!$W$5:$W$1021, 0)), "") | D85: =IFERROR(INDEX('Detalles movimientos'!E$5:E$1021, MATCH(76, 'Detalles movimientos'!$W$5:$W$1021, 0)), "") | E85: =IFERROR(INDEX('Detalles movimientos'!F$5:F$1021, MATCH(76, 'Detalles movimientos'!$W$5:$W$1021, 0)), "") | F85: =IFERROR(INDEX('Detalles movimientos'!G$5:G$1021, MATCH(76, 'Detalles movimientos'!$W$5:$W$1021, 0)), "") | G85: =IFERROR(INDEX('Detalles movimientos'!H$5:H$1021, MATCH(76, 'Detalles movimientos'!$W$5:$W$1021, 0)), "") | H85: =IFERROR(INDEX('Detalles movimientos'!I$5:I$1021, MATCH(76, 'Detalles movimientos'!$W$5:$W$1021, 0)), "") | I85: =IFERROR(INDEX('Detalles movimientos'!M$5:M$1021, MATCH(76, 'Detalles movimientos'!$W$5:$W$1021, 0)), "") | J85: =IFERROR(INDEX('Detalles movimientos'!N$5:N$1021, MATCH(76, 'Detalles movimientos'!$W$5:$W$1021, 0)), "") | K85: =IFERROR(INDEX('Detalles movimientos'!O$5:O$1021, MATCH(76, 'Detalles movimientos'!$W$5:$W$1021, 0)), "") | L85: =IFERROR(INDEX('Detalles movimientos'!P$5:P$1021, MATCH(76, 'Detalles movimientos'!$W$5:$W$1021, 0)), "") | M85: =IFERROR(INDEX('Detalles movimientos'!S$5:S$1021, MATCH(76, 'Detalles movimientos'!$W$5:$W$1021, 0)), "")
B86: =IFERROR(INDEX('Detalles movimientos'!C$5:C$1021, MATCH(77, 'Detalles movimientos'!$W$5:$W$1021, 0)), "") | C86: =IFERROR(INDEX('Detalles movimientos'!D$5:D$1021, MATCH(77, 'Detalles movimientos'!$W$5:$W$1021, 0)), "") | D86: =IFERROR(INDEX('Detalles movimientos'!E$5:E$1021, MATCH(77, 'Detalles movimientos'!$W$5:$W$1021, 0)), "") | E86: =IFERROR(INDEX('Detalles movimientos'!F$5:F$1021, MATCH(77, 'Detalles movimientos'!$W$5:$W$1021, 0)), "") | F86: =IFERROR(INDEX('Detalles movimientos'!G$5:G$1021, MATCH(77, 'Detalles movimientos'!$W$5:$W$1021, 0)), "") | G86: =IFERROR(INDEX('Detalles movimientos'!H$5:H$1021, MATCH(77, 'Detalles movimientos'!$W$5:$W$1021, 0)), "") | H86: =IFERROR(INDEX('Detalles movimientos'!I$5:I$1021, MATCH(77, 'Detalles movimientos'!$W$5:$W$1021, 0)), "") | I86: =IFERROR(INDEX('Detalles movimientos'!M$5:M$1021, MATCH(77, 'Detalles movimientos'!$W$5:$W$1021, 0)), "") | J86: =IFERROR(INDEX('Detalles movimientos'!N$5:N$1021, MATCH(77, 'Detalles movimientos'!$W$5:$W$1021, 0)), "") | K86: =IFERROR(INDEX('Detalles movimientos'!O$5:O$1021, MATCH(77, 'Detalles movimientos'!$W$5:$W$1021, 0)), "") | L86: =IFERROR(INDEX('Detalles movimientos'!P$5:P$1021, MATCH(77, 'Detalles movimientos'!$W$5:$W$1021, 0)), "") | M86: =IFERROR(INDEX('Detalles movimientos'!S$5:S$1021, MATCH(77, 'Detalles movimientos'!$W$5:$W$1021, 0)), "")
B87: =IFERROR(INDEX('Detalles movimientos'!C$5:C$1021, MATCH(78, 'Detalles movimientos'!$W$5:$W$1021, 0)), "") | C87: =IFERROR(INDEX('Detalles movimientos'!D$5:D$1021, MATCH(78, 'Detalles movimientos'!$W$5:$W$1021, 0)), "") | D87: =IFERROR(INDEX('Detalles movimientos'!E$5:E$1021, MATCH(78, 'Detalles movimientos'!$W$5:$W$1021, 0)), "") | E87: =IFERROR(INDEX('Detalles movimientos'!F$5:F$1021, MATCH(78, 'Detalles movimientos'!$W$5:$W$1021, 0)), "") | F87: =IFERROR(INDEX('Detalles movimientos'!G$5:G$1021, MATCH(78, 'Detalles movimientos'!$W$5:$W$1021, 0)), "") | G87: =IFERROR(INDEX('Detalles movimientos'!H$5:H$1021, MATCH(78, 'Detalles movimientos'!$W$5:$W$1021, 0)), "") | H87: =IFERROR(INDEX('Detalles movimientos'!I$5:I$1021, MATCH(78, 'Detalles movimientos'!$W$5:$W$1021, 0)), "") | I87: =IFERROR(INDEX('Detalles movimientos'!M$5:M$1021, MATCH(78, 'Detalles movimientos'!$W$5:$W$1021, 0)), "") | J87: =IFERROR(INDEX('Detalles movimientos'!N$5:N$1021, MATCH(78, 'Detalles movimientos'!$W$5:$W$1021, 0)), "") | K87: =IFERROR(INDEX('Detalles movimientos'!O$5:O$1021, MATCH(78, 'Detalles movimientos'!$W$5:$W$1021, 0)), "") | L87: =IFERROR(INDEX('Detalles movimientos'!P$5:P$1021, MATCH(78, 'Detalles movimientos'!$W$5:$W$1021, 0)), "") | M87: =IFERROR(INDEX('Detalles movimientos'!S$5:S$1021, MATCH(78, 'Detalles movimientos'!$W$5:$W$1021, 0)), "")
B88: =IFERROR(INDEX('Detalles movimientos'!C$5:C$1021, MATCH(79, 'Detalles movimientos'!$W$5:$W$1021, 0)), "") | C88: =IFERROR(INDEX('Detalles movimientos'!D$5:D$1021, MATCH(79, 'Detalles movimientos'!$W$5:$W$1021, 0)), "") | D88: =IFERROR(INDEX('Detalles movimientos'!E$5:E$1021, MATCH(79, 'Detalles movimientos'!$W$5:$W$1021, 0)), "") | E88: =IFERROR(INDEX('Detalles movimientos'!F$5:F$1021, MATCH(79, 'Detalles movimientos'!$W$5:$W$1021, 0)), "") | F88: =IFERROR(INDEX('Detalles movimientos'!G$5:G$1021, MATCH(79, 'Detalles movimientos'!$W$5:$W$1021, 0)), "") | G88: =IFERROR(INDEX('Detalles movimientos'!H$5:H$1021, MATCH(79, 'Detalles movimientos'!$W$5:$W$1021, 0)), "") | H88: =IFERROR(INDEX('Detalles movimientos'!I$5:I$1021, MATCH(79, 'Detalles movimientos'!$W$5:$W$1021, 0)), "") | I88: =IFERROR(INDEX('Detalles movimientos'!M$5:M$1021, MATCH(79, 'Detalles movimientos'!$W$5:$W$1021, 0)), "") | J88: =IFERROR(INDEX('Detalles movimientos'!N$5:N$1021, MATCH(79, 'Detalles movimientos'!$W$5:$W$1021, 0)), "") | K88: =IFERROR(INDEX('Detalles movimientos'!O$5:O$1021, MATCH(79, 'Detalles movimientos'!$W$5:$W$1021, 0)), "") | L88: =IFERROR(INDEX('Detalles movimientos'!P$5:P$1021, MATCH(79, 'Detalles movimientos'!$W$5:$W$1021, 0)), "") | M88: =IFERROR(INDEX('Detalles movimientos'!S$5:S$1021, MATCH(79, 'Detalles movimientos'!$W$5:$W$1021, 0)), "")
B89: =IFERROR(INDEX('Detalles movimientos'!C$5:C$1021, MATCH(80, 'Detalles movimientos'!$W$5:$W$1021, 0)), "") | C89: =IFERROR(INDEX('Detalles movimientos'!D$5:D$1021, MATCH(80, 'Detalles movimientos'!$W$5:$W$1021, 0)), "") | D89: =IFERROR(INDEX('Detalles movimientos'!E$5:E$1021, MATCH(80, 'Detalles movimientos'!$W$5:$W$1021, 0)), "") | E89: =IFERROR(INDEX('Detalles movimientos'!F$5:F$1021, MATCH(80, 'Detalles movimientos'!$W$5:$W$1021, 0)), "") | F89: =IFERROR(INDEX('Detalles movimientos'!G$5:G$1021, MATCH(80, 'Detalles movimientos'!$W$5:$W$1021, 0)), "") | G89: =IFERROR(INDEX('Detalles movimientos'!H$5:H$1021, MATCH(80, 'Detalles movimientos'!$W$5:$W$1021, 0)), "") | H89: =IFERROR(INDEX('Detalles movimientos'!I$5:I$1021, MATCH(80, 'Detalles movimientos'!$W$5:$W$1021, 0)), "") | I89: =IFERROR(INDEX('Detalles movimientos'!M$5:M$1021, MATCH(80, 'Detalles movimientos'!$W$5:$W$1021, 0)), "") | J89: =IFERROR(INDEX('Detalles movimientos'!N$5:N$1021, MATCH(80, 'Detalles movimientos'!$W$5:$W$1021, 0)), "") | K89: =IFERROR(INDEX('Detalles movimientos'!O$5:O$1021, MATCH(80, 'Detalles movimientos'!$W$5:$W$1021, 0)), "") | L89: =IFERROR(INDEX('Detalles movimientos'!P$5:P$1021, MATCH(80, 'Detalles movimientos'!$W$5:$W$1021, 0)), "") | M89: =IFERROR(INDEX('Detalles movimientos'!S$5:S$1021, MATCH(80, 'Detalles movimientos'!$W$5:$W$1021, 0)), "")
B90: =IFERROR(INDEX('Detalles movimientos'!C$5:C$1021, MATCH(81, 'Detalles movimientos'!$W$5:$W$1021, 0)), "") | C90: =IFERROR(INDEX('Detalles movimientos'!D$5:D$1021, MATCH(81, 'Detalles movimientos'!$W$5:$W$1021, 0)), "") | D90: =IFERROR(INDEX('Detalles movimientos'!E$5:E$1021, MATCH(81, 'Detalles movimientos'!$W$5:$W$1021, 0)), "") | E90: =IFERROR(INDEX('Detalles movimientos'!F$5:F$1021, MATCH(81, 'Detalles movimientos'!$W$5:$W$1021, 0)), "") | F90: =IFERROR(INDEX('Detalles movimientos'!G$5:G$1021, MATCH(81, 'Detalles movimientos'!$W$5:$W$1021, 0)), "") | G90: =IFERROR(INDEX('Detalles movimientos'!H$5:H$1021, MATCH(81, 'Detalles movimientos'!$W$5:$W$1021, 0)), "") | H90: =IFERROR(INDEX('Detalles movimientos'!I$5:I$1021, MATCH(81, 'Detalles movimientos'!$W$5:$W$1021, 0)), "") | I90: =IFERROR(INDEX('Detalles movimientos'!M$5:M$1021, MATCH(81, 'Detalles movimientos'!$W$5:$W$1021, 0)), "") | J90: =IFERROR(INDEX('Detalles movimientos'!N$5:N$1021, MATCH(81, 'Detalles movimientos'!$W$5:$W$1021, 0)), "") | K90: =IFERROR(INDEX('Detalles movimientos'!O$5:O$1021, MATCH(81, 'Detalles movimientos'!$W$5:$W$1021, 0)), "") | L90: =IFERROR(INDEX('Detalles movimientos'!P$5:P$1021, MATCH(81, 'Detalles movimientos'!$W$5:$W$1021, 0)), "") | M90: =IFERROR(INDEX('Detalles movimientos'!S$5:S$1021, MATCH(81, 'Detalles movimientos'!$W$5:$W$1021, 0)), "")
B91: =IFERROR(INDEX('Detalles movimientos'!C$5:C$1021, MATCH(82, 'Detalles movimientos'!$W$5:$W$1021, 0)), "") | C91: =IFERROR(INDEX('Detalles movimientos'!D$5:D$1021, MATCH(82, 'Detalles movimientos'!$W$5:$W$1021, 0)), "") | D91: =IFERROR(INDEX('Detalles movimientos'!E$5:E$1021, MATCH(82, 'Detalles movimientos'!$W$5:$W$1021, 0)), "") | E91: =IFERROR(INDEX('Detalles movimientos'!F$5:F$1021, MATCH(82, 'Detalles movimientos'!$W$5:$W$1021, 0)), "") | F91: =IFERROR(INDEX('Detalles movimientos'!G$5:G$1021, MATCH(82, 'Detalles movimientos'!$W$5:$W$1021, 0)), "") | G91: =IFERROR(INDEX('Detalles movimientos'!H$5:H$1021, MATCH(82, 'Detalles movimientos'!$W$5:$W$1021, 0)), "") | H91: =IFERROR(INDEX('Detalles movimientos'!I$5:I$1021, MATCH(82, 'Detalles movimientos'!$W$5:$W$1021, 0)), "") | I91: =IFERROR(INDEX('Detalles movimientos'!M$5:M$1021, MATCH(82, 'Detalles movimientos'!$W$5:$W$1021, 0)), "") | J91: =IFERROR(INDEX('Detalles movimientos'!N$5:N$1021, MATCH(82, 'Detalles movimientos'!$W$5:$W$1021, 0)), "") | K91: =IFERROR(INDEX('Detalles movimientos'!O$5:O$1021, MATCH(82, 'Detalles movimientos'!$W$5:$W$1021, 0)), "") | L91: =IFERROR(INDEX('Detalles movimientos'!P$5:P$1021, MATCH(82, 'Detalles movimientos'!$W$5:$W$1021, 0)), "") | M91: =IFERROR(INDEX('Detalles movimientos'!S$5:S$1021, MATCH(82, 'Detalles movimientos'!$W$5:$W$1021, 0)), "")
B92: =IFERROR(INDEX('Detalles movimientos'!C$5:C$1021, MATCH(83, 'Detalles movimientos'!$W$5:$W$1021, 0)), "") | C92: =IFERROR(INDEX('Detalles movimientos'!D$5:D$1021, MATCH(83, 'Detalles movimientos'!$W$5:$W$1021, 0)), "") | D92: =IFERROR(INDEX('Detalles movimientos'!E$5:E$1021, MATCH(83, 'Detalles movimientos'!$W$5:$W$1021, 0)), "") | E92: =IFERROR(INDEX('Detalles movimientos'!F$5:F$1021, MATCH(83, 'Detalles movimientos'!$W$5:$W$1021, 0)), "") | F92: =IFERROR(INDEX('Detalles movimientos'!G$5:G$1021, MATCH(83, 'Detalles movimientos'!$W$5:$W$1021, 0)), "") | G92: =IFERROR(INDEX('Detalles movimientos'!H$5:H$1021, MATCH(83, 'Detalles movimientos'!$W$5:$W$1021, 0)), "") | H92: =IFERROR(INDEX('Detalles movimientos'!I$5:I$1021, MATCH(83, 'Detalles movimientos'!$W$5:$W$1021, 0)), "") | I92: =IFERROR(INDEX('Detalles movimientos'!M$5:M$1021, MATCH(83, 'Detalles movimientos'!$W$5:$W$1021, 0)), "") | J92: =IFERROR(INDEX('Detalles movimientos'!N$5:N$1021, MATCH(83, 'Detalles movimientos'!$W$5:$W$1021, 0)), "") | K92: =IFERROR(INDEX('Detalles movimientos'!O$5:O$1021, MATCH(83, 'Detalles movimientos'!$W$5:$W$1021, 0)), "") | L92: =IFERROR(INDEX('Detalles movimientos'!P$5:P$1021, MATCH(83, 'Detalles movimientos'!$W$5:$W$1021, 0)), "") | M92: =IFERROR(INDEX('Detalles movimientos'!S$5:S$1021, MATCH(83, 'Detalles movimientos'!$W$5:$W$1021, 0)), "")
B93: =IFERROR(INDEX('Detalles movimientos'!C$5:C$1021, MATCH(84, 'Detalles movimientos'!$W$5:$W$1021, 0)), "") | C93: =IFERROR(INDEX('Detalles movimientos'!D$5:D$1021, MATCH(84, 'Detalles movimientos'!$W$5:$W$1021, 0)), "") | D93: =IFERROR(INDEX('Detalles movimientos'!E$5:E$1021, MATCH(84, 'Detalles movimientos'!$W$5:$W$1021, 0)), "") | E93: =IFERROR(INDEX('Detalles movimientos'!F$5:F$1021, MATCH(84, 'Detalles movimientos'!$W$5:$W$1021, 0)), "") | F93: =IFERROR(INDEX('Detalles movimientos'!G$5:G$1021, MATCH(84, 'Detalles movimientos'!$W$5:$W$1021, 0)), "") | G93: =IFERROR(INDEX('Detalles movimientos'!H$5:H$1021, MATCH(84, 'Detalles movimientos'!$W$5:$W$1021, 0)), "") | H93: =IFERROR(INDEX('Detalles movimientos'!I$5:I$1021, MATCH(84, 'Detalles movimientos'!$W$5:$W$1021, 0)), "") | I93: =IFERROR(INDEX('Detalles movimientos'!M$5:M$1021, MATCH(84, 'Detalles movimientos'!$W$5:$W$1021, 0)), "") | J93: =IFERROR(INDEX('Detalles movimientos'!N$5:N$1021, MATCH(84, 'Detalles movimientos'!$W$5:$W$1021, 0)), "") | K93: =IFERROR(INDEX('Detalles movimientos'!O$5:O$1021, MATCH(84, 'Detalles movimientos'!$W$5:$W$1021, 0)), "") | L93: =IFERROR(INDEX('Detalles movimientos'!P$5:P$1021, MATCH(84, 'Detalles movimientos'!$W$5:$W$1021, 0)), "") | M93: =IFERROR(INDEX('Detalles movimientos'!S$5:S$1021, MATCH(84, 'Detalles movimientos'!$W$5:$W$1021, 0)), "")
B94: =IFERROR(INDEX('Detalles movimientos'!C$5:C$1021, MATCH(85, 'Detalles movimientos'!$W$5:$W$1021, 0)), "") | C94: =IFERROR(INDEX('Detalles movimientos'!D$5:D$1021, MATCH(85, 'Detalles movimientos'!$W$5:$W$1021, 0)), "") | D94: =IFERROR(INDEX('Detalles movimientos'!E$5:E$1021, MATCH(85, 'Detalles movimientos'!$W$5:$W$1021, 0)), "") | E94: =IFERROR(INDEX('Detalles movimientos'!F$5:F$1021, MATCH(85, 'Detalles movimientos'!$W$5:$W$1021, 0)), "") | F94: =IFERROR(INDEX('Detalles movimientos'!G$5:G$1021, MATCH(85, 'Detalles movimientos'!$W$5:$W$1021, 0)), "") | G94: =IFERROR(INDEX('Detalles movimientos'!H$5:H$1021, MATCH(85, 'Detalles movimientos'!$W$5:$W$1021, 0)), "") | H94: =IFERROR(INDEX('Detalles movimientos'!I$5:I$1021, MATCH(85, 'Detalles movimientos'!$W$5:$W$1021, 0)), "") | I94: =IFERROR(INDEX('Detalles movimientos'!M$5:M$1021, MATCH(85, 'Detalles movimientos'!$W$5:$W$1021, 0)), "") | J94: =IFERROR(INDEX('Detalles movimientos'!N$5:N$1021, MATCH(85, 'Detalles movimientos'!$W$5:$W$1021, 0)), "") | K94: =IFERROR(INDEX('Detalles movimientos'!O$5:O$1021, MATCH(85, 'Detalles movimientos'!$W$5:$W$1021, 0)), "") | L94: =IFERROR(INDEX('Detalles movimientos'!P$5:P$1021, MATCH(85, 'Detalles movimientos'!$W$5:$W$1021, 0)), "") | M94: =IFERROR(INDEX('Detalles movimientos'!S$5:S$1021, MATCH(85, 'Detalles movimientos'!$W$5:$W$1021, 0)), "")
B95: =IFERROR(INDEX('Detalles movimientos'!C$5:C$1021, MATCH(86, 'Detalles movimientos'!$W$5:$W$1021, 0)), "") | C95: =IFERROR(INDEX('Detalles movimientos'!D$5:D$1021, MATCH(86, 'Detalles movimientos'!$W$5:$W$1021, 0)), "") | D95: =IFERROR(INDEX('Detalles movimientos'!E$5:E$1021, MATCH(86, 'Detalles movimientos'!$W$5:$W$1021, 0)), "") | E95: =IFERROR(INDEX('Detalles movimientos'!F$5:F$1021, MATCH(86, 'Detalles movimientos'!$W$5:$W$1021, 0)), "") | F95: =IFERROR(INDEX('Detalles movimientos'!G$5:G$1021, MATCH(86, 'Detalles movimientos'!$W$5:$W$1021, 0)), "") | G95: =IFERROR(INDEX('Detalles movimientos'!H$5:H$1021, MATCH(86, 'Detalles movimientos'!$W$5:$W$1021, 0)), "") | H95: =IFERROR(INDEX('Detalles movimientos'!I$5:I$1021, MATCH(86, 'Detalles movimientos'!$W$5:$W$1021, 0)), "") | I95: =IFERROR(INDEX('Detalles movimientos'!M$5:M$1021, MATCH(86, 'Detalles movimientos'!$W$5:$W$1021, 0)), "") | J95: =IFERROR(INDEX('Detalles movimientos'!N$5:N$1021, MATCH(86, 'Detalles movimientos'!$W$5:$W$1021, 0)), "") | K95: =IFERROR(INDEX('Detalles movimientos'!O$5:O$1021, MATCH(86, 'Detalles movimientos'!$W$5:$W$1021, 0)), "") | L95: =IFERROR(INDEX('Detalles movimientos'!P$5:P$1021, MATCH(86, 'Detalles movimientos'!$W$5:$W$1021, 0)), "") | M95: =IFERROR(INDEX('Detalles movimientos'!S$5:S$1021, MATCH(86, 'Detalles movimientos'!$W$5:$W$1021, 0)), "")
B96: =IFERROR(INDEX('Detalles movimientos'!C$5:C$1021, MATCH(87, 'Detalles movimientos'!$W$5:$W$1021, 0)), "") | C96: =IFERROR(INDEX('Detalles movimientos'!D$5:D$1021, MATCH(87, 'Detalles movimientos'!$W$5:$W$1021, 0)), "") | D96: =IFERROR(INDEX('Detalles movimientos'!E$5:E$1021, MATCH(87, 'Detalles movimientos'!$W$5:$W$1021, 0)), "") | E96: =IFERROR(INDEX('Detalles movimientos'!F$5:F$1021, MATCH(87, 'Detalles movimientos'!$W$5:$W$1021, 0)), "") | F96: =IFERROR(INDEX('Detalles movimientos'!G$5:G$1021, MATCH(87, 'Detalles movimientos'!$W$5:$W$1021, 0)), "") | G96: =IFERROR(INDEX('Detalles movimientos'!H$5:H$1021, MATCH(87, 'Detalles movimientos'!$W$5:$W$1021, 0)), "") | H96: =IFERROR(INDEX('Detalles movimientos'!I$5:I$1021, MATCH(87, 'Detalles movimientos'!$W$5:$W$1021, 0)), "") | I96: =IFERROR(INDEX('Detalles movimientos'!M$5:M$1021, MATCH(87, 'Detalles movimientos'!$W$5:$W$1021, 0)), "") | J96: =IFERROR(INDEX('Detalles movimientos'!N$5:N$1021, MATCH(87, 'Detalles movimientos'!$W$5:$W$1021, 0)), "") | K96: =IFERROR(INDEX('Detalles movimientos'!O$5:O$1021, MATCH(87, 'Detalles movimientos'!$W$5:$W$1021, 0)), "") | L96: =IFERROR(INDEX('Detalles movimientos'!P$5:P$1021, MATCH(87, 'Detalles movimientos'!$W$5:$W$1021, 0)), "") | M96: =IFERROR(INDEX('Detalles movimientos'!S$5:S$1021, MATCH(87, 'Detalles movimientos'!$W$5:$W$1021, 0)), "")
B97: =IFERROR(INDEX('Detalles movimientos'!C$5:C$1021, MATCH(88, 'Detalles movimientos'!$W$5:$W$1021, 0)), "") | C97: =IFERROR(INDEX('Detalles movimientos'!D$5:D$1021, MATCH(88, 'Detalles movimientos'!$W$5:$W$1021, 0)), "") | D97: =IFERROR(INDEX('Detalles movimientos'!E$5:E$1021, MATCH(88, 'Detalles movimientos'!$W$5:$W$1021, 0)), "") | E97: =IFERROR(INDEX('Detalles movimientos'!F$5:F$1021, MATCH(88, 'Detalles movimientos'!$W$5:$W$1021, 0)), "") | F97: =IFERROR(INDEX('Detalles movimientos'!G$5:G$1021, MATCH(88, 'Detalles movimientos'!$W$5:$W$1021, 0)), "") | G97: =IFERROR(INDEX('Detalles movimientos'!H$5:H$1021, MATCH(88, 'Detalles movimientos'!$W$5:$W$1021, 0)), "") | H97: =IFERROR(INDEX('Detalles movimientos'!I$5:I$1021, MATCH(88, 'Detalles movimientos'!$W$5:$W$1021, 0)), "") | I97: =IFERROR(INDEX('Detalles movimientos'!M$5:M$1021, MATCH(88, 'Detalles movimientos'!$W$5:$W$1021, 0)), "") | J97: =IFERROR(INDEX('Detalles movimientos'!N$5:N$1021, MATCH(88, 'Detalles movimientos'!$W$5:$W$1021, 0)), "") | K97: =IFERROR(INDEX('Detalles movimientos'!O$5:O$1021, MATCH(88, 'Detalles movimientos'!$W$5:$W$1021, 0)), "") | L97: =IFERROR(INDEX('Detalles movimientos'!P$5:P$1021, MATCH(88, 'Detalles movimientos'!$W$5:$W$1021, 0)), "") | M97: =IFERROR(INDEX('Detalles movimientos'!S$5:S$1021, MATCH(88, 'Detalles movimientos'!$W$5:$W$1021, 0)), "")
B98: =IFERROR(INDEX('Detalles movimientos'!C$5:C$1021, MATCH(89, 'Detalles movimientos'!$W$5:$W$1021, 0)), "") | C98: =IFERROR(INDEX('Detalles movimientos'!D$5:D$1021, MATCH(89, 'Detalles movimientos'!$W$5:$W$1021, 0)), "") | D98: =IFERROR(INDEX('Detalles movimientos'!E$5:E$1021, MATCH(89, 'Detalles movimientos'!$W$5:$W$1021, 0)), "") | E98: =IFERROR(INDEX('Detalles movimientos'!F$5:F$1021, MATCH(89, 'Detalles movimientos'!$W$5:$W$1021, 0)), "") | F98: =IFERROR(INDEX('Detalles movimientos'!G$5:G$1021, MATCH(89, 'Detalles movimientos'!$W$5:$W$1021, 0)), "") | G98: =IFERROR(INDEX('Detalles movimientos'!H$5:H$1021, MATCH(89, 'Detalles movimientos'!$W$5:$W$1021, 0)), "") | H98: =IFERROR(INDEX('Detalles movimientos'!I$5:I$1021, MATCH(89, 'Detalles movimientos'!$W$5:$W$1021, 0)), "") | I98: =IFERROR(INDEX('Detalles movimientos'!M$5:M$1021, MATCH(89, 'Detalles movimientos'!$W$5:$W$1021, 0)), "") | J98: =IFERROR(INDEX('Detalles movimientos'!N$5:N$1021, MATCH(89, 'Detalles movimientos'!$W$5:$W$1021, 0)), "") | K98: =IFERROR(INDEX('Detalles movimientos'!O$5:O$1021, MATCH(89, 'Detalles movimientos'!$W$5:$W$1021, 0)), "") | L98: =IFERROR(INDEX('Detalles movimientos'!P$5:P$1021, MATCH(89, 'Detalles movimientos'!$W$5:$W$1021, 0)), "") | M98: =IFERROR(INDEX('Detalles movimientos'!S$5:S$1021, MATCH(89, 'Detalles movimientos'!$W$5:$W$1021, 0)), "")
B99: =IFERROR(INDEX('Detalles movimientos'!C$5:C$1021, MATCH(90, 'Detalles movimientos'!$W$5:$W$1021, 0)), "") | C99: =IFERROR(INDEX('Detalles movimientos'!D$5:D$1021, MATCH(90, 'Detalles movimientos'!$W$5:$W$1021, 0)), "") | D99: =IFERROR(INDEX('Detalles movimientos'!E$5:E$1021, MATCH(90, 'Detalles movimientos'!$W$5:$W$1021, 0)), "") | E99: =IFERROR(INDEX('Detalles movimientos'!F$5:F$1021, MATCH(90, 'Detalles movimientos'!$W$5:$W$1021, 0)), "") | F99: =IFERROR(INDEX('Detalles movimientos'!G$5:G$1021, MATCH(90, 'Detalles movimientos'!$W$5:$W$1021, 0)), "") | G99: =IFERROR(INDEX('Detalles movimientos'!H$5:H$1021, MATCH(90, 'Detalles movimientos'!$W$5:$W$1021, 0)), "") | H99: =IFERROR(INDEX('Detalles movimientos'!I$5:I$1021, MATCH(90, 'Detalles movimientos'!$W$5:$W$1021, 0)), "") | I99: =IFERROR(INDEX('Detalles movimientos'!M$5:M$1021, MATCH(90, 'Detalles movimientos'!$W$5:$W$1021, 0)), "") | J99: =IFERROR(INDEX('Detalles movimientos'!N$5:N$1021, MATCH(90, 'Detalles movimientos'!$W$5:$W$1021, 0)), "") | K99: =IFERROR(INDEX('Detalles movimientos'!O$5:O$1021, MATCH(90, 'Detalles movimientos'!$W$5:$W$1021, 0)), "") | L99: =IFERROR(INDEX('Detalles movimientos'!P$5:P$1021, MATCH(90, 'Detalles movimientos'!$W$5:$W$1021, 0)), "") | M99: =IFERROR(INDEX('Detalles movimientos'!S$5:S$1021, MATCH(90, 'Detalles movimientos'!$W$5:$W$1021, 0)), "")
B100: =IFERROR(INDEX('Detalles movimientos'!C$5:C$1021, MATCH(91, 'Detalles movimientos'!$W$5:$W$1021, 0)), "") | C100: =IFERROR(INDEX('Detalles movimientos'!D$5:D$1021, MATCH(91, 'Detalles movimientos'!$W$5:$W$1021, 0)), "") | D100: =IFERROR(INDEX('Detalles movimientos'!E$5:E$1021, MATCH(91, 'Detalles movimientos'!$W$5:$W$1021, 0)), "") | E100: =IFERROR(INDEX('Detalles movimientos'!F$5:F$1021, MATCH(91, 'Detalles movimientos'!$W$5:$W$1021, 0)), "") | F100: =IFERROR(INDEX('Detalles movimientos'!G$5:G$1021, MATCH(91, 'Detalles movimientos'!$W$5:$W$1021, 0)), "") | G100: =IFERROR(INDEX('Detalles movimientos'!H$5:H$1021, MATCH(91, 'Detalles movimientos'!$W$5:$W$1021, 0)), "") | H100: =IFERROR(INDEX('Detalles movimientos'!I$5:I$1021, MATCH(91, 'Detalles movimientos'!$W$5:$W$1021, 0)), "") | I100: =IFERROR(INDEX('Detalles movimientos'!M$5:M$1021, MATCH(91, 'Detalles movimientos'!$W$5:$W$1021, 0)), "") | J100: =IFERROR(INDEX('Detalles movimientos'!N$5:N$1021, MATCH(91, 'Detalles movimientos'!$W$5:$W$1021, 0)), "") | K100: =IFERROR(INDEX('Detalles movimientos'!O$5:O$1021, MATCH(91, 'Detalles movimientos'!$W$5:$W$1021, 0)), "") | L100: =IFERROR(INDEX('Detalles movimientos'!P$5:P$1021, MATCH(91, 'Detalles movimientos'!$W$5:$W$1021, 0)), "") | M100: =IFERROR(INDEX('Detalles movimientos'!S$5:S$1021, MATCH(91, 'Detalles movimientos'!$W$5:$W$1021, 0)), "")
B101: =IFERROR(INDEX('Detalles movimientos'!C$5:C$1021, MATCH(92, 'Detalles movimientos'!$W$5:$W$1021, 0)), "") | C101: =IFERROR(INDEX('Detalles movimientos'!D$5:D$1021, MATCH(92, 'Detalles movimientos'!$W$5:$W$1021, 0)), "") | D101: =IFERROR(INDEX('Detalles movimientos'!E$5:E$1021, MATCH(92, 'Detalles movimientos'!$W$5:$W$1021, 0)), "") | E101: =IFERROR(INDEX('Detalles movimientos'!F$5:F$1021, MATCH(92, 'Detalles movimientos'!$W$5:$W$1021, 0)), "") | F101: =IFERROR(INDEX('Detalles movimientos'!G$5:G$1021, MATCH(92, 'Detalles movimientos'!$W$5:$W$1021, 0)), "") | G101: =IFERROR(INDEX('Detalles movimientos'!H$5:H$1021, MATCH(92, 'Detalles movimientos'!$W$5:$W$1021, 0)), "") | H101: =IFERROR(INDEX('Detalles movimientos'!I$5:I$1021, MATCH(92, 'Detalles movimientos'!$W$5:$W$1021, 0)), "") | I101: =IFERROR(INDEX('Detalles movimientos'!M$5:M$1021, MATCH(92, 'Detalles movimientos'!$W$5:$W$1021, 0)), "") | J101: =IFERROR(INDEX('Detalles movimientos'!N$5:N$1021, MATCH(92, 'Detalles movimientos'!$W$5:$W$1021, 0)), "") | K101: =IFERROR(INDEX('Detalles movimientos'!O$5:O$1021, MATCH(92, 'Detalles movimientos'!$W$5:$W$1021, 0)), "") | L101: =IFERROR(INDEX('Detalles movimientos'!P$5:P$1021, MATCH(92, 'Detalles movimientos'!$W$5:$W$1021, 0)), "") | M101: =IFERROR(INDEX('Detalles movimientos'!S$5:S$1021, MATCH(92, 'Detalles movimientos'!$W$5:$W$1021, 0)), "")
B102: =IFERROR(INDEX('Detalles movimientos'!C$5:C$1021, MATCH(93, 'Detalles movimientos'!$W$5:$W$1021, 0)), "") | C102: =IFERROR(INDEX('Detalles movimientos'!D$5:D$1021, MATCH(93, 'Detalles movimientos'!$W$5:$W$1021, 0)), "") | D102: =IFERROR(INDEX('Detalles movimientos'!E$5:E$1021, MATCH(93, 'Detalles movimientos'!$W$5:$W$1021, 0)), "") | E102: =IFERROR(INDEX('Detalles movimientos'!F$5:F$1021, MATCH(93, 'Detalles movimientos'!$W$5:$W$1021, 0)), "") | F102: =IFERROR(INDEX('Detalles movimientos'!G$5:G$1021, MATCH(93, 'Detalles movimientos'!$W$5:$W$1021, 0)), "") | G102: =IFERROR(INDEX('Detalles movimientos'!H$5:H$1021, MATCH(93, 'Detalles movimientos'!$W$5:$W$1021, 0)), "") | H102: =IFERROR(INDEX('Detalles movimientos'!I$5:I$1021, MATCH(93, 'Detalles movimientos'!$W$5:$W$1021, 0)), "") | I102: =IFERROR(INDEX('Detalles movimientos'!M$5:M$1021, MATCH(93, 'Detalles movimientos'!$W$5:$W$1021, 0)), "") | J102: =IFERROR(INDEX('Detalles movimientos'!N$5:N$1021, MATCH(93, 'Detalles movimientos'!$W$5:$W$1021, 0)), "") | K102: =IFERROR(INDEX('Detalles movimientos'!O$5:O$1021, MATCH(93, 'Detalles movimientos'!$W$5:$W$1021, 0)), "") | L102: =IFERROR(INDEX('Detalles movimientos'!P$5:P$1021, MATCH(93, 'Detalles movimientos'!$W$5:$W$1021, 0)), "") | M102: =IFERROR(INDEX('Detalles movimientos'!S$5:S$1021, MATCH(93, 'Detalles movimientos'!$W$5:$W$1021, 0)), "")
B103: =IFERROR(INDEX('Detalles movimientos'!C$5:C$1021, MATCH(94, 'Detalles movimientos'!$W$5:$W$1021, 0)), "") | C103: =IFERROR(INDEX('Detalles movimientos'!D$5:D$1021, MATCH(94, 'Detalles movimientos'!$W$5:$W$1021, 0)), "") | D103: =IFERROR(INDEX('Detalles movimientos'!E$5:E$1021, MATCH(94, 'Detalles movimientos'!$W$5:$W$1021, 0)), "") | E103: =IFERROR(INDEX('Detalles movimientos'!F$5:F$1021, MATCH(94, 'Detalles movimientos'!$W$5:$W$1021, 0)), "") | F103: =IFERROR(INDEX('Detalles movimientos'!G$5:G$1021, MATCH(94, 'Detalles movimientos'!$W$5:$W$1021, 0)), "") | G103: =IFERROR(INDEX('Detalles movimientos'!H$5:H$1021, MATCH(94, 'Detalles movimientos'!$W$5:$W$1021, 0)), "") | H103: =IFERROR(INDEX('Detalles movimientos'!I$5:I$1021, MATCH(94, 'Detalles movimientos'!$W$5:$W$1021, 0)), "") | I103: =IFERROR(INDEX('Detalles movimientos'!M$5:M$1021, MATCH(94, 'Detalles movimientos'!$W$5:$W$1021, 0)), "") | J103: =IFERROR(INDEX('Detalles movimientos'!N$5:N$1021, MATCH(94, 'Detalles movimientos'!$W$5:$W$1021, 0)), "") | K103: =IFERROR(INDEX('Detalles movimientos'!O$5:O$1021, MATCH(94, 'Detalles movimientos'!$W$5:$W$1021, 0)), "") | L103: =IFERROR(INDEX('Detalles movimientos'!P$5:P$1021, MATCH(94, 'Detalles movimientos'!$W$5:$W$1021, 0)), "") | M103: =IFERROR(INDEX('Detalles movimientos'!S$5:S$1021, MATCH(94, 'Detalles movimientos'!$W$5:$W$1021, 0)), "")
B104: =IFERROR(INDEX('Detalles movimientos'!C$5:C$1021, MATCH(95, 'Detalles movimientos'!$W$5:$W$1021, 0)), "") | C104: =IFERROR(INDEX('Detalles movimientos'!D$5:D$1021, MATCH(95, 'Detalles movimientos'!$W$5:$W$1021, 0)), "") | D104: =IFERROR(INDEX('Detalles movimientos'!E$5:E$1021, MATCH(95, 'Detalles movimientos'!$W$5:$W$1021, 0)), "") | E104: =IFERROR(INDEX('Detalles movimientos'!F$5:F$1021, MATCH(95, 'Detalles movimientos'!$W$5:$W$1021, 0)), "") | F104: =IFERROR(INDEX('Detalles movimientos'!G$5:G$1021, MATCH(95, 'Detalles movimientos'!$W$5:$W$1021, 0)), "") | G104: =IFERROR(INDEX('Detalles movimientos'!H$5:H$1021, MATCH(95, 'Detalles movimientos'!$W$5:$W$1021, 0)), "") | H104: =IFERROR(INDEX('Detalles movimientos'!I$5:I$1021, MATCH(95, 'Detalles movimientos'!$W$5:$W$1021, 0)), "") | I104: =IFERROR(INDEX('Detalles movimientos'!M$5:M$1021, MATCH(95, 'Detalles movimientos'!$W$5:$W$1021, 0)), "") | J104: =IFERROR(INDEX('Detalles movimientos'!N$5:N$1021, MATCH(95, 'Detalles movimientos'!$W$5:$W$1021, 0)), "") | K104: =IFERROR(INDEX('Detalles movimientos'!O$5:O$1021, MATCH(95, 'Detalles movimientos'!$W$5:$W$1021, 0)), "") | L104: =IFERROR(INDEX('Detalles movimientos'!P$5:P$1021, MATCH(95, 'Detalles movimientos'!$W$5:$W$1021, 0)), "") | M104: =IFERROR(INDEX('Detalles movimientos'!S$5:S$1021, MATCH(95, 'Detalles movimientos'!$W$5:$W$1021, 0)), "")
...

Sheet Análisis de Negocio
A1: Dashboard de Análisis de Negocio
A3: Métricas de Inventario (Litros)
A4: Total Litros Comprados (ENAP) | B4: =SUM('Detalles movimientos'!R:R)
A5: Total Litros Vendidos | B5: =SUM('Detalles movimientos'!I:I)
A6: Saldo Actual (Stock) | B6: =B4-B5
A8: Métricas Financieras ($)
A9: Monto Total de Compras (ENAP) | B9: =SUM('Detalles movimientos'!Q:Q)
A10: Total Recaudado (Ventas) | B10: =SUM('Detalles movimientos'!M:M)
A11: Total Comisiones Pagadas | B11: =SUM('Detalles movimientos'!O:O)
A12: Beneficio Bruto | B12: =B10-B9
A13: Beneficio Neto | B13: =B11-B10
A15: Indicadores Clave de Rendimiento (KPIs)
A16: Costo Promedio por Litro | B16: =IF(B4>0, B9/B4, 0)
A17: Precio Promedio de Venta por Litro | B17: =IF(B5>0, B10/B5, 0)
A18: Margen de Ganancia Neto | B18: =IF(B10>0, B13/B10, 0)

Sheet CJ
B2: RESUMEN Y MOVIMIENTOS INDIVIDUALES: CJ (COMISIONISTA JC)
B3: Sincronización en tiempo real - Control de Comisiones y Ventas
B5: TOTAL LITROS | E5: TOTAL VENTAS ($) | H5: COMISIONES PAGADAS ($) | K5: COMISIONES PENDIENTES ($)
B6: =SUMIFS('Detalles movimientos'!I$5:I$1021, 'Detalles movimientos'!F$5:F$1021, "CJ") | E6: =SUMIFS('Detalles movimientos'!M$5:M$1021, 'Detalles movimientos'!F$5:F$1021, "CJ") | H6: =SUMIFS('Detalles movimientos'!O$5:O$1021, 'Detalles movimientos'!F$5:F$1021, "CJ", 'Detalles movimientos'!P$5:P$1021, "*Comision Pagada*") | K6: =SUMIFS('Detalles movimientos'!O$5:O$1021, 'Detalles movimientos'!F$5:F$1021, "CJ", 'Detalles movimientos'!P$5:P$1021, "<>*Comision Pagada*")
B9: PERÍODO COMISIONES PAGADAS: | D9: ="Del " & TEXT(_xlfn.MINIFS('Detalles movimientos'!C$5:C$1021, 'Detalles movimientos'!F$5:F$1021, "CJ", 'Detalles movimientos'!P$5:P$1021, "*Comision Pagada*"), "dd/mm/yyyy") & " al " & TEXT(_xlfn.MAXIFS('Detalles movimientos'!C$5:C$1021, 'Detalles movimientos'!F$5:F$1021, "CJ", 'Detalles movimientos'!P$5:P$1021, "*Comision Pagada*"), "dd/mm/yyyy") | H9: PERÍODO COMISIONES PENDIENTES: | J9: ="Del " & TEXT(_xlfn.MINIFS('Detalles movimientos'!C$5:C$1021, 'Detalles movimientos'!F$5:F$1021, "CJ", 'Detalles movimientos'!P$5:P$1021, "<>*Comision Pagada*", 'Detalles movimientos'!C$5:C$1021, ">0"), "dd/mm/yyyy") & " al " & TEXT(_xlfn.MAXIFS('Detalles movimientos'!C$5:C$1021, 'Detalles movimientos'!F$5:F$1021, "CJ", 'Detalles movimientos'!P$5:P$1021, "<>*Comision Pagada*"), "dd/mm/yyyy")
B12: Fecha | C12: Nombre Cliente | D12: Camión | E12: Vende | F12: Dirección | G12: Precio | H12: Litros | I12: Total | J12: Medio de pago | K12: Comisiones | L12: Observación | M12: Facturación / Detalles
B13: =IFERROR(INDEX('Detalles movimientos'!C$5:C$1021, MATCH(1, 'Detalles movimientos'!$T$5:$T$1021, 0)), "") | C13: =IFERROR(INDEX('Detalles movimientos'!D$5:D$1021, MATCH(1, 'Detalles movimientos'!$T$5:$T$1021, 0)), "") | D13: =IFERROR(INDEX('Detalles movimientos'!E$5:E$1021, MATCH(1, 'Detalles movimientos'!$T$5:$T$1021, 0)), "") | E13: =IFERROR(INDEX('Detalles movimientos'!F$5:F$1021, MATCH(1, 'Detalles movimientos'!$T$5:$T$1021, 0)), "") | F13: =IFERROR(INDEX('Detalles movimientos'!G$5:G$1021, MATCH(1, 'Detalles movimientos'!$T$5:$T$1021, 0)), "") | G13: =IFERROR(INDEX('Detalles movimientos'!H$5:H$1021, MATCH(1, 'Detalles movimientos'!$T$5:$T$1021, 0)), "") | H13: =IFERROR(INDEX('Detalles movimientos'!I$5:I$1021, MATCH(1, 'Detalles movimientos'!$T$5:$T$1021, 0)), "") | I13: =IFERROR(INDEX('Detalles movimientos'!M$5:M$1021, MATCH(1, 'Detalles movimientos'!$T$5:$T$1021, 0)), "") | J13: =IFERROR(INDEX('Detalles movimientos'!N$5:N$1021, MATCH(1, 'Detalles movimientos'!$T$5:$T$1021, 0)), "") | K13: =IFERROR(INDEX('Detalles movimientos'!O$5:O$1021, MATCH(1, 'Detalles movimientos'!$T$5:$T$1021, 0)), "") | L13: =IFERROR(INDEX('Detalles movimientos'!P$5:P$1021, MATCH(1, 'Detalles movimientos'!$T$5:$T$1021, 0)), "") | M13: =IFERROR(INDEX('Detalles movimientos'!S$5:S$1021, MATCH(1, 'Detalles movimientos'!$T$5:$T$1021, 0)), "")
B14: =IFERROR(INDEX('Detalles movimientos'!C$5:C$1021, MATCH(2, 'Detalles movimientos'!$T$5:$T$1021, 0)), "") | C14: =IFERROR(INDEX('Detalles movimientos'!D$5:D$1021, MATCH(2, 'Detalles movimientos'!$T$5:$T$1021, 0)), "") | D14: =IFERROR(INDEX('Detalles movimientos'!E$5:E$1021, MATCH(2, 'Detalles movimientos'!$T$5:$T$1021, 0)), "") | E14: =IFERROR(INDEX('Detalles movimientos'!F$5:F$1021, MATCH(2, 'Detalles movimientos'!$T$5:$T$1021, 0)), "") | F14: =IFERROR(INDEX('Detalles movimientos'!G$5:G$1021, MATCH(2, 'Detalles movimientos'!$T$5:$T$1021, 0)), "") | G14: =IFERROR(INDEX('Detalles movimientos'!H$5:H$1021, MATCH(2, 'Detalles movimientos'!$T$5:$T$1021, 0)), "") | H14: =IFERROR(INDEX('Detalles movimientos'!I$5:I$1021, MATCH(2, 'Detalles movimientos'!$T$5:$T$1021, 0)), "") | I14: =IFERROR(INDEX('Detalles movimientos'!M$5:M$1021, MATCH(2, 'Detalles movimientos'!$T$5:$T$1021, 0)), "") | J14: =IFERROR(INDEX('Detalles movimientos'!N$5:N$1021, MATCH(2, 'Detalles movimientos'!$T$5:$T$1021, 0)), "") | K14: =IFERROR(INDEX('Detalles movimientos'!O$5:O$1021, MATCH(2, 'Detalles movimientos'!$T$5:$T$1021, 0)), "") | L14: =IFERROR(INDEX('Detalles movimientos'!P$5:P$1021, MATCH(2, 'Detalles movimientos'!$T$5:$T$1021, 0)), "") | M14: =IFERROR(INDEX('Detalles movimientos'!S$5:S$1021, MATCH(2, 'Detalles movimientos'!$T$5:$T$1021, 0)), "")
B15: =IFERROR(INDEX('Detalles movimientos'!C$5:C$1021, MATCH(3, 'Detalles movimientos'!$T$5:$T$1021, 0)), "") | C15: =IFERROR(INDEX('Detalles movimientos'!D$5:D$1021, MATCH(3, 'Detalles movimientos'!$T$5:$T$1021, 0)), "") | D15: =IFERROR(INDEX('Detalles movimientos'!E$5:E$1021, MATCH(3, 'Detalles movimientos'!$T$5:$T$1021, 0)), "") | E15: =IFERROR(INDEX('Detalles movimientos'!F$5:F$1021, MATCH(3, 'Detalles movimientos'!$T$5:$T$1021, 0)), "") | F15: =IFERROR(INDEX('Detalles movimientos'!G$5:G$1021, MATCH(3, 'Detalles movimientos'!$T$5:$T$1021, 0)), "") | G15: =IFERROR(INDEX('Detalles movimientos'!H$5:H$1021, MATCH(3, 'Detalles movimientos'!$T$5:$T$1021, 0)), "") | H15: =IFERROR(INDEX('Detalles movimientos'!I$5:I$1021, MATCH(3, 'Detalles movimientos'!$T$5:$T$1021, 0)), "") | I15: =IFERROR(INDEX('Detalles movimientos'!M$5:M$1021, MATCH(3, 'Detalles movimientos'!$T$5:$T$1021, 0)), "") | J15: =IFERROR(INDEX('Detalles movimientos'!N$5:N$1021, MATCH(3, 'Detalles movimientos'!$T$5:$T$1021, 0)), "") | K15: =IFERROR(INDEX('Detalles movimientos'!O$5:O$1021, MATCH(3, 'Detalles movimientos'!$T$5:$T$1021, 0)), "") | L15: =IFERROR(INDEX('Detalles movimientos'!P$5:P$1021, MATCH(3, 'Detalles movimientos'!$T$5:$T$1021, 0)), "") | M15: =IFERROR(INDEX('Detalles movimientos'!S$5:S$1021, MATCH(3, 'Detalles movimientos'!$T$5:$T$1021, 0)), "")
B16: =IFERROR(INDEX('Detalles movimientos'!C$5:C$1021, MATCH(4, 'Detalles movimientos'!$T$5:$T$1021, 0)), "") | C16: =IFERROR(INDEX('Detalles movimientos'!D$5:D$1021, MATCH(4, 'Detalles movimientos'!$T$5:$T$1021, 0)), "") | D16: =IFERROR(INDEX('Detalles movimientos'!E$5:E$1021, MATCH(4, 'Detalles movimientos'!$T$5:$T$1021, 0)), "") | E16: =IFERROR(INDEX('Detalles movimientos'!F$5:F$1021, MATCH(4, 'Detalles movimientos'!$T$5:$T$1021, 0)), "") | F16: =IFERROR(INDEX('Detalles movimientos'!G$5:G$1021, MATCH(4, 'Detalles movimientos'!$T$5:$T$1021, 0)), "") | G16: =IFERROR(INDEX('Detalles movimientos'!H$5:H$1021, MATCH(4, 'Detalles movimientos'!$T$5:$T$1021, 0)), "") | H16: =IFERROR(INDEX('Detalles movimientos'!I$5:I$1021, MATCH(4, 'Detalles movimientos'!$T$5:$T$1021, 0)), "") | I16: =IFERROR(INDEX('Detalles movimientos'!M$5:M$1021, MATCH(4, 'Detalles movimientos'!$T$5:$T$1021, 0)), "") | J16: =IFERROR(INDEX('Detalles movimientos'!N$5:N$1021, MATCH(4, 'Detalles movimientos'!$T$5:$T$1021, 0)), "") | K16: =IFERROR(INDEX('Detalles movimientos'!O$5:O$1021, MATCH(4, 'Detalles movimientos'!$T$5:$T$1021, 0)), "") | L16: =IFERROR(INDEX('Detalles movimientos'!P$5:P$1021, MATCH(4, 'Detalles movimientos'!$T$5:$T$1021, 0)), "") | M16: =IFERROR(INDEX('Detalles movimientos'!S$5:S$1021, MATCH(4, 'Detalles movimientos'!$T$5:$T$1021, 0)), "")
B17: =IFERROR(INDEX('Detalles movimientos'!C$5:C$1021, MATCH(5, 'Detalles movimientos'!$T$5:$T$1021, 0)), "") | C17: =IFERROR(INDEX('Detalles movimientos'!D$5:D$1021, MATCH(5, 'Detalles movimientos'!$T$5:$T$1021, 0)), "") | D17: =IFERROR(INDEX('Detalles movimientos'!E$5:E$1021, MATCH(5, 'Detalles movimientos'!$T$5:$T$1021, 0)), "") | E17: =IFERROR(INDEX('Detalles movimientos'!F$5:F$1021, MATCH(5, 'Detalles movimientos'!$T$5:$T$1021, 0)), "") | F17: =IFERROR(INDEX('Detalles movimientos'!G$5:G$1021, MATCH(5, 'Detalles movimientos'!$T$5:$T$1021, 0)), "") | G17: =IFERROR(INDEX('Detalles movimientos'!H$5:H$1021, MATCH(5, 'Detalles movimientos'!$T$5:$T$1021, 0)), "") | H17: =IFERROR(INDEX('Detalles movimientos'!I$5:I$1021, MATCH(5, 'Detalles movimientos'!$T$5:$T$1021, 0)), "") | I17: =IFERROR(INDEX('Detalles movimientos'!M$5:M$1021, MATCH(5, 'Detalles movimientos'!$T$5:$T$1021, 0)), "") | J17: =IFERROR(INDEX('Detalles movimientos'!N$5:N$1021, MATCH(5, 'Detalles movimientos'!$T$5:$T$1021, 0)), "") | K17: =IFERROR(INDEX('Detalles movimientos'!O$5:O$1021, MATCH(5, 'Detalles movimientos'!$T$5:$T$1021, 0)), "") | L17: =IFERROR(INDEX('Detalles movimientos'!P$5:P$1021, MATCH(5, 'Detalles movimientos'!$T$5:$T$1021, 0)), "") | M17: =IFERROR(INDEX('Detalles movimientos'!S$5:S$1021, MATCH(5, 'Detalles movimientos'!$T$5:$T$1021, 0)), "")
B18: =IFERROR(INDEX('Detalles movimientos'!C$5:C$1021, MATCH(6, 'Detalles movimientos'!$T$5:$T$1021, 0)), "") | C18: =IFERROR(INDEX('Detalles movimientos'!D$5:D$1021, MATCH(6, 'Detalles movimientos'!$T$5:$T$1021, 0)), "") | D18: =IFERROR(INDEX('Detalles movimientos'!E$5:E$1021, MATCH(6, 'Detalles movimientos'!$T$5:$T$1021, 0)), "") | E18: =IFERROR(INDEX('Detalles movimientos'!F$5:F$1021, MATCH(6, 'Detalles movimientos'!$T$5:$T$1021, 0)), "") | F18: =IFERROR(INDEX('Detalles movimientos'!G$5:G$1021, MATCH(6, 'Detalles movimientos'!$T$5:$T$1021, 0)), "") | G18: =IFERROR(INDEX('Detalles movimientos'!H$5:H$1021, MATCH(6, 'Detalles movimientos'!$T$5:$T$1021, 0)), "") | H18: =IFERROR(INDEX('Detalles movimientos'!I$5:I$1021, MATCH(6, 'Detalles movimientos'!$T$5:$T$1021, 0)), "") | I18: =IFERROR(INDEX('Detalles movimientos'!M$5:M$1021, MATCH(6, 'Detalles movimientos'!$T$5:$T$1021, 0)), "") | J18: =IFERROR(INDEX('Detalles movimientos'!N$5:N$1021, MATCH(6, 'Detalles movimientos'!$T$5:$T$1021, 0)), "") | K18: =IFERROR(INDEX('Detalles movimientos'!O$5:O$1021, MATCH(6, 'Detalles movimientos'!$T$5:$T$1021, 0)), "") | L18: =IFERROR(INDEX('Detalles movimientos'!P$5:P$1021, MATCH(6, 'Detalles movimientos'!$T$5:$T$1021, 0)), "") | M18: =IFERROR(INDEX('Detalles movimientos'!S$5:S$1021, MATCH(6, 'Detalles movimientos'!$T$5:$T$1021, 0)), "")
B19: =IFERROR(INDEX('Detalles movimientos'!C$5:C$1021, MATCH(7, 'Detalles movimientos'!$T$5:$T$1021, 0)), "") | C19: =IFERROR(INDEX('Detalles movimientos'!D$5:D$1021, MATCH(7, 'Detalles movimientos'!$T$5:$T$1021, 0)), "") | D19: =IFERROR(INDEX('Detalles movimientos'!E$5:E$1021, MATCH(7, 'Detalles movimientos'!$T$5:$T$1021, 0)), "") | E19: =IFERROR(INDEX('Detalles movimientos'!F$5:F$1021, MATCH(7, 'Detalles movimientos'!$T$5:$T$1021, 0)), "") | F19: =IFERROR(INDEX('Detalles movimientos'!G$5:G$1021, MATCH(7, 'Detalles movimientos'!$T$5:$T$1021, 0)), "") | G19: =IFERROR(INDEX('Detalles movimientos'!H$5:H$1021, MATCH(7, 'Detalles movimientos'!$T$5:$T$1021, 0)), "") | H19: =IFERROR(INDEX('Detalles movimientos'!I$5:I$1021, MATCH(7, 'Detalles movimientos'!$T$5:$T$1021, 0)), "") | I19: =IFERROR(INDEX('Detalles movimientos'!M$5:M$1021, MATCH(7, 'Detalles movimientos'!$T$5:$T$1021, 0)), "") | J19: =IFERROR(INDEX('Detalles movimientos'!N$5:N$1021, MATCH(7, 'Detalles movimientos'!$T$5:$T$1021, 0)), "") | K19: =IFERROR(INDEX('Detalles movimientos'!O$5:O$1021, MATCH(7, 'Detalles movimientos'!$T$5:$T$1021, 0)), "") | L19: =IFERROR(INDEX('Detalles movimientos'!P$5:P$1021, MATCH(7, 'Detalles movimientos'!$T$5:$T$1021, 0)), "") | M19: =IFERROR(INDEX('Detalles movimientos'!S$5:S$1021, MATCH(7, 'Detalles movimientos'!$T$5:$T$1021, 0)), "")
B20: =IFERROR(INDEX('Detalles movimientos'!C$5:C$1021, MATCH(8, 'Detalles movimientos'!$T$5:$T$1021, 0)), "") | C20: =IFERROR(INDEX('Detalles movimientos'!D$5:D$1021, MATCH(8, 'Detalles movimientos'!$T$5:$T$1021, 0)), "") | D20: =IFERROR(INDEX('Detalles movimientos'!E$5:E$1021, MATCH(8, 'Detalles movimientos'!$T$5:$T$1021, 0)), "") | E20: =IFERROR(INDEX('Detalles movimientos'!F$5:F$1021, MATCH(8, 'Detalles movimientos'!$T$5:$T$1021, 0)), "") | F20: =IFERROR(INDEX('Detalles movimientos'!G$5:G$1021, MATCH(8, 'Detalles movimientos'!$T$5:$T$1021, 0)), "") | G20: =IFERROR(INDEX('Detalles movimientos'!H$5:H$1021, MATCH(8, 'Detalles movimientos'!$T$5:$T$1021, 0)), "") | H20: =IFERROR(INDEX('Detalles movimientos'!I$5:I$1021, MATCH(8, 'Detalles movimientos'!$T$5:$T$1021, 0)), "") | I20: =IFERROR(INDEX('Detalles movimientos'!M$5:M$1021, MATCH(8, 'Detalles movimientos'!$T$5:$T$1021, 0)), "") | J20: =IFERROR(INDEX('Detalles movimientos'!N$5:N$1021, MATCH(8, 'Detalles movimientos'!$T$5:$T$1021, 0)), "") | K20: =IFERROR(INDEX('Detalles movimientos'!O$5:O$1021, MATCH(8, 'Detalles movimientos'!$T$5:$T$1021, 0)), "") | L20: =IFERROR(INDEX('Detalles movimientos'!P$5:P$1021, MATCH(8, 'Detalles movimientos'!$T$5:$T$1021, 0)), "") | M20: =IFERROR(INDEX('Detalles movimientos'!S$5:S$1021, MATCH(8, 'Detalles movimientos'!$T$5:$T$1021, 0)), "")
B21: =IFERROR(INDEX('Detalles movimientos'!C$5:C$1021, MATCH(9, 'Detalles movimientos'!$T$5:$T$1021, 0)), "") | C21: =IFERROR(INDEX('Detalles movimientos'!D$5:D$1021, MATCH(9, 'Detalles movimientos'!$T$5:$T$1021, 0)), "") | D21: =IFERROR(INDEX('Detalles movimientos'!E$5:E$1021, MATCH(9, 'Detalles movimientos'!$T$5:$T$1021, 0)), "") | E21: =IFERROR(INDEX('Detalles movimientos'!F$5:F$1021, MATCH(9, 'Detalles movimientos'!$T$5:$T$1021, 0)), "") | F21: =IFERROR(INDEX('Detalles movimientos'!G$5:G$1021, MATCH(9, 'Detalles movimientos'!$T$5:$T$1021, 0)), "") | G21: =IFERROR(INDEX('Detalles movimientos'!H$5:H$1021, MATCH(9, 'Detalles movimientos'!$T$5:$T$1021, 0)), "") | H21: =IFERROR(INDEX('Detalles movimientos'!I$5:I$1021, MATCH(9, 'Detalles movimientos'!$T$5:$T$1021, 0)), "") | I21: =IFERROR(INDEX('Detalles movimientos'!M$5:M$1021, MATCH(9, 'Detalles movimientos'!$T$5:$T$1021, 0)), "") | J21: =IFERROR(INDEX('Detalles movimientos'!N$5:N$1021, MATCH(9, 'Detalles movimientos'!$T$5:$T$1021, 0)), "") | K21: =IFERROR(INDEX('Detalles movimientos'!O$5:O$1021, MATCH(9, 'Detalles movimientos'!$T$5:$T$1021, 0)), "") | L21: =IFERROR(INDEX('Detalles movimientos'!P$5:P$1021, MATCH(9, 'Detalles movimientos'!$T$5:$T$1021, 0)), "") | M21: =IFERROR(INDEX('Detalles movimientos'!S$5:S$1021, MATCH(9, 'Detalles movimientos'!$T$5:$T$1021, 0)), "")
B22: =IFERROR(INDEX('Detalles movimientos'!C$5:C$1021, MATCH(10, 'Detalles movimientos'!$T$5:$T$1021, 0)), "") | C22: =IFERROR(INDEX('Detalles movimientos'!D$5:D$1021, MATCH(10, 'Detalles movimientos'!$T$5:$T$1021, 0)), "") | D22: =IFERROR(INDEX('Detalles movimientos'!E$5:E$1021, MATCH(10, 'Detalles movimientos'!$T$5:$T$1021, 0)), "") | E22: =IFERROR(INDEX('Detalles movimientos'!F$5:F$1021, MATCH(10, 'Detalles movimientos'!$T$5:$T$1021, 0)), "") | F22: =IFERROR(INDEX('Detalles movimientos'!G$5:G$1021, MATCH(10, 'Detalles movimientos'!$T$5:$T$1021, 0)), "") | G22: =IFERROR(INDEX('Detalles movimientos'!H$5:H$1021, MATCH(10, 'Detalles movimientos'!$T$5:$T$1021, 0)), "") | H22: =IFERROR(INDEX('Detalles movimientos'!I$5:I$1021, MATCH(10, 'Detalles movimientos'!$T$5:$T$1021, 0)), "") | I22: =IFERROR(INDEX('Detalles movimientos'!M$5:M$1021, MATCH(10, 'Detalles movimientos'!$T$5:$T$1021, 0)), "") | J22: =IFERROR(INDEX('Detalles movimientos'!N$5:N$1021, MATCH(10, 'Detalles movimientos'!$T$5:$T$1021, 0)), "") | K22: =IFERROR(INDEX('Detalles movimientos'!O$5:O$1021, MATCH(10, 'Detalles movimientos'!$T$5:$T$1021, 0)), "") | L22: =IFERROR(INDEX('Detalles movimientos'!P$5:P$1021, MATCH(10, 'Detalles movimientos'!$T$5:$T$1021, 0)), "") | M22: =IFERROR(INDEX('Detalles movimientos'!S$5:S$1021, MATCH(10, 'Detalles movimientos'!$T$5:$T$1021, 0)), "")
B23: =IFERROR(INDEX('Detalles movimientos'!C$5:C$1021, MATCH(11, 'Detalles movimientos'!$T$5:$T$1021, 0)), "") | C23: =IFERROR(INDEX('Detalles movimientos'!D$5:D$1021, MATCH(11, 'Detalles movimientos'!$T$5:$T$1021, 0)), "") | D23: =IFERROR(INDEX('Detalles movimientos'!E$5:E$1021, MATCH(11, 'Detalles movimientos'!$T$5:$T$1021, 0)), "") | E23: =IFERROR(INDEX('Detalles movimientos'!F$5:F$1021, MATCH(11, 'Detalles movimientos'!$T$5:$T$1021, 0)), "") | F23: =IFERROR(INDEX('Detalles movimientos'!G$5:G$1021, MATCH(11, 'Detalles movimientos'!$T$5:$T$1021, 0)), "") | G23: =IFERROR(INDEX('Detalles movimientos'!H$5:H$1021, MATCH(11, 'Detalles movimientos'!$T$5:$T$1021, 0)), "") | H23: =IFERROR(INDEX('Detalles movimientos'!I$5:I$1021, MATCH(11, 'Detalles movimientos'!$T$5:$T$1021, 0)), "") | I23: =IFERROR(INDEX('Detalles movimientos'!M$5:M$1021, MATCH(11, 'Detalles movimientos'!$T$5:$T$1021, 0)), "") | J23: =IFERROR(INDEX('Detalles movimientos'!N$5:N$1021, MATCH(11, 'Detalles movimientos'!$T$5:$T$1021, 0)), "") | K23: =IFERROR(INDEX('Detalles movimientos'!O$5:O$1021, MATCH(11, 'Detalles movimientos'!$T$5:$T$1021, 0)), "") | L23: =IFERROR(INDEX('Detalles movimientos'!P$5:P$1021, MATCH(11, 'Detalles movimientos'!$T$5:$T$1021, 0)), "") | M23: =IFERROR(INDEX('Detalles movimientos'!S$5:S$1021, MATCH(11, 'Detalles movimientos'!$T$5:$T$1021, 0)), "")
B24: =IFERROR(INDEX('Detalles movimientos'!C$5:C$1021, MATCH(12, 'Detalles movimientos'!$T$5:$T$1021, 0)), "") | C24: =IFERROR(INDEX('Detalles movimientos'!D$5:D$1021, MATCH(12, 'Detalles movimientos'!$T$5:$T$1021, 0)), "") | D24: =IFERROR(INDEX('Detalles movimientos'!E$5:E$1021, MATCH(12, 'Detalles movimientos'!$T$5:$T$1021, 0)), "") | E24: =IFERROR(INDEX('Detalles movimientos'!F$5:F$1021, MATCH(12, 'Detalles movimientos'!$T$5:$T$1021, 0)), "") | F24: =IFERROR(INDEX('Detalles movimientos'!G$5:G$1021, MATCH(12, 'Detalles movimientos'!$T$5:$T$1021, 0)), "") | G24: =IFERROR(INDEX('Detalles movimientos'!H$5:H$1021, MATCH(12, 'Detalles movimientos'!$T$5:$T$1021, 0)), "") | H24: =IFERROR(INDEX('Detalles movimientos'!I$5:I$1021, MATCH(12, 'Detalles movimientos'!$T$5:$T$1021, 0)), "") | I24: =IFERROR(INDEX('Detalles movimientos'!M$5:M$1021, MATCH(12, 'Detalles movimientos'!$T$5:$T$1021, 0)), "") | J24: =IFERROR(INDEX('Detalles movimientos'!N$5:N$1021, MATCH(12, 'Detalles movimientos'!$T$5:$T$1021, 0)), "") | K24: =IFERROR(INDEX('Detalles movimientos'!O$5:O$1021, MATCH(12, 'Detalles movimientos'!$T$5:$T$1021, 0)), "") | L24: =IFERROR(INDEX('Detalles movimientos'!P$5:P$1021, MATCH(12, 'Detalles movimientos'!$T$5:$T$1021, 0)), "") | M24: =IFERROR(INDEX('Detalles movimientos'!S$5:S$1021, MATCH(12, 'Detalles movimientos'!$T$5:$T$1021, 0)), "")
B25: =IFERROR(INDEX('Detalles movimientos'!C$5:C$1021, MATCH(13, 'Detalles movimientos'!$T$5:$T$1021, 0)), "") | C25: =IFERROR(INDEX('Detalles movimientos'!D$5:D$1021, MATCH(13, 'Detalles movimientos'!$T$5:$T$1021, 0)), "") | D25: =IFERROR(INDEX('Detalles movimientos'!E$5:E$1021, MATCH(13, 'Detalles movimientos'!$T$5:$T$1021, 0)), "") | E25: =IFERROR(INDEX('Detalles movimientos'!F$5:F$1021, MATCH(13, 'Detalles movimientos'!$T$5:$T$1021, 0)), "") | F25: =IFERROR(INDEX('Detalles movimientos'!G$5:G$1021, MATCH(13, 'Detalles movimientos'!$T$5:$T$1021, 0)), "") | G25: =IFERROR(INDEX('Detalles movimientos'!H$5:H$1021, MATCH(13, 'Detalles movimientos'!$T$5:$T$1021, 0)), "") | H25: =IFERROR(INDEX('Detalles movimientos'!I$5:I$1021, MATCH(13, 'Detalles movimientos'!$T$5:$T$1021, 0)), "") | I25: =IFERROR(INDEX('Detalles movimientos'!M$5:M$1021, MATCH(13, 'Detalles movimientos'!$T$5:$T$1021, 0)), "") | J25: =IFERROR(INDEX('Detalles movimientos'!N$5:N$1021, MATCH(13, 'Detalles movimientos'!$T$5:$T$1021, 0)), "") | K25: =IFERROR(INDEX('Detalles movimientos'!O$5:O$1021, MATCH(13, 'Detalles movimientos'!$T$5:$T$1021, 0)), "") | L25: =IFERROR(INDEX('Detalles movimientos'!P$5:P$1021, MATCH(13, 'Detalles movimientos'!$T$5:$T$1021, 0)), "") | M25: =IFERROR(INDEX('Detalles movimientos'!S$5:S$1021, MATCH(13, 'Detalles movimientos'!$T$5:$T$1021, 0)), "")
B26: =IFERROR(INDEX('Detalles movimientos'!C$5:C$1021, MATCH(14, 'Detalles movimientos'!$T$5:$T$1021, 0)), "") | C26: =IFERROR(INDEX('Detalles movimientos'!D$5:D$1021, MATCH(14, 'Detalles movimientos'!$T$5:$T$1021, 0)), "") | D26: =IFERROR(INDEX('Detalles movimientos'!E$5:E$1021, MATCH(14, 'Detalles movimientos'!$T$5:$T$1021, 0)), "") | E26: =IFERROR(INDEX('Detalles movimientos'!F$5:F$1021, MATCH(14, 'Detalles movimientos'!$T$5:$T$1021, 0)), "") | F26: =IFERROR(INDEX('Detalles movimientos'!G$5:G$1021, MATCH(14, 'Detalles movimientos'!$T$5:$T$1021, 0)), "") | G26: =IFERROR(INDEX('Detalles movimientos'!H$5:H$1021, MATCH(14, 'Detalles movimientos'!$T$5:$T$1021, 0)), "") | H26: =IFERROR(INDEX('Detalles movimientos'!I$5:I$1021, MATCH(14, 'Detalles movimientos'!$T$5:$T$1021, 0)), "") | I26: =IFERROR(INDEX('Detalles movimientos'!M$5:M$1021, MATCH(14, 'Detalles movimientos'!$T$5:$T$1021, 0)), "") | J26: =IFERROR(INDEX('Detalles movimientos'!N$5:N$1021, MATCH(14, 'Detalles movimientos'!$T$5:$T$1021, 0)), "") | K26: =IFERROR(INDEX('Detalles movimientos'!O$5:O$1021, MATCH(14, 'Detalles movimientos'!$T$5:$T$1021, 0)), "") | L26: =IFERROR(INDEX('Detalles movimientos'!P$5:P$1021, MATCH(14, 'Detalles movimientos'!$T$5:$T$1021, 0)), "") | M26: =IFERROR(INDEX('Detalles movimientos'!S$5:S$1021, MATCH(14, 'Detalles movimientos'!$T$5:$T$1021, 0)), "")
B27: =IFERROR(INDEX('Detalles movimientos'!C$5:C$1021, MATCH(15, 'Detalles movimientos'!$T$5:$T$1021, 0)), "") | C27: =IFERROR(INDEX('Detalles movimientos'!D$5:D$1021, MATCH(15, 'Detalles movimientos'!$T$5:$T$1021, 0)), "") | D27: =IFERROR(INDEX('Detalles movimientos'!E$5:E$1021, MATCH(15, 'Detalles movimientos'!$T$5:$T$1021, 0)), "") | E27: =IFERROR(INDEX('Detalles movimientos'!F$5:F$1021, MATCH(15, 'Detalles movimientos'!$T$5:$T$1021, 0)), "") | F27: =IFERROR(INDEX('Detalles movimientos'!G$5:G$1021, MATCH(15, 'Detalles movimientos'!$T$5:$T$1021, 0)), "") | G27: =IFERROR(INDEX('Detalles movimientos'!H$5:H$1021, MATCH(15, 'Detalles movimientos'!$T$5:$T$1021, 0)), "") | H27: =IFERROR(INDEX('Detalles movimientos'!I$5:I$1021, MATCH(15, 'Detalles movimientos'!$T$5:$T$1021, 0)), "") | I27: =IFERROR(INDEX('Detalles movimientos'!M$5:M$1021, MATCH(15, 'Detalles movimientos'!$T$5:$T$1021, 0)), "") | J27: =IFERROR(INDEX('Detalles movimientos'!N$5:N$1021, MATCH(15, 'Detalles movimientos'!$T$5:$T$1021, 0)), "") | K27: =IFERROR(INDEX('Detalles movimientos'!O$5:O$1021, MATCH(15, 'Detalles movimientos'!$T$5:$T$1021, 0)), "") | L27: =IFERROR(INDEX('Detalles movimientos'!P$5:P$1021, MATCH(15, 'Detalles movimientos'!$T$5:$T$1021, 0)), "") | M27: =IFERROR(INDEX('Detalles movimientos'!S$5:S$1021, MATCH(15, 'Detalles movimientos'!$T$5:$T$1021, 0)), "")
B28: =IFERROR(INDEX('Detalles movimientos'!C$5:C$1021, MATCH(16, 'Detalles movimientos'!$T$5:$T$1021, 0)), "") | C28: =IFERROR(INDEX('Detalles movimientos'!D$5:D$1021, MATCH(16, 'Detalles movimientos'!$T$5:$T$1021, 0)), "") | D28: =IFERROR(INDEX('Detalles movimientos'!E$5:E$1021, MATCH(16, 'Detalles movimientos'!$T$5:$T$1021, 0)), "") | E28: =IFERROR(INDEX('Detalles movimientos'!F$5:F$1021, MATCH(16, 'Detalles movimientos'!$T$5:$T$1021, 0)), "") | F28: =IFERROR(INDEX('Detalles movimientos'!G$5:G$1021, MATCH(16, 'Detalles movimientos'!$T$5:$T$1021, 0)), "") | G28: =IFERROR(INDEX('Detalles movimientos'!H$5:H$1021, MATCH(16, 'Detalles movimientos'!$T$5:$T$1021, 0)), "") | H28: =IFERROR(INDEX('Detalles movimientos'!I$5:I$1021, MATCH(16, 'Detalles movimientos'!$T$5:$T$1021, 0)), "") | I28: =IFERROR(INDEX('Detalles movimientos'!M$5:M$1021, MATCH(16, 'Detalles movimientos'!$T$5:$T$1021, 0)), "") | J28: =IFERROR(INDEX('Detalles movimientos'!N$5:N$1021, MATCH(16, 'Detalles movimientos'!$T$5:$T$1021, 0)), "") | K28: =IFERROR(INDEX('Detalles movimientos'!O$5:O$1021, MATCH(16, 'Detalles movimientos'!$T$5:$T$1021, 0)), "") | L28: =IFERROR(INDEX('Detalles movimientos'!P$5:P$1021, MATCH(16, 'Detalles movimientos'!$T$5:$T$1021, 0)), "") | M28: =IFERROR(INDEX('Detalles movimientos'!S$5:S$1021, MATCH(16, 'Detalles movimientos'!$T$5:$T$1021, 0)), "")
B29: =IFERROR(INDEX('Detalles movimientos'!C$5:C$1021, MATCH(17, 'Detalles movimientos'!$T$5:$T$1021, 0)), "") | C29: =IFERROR(INDEX('Detalles movimientos'!D$5:D$1021, MATCH(17, 'Detalles movimientos'!$T$5:$T$1021, 0)), "") | D29: =IFERROR(INDEX('Detalles movimientos'!E$5:E$1021, MATCH(17, 'Detalles movimientos'!$T$5:$T$1021, 0)), "") | E29: =IFERROR(INDEX('Detalles movimientos'!F$5:F$1021, MATCH(17, 'Detalles movimientos'!$T$5:$T$1021, 0)), "") | F29: =IFERROR(INDEX('Detalles movimientos'!G$5:G$1021, MATCH(17, 'Detalles movimientos'!$T$5:$T$1021, 0)), "") | G29: =IFERROR(INDEX('Detalles movimientos'!H$5:H$1021, MATCH(17, 'Detalles movimientos'!$T$5:$T$1021, 0)), "") | H29: =IFERROR(INDEX('Detalles movimientos'!I$5:I$1021, MATCH(17, 'Detalles movimientos'!$T$5:$T$1021, 0)), "") | I29: =IFERROR(INDEX('Detalles movimientos'!M$5:M$1021, MATCH(17, 'Detalles movimientos'!$T$5:$T$1021, 0)), "") | J29: =IFERROR(INDEX('Detalles movimientos'!N$5:N$1021, MATCH(17, 'Detalles movimientos'!$T$5:$T$1021, 0)), "") | K29: =IFERROR(INDEX('Detalles movimientos'!O$5:O$1021, MATCH(17, 'Detalles movimientos'!$T$5:$T$1021, 0)), "") | L29: =IFERROR(INDEX('Detalles movimientos'!P$5:P$1021, MATCH(17, 'Detalles movimientos'!$T$5:$T$1021, 0)), "") | M29: =IFERROR(INDEX('Detalles movimientos'!S$5:S$1021, MATCH(17, 'Detalles movimientos'!$T$5:$T$1021, 0)), "")
B30: =IFERROR(INDEX('Detalles movimientos'!C$5:C$1021, MATCH(18, 'Detalles movimientos'!$T$5:$T$1021, 0)), "") | C30: =IFERROR(INDEX('Detalles movimientos'!D$5:D$1021, MATCH(18, 'Detalles movimientos'!$T$5:$T$1021, 0)), "") | D30: =IFERROR(INDEX('Detalles movimientos'!E$5:E$1021, MATCH(18, 'Detalles movimientos'!$T$5:$T$1021, 0)), "") | E30: =IFERROR(INDEX('Detalles movimientos'!F$5:F$1021, MATCH(18, 'Detalles movimientos'!$T$5:$T$1021, 0)), "") | F30: =IFERROR(INDEX('Detalles movimientos'!G$5:G$1021, MATCH(18, 'Detalles movimientos'!$T$5:$T$1021, 0)), "") | G30: =IFERROR(INDEX('Detalles movimientos'!H$5:H$1021, MATCH(18, 'Detalles movimientos'!$T$5:$T$1021, 0)), "") | H30: =IFERROR(INDEX('Detalles movimientos'!I$5:I$1021, MATCH(18, 'Detalles movimientos'!$T$5:$T$1021, 0)), "") | I30: =IFERROR(INDEX('Detalles movimientos'!M$5:M$1021, MATCH(18, 'Detalles movimientos'!$T$5:$T$1021, 0)), "") | J30: =IFERROR(INDEX('Detalles movimientos'!N$5:N$1021, MATCH(18, 'Detalles movimientos'!$T$5:$T$1021, 0)), "") | K30: =IFERROR(INDEX('Detalles movimientos'!O$5:O$1021, MATCH(18, 'Detalles movimientos'!$T$5:$T$1021, 0)), "") | L30: =IFERROR(INDEX('Detalles movimientos'!P$5:P$1021, MATCH(18, 'Detalles movimientos'!$T$5:$T$1021, 0)), "") | M30: =IFERROR(INDEX('Detalles movimientos'!S$5:S$1021, MATCH(18, 'Detalles movimientos'!$T$5:$T$1021, 0)), "")
B31: =IFERROR(INDEX('Detalles movimientos'!C$5:C$1021, MATCH(19, 'Detalles movimientos'!$T$5:$T$1021, 0)), "") | C31: =IFERROR(INDEX('Detalles movimientos'!D$5:D$1021, MATCH(19, 'Detalles movimientos'!$T$5:$T$1021, 0)), "") | D31: =IFERROR(INDEX('Detalles movimientos'!E$5:E$1021, MATCH(19, 'Detalles movimientos'!$T$5:$T$1021, 0)), "") | E31: =IFERROR(INDEX('Detalles movimientos'!F$5:F$1021, MATCH(19, 'Detalles movimientos'!$T$5:$T$1021, 0)), "") | F31: =IFERROR(INDEX('Detalles movimientos'!G$5:G$1021, MATCH(19, 'Detalles movimientos'!$T$5:$T$1021, 0)), "") | G31: =IFERROR(INDEX('Detalles movimientos'!H$5:H$1021, MATCH(19, 'Detalles movimientos'!$T$5:$T$1021, 0)), "") | H31: =IFERROR(INDEX('Detalles movimientos'!I$5:I$1021, MATCH(19, 'Detalles movimientos'!$T$5:$T$1021, 0)), "") | I31: =IFERROR(INDEX('Detalles movimientos'!M$5:M$1021, MATCH(19, 'Detalles movimientos'!$T$5:$T$1021, 0)), "") | J31: =IFERROR(INDEX('Detalles movimientos'!N$5:N$1021, MATCH(19, 'Detalles movimientos'!$T$5:$T$1021, 0)), "") | K31: =IFERROR(INDEX('Detalles movimientos'!O$5:O$1021, MATCH(19, 'Detalles movimientos'!$T$5:$T$1021, 0)), "") | L31: =IFERROR(INDEX('Detalles movimientos'!P$5:P$1021, MATCH(19, 'Detalles movimientos'!$T$5:$T$1021, 0)), "") | M31: =IFERROR(INDEX('Detalles movimientos'!S$5:S$1021, MATCH(19, 'Detalles movimientos'!$T$5:$T$1021, 0)), "")
B32: =IFERROR(INDEX('Detalles movimientos'!C$5:C$1021, MATCH(20, 'Detalles movimientos'!$T$5:$T$1021, 0)), "") | C32: =IFERROR(INDEX('Detalles movimientos'!D$5:D$1021, MATCH(20, 'Detalles movimientos'!$T$5:$T$1021, 0)), "") | D32: =IFERROR(INDEX('Detalles movimientos'!E$5:E$1021, MATCH(20, 'Detalles movimientos'!$T$5:$T$1021, 0)), "") | E32: =IFERROR(INDEX('Detalles movimientos'!F$5:F$1021, MATCH(20, 'Detalles movimientos'!$T$5:$T$1021, 0)), "") | F32: =IFERROR(INDEX('Detalles movimientos'!G$5:G$1021, MATCH(20, 'Detalles movimientos'!$T$5:$T$1021, 0)), "") | G32: =IFERROR(INDEX('Detalles movimientos'!H$5:H$1021, MATCH(20, 'Detalles movimientos'!$T$5:$T$1021, 0)), "") | H32: =IFERROR(INDEX('Detalles movimientos'!I$5:I$1021, MATCH(20, 'Detalles movimientos'!$T$5:$T$1021, 0)), "") | I32: =IFERROR(INDEX('Detalles movimientos'!M$5:M$1021, MATCH(20, 'Detalles movimientos'!$T$5:$T$1021, 0)), "") | J32: =IFERROR(INDEX('Detalles movimientos'!N$5:N$1021, MATCH(20, 'Detalles movimientos'!$T$5:$T$1021, 0)), "") | K32: =IFERROR(INDEX('Detalles movimientos'!O$5:O$1021, MATCH(20, 'Detalles movimientos'!$T$5:$T$1021, 0)), "") | L32: =IFERROR(INDEX('Detalles movimientos'!P$5:P$1021, MATCH(20, 'Detalles movimientos'!$T$5:$T$1021, 0)), "") | M32: =IFERROR(INDEX('Detalles movimientos'!S$5:S$1021, MATCH(20, 'Detalles movimientos'!$T$5:$T$1021, 0)), "")
B33: =IFERROR(INDEX('Detalles movimientos'!C$5:C$1021, MATCH(21, 'Detalles movimientos'!$T$5:$T$1021, 0)), "") | C33: =IFERROR(INDEX('Detalles movimientos'!D$5:D$1021, MATCH(21, 'Detalles movimientos'!$T$5:$T$1021, 0)), "") | D33: =IFERROR(INDEX('Detalles movimientos'!E$5:E$1021, MATCH(21, 'Detalles movimientos'!$T$5:$T$1021, 0)), "") | E33: =IFERROR(INDEX('Detalles movimientos'!F$5:F$1021, MATCH(21, 'Detalles movimientos'!$T$5:$T$1021, 0)), "") | F33: =IFERROR(INDEX('Detalles movimientos'!G$5:G$1021, MATCH(21, 'Detalles movimientos'!$T$5:$T$1021, 0)), "") | G33: =IFERROR(INDEX('Detalles movimientos'!H$5:H$1021, MATCH(21, 'Detalles movimientos'!$T$5:$T$1021, 0)), "") | H33: =IFERROR(INDEX('Detalles movimientos'!I$5:I$1021, MATCH(21, 'Detalles movimientos'!$T$5:$T$1021, 0)), "") | I33: =IFERROR(INDEX('Detalles movimientos'!M$5:M$1021, MATCH(21, 'Detalles movimientos'!$T$5:$T$1021, 0)), "") | J33: =IFERROR(INDEX('Detalles movimientos'!N$5:N$1021, MATCH(21, 'Detalles movimientos'!$T$5:$T$1021, 0)), "") | K33: =IFERROR(INDEX('Detalles movimientos'!O$5:O$1021, MATCH(21, 'Detalles movimientos'!$T$5:$T$1021, 0)), "") | L33: =IFERROR(INDEX('Detalles movimientos'!P$5:P$1021, MATCH(21, 'Detalles movimientos'!$T$5:$T$1021, 0)), "") | M33: =IFERROR(INDEX('Detalles movimientos'!S$5:S$1021, MATCH(21, 'Detalles movimientos'!$T$5:$T$1021, 0)), "")
B34: =IFERROR(INDEX('Detalles movimientos'!C$5:C$1021, MATCH(22, 'Detalles movimientos'!$T$5:$T$1021, 0)), "") | C34: =IFERROR(INDEX('Detalles movimientos'!D$5:D$1021, MATCH(22, 'Detalles movimientos'!$T$5:$T$1021, 0)), "") | D34: =IFERROR(INDEX('Detalles movimientos'!E$5:E$1021, MATCH(22, 'Detalles movimientos'!$T$5:$T$1021, 0)), "") | E34: =IFERROR(INDEX('Detalles movimientos'!F$5:F$1021, MATCH(22, 'Detalles movimientos'!$T$5:$T$1021, 0)), "") | F34: =IFERROR(INDEX('Detalles movimientos'!G$5:G$1021, MATCH(22, 'Detalles movimientos'!$T$5:$T$1021, 0)), "") | G34: =IFERROR(INDEX('Detalles movimientos'!H$5:H$1021, MATCH(22, 'Detalles movimientos'!$T$5:$T$1021, 0)), "") | H34: =IFERROR(INDEX('Detalles movimientos'!I$5:I$1021, MATCH(22, 'Detalles movimientos'!$T$5:$T$1021, 0)), "") | I34: =IFERROR(INDEX('Detalles movimientos'!M$5:M$1021, MATCH(22, 'Detalles movimientos'!$T$5:$T$1021, 0)), "") | J34: =IFERROR(INDEX('Detalles movimientos'!N$5:N$1021, MATCH(22, 'Detalles movimientos'!$T$5:$T$1021, 0)), "") | K34: =IFERROR(INDEX('Detalles movimientos'!O$5:O$1021, MATCH(22, 'Detalles movimientos'!$T$5:$T$1021, 0)), "") | L34: =IFERROR(INDEX('Detalles movimientos'!P$5:P$1021, MATCH(22, 'Detalles movimientos'!$T$5:$T$1021, 0)), "") | M34: =IFERROR(INDEX('Detalles movimientos'!S$5:S$1021, MATCH(22, 'Detalles movimientos'!$T$5:$T$1021, 0)), "")
B35: =IFERROR(INDEX('Detalles movimientos'!C$5:C$1021, MATCH(23, 'Detalles movimientos'!$T$5:$T$1021, 0)), "") | C35: =IFERROR(INDEX('Detalles movimientos'!D$5:D$1021, MATCH(23, 'Detalles movimientos'!$T$5:$T$1021, 0)), "") | D35: =IFERROR(INDEX('Detalles movimientos'!E$5:E$1021, MATCH(23, 'Detalles movimientos'!$T$5:$T$1021, 0)), "") | E35: =IFERROR(INDEX('Detalles movimientos'!F$5:F$1021, MATCH(23, 'Detalles movimientos'!$T$5:$T$1021, 0)), "") | F35: =IFERROR(INDEX('Detalles movimientos'!G$5:G$1021, MATCH(23, 'Detalles movimientos'!$T$5:$T$1021, 0)), "") | G35: =IFERROR(INDEX('Detalles movimientos'!H$5:H$1021, MATCH(23, 'Detalles movimientos'!$T$5:$T$1021, 0)), "") | H35: =IFERROR(INDEX('Detalles movimientos'!I$5:I$1021, MATCH(23, 'Detalles movimientos'!$T$5:$T$1021, 0)), "") | I35: =IFERROR(INDEX('Detalles movimientos'!M$5:M$1021, MATCH(23, 'Detalles movimientos'!$T$5:$T$1021, 0)), "") | J35: =IFERROR(INDEX('Detalles movimientos'!N$5:N$1021, MATCH(23, 'Detalles movimientos'!$T$5:$T$1021, 0)), "") | K35: =IFERROR(INDEX('Detalles movimientos'!O$5:O$1021, MATCH(23, 'Detalles movimientos'!$T$5:$T$1021, 0)), "") | L35: =IFERROR(INDEX('Detalles movimientos'!P$5:P$1021, MATCH(23, 'Detalles movimientos'!$T$5:$T$1021, 0)), "") | M35: =IFERROR(INDEX('Detalles movimientos'!S$5:S$1021, MATCH(23, 'Detalles movimientos'!$T$5:$T$1021, 0)), "")
B36: =IFERROR(INDEX('Detalles movimientos'!C$5:C$1021, MATCH(24, 'Detalles movimientos'!$T$5:$T$1021, 0)), "") | C36: =IFERROR(INDEX('Detalles movimientos'!D$5:D$1021, MATCH(24, 'Detalles movimientos'!$T$5:$T$1021, 0)), "") | D36: =IFERROR(INDEX('Detalles movimientos'!E$5:E$1021, MATCH(24, 'Detalles movimientos'!$T$5:$T$1021, 0)), "") | E36: =IFERROR(INDEX('Detalles movimientos'!F$5:F$1021, MATCH(24, 'Detalles movimientos'!$T$5:$T$1021, 0)), "") | F36: =IFERROR(INDEX('Detalles movimientos'!G$5:G$1021, MATCH(24, 'Detalles movimientos'!$T$5:$T$1021, 0)), "") | G36: =IFERROR(INDEX('Detalles movimientos'!H$5:H$1021, MATCH(24, 'Detalles movimientos'!$T$5:$T$1021, 0)), "") | H36: =IFERROR(INDEX('Detalles movimientos'!I$5:I$1021, MATCH(24, 'Detalles movimientos'!$T$5:$T$1021, 0)), "") | I36: =IFERROR(INDEX('Detalles movimientos'!M$5:M$1021, MATCH(24, 'Detalles movimientos'!$T$5:$T$1021, 0)), "") | J36: =IFERROR(INDEX('Detalles movimientos'!N$5:N$1021, MATCH(24, 'Detalles movimientos'!$T$5:$T$1021, 0)), "") | K36: =IFERROR(INDEX('Detalles movimientos'!O$5:O$1021, MATCH(24, 'Detalles movimientos'!$T$5:$T$1021, 0)), "") | L36: =IFERROR(INDEX('Detalles movimientos'!P$5:P$1021, MATCH(24, 'Detalles movimientos'!$T$5:$T$1021, 0)), "") | M36: =IFERROR(INDEX('Detalles movimientos'!S$5:S$1021, MATCH(24, 'Detalles movimientos'!$T$5:$T$1021, 0)), "")
B37: =IFERROR(INDEX('Detalles movimientos'!C$5:C$1021, MATCH(25, 'Detalles movimientos'!$T$5:$T$1021, 0)), "") | C37: =IFERROR(INDEX('Detalles movimientos'!D$5:D$1021, MATCH(25, 'Detalles movimientos'!$T$5:$T$1021, 0)), "") | D37: =IFERROR(INDEX('Detalles movimientos'!E$5:E$1021, MATCH(25, 'Detalles movimientos'!$T$5:$T$1021, 0)), "") | E37: =IFERROR(INDEX('Detalles movimientos'!F$5:F$1021, MATCH(25, 'Detalles movimientos'!$T$5:$T$1021, 0)), "") | F37: =IFERROR(INDEX('Detalles movimientos'!G$5:G$1021, MATCH(25, 'Detalles movimientos'!$T$5:$T$1021, 0)), "") | G37: =IFERROR(INDEX('Detalles movimientos'!H$5:H$1021, MATCH(25, 'Detalles movimientos'!$T$5:$T$1021, 0)), "") | H37: =IFERROR(INDEX('Detalles movimientos'!I$5:I$1021, MATCH(25, 'Detalles movimientos'!$T$5:$T$1021, 0)), "") | I37: =IFERROR(INDEX('Detalles movimientos'!M$5:M$1021, MATCH(25, 'Detalles movimientos'!$T$5:$T$1021, 0)), "") | J37: =IFERROR(INDEX('Detalles movimientos'!N$5:N$1021, MATCH(25, 'Detalles movimientos'!$T$5:$T$1021, 0)), "") | K37: =IFERROR(INDEX('Detalles movimientos'!O$5:O$1021, MATCH(25, 'Detalles movimientos'!$T$5:$T$1021, 0)), "") | L37: =IFERROR(INDEX('Detalles movimientos'!P$5:P$1021, MATCH(25, 'Detalles movimientos'!$T$5:$T$1021, 0)), "") | M37: =IFERROR(INDEX('Detalles movimientos'!S$5:S$1021, MATCH(25, 'Detalles movimientos'!$T$5:$T$1021, 0)), "")
B38: =IFERROR(INDEX('Detalles movimientos'!C$5:C$1021, MATCH(26, 'Detalles movimientos'!$T$5:$T$1021, 0)), "") | C38: =IFERROR(INDEX('Detalles movimientos'!D$5:D$1021, MATCH(26, 'Detalles movimientos'!$T$5:$T$1021, 0)), "") | D38: =IFERROR(INDEX('Detalles movimientos'!E$5:E$1021, MATCH(26, 'Detalles movimientos'!$T$5:$T$1021, 0)), "") | E38: =IFERROR(INDEX('Detalles movimientos'!F$5:F$1021, MATCH(26, 'Detalles movimientos'!$T$5:$T$1021, 0)), "") | F38: =IFERROR(INDEX('Detalles movimientos'!G$5:G$1021, MATCH(26, 'Detalles movimientos'!$T$5:$T$1021, 0)), "") | G38: =IFERROR(INDEX('Detalles movimientos'!H$5:H$1021, MATCH(26, 'Detalles movimientos'!$T$5:$T$1021, 0)), "") | H38: =IFERROR(INDEX('Detalles movimientos'!I$5:I$1021, MATCH(26, 'Detalles movimientos'!$T$5:$T$1021, 0)), "") | I38: =IFERROR(INDEX('Detalles movimientos'!M$5:M$1021, MATCH(26, 'Detalles movimientos'!$T$5:$T$1021, 0)), "") | J38: =IFERROR(INDEX('Detalles movimientos'!N$5:N$1021, MATCH(26, 'Detalles movimientos'!$T$5:$T$1021, 0)), "") | K38: =IFERROR(INDEX('Detalles movimientos'!O$5:O$1021, MATCH(26, 'Detalles movimientos'!$T$5:$T$1021, 0)), "") | L38: =IFERROR(INDEX('Detalles movimientos'!P$5:P$1021, MATCH(26, 'Detalles movimientos'!$T$5:$T$1021, 0)), "") | M38: =IFERROR(INDEX('Detalles movimientos'!S$5:S$1021, MATCH(26, 'Detalles movimientos'!$T$5:$T$1021, 0)), "")
